Workbook

Sheet Objekt
A1: 06 · Interessentenmanagement – Objektkopf
A2: Gelb hinterlegte Spalten sind Eingabefelder. Auswahlfelder haben eine Liste. Die Spalte «Register» verweist auf Teil W des Makler-Handbuchs.
A3: Feld | B3: Eintrag | C3: Hinweis
A4: Objekt
A5: Objektnummer intern | C5: Aus dem CRM
A6: Strasse und Hausnummer
A7: PLZ und Ort
A8: Gemeinde
A9: Kanton | C9: Bestimmt Notariatssystem, Steuern, Gebühren und GEAK-Pflicht
A10: Parzellennummer | C10: Aus Grundbuchauszug
A11: Grundbuchblatt | C11: Aus Grundbuchauszug
A12: Objekttyp
A13: Eigentümerschaft
A14: Eigentümer 1
A15: Eigentümer 2
A16: Eigentumsform | C16: Allein-, Mit-, Gesamteigentum, Stockwerkeigentum, Baurecht
A17: Alle Verfügungsberechtigten bekannt | C17: Register R13, R14
A18: Mandat
A19: Zuständiger Makler
A20: Mandat unterzeichnet am
A21: Mandat läuft bis
A22: Angebotspreis CHF
A23: Mindestpreis CHF (intern) | C23: Wird keinem Interessenten genannt
A24: Identifikation GwG abgeschlossen | C24: Register R37; vor Vermarktungsstart
A25: Termine
A26: Vermarktungsstart | C26: Startpunkt der Zählung «Tage am Markt»
A27: Beurkundungstermin
A28: Eintragung im Grundbuch
A29: Übergabetermin
A30: Kantonale Abklärungen
A31: Notariatssystem und zuständiges Notariat | C31: Register R1
A32: Handänderungssteuer: Höhe und Kostenträger | C32: Register R26
A33: Grundstückgewinnsteuer: Stelle und Frist | C33: Register R22
A34: GEAK-Pflicht im Kanton | C34: Obligatorisch in FR, VD, NE, JU; Register R33
A35: Formerfordernis Vollmachten | C35: Register R16

Sheet Interessenten
A1: 06 · CRM-Liste der Kaufinteressenten
A2: Eine Zeile je Interessent. Feld «Datenschutz: Löschfrist» ist ein Pflichtfeld (Register R39). Erwerbsrechtliche Zulässigkeit vor der Terminvergabe klären (R34).
A3: Interessenten-Nr. | B3: Objekt | C3: Name | D3: Kontakt Telefon | E3: Kontakt E-Mail | F3: Datum Anfrage | G3: Quelle | H3: Personen im Haushalt | I3: Aktuelle Wohnsituation | J3: Staatsangehörigkeit und Ausländerstatus | K3: Finanzierung vorhanden | L3: Finanzierende Bank | M3: Eigenmittel total | N3: davon harte Eigenmittel | O3: Gewünschter Einzug | P3: Dossier versandt am | Q3: Besichtigung am | R3: Zweitbesichtigung am | S3: Interesse | T3: Stufe | U3: Angebot | V3: Angebotsdatum | W3: Angebotspreis | X3: Bedingungen und Vorbehalte | Y3: Finanzierungsnachweis | Z3: Identifikation GwG | AA3: Status | AB3: Absagegrund | AC3: Nächste Aktion | AD3: Nächste Aktion fällig | AE3: Zuständig | AF3: Datenschutz: Löschfrist | AG3: Bemerkungen

Sheet Feldbeschreibung
A1: 06 · Bedeutung der CRM-Felder
A2: Fundstelle: Teil K3 des Makler-Handbuchs.
A3: Feld | B3: Art | C3: Zweck
A4: Interessenten-Nr. | B4: Text | C4: Eindeutige Kennung, fortlaufend je Objekt
A5: Objekt | B5: Text | C5: Objektnummer, damit Interessenten über Objekte hinweg auswertbar sind
A6: Name | B6: Text | C6: Vollständiger Name aller Kaufinteressenten
A7: Kontakt Telefon | B7: Text | C7: Direktnummer
A8: Kontakt E-Mail | B8: Text | C8: Korrespondenzadresse
A9: Datum Anfrage | B9: Datum | C9: Startpunkt der Reaktionszeitmessung
A10: Quelle | B10: Auswahl | C10: Portal, Website, Newsletter, Empfehlung, Schild, Direktkontakt
A11: Personen im Haushalt | B11: Zahl | C11: Passung zum Objekt
A12: Aktuelle Wohnsituation | B12: Auswahl | C12: Miete, Eigentum mit Verkaufsbedarf, Eigentum ohne Verkaufsbedarf
A13: Staatsangehörigkeit und Ausländerstatus | B13: Text | C13: Erwerbsrechtliche Zulässigkeit (R34); vor Terminvergabe erfassen
A14: Finanzierung vorhanden | B14: Auswahl | C14: nein, in Abklärung, Selbstauskunft, schriftliche Bestätigung
... A36: Bemerkungen | B36: Text | C36: Gesprächsnotizen, sachlich formuliert – der Eintrag ist auskunftspflichtig (R39)

Sheet Besichtigungen
A1: 06 · Besichtigungsjournal
A2: Der Vermerk «Mängel offengelegt und protokolliert» ist der Nachweis der Offenlegung (Register R10, R11).
A3: Nr. | B3: Datum | C3: Zeit | D3: Interessent | E3: Stufe | F3: Teilnehmer | G3: Erstbesichtigung / Zweitbesichtigung | H3: Interessentenformular vollständig | I3: Mängel offengelegt und protokolliert | J3: Preisempfinden | K3: Rückmeldung erhalten am | L3: Ergebnis | M3: Absagegrund | N3: Nächste Aktion

Sheet Angebote
A1: 06 · Eingegangene Kaufangebote
A2: Die Spalten «Total» und «Abweichung» rechnen selbst. Angebotspreis der Vermarktung wird dem Blatt Objekt entnommen.
A3: Nr. | B3: Eingang Datum | C3: Eingang Zeit | D3: Kaufinteressent | E3: Angebot Liegenschaft CHF | F3: Angebot Inventar CHF | G3: Total CHF | H3: Abweichung zum Angebotspreis | I3: Finanzierungsnachweis | J3: Harte Eigenmittel CHF | K3: Bedingungen und Vorbehalte | L3: Gewünschter Übergabetermin | M3: Bewilligung erforderlich | N3: Identifikation GwG | O3: Gültig bis | P3: Abschlusswahrscheinlichkeit | Q3: Entscheid der Verkäuferschaft | R3: Entscheid am
A4: 1 | G4: =IF(E4="","",E4+N(F4)) | H4: =IF(OR(G4="",Objekt!$B$22=""),"",G4/Objekt!$B$22-1) | Q4: offen
A5: 2 | G5: =IF(E5="","",E5+N(F5)) | H5: =IF(OR(G5="",Objekt!$B$22=""),"",G5/Objekt!$B$22-1) | Q5: offen
A6: 3 | G6: =IF(E6="","",E6+N(F6)) | H6: =IF(OR(G6="",Objekt!$B$22=""),"",G6/Objekt!$B$22-1) | Q6: offen
A7: 4 | G7: =IF(E7="","",E7+N(F7)) | H7: =IF(OR(G7="",Objekt!$B$22=""),"",G7/Objekt!$B$22-1) | Q7: offen
A8: 5 | G8: =IF(E8="","",E8+N(F8)) | H8: =IF(OR(G8="",Objekt!$B$22=""),"",G8/Objekt!$B$22-1) | Q8: offen
A9: 6 | G9: =IF(E9="","",E9+N(F9)) | H9: =IF(OR(G9="",Objekt!$B$22=""),"",G9/Objekt!$B$22-1) | Q9: offen
A10: 7 | G10: =IF(E10="","",E10+N(F10)) | H10: =IF(OR(G10="",Objekt!$B$22=""),"",G10/Objekt!$B$22-1) | Q10: offen
A11: 8 | G11: =IF(E11="","",E11+N(F11)) | H11: =IF(OR(G11="",Objekt!$B$22=""),"",G11/Objekt!$B$22-1) | Q11: offen
A12: 9 | G12: =IF(E12="","",E12+N(F12)) | H12: =IF(OR(G12="",Objekt!$B$22=""),"",G12/Objekt!$B$22-1) | Q12: offen
A13: 10 | G13: =IF(E13="","",E13+N(F13)) | H13: =IF(OR(G13="",Objekt!$B$22=""),"",G13/Objekt!$B$22-1) | Q13: offen
A14: 11 | G14: =IF(E14="","",E14+N(F14)) | H14: =IF(OR(G14="",Objekt!$B$22=""),"",G14/Objekt!$B$22-1) | Q14: offen
A15: 12 | G15: =IF(E15="","",E15+N(F15)) | H15: =IF(OR(G15="",Objekt!$B$22=""),"",G15/Objekt!$B$22-1) | Q15: offen

Sheet Controlling
A1: 06 · Controlling-Dashboard
A2: Wöchentlich aktualisieren. Berechnete Felder ziehen aus den Blättern Interessenten, Besichtigungen und Angebote.
A3: Kennzahl | B3: Wert | C3: Definition | D3: Orientierung und Handlungsauslöser
A4: Tage am Markt | B4: =IF(Objekt!$B$26="","",TODAY()-Objekt!$B$26) | C4: Kalendertage seit der Veröffentlichung | D4: Segmentabhängig; ab 90 Tagen Strategieüberprüfung
A5: Anzahl Anfragen | C5: Alle eingegangenen Kontaktaufnahmen | D5: In den ersten 14 Tagen der grösste Teil
A6: Anfragen pro Woche | C6: Anfragen der Kalenderwoche | D6: Rückgang unter 20 Prozent des Startwerts ist ein Warnsignal
A7: Reaktionszeit | C7: Stunden von der Anfrage bis zur ersten Antwort | D7: Unter 4 Arbeitsstunden
A8: Anzahl Interessenten | B8: =COUNTA(Interessenten!C4:C400) | C8: Im CRM erfasste Personen oder Haushalte | D8: —
A9: Anzahl qualifizierte Interessenten | B9: =COUNTIF(Interessenten!T4:T400,"A") | C9: Stufe A: finanziert und entscheidungsfähig | D9: Mindestens 20 Prozent der Anfragen
A10: Anzahl Besichtigungen | B10: =COUNTA(Besichtigungen!D4:D200) | C10: Durchgeführte Termine | D10: —
A11: Quote Anfrage zu Besichtigung | B11: =IF(COUNTA(Interessenten!C4:C400)=0,"",COUNTA(Besichtigungen!D4:D200)/COUNTA(Interessenten!C4:C400)) | C11: Besichtigungen geteilt durch Anfragen | D11: Tiefe Quote deutet auf Preis- oder Erwartungsproblem
A12: Anzahl Zweitbesichtigungen | B12: =COUNTIF(Besichtigungen!G4:G200,"Zweitbesichtigung") | C12: Termine mit demselben Interessenten | D12: Stärkster Frühindikator für ein Angebot
A13: Anzahl Absagen | B13: =COUNTIF(Interessenten!AA4:AA400,"abgesagt") | C13: Interessenten mit Status abgesagt | D13: —
A14: Gründe für Absagen | C14: Verteilung nach Absagegrund | D14: Häufung bei «Preis» ab 5 Nennungen erfordert Preisgespräch
A15: Anzahl Angebote | B15: =COUNT(Angebote!E4:E200) | C15: Schriftlich eingegangene Kaufangebote | D15: —
A16: Angebotspreise | C16: Einzelwerte aller Angebote | D16: —
A17: Durchschnittlicher Angebotspreis | B17: =IF(COUNT(Angebote!G4:G200)=0,"",AVERAGE(Angebote!G4:G200)) | C17: Mittel aller eingegangenen Angebote | D17: —
A18: Höchstes Angebot | B18: =IF(COUNT(Angebote!G4:G200)=0,"",MAX(Angebote!G4:G200)) | C18: Grösster Angebotswert | D18: —
A19: Abweichung zum Angebotspreis | B19: =IF(OR(COUNT(Angebote!G4:G200)=0,Objekt!$B$22=""),"",MAX(Angebote!G4:G200)/Objekt!$B$22-1) | C19: Höchstes Angebot geteilt durch Angebotspreis, minus 1 | D19: Abweichung über 10 Prozent nach unten: Preisstrategie prüfen
A20: Abweichung zur Bewertung | C20: Erzielter Preis im Verhältnis zur bewerteten Spanne | D20: Innerhalb der Spanne
A21: Preisreduktionen | C21: Anzahl und Höhe der Anpassungen mit Datum | D21: Möglichst keine; jede Reduktion schwächt die Verhandlungsposition
A22: Quote Besichtigung zu Angebot | B22: =IF(COUNTA(Besichtigungen!D4:D200)=0,"",COUNT(Angebote!E4:E200)/COUNTA(Besichtigungen!D4:D200)) | C22: Angebote geteilt durch Besichtigungen | D22: Unter 10 Prozent nach 10 Besichtigungen: Ursache klären
A23: Dauer Einigung bis Beurkundung | C23: Kalendertage | D23: Verzögerungen meist durch fehlende Unterlagen beim Notariat
A24: Dauer Beurkundung bis Eintragung | C24: Kalendertage | D24: Kantonal unterschiedlich
A25: Aktueller Status | C25: Phase 1 bis 20 gemäss Teil B | D25: Wöchentlich aktualisieren
A26: Vermarktungskosten | C26: Aufgelaufene Kosten gegen Budget | D26: Innerhalb der Budgetfreigabe

Sheet Absagegruende
A1: 06 · Verteilung der Absagegründe
A2: Häufung bei «Preis» ab fünf Nennungen: Preisgespräch mit dem Eigentümer ansetzen (Teil U des Handbuchs).
A3: Grund | B3: Anzahl | C3: Bemerkung
A4: Preis | B4: =COUNTIF(Interessenten!AB4:AB400,A4)
A5: Lage | B5: =COUNTIF(Interessenten!AB4:AB400,A5)
A6: Zustand | B6: =COUNTIF(Interessenten!AB4:AB400,A6)
A7: Grösse | B7: =COUNTIF(Interessenten!AB4:AB400,A7)
A8: Finanzierung | B8: =COUNTIF(Interessenten!AB4:AB400,A8)
A9: Zeitpunkt | B9: =COUNTIF(Interessenten!AB4:AB400,A9)
A10: anderes Objekt | B10: =COUNTIF(Interessenten!AB4:AB400,A10)
A11: Lärm | B11: =COUNTIF(Interessenten!AB4:AB400,A11)
A12: Sanierungsbedarf | B12: =COUNTIF(Interessenten!AB4:AB400,A12)
A13: kein Grund genannt | B13: =COUNTIF(Interessenten!AB4:AB400,A13)
