Workbook

Sheet Objekt
A1: 08 · Bewertung – Objektkopf
A2: Gelb hinterlegte Spalten sind Eingabefelder. Auswahlfelder haben eine Liste. Die Spalte «Register» verweist auf Teil W des Makler-Handbuchs.
A3: Feld | B3: Eintrag | C3: Hinweis
A4: Objekt
A5: Objektnummer intern | C5: Aus dem CRM
A6: Strasse und Hausnummer
A7: PLZ und Ort
A8: Gemeinde
A9: Kanton | C9: Bestimmt Notariatssystem, Steuern, Gebühren und GEAK-Pflicht
A10: Parzellennummer | C10: Aus Grundbuchauszug
A11: Grundbuchblatt | C11: Aus Grundbuchauszug
A12: Objekttyp
A13: Eigentümerschaft
A14: Eigentümer 1
A15: Eigentümer 2
A16: Eigentumsform | C16: Allein-, Mit-, Gesamteigentum, Stockwerkeigentum, Baurecht
A17: Alle Verfügungsberechtigten bekannt | C17: Register R13, R14
A18: Mandat
A19: Zuständiger Makler
A20: Mandat unterzeichnet am
A21: Mandat läuft bis
A22: Angebotspreis CHF
A23: Mindestpreis CHF (intern) | C23: Wird keinem Interessenten genannt
A24: Identifikation GwG abgeschlossen | C24: Register R37; vor Vermarktungsstart
A25: Termine
A26: Vermarktungsstart | C26: Startpunkt der Zählung «Tage am Markt»
A27: Beurkundungstermin
A28: Eintragung im Grundbuch
A29: Übergabetermin
A30: Kantonale Abklärungen
A31: Notariatssystem und zuständiges Notariat | C31: Register R1
A32: Handänderungssteuer: Höhe und Kostenträger | C32: Register R26
A33: Grundstückgewinnsteuer: Stelle und Frist | C33: Register R22
A34: GEAK-Pflicht im Kanton | C34: Obligatorisch in FR, VD, NE, JU; Register R33
A35: Formerfordernis Vollmachten | C35: Register R16

Sheet Vergleichswert
A1: 08 · Vergleichswertmethode
A2: Mindestens drei, besser fünf Vergleichsobjekte. Angebotspreise sind keine Abschlusspreise und entsprechend zu korrigieren. Unter drei belastbaren Vergleichen ist die Methode allein nicht tragfähig.
A3: Nr. | B3: Lage / Adresse | C3: Wohnfläche m² | D3: Grundstück m² | E3: Baujahr | F3: Zustand | G3: Preis CHF | H3: Preis pro m² Wohnfläche | I3: Angebots- oder Abschlusspreis | J3: Angebotsdauer Tage | K3: Zu-/Abschlag % | L3: Begründung des Zu-/Abschlags | M3: Umgerechnet auf Bewertungsobjekt CHF | N3: Quelle und Abrufdatum
A4: 1 | H4: =IF(OR(G4="",C4=""),"",G4/C4) | M4: =IF(G4="","",G4*(1+N(K4)))
A5: 2 | H5: =IF(OR(G5="",C5=""),"",G5/C5) | M5: =IF(G5="","",G5*(1+N(K5)))
A6: 3 | H6: =IF(OR(G6="",C6=""),"",G6/C6) | M6: =IF(G6="","",G6*(1+N(K6)))
A7: 4 | H7: =IF(OR(G7="",C7=""),"",G7/C7) | M7: =IF(G7="","",G7*(1+N(K7)))
A8: 5 | H8: =IF(OR(G8="",C8=""),"",G8/C8) | M8: =IF(G8="","",G8*(1+N(K8)))
A9: 6 | H9: =IF(OR(G9="",C9=""),"",G9/C9) | M9: =IF(G9="","",G9*(1+N(K9)))
B11: **Mittelwert umgerechnet | M11: =IF(COUNT(M4:M9)=0,"",AVERAGE(M4:M9))
B12: **Tiefster Wert | M12: =IF(COUNT(M4:M9)=0,"",MIN(M4:M9))
B13: **Höchster Wert | M13: =IF(COUNT(M4:M9)=0,"",MAX(M4:M9))

Sheet Realwert
A1: 08 · Realwertmethode als Kontrollrechnung
A2: Gelbe Felder ausfüllen. Die berechneten Zeilen rechnen selbst. Der Gebäudeversicherungswert ist Kontrollgrösse für den Neuwert, kein Marktwert.
A3: Position | B3: Einheit | C3: Wert | D3: Hinweis
A4: Landfläche | B4: m² | D4: Eingabe
A5: Landpreis | B5: CHF/m² | D5: Quelle und Datum in der Bemerkung
A6: Landwert | B6: CHF | C6: =IF(OR(C4="",C5=""),"",C4*C5) | D6: Berechnet
A7: Gebäudevolumen | B7: m³ | D7: Aus Gebäudeversicherungsausweis
A8: Neuwert pro m³ | B8: CHF/m³ | D8: Eingabe
A9: Neuwert Gebäude | B9: CHF | C9: =IF(OR(C7="",C8=""),"",C7*C8) | D9: Berechnet
A10: Altersentwertung | B10: % | D10: Bauteilgewichtet, unter Berücksichtigung erfolgter Sanierungen
A11: Zeitbauwert Gebäude | B11: CHF | C11: =IF(OR(C9="",C10=""),"",C9*(1-C10)) | D11: Berechnet
A12: Umgebung und Nebenbauten | B12: CHF | D12: Eingabe
A13: Baunebenkosten | B13: CHF | D13: Eingabe
A14: Zwischentotal | B14: CHF | C14: =IF(C6="","",N(C6)+N(C11)+N(C12)+N(C13)) | D14: Berechnet
A15: Abzug aufgestauter Sanierungsbedarf | B15: CHF | D15: Summe aus dem Blatt Sanierungsbedarf
A16: Realwert | B16: CHF | C16: =IF(C14="","",C14-N(C15)) | D16: Berechnet

Sheet Sanierungsbedarf
A1: 08 · Sanierungsbedarf, bauteilweise
A2: Nie als Pauschale. Nur ein bauteilweise bezifferter Bedarf lässt sich gegenüber Eigentümer und Käufer begründen. Die Summe fliesst als Abzug in den Realwert.
A3: Bauteil | B3: Zustand | C3: Jahr der letzten Erneuerung | D3: Feststellung | E3: Zeithorizont | F3: Geschätzte Kosten CHF | G3: Quelle der Schätzung
A4: Dach und Spenglerarbeiten
A5: Fassade und Aussenwärmedämmung
A6: Fenster und Aussentüren
A7: Wärmeerzeuger
A8: Wärmeabgabe und Verteilung
A9: Warmwasseraufbereitung
A10: Lüftung
A11: Sanitärleitungen und Apparate
A12: Elektroinstallation
A13: Küche
A14: Badezimmer und Nassräume
A15: Bodenbeläge
... A18: Kanalisation und Entwässerung
A20: **Total geschätzter Sanierungsbedarf | F20: =SUM(F4:F18)

Sheet Ertragswert
A1: 08 · Ertragswertmethode, nur bei relevantem Mietertrag
A2: Nur ausfüllen bei Einliegerwohnung, vermieteter Garage, Mehrfamilienhaus oder Renditeanteil. Sonst mit Begründung als nicht anwendbar bezeichnen.
A3: Position | B3: Einheit | C3: Wert | D3: Hinweis
A4: Nachhaltig erzielbarer Bruttomietertrag pro Jahr | B4: CHF | D4: Aus Mietverträgen; nicht der Wunschmietzins
A5: Leerstands- und Mietausfallrisiko | B5: % | D5: Marktabhängig
A6: Effektiver Bruttoertrag | B6: CHF | C6: =IF(C4="","",C4*(1-N(C5))) | D6: Berechnet
A7: Nicht überwälzbare Betriebskosten | B7: CHF | D7: Verwaltung, Versicherung, Abgaben
A8: Unterhalt und Instandsetzung | B8: CHF | D8: Langjähriger Durchschnitt
A9: Nettoertrag | B9: CHF | C9: =IF(C6="","",C6-N(C7)-N(C8)) | D9: Berechnet
A10: Kapitalisierungssatz | B10: % | D10: Marktgerecht, mit Begründung in der Bemerkung
A11: Ertragswert | B11: CHF | C11: =IF(OR(C9="",C10=""),"",C9/C10) | D11: Berechnet
A12: Begründung des Kapitalisierungssatzes | B12: Text
A13: Anwendbar | B13: ja/nein | D13: Bei «nein» Begründung in der nächsten Zeile
A14: Begründung bei Nichtanwendbarkeit | B14: Text

Sheet Ergebnis
A1: 08 · Gewichtung, Wertspanne und Angebotspreis
A2: Die Wertspanne ist das Ergebnis, nicht der Punktwert. Abweichungen über 15 Prozent zwischen Vergleichs- und Realwert sind zu begründen, nicht zu mitteln.
A3: Position | B3: Wert | C3: Gewichtung | D3: Hinweis
A4: Vergleichswert, Mittelwert | B4: =IF(Vergleichswert!M11="","",Vergleichswert!M11) | D4: Aus dem Blatt Vergleichswert
A5: Vergleichswert, tiefster Wert | B5: =IF(Vergleichswert!M12="","",Vergleichswert!M12)
A6: Vergleichswert, höchster Wert | B6: =IF(Vergleichswert!M13="","",Vergleichswert!M13)
A7: Realwert | B7: =IF(Realwert!C16="","",Realwert!C16) | D7: Aus dem Blatt Realwert
A8: Ertragswert | B8: =IF(Ertragswert!C11="","",Ertragswert!C11) | D8: Nur bei Anwendbarkeit
A9: Abweichung Vergleichs- zu Realwert | B9: =IF(OR(B4="",B7=""),"",B4/B7-1) | D9: Über 15 Prozent: Ursache benennen
A11: **Gewichteter Wert | B11: =IF(SUM(C12:C14)=0,"",(N(B4)*N(C12)+N(B7)*N(C13)+N(B8)*N(C14))/SUM(C12:C14)) | D11: Die Summe der Gewichtungen muss 100 Prozent ergeben
A12: Gewichtung Vergleichswert | D12: Begründung unten
A13: Gewichtung Realwert
A14: Gewichtung Ertragswert
A15: Begründung der Gewichtung
A17: Wohnfläche m² | D17: Aus der Objektaufnahme, Arbeitsmappe 07
A18: **Wertspanne untere Grenze | D18: Eingabe, hergeleitet aus den Methoden
A19: **Wertspanne obere Grenze
A20: Mittelwert der Spanne | B20: =IF(OR(B18="",B19=""),"",(B18+B19)/2) | D20: Berechnet
A21: Preis pro m² Wohnfläche, Mittelwert | B21: =IF(OR(B20="",B17="",B17=0),"",B20/B17) | D21: Plausibilitätsgrösse gegen die Vergleichsobjekte
A23: **Empfohlener Angebotspreis | D23: Ein Betrag, mit Begründung der Lage innerhalb der Spanne
A24: Begründung
A26: Bewertungsdatum
A27: Bearbeitet durch
A28: Geprüft durch (Vier-Augen-Prinzip) | D28: Vor der Unterschrift zwingend

Sheet Chancen und Risiken
A1: 08 · Chancen, Risiken und Vermarktungsstrategie
A2: Je Position eine Zeile. Vermutetes Potenzial gehört nicht in die Zahl, sondern hierher (Register R27).
A3: Art | B3: Sachverhalt | C3: Wirkung auf Preis oder Angebotsdauer | D3: Voraussetzung bzw. Gegenmassnahme

Sheet Nettoerloes
A1: 08 · Nettoerlösrechnung für die Verkäuferschaft
A2: Unverbindliche Orientierung. Der Makler rechnet die Grundstückgewinnsteuer nicht selbst; er verlangt eine Schätzung des Steueramts (Register R22, R25).
A3: Position | B3: Betrag CHF | C3: Quelle und Datum | D3: Hinweis
A4: Angebotspreis bzw. erwarteter Kaufpreis
A5: Kaufpreis Inventar | D5: Gemäss Inventarliste
A6: **Total Erlös | B6: =IF(B4="","",B4+N(B5)) | D6: Berechnet
A7: ./. Ablösung Hypothek, Saldo | C7: Bestätigung der Bank | D7: Register R41
A8: ./. Vorfälligkeitsentschädigung | C8: Berechnung der Bank | D8: Register R41
A9: ./. Grundstückgewinnsteuer | C9: Schätzung Steueramt | D9: Kantonal; Register R22
A10: ./. Handänderungsabgabe, Anteil Verkäufer | C10: Notariat | D10: Kantonal; Register R26
A11: ./. Beurkundungs- und Grundbuchgebühren, Anteil Verkäufer | C11: Notariat | D11: Kantonal; Register R26
A12: ./. Maklerhonorar | C12: Mandat | D12: Register R18
A13: ./. Mehrwertsteuer auf dem Honorar, 8,1 % | B13: =IF(B12="","",B12*0.081) | C13: Mandat | D13: Berechnet; Register R21
A14: ./. Kosten GEAK, Fotografie, Grundrisse und übrige Vermarktung | C14: Budget
A15: ./. Weitere Kosten
A16: **Geschätzter Nettoerlös | B16: =IF(B6="","",B6-N(B7)-N(B8)-N(B9)-N(B10)-N(B11)-N(B12)-N(B13)-N(B14)-N(B15)) | D16: Berechnet

Sheet Grundlagen
A1: 08 · Verwendete Grundlagen und Vorbehalte
A2: Jede Eingangsgrösse der Bewertung braucht eine belegte Quelle. Fehlt eine Unterlage, ist der Vorbehalt im Bewertungsbericht zu nennen.
A3: Unterlage bzw. Auskunft | B3: Ausstellungsdatum | C3: Bezugsquelle | D3: Vorhanden | E3: Bemerkung bzw. Vorbehalt
A4: Grundbuchauszug
A5: Belege zu Dienstbarkeiten und Anmerkungen
A6: Katasterplan
A7: Zonenauskunft und Nutzungskennzahlen
A8: Baupläne, Grundrisse, Schnitte
A9: Baubewilligungen
A10: Gebäudeversicherungsausweis
A11: Renovationsnachweise und Belege
A12: Heizungs- und Haustechnikunterlagen
A13: GEAK
A14: Katasterauszug belastete Standorte
A15: Naturgefahrenkarte
... A18: Mietverträge, soweit vermietet
