Workbook

Sheet Start
B2: Vermieter-Toolkit Schweiz
B3: Nebenkosten · Mietzinsanpassung · Mieterwechsel · Wohnungsabnahme
B5: So gehen Sie vor
B6: 1. «Liegenschaft»: Abrechnungsperiode, Wohnungen und Verteilschlüssel erfassen (gelbe Felder).
B7: 2. «Mieter»: alle Mietverhältnisse der Periode erfassen – auch Mieterwechsel unterjährig. Leere Daten = ganze Periode.
B8: 3. «Kosten»: Rechnungsbeträge erfassen, Art und Schlüssel wählen. Nur im Mietvertrag ausgeschiedene Nebenkosten werden belastet.
B9: 4. «Abrechnung»: Mieter-Nr. wählen, prüfen, drucken oder als PDF speichern. Leerstandskosten trägt automatisch der Vermieter.
B10: 5. «Mietzins»: Anpassung nach Referenzzinssatz, Teuerung und Kostensteigerung berechnen – inkl. spätestem Zustelltermin.
B11: 6. «Mieterwechsel» und «Abnahme»: Checkliste mit Terminen und druckbares Abnahmeprotokoll.
B13: Was dieses Toolkit automatisch berücksichtigt
B14: • Heiz- und Warmwasserkosten nach Heizgradtagen gewichtet (Mieterwechsel im Sommer ≠ im Winter). Skala anpassbar.
B15: • Andere Nebenkosten zeitanteilig nach Tagen.
... B27: Version 1.0 · Stand Oktober 2026

Sheet Liegenschaft
B2: Liegenschaft & Abrechnungsperiode
B3: Gelbe Felder ausfüllen. Die Periode muss 12 Monate umfassen und am Monatsersten beginnen.
B4: Liegenschaft
B5: Ort
B6: Vermieter/in
B7: Periode von
B8: Periode bis | D8: =IF(OR(C7="",C8=""),"",IF(AND(DAY(C7)=1,C8=DATE(YEAR(C7),MONTH(C7)+12,0)),"✓ 12 Monate","⚠ Periode muss 12 volle Monate ab Monatserstem umfassen"))
B9: Tage in Periode | C9: =IF(OR(C7="",C8=""),"",C8-C7+1)
B10: Verwaltungshonorar in % der Nebenkosten | C10: 0.03
B11: Honorar im Mietvertrag vereinbart? | C11: Nein
L12: Hilfstabelle (nicht bearbeiten)
B13: Wohnung / Einheit | C13: Fläche m² | D13: Zimmer | E13: Wertquote ‰ | F13: Volumen m³ | G13: Einheiten gleich | I13: Monat | J13: Heizgradtage % | L13: Nr | M13: Beginn | N13: Ende | O13: Gewicht
G14: =IF(B14="",0,1) | I14: Januar | J14: 18 | L14: 1 | M14: =IF($C$7="","",DATE(YEAR($C$7),MONTH($C$7)+0,1)) | N14: =IF($C$7="","",DATE(YEAR($C$7),MONTH($C$7)+1,0)) | O14: =IF($C$7="",0,INDEX($J$14:$J$25,MONTH(M14)))
G15: =IF(B15="",0,1) | I15: Februar | J15: 15 | L15: 2 | M15: =IF($C$7="","",DATE(YEAR($C$7),MONTH($C$7)+1,1)) | N15: =IF($C$7="","",DATE(YEAR($C$7),MONTH($C$7)+2,0)) | O15: =IF($C$7="",0,INDEX($J$14:$J$25,MONTH(M15)))
G16: =IF(B16="",0,1) | I16: März | J16: 13 | L16: 3 | M16: =IF($C$7="","",DATE(YEAR($C$7),MONTH($C$7)+2,1)) | N16: =IF($C$7="","",DATE(YEAR($C$7),MONTH($C$7)+3,0)) | O16: =IF($C$7="",0,INDEX($J$14:$J$25,MONTH(M16)))
G17: =IF(B17="",0,1) | I17: April | J17: 9 | L17: 4 | M17: =IF($C$7="","",DATE(YEAR($C$7),MONTH($C$7)+3,1)) | N17: =IF($C$7="","",DATE(YEAR($C$7),MONTH($C$7)+4,0)) | O17: =IF($C$7="",0,INDEX($J$14:$J$25,MONTH(M17)))
G18: =IF(B18="",0,1) | I18: Mai | J18: 4 | L18: 5 | M18: =IF($C$7="","",DATE(YEAR($C$7),MONTH($C$7)+4,1)) | N18: =IF($C$7="","",DATE(YEAR($C$7),MONTH($C$7)+5,0)) | O18: =IF($C$7="",0,INDEX($J$14:$J$25,MONTH(M18)))
G19: =IF(B19="",0,1) | I19: Juni | J19: 0 | L19: 6 | M19: =IF($C$7="","",DATE(YEAR($C$7),MONTH($C$7)+5,1)) | N19: =IF($C$7="","",DATE(YEAR($C$7),MONTH($C$7)+6,0)) | O19: =IF($C$7="",0,INDEX($J$14:$J$25,MONTH(M19)))
G20: =IF(B20="",0,1) | I20: Juli | J20: 0 | L20: 7 | M20: =IF($C$7="","",DATE(YEAR($C$7),MONTH($C$7)+6,1)) | N20: =IF($C$7="","",DATE(YEAR($C$7),MONTH($C$7)+7,0)) | O20: =IF($C$7="",0,INDEX($J$14:$J$25,MONTH(M20)))
G21: =IF(B21="",0,1) | I21: August | J21: 0 | L21: 8 | M21: =IF($C$7="","",DATE(YEAR($C$7),MONTH($C$7)+7,1)) | N21: =IF($C$7="","",DATE(YEAR($C$7),MONTH($C$7)+8,0)) | O21: =IF($C$7="",0,INDEX($J$14:$J$25,MONTH(M21)))
G22: =IF(B22="",0,1) | I22: September | J22: 3 | L22: 9 | M22: =IF($C$7="","",DATE(YEAR($C$7),MONTH($C$7)+8,1)) | N22: =IF($C$7="","",DATE(YEAR($C$7),MONTH($C$7)+9,0)) | O22: =IF($C$7="",0,INDEX($J$14:$J$25,MONTH(M22)))
G23: =IF(B23="",0,1) | I23: Oktober | J23: 8 | L23: 10 | M23: =IF($C$7="","",DATE(YEAR($C$7),MONTH($C$7)+9,1)) | N23: =IF($C$7="","",DATE(YEAR($C$7),MONTH($C$7)+10,0)) | O23: =IF($C$7="",0,INDEX($J$14:$J$25,MONTH(M23)))
G24: =IF(B24="",0,1) | I24: November | J24: 13 | L24: 11 | M24: =IF($C$7="","",DATE(YEAR($C$7),MONTH($C$7)+10,1)) | N24: =IF($C$7="","",DATE(YEAR($C$7),MONTH($C$7)+11,0)) | O24: =IF($C$7="",0,INDEX($J$14:$J$25,MONTH(M24)))
G25: =IF(B25="",0,1) | I25: Dezember | J25: 17 | L25: 12 | M25: =IF($C$7="","",DATE(YEAR($C$7),MONTH($C$7)+11,1)) | N25: =IF($C$7="","",DATE(YEAR($C$7),MONTH($C$7)+12,0)) | O25: =IF($C$7="",0,INDEX($J$14:$J$25,MONTH(M25)))
B26: Total | C26: =SUM(C14:C25) | D26: =SUM(D14:D25) | E26: =SUM(E14:E25) | F26: =SUM(F14:F25) | G26: =SUM(G14:G25) | I26: Summe | J26: =SUM(J14:J25)
I27: =IF(ABS(J26-100)<0.01,"✓","⚠ Summe ≠ 100")

Sheet Mieter
B2: Mietverhältnisse in der Periode
B3: Eine Zeile pro Mietverhältnis. Mietbeginn/-ende leer lassen, wenn vor bzw. nach der Periode.
B5: Nr | C5: Wohnung | D5: Mieter/in | E5: Mietbeginn | F5: Mietende | G5: Akonto bezahlt | H5: von (eff.) | I5: bis (eff.) | J5: Tage | K5: Zeitanteil | L5: Heizanteil | M5: Prüfung | O5: Hilfsspalten Heizgewichtung (nicht bearbeiten)
B6: 1 | H6: =IF(D6="","",MAX(E6,Liegenschaft!$C$7)) | I6: =IF(D6="","",IF(F6="",Liegenschaft!$C$8,MIN(F6,Liegenschaft!$C$8))) | J6: =IF(D6="",0,MAX(0,I6-H6+1)) | K6: =IF(OR(D6="",Liegenschaft!$C$9=""),0,J6/Liegenschaft!$C$9) | L6: =IF(OR(D6="",Liegenschaft!$J$26=0),0,SUM(O6:Z6)/Liegenschaft!$J$26) | M6: =IF(D6="","",IF(ISNA(MATCH(C6,Liegenschaft!$B$14:$B$25,0)),"⚠ Wohnung unbekannt",IF(J6=0,"⚠ nicht in Periode",IF(SUMPRODUCT(($C$6:$C$35=C6)*($D$6:$D$35<>"")*($J$6:$J$35>0)*($H$6:$H$35<=I6)*($I$6:$I$35>=H6))>1,"⚠ Überschneidung mit anderem Mieter","✓")))) | O6: =IF(OR(D6="",Liegenschaft!$C$7=""),0,MAX(0,MIN(I6,Liegenschaft!$N$14)-MAX(H6,Liegenschaft!$M$14)+1)/DAY(Liegenschaft!$N$14)*Liegenschaft!$O$14) | P6: =IF(OR(D6="",Liegenschaft!$C$7=""),0,MAX(0,MIN(I6,Liegenschaft!$N$15)-MAX(H6,Liegenschaft!$M$15)+1)/DAY(Liegenschaft!$N$15)*Liegenschaft!$O$15) | Q6: =IF(OR(D6="",Liegenschaft!$C$7=""),0,MAX(0,MIN(I6,Liegenschaft!$N$16)-MAX(H6,Liegenschaft!$M$16)+1)/DAY(Liegenschaft!$N$16)*Liegenschaft!$O$16) | R6: =IF(OR(D6="",Liegenschaft!$C$7=""),0,MAX(0,MIN(I6,Liegenschaft!$N$17)-MAX(H6,Liegenschaft!$M$17)+1)/DAY(Liegenschaft!$N$17)*Liegenschaft!$O$17) | S6: =IF(OR(D6="",Liegenschaft!$C$7=""),0,MAX(0,MIN(I6,Liegenschaft!$N$18)-MAX(H6,Liegenschaft!$M$18)+1)/DAY(Liegenschaft!$N$18)*Liegenschaft!$O$18) | T6: =IF(OR(D6="",Liegenschaft!$C$7=""),0,MAX(0,MIN(I6,Liegenschaft!$N$19)-MAX(H6,Liegenschaft!$M$19)+1)/DAY(Liegenschaft!$N$19)*Liegenschaft!$O$19) | U6: =IF(OR(D6="",Liegenschaft!$C$7=""),0,MAX(0,MIN(I6,Liegenschaft!$N$20)-MAX(H6,Liegenschaft!$M$20)+1)/DAY(Liegenschaft!$N$20)*Liegenschaft!$O$20) | V6: =IF(OR(D6="",Liegenschaft!$C$7=""),0,MAX(0,MIN(I6,Liegenschaft!$N$21)-MAX(H6,Liegenschaft!$M$21)+1)/DAY(Liegenschaft!$N$21)*Liegenschaft!$O$21) | W6: =IF(OR(D6="",Liegenschaft!$C$7=""),0,MAX(0,MIN(I6,Liegenschaft!$N$22)-MAX(H6,Liegenschaft!$M$22)+1)/DAY(Liegenschaft!$N$22)*Liegenschaft!$O$22) | X6: =IF(OR(D6="",Liegenschaft!$C$7=""),0,MAX(0,MIN(I6,Liegenschaft!$N$23)-MAX(H6,Liegenschaft!$M$23)+1)/DAY(Liegenschaft!$N$23)*Liegenschaft!$O$23) | Y6: =IF(OR(D6="",Liegenschaft!$C$7=""),0,MAX(0,MIN(I6,Liegenschaft!$N$24)-MAX(H6,Liegenschaft!$M$24)+1)/DAY(Liegenschaft!$N$24)*Liegenschaft!$O$24) | Z6: =IF(OR(D6="",Liegenschaft!$C$7=""),0,MAX(0,MIN(I6,Liegenschaft!$N$25)-MAX(H6,Liegenschaft!$M$25)+1)/DAY(Liegenschaft!$N$25)*Liegenschaft!$O$25)
B7: 2 | H7: =IF(D7="","",MAX(E7,Liegenschaft!$C$7)) | I7: =IF(D7="","",IF(F7="",Liegenschaft!$C$8,MIN(F7,Liegenschaft!$C$8))) | J7: =IF(D7="",0,MAX(0,I7-H7+1)) | K7: =IF(OR(D7="",Liegenschaft!$C$9=""),0,J7/Liegenschaft!$C$9) | L7: =IF(OR(D7="",Liegenschaft!$J$26=0),0,SUM(O7:Z7)/Liegenschaft!$J$26) | M7: =IF(D7="","",IF(ISNA(MATCH(C7,Liegenschaft!$B$14:$B$25,0)),"⚠ Wohnung unbekannt",IF(J7=0,"⚠ nicht in Periode",IF(SUMPRODUCT(($C$6:$C$35=C7)*($D$6:$D$35<>"")*($J$6:$J$35>0)*($H$6:$H$35<=I7)*($I$6:$I$35>=H7))>1,"⚠ Überschneidung mit anderem Mieter","✓")))) | O7: =IF(OR(D7="",Liegenschaft!$C$7=""),0,MAX(0,MIN(I7,Liegenschaft!$N$14)-MAX(H7,Liegenschaft!$M$14)+1)/DAY(Liegenschaft!$N$14)*Liegenschaft!$O$14) | P7: =IF(OR(D7="",Liegenschaft!$C$7=""),0,MAX(0,MIN(I7,Liegenschaft!$N$15)-MAX(H7,Liegenschaft!$M$15)+1)/DAY(Liegenschaft!$N$15)*Liegenschaft!$O$15) | Q7: =IF(OR(D7="",Liegenschaft!$C$7=""),0,MAX(0,MIN(I7,Liegenschaft!$N$16)-MAX(H7,Liegenschaft!$M$16)+1)/DAY(Liegenschaft!$N$16)*Liegenschaft!$O$16) | R7: =IF(OR(D7="",Liegenschaft!$C$7=""),0,MAX(0,MIN(I7,Liegenschaft!$N$17)-MAX(H7,Liegenschaft!$M$17)+1)/DAY(Liegenschaft!$N$17)*Liegenschaft!$O$17) | S7: =IF(OR(D7="",Liegenschaft!$C$7=""),0,MAX(0,MIN(I7,Liegenschaft!$N$18)-MAX(H7,Liegenschaft!$M$18)+1)/DAY(Liegenschaft!$N$18)*Liegenschaft!$O$18) | T7: =IF(OR(D7="",Liegenschaft!$C$7=""),0,MAX(0,MIN(I7,Liegenschaft!$N$19)-MAX(H7,Liegenschaft!$M$19)+1)/DAY(Liegenschaft!$N$19)*Liegenschaft!$O$19) | U7: =IF(OR(D7="",Liegenschaft!$C$7=""),0,MAX(0,MIN(I7,Liegenschaft!$N$20)-MAX(H7,Liegenschaft!$M$20)+1)/DAY(Liegenschaft!$N$20)*Liegenschaft!$O$20) | V7: =IF(OR(D7="",Liegenschaft!$C$7=""),0,MAX(0,MIN(I7,Liegenschaft!$N$21)-MAX(H7,Liegenschaft!$M$21)+1)/DAY(Liegenschaft!$N$21)*Liegenschaft!$O$21) | W7: =IF(OR(D7="",Liegenschaft!$C$7=""),0,MAX(0,MIN(I7,Liegenschaft!$N$22)-MAX(H7,Liegenschaft!$M$22)+1)/DAY(Liegenschaft!$N$22)*Liegenschaft!$O$22) | X7: =IF(OR(D7="",Liegenschaft!$C$7=""),0,MAX(0,MIN(I7,Liegenschaft!$N$23)-MAX(H7,Liegenschaft!$M$23)+1)/DAY(Liegenschaft!$N$23)*Liegenschaft!$O$23) | Y7: =IF(OR(D7="",Liegenschaft!$C$7=""),0,MAX(0,MIN(I7,Liegenschaft!$N$24)-MAX(H7,Liegenschaft!$M$24)+1)/DAY(Liegenschaft!$N$24)*Liegenschaft!$O$24) | Z7: =IF(OR(D7="",Liegenschaft!$C$7=""),0,MAX(0,MIN(I7,Liegenschaft!$N$25)-MAX(H7,Liegenschaft!$M$25)+1)/DAY(Liegenschaft!$N$25)*Liegenschaft!$O$25)
B8: 3 | H8: =IF(D8="","",MAX(E8,Liegenschaft!$C$7)) | I8: =IF(D8="","",IF(F8="",Liegenschaft!$C$8,MIN(F8,Liegenschaft!$C$8))) | J8: =IF(D8="",0,MAX(0,I8-H8+1)) | K8: =IF(OR(D8="",Liegenschaft!$C$9=""),0,J8/Liegenschaft!$C$9) | L8: =IF(OR(D8="",Liegenschaft!$J$26=0),0,SUM(O8:Z8)/Liegenschaft!$J$26) | M8: =IF(D8="","",IF(ISNA(MATCH(C8,Liegenschaft!$B$14:$B$25,0)),"⚠ Wohnung unbekannt",IF(J8=0,"⚠ nicht in Periode",IF(SUMPRODUCT(($C$6:$C$35=C8)*($D$6:$D$35<>"")*($J$6:$J$35>0)*($H$6:$H$35<=I8)*($I$6:$I$35>=H8))>1,"⚠ Überschneidung mit anderem Mieter","✓")))) | O8: =IF(OR(D8="",Liegenschaft!$C$7=""),0,MAX(0,MIN(I8,Liegenschaft!$N$14)-MAX(H8,Liegenschaft!$M$14)+1)/DAY(Liegenschaft!$N$14)*Liegenschaft!$O$14) | P8: =IF(OR(D8="",Liegenschaft!$C$7=""),0,MAX(0,MIN(I8,Liegenschaft!$N$15)-MAX(H8,Liegenschaft!$M$15)+1)/DAY(Liegenschaft!$N$15)*Liegenschaft!$O$15) | Q8: =IF(OR(D8="",Liegenschaft!$C$7=""),0,MAX(0,MIN(I8,Liegenschaft!$N$16)-MAX(H8,Liegenschaft!$M$16)+1)/DAY(Liegenschaft!$N$16)*Liegenschaft!$O$16) | R8: =IF(OR(D8="",Liegenschaft!$C$7=""),0,MAX(0,MIN(I8,Liegenschaft!$N$17)-MAX(H8,Liegenschaft!$M$17)+1)/DAY(Liegenschaft!$N$17)*Liegenschaft!$O$17) | S8: =IF(OR(D8="",Liegenschaft!$C$7=""),0,MAX(0,MIN(I8,Liegenschaft!$N$18)-MAX(H8,Liegenschaft!$M$18)+1)/DAY(Liegenschaft!$N$18)*Liegenschaft!$O$18) | T8: =IF(OR(D8="",Liegenschaft!$C$7=""),0,MAX(0,MIN(I8,Liegenschaft!$N$19)-MAX(H8,Liegenschaft!$M$19)+1)/DAY(Liegenschaft!$N$19)*Liegenschaft!$O$19) | U8: =IF(OR(D8="",Liegenschaft!$C$7=""),0,MAX(0,MIN(I8,Liegenschaft!$N$20)-MAX(H8,Liegenschaft!$M$20)+1)/DAY(Liegenschaft!$N$20)*Liegenschaft!$O$20) | V8: =IF(OR(D8="",Liegenschaft!$C$7=""),0,MAX(0,MIN(I8,Liegenschaft!$N$21)-MAX(H8,Liegenschaft!$M$21)+1)/DAY(Liegenschaft!$N$21)*Liegenschaft!$O$21) | W8: =IF(OR(D8="",Liegenschaft!$C$7=""),0,MAX(0,MIN(I8,Liegenschaft!$N$22)-MAX(H8,Liegenschaft!$M$22)+1)/DAY(Liegenschaft!$N$22)*Liegenschaft!$O$22) | X8: =IF(OR(D8="",Liegenschaft!$C$7=""),0,MAX(0,MIN(I8,Liegenschaft!$N$23)-MAX(H8,Liegenschaft!$M$23)+1)/DAY(Liegenschaft!$N$23)*Liegenschaft!$O$23) | Y8: =IF(OR(D8="",Liegenschaft!$C$7=""),0,MAX(0,MIN(I8,Liegenschaft!$N$24)-MAX(H8,Liegenschaft!$M$24)+1)/DAY(Liegenschaft!$N$24)*Liegenschaft!$O$24) | Z8: =IF(OR(D8="",Liegenschaft!$C$7=""),0,MAX(0,MIN(I8,Liegenschaft!$N$25)-MAX(H8,Liegenschaft!$M$25)+1)/DAY(Liegenschaft!$N$25)*Liegenschaft!$O$25)
B9: 4 | H9: =IF(D9="","",MAX(E9,Liegenschaft!$C$7)) | I9: =IF(D9="","",IF(F9="",Liegenschaft!$C$8,MIN(F9,Liegenschaft!$C$8))) | J9: =IF(D9="",0,MAX(0,I9-H9+1)) | K9: =IF(OR(D9="",Liegenschaft!$C$9=""),0,J9/Liegenschaft!$C$9) | L9: =IF(OR(D9="",Liegenschaft!$J$26=0),0,SUM(O9:Z9)/Liegenschaft!$J$26) | M9: =IF(D9="","",IF(ISNA(MATCH(C9,Liegenschaft!$B$14:$B$25,0)),"⚠ Wohnung unbekannt",IF(J9=0,"⚠ nicht in Periode",IF(SUMPRODUCT(($C$6:$C$35=C9)*($D$6:$D$35<>"")*($J$6:$J$35>0)*($H$6:$H$35<=I9)*($I$6:$I$35>=H9))>1,"⚠ Überschneidung mit anderem Mieter","✓")))) | O9: =IF(OR(D9="",Liegenschaft!$C$7=""),0,MAX(0,MIN(I9,Liegenschaft!$N$14)-MAX(H9,Liegenschaft!$M$14)+1)/DAY(Liegenschaft!$N$14)*Liegenschaft!$O$14) | P9: =IF(OR(D9="",Liegenschaft!$C$7=""),0,MAX(0,MIN(I9,Liegenschaft!$N$15)-MAX(H9,Liegenschaft!$M$15)+1)/DAY(Liegenschaft!$N$15)*Liegenschaft!$O$15) | Q9: =IF(OR(D9="",Liegenschaft!$C$7=""),0,MAX(0,MIN(I9,Liegenschaft!$N$16)-MAX(H9,Liegenschaft!$M$16)+1)/DAY(Liegenschaft!$N$16)*Liegenschaft!$O$16) | R9: =IF(OR(D9="",Liegenschaft!$C$7=""),0,MAX(0,MIN(I9,Liegenschaft!$N$17)-MAX(H9,Liegenschaft!$M$17)+1)/DAY(Liegenschaft!$N$17)*Liegenschaft!$O$17) | S9: =IF(OR(D9="",Liegenschaft!$C$7=""),0,MAX(0,MIN(I9,Liegenschaft!$N$18)-MAX(H9,Liegenschaft!$M$18)+1)/DAY(Liegenschaft!$N$18)*Liegenschaft!$O$18) | T9: =IF(OR(D9="",Liegenschaft!$C$7=""),0,MAX(0,MIN(I9,Liegenschaft!$N$19)-MAX(H9,Liegenschaft!$M$19)+1)/DAY(Liegenschaft!$N$19)*Liegenschaft!$O$19) | U9: =IF(OR(D9="",Liegenschaft!$C$7=""),0,MAX(0,MIN(I9,Liegenschaft!$N$20)-MAX(H9,Liegenschaft!$M$20)+1)/DAY(Liegenschaft!$N$20)*Liegenschaft!$O$20) | V9: =IF(OR(D9="",Liegenschaft!$C$7=""),0,MAX(0,MIN(I9,Liegenschaft!$N$21)-MAX(H9,Liegenschaft!$M$21)+1)/DAY(Liegenschaft!$N$21)*Liegenschaft!$O$21) | W9: =IF(OR(D9="",Liegenschaft!$C$7=""),0,MAX(0,MIN(I9,Liegenschaft!$N$22)-MAX(H9,Liegenschaft!$M$22)+1)/DAY(Liegenschaft!$N$22)*Liegenschaft!$O$22) | X9: =IF(OR(D9="",Liegenschaft!$C$7=""),0,MAX(0,MIN(I9,Liegenschaft!$N$23)-MAX(H9,Liegenschaft!$M$23)+1)/DAY(Liegenschaft!$N$23)*Liegenschaft!$O$23) | Y9: =IF(OR(D9="",Liegenschaft!$C$7=""),0,MAX(0,MIN(I9,Liegenschaft!$N$24)-MAX(H9,Liegenschaft!$M$24)+1)/DAY(Liegenschaft!$N$24)*Liegenschaft!$O$24) | Z9: =IF(OR(D9="",Liegenschaft!$C$7=""),0,MAX(0,MIN(I9,Liegenschaft!$N$25)-MAX(H9,Liegenschaft!$M$25)+1)/DAY(Liegenschaft!$N$25)*Liegenschaft!$O$25)
B10: 5 | H10: =IF(D10="","",MAX(E10,Liegenschaft!$C$7)) | I10: =IF(D10="","",IF(F10="",Liegenschaft!$C$8,MIN(F10,Liegenschaft!$C$8))) | J10: =IF(D10="",0,MAX(0,I10-H10+1)) | K10: =IF(OR(D10="",Liegenschaft!$C$9=""),0,J10/Liegenschaft!$C$9) | L10: =IF(OR(D10="",Liegenschaft!$J$26=0),0,SUM(O10:Z10)/Liegenschaft!$J$26) | M10: =IF(D10="","",IF(ISNA(MATCH(C10,Liegenschaft!$B$14:$B$25,0)),"⚠ Wohnung unbekannt",IF(J10=0,"⚠ nicht in Periode",IF(SUMPRODUCT(($C$6:$C$35=C10)*($D$6:$D$35<>"")*($J$6:$J$35>0)*($H$6:$H$35<=I10)*($I$6:$I$35>=H10))>1,"⚠ Überschneidung mit anderem Mieter","✓")))) | O10: =IF(OR(D10="",Liegenschaft!$C$7=""),0,MAX(0,MIN(I10,Liegenschaft!$N$14)-MAX(H10,Liegenschaft!$M$14)+1)/DAY(Liegenschaft!$N$14)*Liegenschaft!$O$14) | P10: =IF(OR(D10="",Liegenschaft!$C$7=""),0,MAX(0,MIN(I10,Liegenschaft!$N$15)-MAX(H10,Liegenschaft!$M$15)+1)/DAY(Liegenschaft!$N$15)*Liegenschaft!$O$15) | Q10: =IF(OR(D10="",Liegenschaft!$C$7=""),0,MAX(0,MIN(I10,Liegenschaft!$N$16)-MAX(H10,Liegenschaft!$M$16)+1)/DAY(Liegenschaft!$N$16)*Liegenschaft!$O$16) | R10: =IF(OR(D10="",Liegenschaft!$C$7=""),0,MAX(0,MIN(I10,Liegenschaft!$N$17)-MAX(H10,Liegenschaft!$M$17)+1)/DAY(Liegenschaft!$N$17)*Liegenschaft!$O$17) | S10: =IF(OR(D10="",Liegenschaft!$C$7=""),0,MAX(0,MIN(I10,Liegenschaft!$N$18)-MAX(H10,Liegenschaft!$M$18)+1)/DAY(Liegenschaft!$N$18)*Liegenschaft!$O$18) | T10: =IF(OR(D10="",Liegenschaft!$C$7=""),0,MAX(0,MIN(I10,Liegenschaft!$N$19)-MAX(H10,Liegenschaft!$M$19)+1)/DAY(Liegenschaft!$N$19)*Liegenschaft!$O$19) | U10: =IF(OR(D10="",Liegenschaft!$C$7=""),0,MAX(0,MIN(I10,Liegenschaft!$N$20)-MAX(H10,Liegenschaft!$M$20)+1)/DAY(Liegenschaft!$N$20)*Liegenschaft!$O$20) | V10: =IF(OR(D10="",Liegenschaft!$C$7=""),0,MAX(0,MIN(I10,Liegenschaft!$N$21)-MAX(H10,Liegenschaft!$M$21)+1)/DAY(Liegenschaft!$N$21)*Liegenschaft!$O$21) | W10: =IF(OR(D10="",Liegenschaft!$C$7=""),0,MAX(0,MIN(I10,Liegenschaft!$N$22)-MAX(H10,Liegenschaft!$M$22)+1)/DAY(Liegenschaft!$N$22)*Liegenschaft!$O$22) | X10: =IF(OR(D10="",Liegenschaft!$C$7=""),0,MAX(0,MIN(I10,Liegenschaft!$N$23)-MAX(H10,Liegenschaft!$M$23)+1)/DAY(Liegenschaft!$N$23)*Liegenschaft!$O$23) | Y10: =IF(OR(D10="",Liegenschaft!$C$7=""),0,MAX(0,MIN(I10,Liegenschaft!$N$24)-MAX(H10,Liegenschaft!$M$24)+1)/DAY(Liegenschaft!$N$24)*Liegenschaft!$O$24) | Z10: =IF(OR(D10="",Liegenschaft!$C$7=""),0,MAX(0,MIN(I10,Liegenschaft!$N$25)-MAX(H10,Liegenschaft!$M$25)+1)/DAY(Liegenschaft!$N$25)*Liegenschaft!$O$25)
B11: 6 | H11: =IF(D11="","",MAX(E11,Liegenschaft!$C$7)) | I11: =IF(D11="","",IF(F11="",Liegenschaft!$C$8,MIN(F11,Liegenschaft!$C$8))) | J11: =IF(D11="",0,MAX(0,I11-H11+1)) | K11: =IF(OR(D11="",Liegenschaft!$C$9=""),0,J11/Liegenschaft!$C$9) | L11: =IF(OR(D11="",Liegenschaft!$J$26=0),0,SUM(O11:Z11)/Liegenschaft!$J$26) | M11: =IF(D11="","",IF(ISNA(MATCH(C11,Liegenschaft!$B$14:$B$25,0)),"⚠ Wohnung unbekannt",IF(J11=0,"⚠ nicht in Periode",IF(SUMPRODUCT(($C$6:$C$35=C11)*($D$6:$D$35<>"")*($J$6:$J$35>0)*($H$6:$H$35<=I11)*($I$6:$I$35>=H11))>1,"⚠ Überschneidung mit anderem Mieter","✓")))) | O11: =IF(OR(D11="",Liegenschaft!$C$7=""),0,MAX(0,MIN(I11,Liegenschaft!$N$14)-MAX(H11,Liegenschaft!$M$14)+1)/DAY(Liegenschaft!$N$14)*Liegenschaft!$O$14) | P11: =IF(OR(D11="",Liegenschaft!$C$7=""),0,MAX(0,MIN(I11,Liegenschaft!$N$15)-MAX(H11,Liegenschaft!$M$15)+1)/DAY(Liegenschaft!$N$15)*Liegenschaft!$O$15) | Q11: =IF(OR(D11="",Liegenschaft!$C$7=""),0,MAX(0,MIN(I11,Liegenschaft!$N$16)-MAX(H11,Liegenschaft!$M$16)+1)/DAY(Liegenschaft!$N$16)*Liegenschaft!$O$16) | R11: =IF(OR(D11="",Liegenschaft!$C$7=""),0,MAX(0,MIN(I11,Liegenschaft!$N$17)-MAX(H11,Liegenschaft!$M$17)+1)/DAY(Liegenschaft!$N$17)*Liegenschaft!$O$17) | S11: =IF(OR(D11="",Liegenschaft!$C$7=""),0,MAX(0,MIN(I11,Liegenschaft!$N$18)-MAX(H11,Liegenschaft!$M$18)+1)/DAY(Liegenschaft!$N$18)*Liegenschaft!$O$18) | T11: =IF(OR(D11="",Liegenschaft!$C$7=""),0,MAX(0,MIN(I11,Liegenschaft!$N$19)-MAX(H11,Liegenschaft!$M$19)+1)/DAY(Liegenschaft!$N$19)*Liegenschaft!$O$19) | U11: =IF(OR(D11="",Liegenschaft!$C$7=""),0,MAX(0,MIN(I11,Liegenschaft!$N$20)-MAX(H11,Liegenschaft!$M$20)+1)/DAY(Liegenschaft!$N$20)*Liegenschaft!$O$20) | V11: =IF(OR(D11="",Liegenschaft!$C$7=""),0,MAX(0,MIN(I11,Liegenschaft!$N$21)-MAX(H11,Liegenschaft!$M$21)+1)/DAY(Liegenschaft!$N$21)*Liegenschaft!$O$21) | W11: =IF(OR(D11="",Liegenschaft!$C$7=""),0,MAX(0,MIN(I11,Liegenschaft!$N$22)-MAX(H11,Liegenschaft!$M$22)+1)/DAY(Liegenschaft!$N$22)*Liegenschaft!$O$22) | X11: =IF(OR(D11="",Liegenschaft!$C$7=""),0,MAX(0,MIN(I11,Liegenschaft!$N$23)-MAX(H11,Liegenschaft!$M$23)+1)/DAY(Liegenschaft!$N$23)*Liegenschaft!$O$23) | Y11: =IF(OR(D11="",Liegenschaft!$C$7=""),0,MAX(0,MIN(I11,Liegenschaft!$N$24)-MAX(H11,Liegenschaft!$M$24)+1)/DAY(Liegenschaft!$N$24)*Liegenschaft!$O$24) | Z11: =IF(OR(D11="",Liegenschaft!$C$7=""),0,MAX(0,MIN(I11,Liegenschaft!$N$25)-MAX(H11,Liegenschaft!$M$25)+1)/DAY(Liegenschaft!$N$25)*Liegenschaft!$O$25)
B12: 7 | H12: =IF(D12="","",MAX(E12,Liegenschaft!$C$7)) | I12: =IF(D12="","",IF(F12="",Liegenschaft!$C$8,MIN(F12,Liegenschaft!$C$8))) | J12: =IF(D12="",0,MAX(0,I12-H12+1)) | K12: =IF(OR(D12="",Liegenschaft!$C$9=""),0,J12/Liegenschaft!$C$9) | L12: =IF(OR(D12="",Liegenschaft!$J$26=0),0,SUM(O12:Z12)/Liegenschaft!$J$26) | M12: =IF(D12="","",IF(ISNA(MATCH(C12,Liegenschaft!$B$14:$B$25,0)),"⚠ Wohnung unbekannt",IF(J12=0,"⚠ nicht in Periode",IF(SUMPRODUCT(($C$6:$C$35=C12)*($D$6:$D$35<>"")*($J$6:$J$35>0)*($H$6:$H$35<=I12)*($I$6:$I$35>=H12))>1,"⚠ Überschneidung mit anderem Mieter","✓")))) | O12: =IF(OR(D12="",Liegenschaft!$C$7=""),0,MAX(0,MIN(I12,Liegenschaft!$N$14)-MAX(H12,Liegenschaft!$M$14)+1)/DAY(Liegenschaft!$N$14)*Liegenschaft!$O$14) | P12: =IF(OR(D12="",Liegenschaft!$C$7=""),0,MAX(0,MIN(I12,Liegenschaft!$N$15)-MAX(H12,Liegenschaft!$M$15)+1)/DAY(Liegenschaft!$N$15)*Liegenschaft!$O$15) | Q12: =IF(OR(D12="",Liegenschaft!$C$7=""),0,MAX(0,MIN(I12,Liegenschaft!$N$16)-MAX(H12,Liegenschaft!$M$16)+1)/DAY(Liegenschaft!$N$16)*Liegenschaft!$O$16) | R12: =IF(OR(D12="",Liegenschaft!$C$7=""),0,MAX(0,MIN(I12,Liegenschaft!$N$17)-MAX(H12,Liegenschaft!$M$17)+1)/DAY(Liegenschaft!$N$17)*Liegenschaft!$O$17) | S12: =IF(OR(D12="",Liegenschaft!$C$7=""),0,MAX(0,MIN(I12,Liegenschaft!$N$18)-MAX(H12,Liegenschaft!$M$18)+1)/DAY(Liegenschaft!$N$18)*Liegenschaft!$O$18) | T12: =IF(OR(D12="",Liegenschaft!$C$7=""),0,MAX(0,MIN(I12,Liegenschaft!$N$19)-MAX(H12,Liegenschaft!$M$19)+1)/DAY(Liegenschaft!$N$19)*Liegenschaft!$O$19) | U12: =IF(OR(D12="",Liegenschaft!$C$7=""),0,MAX(0,MIN(I12,Liegenschaft!$N$20)-MAX(H12,Liegenschaft!$M$20)+1)/DAY(Liegenschaft!$N$20)*Liegenschaft!$O$20) | V12: =IF(OR(D12="",Liegenschaft!$C$7=""),0,MAX(0,MIN(I12,Liegenschaft!$N$21)-MAX(H12,Liegenschaft!$M$21)+1)/DAY(Liegenschaft!$N$21)*Liegenschaft!$O$21) | W12: =IF(OR(D12="",Liegenschaft!$C$7=""),0,MAX(0,MIN(I12,Liegenschaft!$N$22)-MAX(H12,Liegenschaft!$M$22)+1)/DAY(Liegenschaft!$N$22)*Liegenschaft!$O$22) | X12: =IF(OR(D12="",Liegenschaft!$C$7=""),0,MAX(0,MIN(I12,Liegenschaft!$N$23)-MAX(H12,Liegenschaft!$M$23)+1)/DAY(Liegenschaft!$N$23)*Liegenschaft!$O$23) | Y12: =IF(OR(D12="",Liegenschaft!$C$7=""),0,MAX(0,MIN(I12,Liegenschaft!$N$24)-MAX(H12,Liegenschaft!$M$24)+1)/DAY(Liegenschaft!$N$24)*Liegenschaft!$O$24) | Z12: =IF(OR(D12="",Liegenschaft!$C$7=""),0,MAX(0,MIN(I12,Liegenschaft!$N$25)-MAX(H12,Liegenschaft!$M$25)+1)/DAY(Liegenschaft!$N$25)*Liegenschaft!$O$25)
B13: 8 | H13: =IF(D13="","",MAX(E13,Liegenschaft!$C$7)) | I13: =IF(D13="","",IF(F13="",Liegenschaft!$C$8,MIN(F13,Liegenschaft!$C$8))) | J13: =IF(D13="",0,MAX(0,I13-H13+1)) | K13: =IF(OR(D13="",Liegenschaft!$C$9=""),0,J13/Liegenschaft!$C$9) | L13: =IF(OR(D13="",Liegenschaft!$J$26=0),0,SUM(O13:Z13)/Liegenschaft!$J$26) | M13: =IF(D13="","",IF(ISNA(MATCH(C13,Liegenschaft!$B$14:$B$25,0)),"⚠ Wohnung unbekannt",IF(J13=0,"⚠ nicht in Periode",IF(SUMPRODUCT(($C$6:$C$35=C13)*($D$6:$D$35<>"")*($J$6:$J$35>0)*($H$6:$H$35<=I13)*($I$6:$I$35>=H13))>1,"⚠ Überschneidung mit anderem Mieter","✓")))) | O13: =IF(OR(D13="",Liegenschaft!$C$7=""),0,MAX(0,MIN(I13,Liegenschaft!$N$14)-MAX(H13,Liegenschaft!$M$14)+1)/DAY(Liegenschaft!$N$14)*Liegenschaft!$O$14) | P13: =IF(OR(D13="",Liegenschaft!$C$7=""),0,MAX(0,MIN(I13,Liegenschaft!$N$15)-MAX(H13,Liegenschaft!$M$15)+1)/DAY(Liegenschaft!$N$15)*Liegenschaft!$O$15) | Q13: =IF(OR(D13="",Liegenschaft!$C$7=""),0,MAX(0,MIN(I13,Liegenschaft!$N$16)-MAX(H13,Liegenschaft!$M$16)+1)/DAY(Liegenschaft!$N$16)*Liegenschaft!$O$16) | R13: =IF(OR(D13="",Liegenschaft!$C$7=""),0,MAX(0,MIN(I13,Liegenschaft!$N$17)-MAX(H13,Liegenschaft!$M$17)+1)/DAY(Liegenschaft!$N$17)*Liegenschaft!$O$17) | S13: =IF(OR(D13="",Liegenschaft!$C$7=""),0,MAX(0,MIN(I13,Liegenschaft!$N$18)-MAX(H13,Liegenschaft!$M$18)+1)/DAY(Liegenschaft!$N$18)*Liegenschaft!$O$18) | T13: =IF(OR(D13="",Liegenschaft!$C$7=""),0,MAX(0,MIN(I13,Liegenschaft!$N$19)-MAX(H13,Liegenschaft!$M$19)+1)/DAY(Liegenschaft!$N$19)*Liegenschaft!$O$19) | U13: =IF(OR(D13="",Liegenschaft!$C$7=""),0,MAX(0,MIN(I13,Liegenschaft!$N$20)-MAX(H13,Liegenschaft!$M$20)+1)/DAY(Liegenschaft!$N$20)*Liegenschaft!$O$20) | V13: =IF(OR(D13="",Liegenschaft!$C$7=""),0,MAX(0,MIN(I13,Liegenschaft!$N$21)-MAX(H13,Liegenschaft!$M$21)+1)/DAY(Liegenschaft!$N$21)*Liegenschaft!$O$21) | W13: =IF(OR(D13="",Liegenschaft!$C$7=""),0,MAX(0,MIN(I13,Liegenschaft!$N$22)-MAX(H13,Liegenschaft!$M$22)+1)/DAY(Liegenschaft!$N$22)*Liegenschaft!$O$22) | X13: =IF(OR(D13="",Liegenschaft!$C$7=""),0,MAX(0,MIN(I13,Liegenschaft!$N$23)-MAX(H13,Liegenschaft!$M$23)+1)/DAY(Liegenschaft!$N$23)*Liegenschaft!$O$23) | Y13: =IF(OR(D13="",Liegenschaft!$C$7=""),0,MAX(0,MIN(I13,Liegenschaft!$N$24)-MAX(H13,Liegenschaft!$M$24)+1)/DAY(Liegenschaft!$N$24)*Liegenschaft!$O$24) | Z13: =IF(OR(D13="",Liegenschaft!$C$7=""),0,MAX(0,MIN(I13,Liegenschaft!$N$25)-MAX(H13,Liegenschaft!$M$25)+1)/DAY(Liegenschaft!$N$25)*Liegenschaft!$O$25)
B14: 9 | H14: =IF(D14="","",MAX(E14,Liegenschaft!$C$7)) | I14: =IF(D14="","",IF(F14="",Liegenschaft!$C$8,MIN(F14,Liegenschaft!$C$8))) | J14: =IF(D14="",0,MAX(0,I14-H14+1)) | K14: =IF(OR(D14="",Liegenschaft!$C$9=""),0,J14/Liegenschaft!$C$9) | L14: =IF(OR(D14="",Liegenschaft!$J$26=0),0,SUM(O14:Z14)/Liegenschaft!$J$26) | M14: =IF(D14="","",IF(ISNA(MATCH(C14,Liegenschaft!$B$14:$B$25,0)),"⚠ Wohnung unbekannt",IF(J14=0,"⚠ nicht in Periode",IF(SUMPRODUCT(($C$6:$C$35=C14)*($D$6:$D$35<>"")*($J$6:$J$35>0)*($H$6:$H$35<=I14)*($I$6:$I$35>=H14))>1,"⚠ Überschneidung mit anderem Mieter","✓")))) | O14: =IF(OR(D14="",Liegenschaft!$C$7=""),0,MAX(0,MIN(I14,Liegenschaft!$N$14)-MAX(H14,Liegenschaft!$M$14)+1)/DAY(Liegenschaft!$N$14)*Liegenschaft!$O$14) | P14: =IF(OR(D14="",Liegenschaft!$C$7=""),0,MAX(0,MIN(I14,Liegenschaft!$N$15)-MAX(H14,Liegenschaft!$M$15)+1)/DAY(Liegenschaft!$N$15)*Liegenschaft!$O$15) | Q14: =IF(OR(D14="",Liegenschaft!$C$7=""),0,MAX(0,MIN(I14,Liegenschaft!$N$16)-MAX(H14,Liegenschaft!$M$16)+1)/DAY(Liegenschaft!$N$16)*Liegenschaft!$O$16) | R14: =IF(OR(D14="",Liegenschaft!$C$7=""),0,MAX(0,MIN(I14,Liegenschaft!$N$17)-MAX(H14,Liegenschaft!$M$17)+1)/DAY(Liegenschaft!$N$17)*Liegenschaft!$O$17) | S14: =IF(OR(D14="",Liegenschaft!$C$7=""),0,MAX(0,MIN(I14,Liegenschaft!$N$18)-MAX(H14,Liegenschaft!$M$18)+1)/DAY(Liegenschaft!$N$18)*Liegenschaft!$O$18) | T14: =IF(OR(D14="",Liegenschaft!$C$7=""),0,MAX(0,MIN(I14,Liegenschaft!$N$19)-MAX(H14,Liegenschaft!$M$19)+1)/DAY(Liegenschaft!$N$19)*Liegenschaft!$O$19) | U14: =IF(OR(D14="",Liegenschaft!$C$7=""),0,MAX(0,MIN(I14,Liegenschaft!$N$20)-MAX(H14,Liegenschaft!$M$20)+1)/DAY(Liegenschaft!$N$20)*Liegenschaft!$O$20) | V14: =IF(OR(D14="",Liegenschaft!$C$7=""),0,MAX(0,MIN(I14,Liegenschaft!$N$21)-MAX(H14,Liegenschaft!$M$21)+1)/DAY(Liegenschaft!$N$21)*Liegenschaft!$O$21) | W14: =IF(OR(D14="",Liegenschaft!$C$7=""),0,MAX(0,MIN(I14,Liegenschaft!$N$22)-MAX(H14,Liegenschaft!$M$22)+1)/DAY(Liegenschaft!$N$22)*Liegenschaft!$O$22) | X14: =IF(OR(D14="",Liegenschaft!$C$7=""),0,MAX(0,MIN(I14,Liegenschaft!$N$23)-MAX(H14,Liegenschaft!$M$23)+1)/DAY(Liegenschaft!$N$23)*Liegenschaft!$O$23) | Y14: =IF(OR(D14="",Liegenschaft!$C$7=""),0,MAX(0,MIN(I14,Liegenschaft!$N$24)-MAX(H14,Liegenschaft!$M$24)+1)/DAY(Liegenschaft!$N$24)*Liegenschaft!$O$24) | Z14: =IF(OR(D14="",Liegenschaft!$C$7=""),0,MAX(0,MIN(I14,Liegenschaft!$N$25)-MAX(H14,Liegenschaft!$M$25)+1)/DAY(Liegenschaft!$N$25)*Liegenschaft!$O$25)
B15: 10 | H15: =IF(D15="","",MAX(E15,Liegenschaft!$C$7)) | I15: =IF(D15="","",IF(F15="",Liegenschaft!$C$8,MIN(F15,Liegenschaft!$C$8))) | J15: =IF(D15="",0,MAX(0,I15-H15+1)) | K15: =IF(OR(D15="",Liegenschaft!$C$9=""),0,J15/Liegenschaft!$C$9) | L15: =IF(OR(D15="",Liegenschaft!$J$26=0),0,SUM(O15:Z15)/Liegenschaft!$J$26) | M15: =IF(D15="","",IF(ISNA(MATCH(C15,Liegenschaft!$B$14:$B$25,0)),"⚠ Wohnung unbekannt",IF(J15=0,"⚠ nicht in Periode",IF(SUMPRODUCT(($C$6:$C$35=C15)*($D$6:$D$35<>"")*($J$6:$J$35>0)*($H$6:$H$35<=I15)*($I$6:$I$35>=H15))>1,"⚠ Überschneidung mit anderem Mieter","✓")))) | O15: =IF(OR(D15="",Liegenschaft!$C$7=""),0,MAX(0,MIN(I15,Liegenschaft!$N$14)-MAX(H15,Liegenschaft!$M$14)+1)/DAY(Liegenschaft!$N$14)*Liegenschaft!$O$14) | P15: =IF(OR(D15="",Liegenschaft!$C$7=""),0,MAX(0,MIN(I15,Liegenschaft!$N$15)-MAX(H15,Liegenschaft!$M$15)+1)/DAY(Liegenschaft!$N$15)*Liegenschaft!$O$15) | Q15: =IF(OR(D15="",Liegenschaft!$C$7=""),0,MAX(0,MIN(I15,Liegenschaft!$N$16)-MAX(H15,Liegenschaft!$M$16)+1)/DAY(Liegenschaft!$N$16)*Liegenschaft!$O$16) | R15: =IF(OR(D15="",Liegenschaft!$C$7=""),0,MAX(0,MIN(I15,Liegenschaft!$N$17)-MAX(H15,Liegenschaft!$M$17)+1)/DAY(Liegenschaft!$N$17)*Liegenschaft!$O$17) | S15: =IF(OR(D15="",Liegenschaft!$C$7=""),0,MAX(0,MIN(I15,Liegenschaft!$N$18)-MAX(H15,Liegenschaft!$M$18)+1)/DAY(Liegenschaft!$N$18)*Liegenschaft!$O$18) | T15: =IF(OR(D15="",Liegenschaft!$C$7=""),0,MAX(0,MIN(I15,Liegenschaft!$N$19)-MAX(H15,Liegenschaft!$M$19)+1)/DAY(Liegenschaft!$N$19)*Liegenschaft!$O$19) | U15: =IF(OR(D15="",Liegenschaft!$C$7=""),0,MAX(0,MIN(I15,Liegenschaft!$N$20)-MAX(H15,Liegenschaft!$M$20)+1)/DAY(Liegenschaft!$N$20)*Liegenschaft!$O$20) | V15: =IF(OR(D15="",Liegenschaft!$C$7=""),0,MAX(0,MIN(I15,Liegenschaft!$N$21)-MAX(H15,Liegenschaft!$M$21)+1)/DAY(Liegenschaft!$N$21)*Liegenschaft!$O$21) | W15: =IF(OR(D15="",Liegenschaft!$C$7=""),0,MAX(0,MIN(I15,Liegenschaft!$N$22)-MAX(H15,Liegenschaft!$M$22)+1)/DAY(Liegenschaft!$N$22)*Liegenschaft!$O$22) | X15: =IF(OR(D15="",Liegenschaft!$C$7=""),0,MAX(0,MIN(I15,Liegenschaft!$N$23)-MAX(H15,Liegenschaft!$M$23)+1)/DAY(Liegenschaft!$N$23)*Liegenschaft!$O$23) | Y15: =IF(OR(D15="",Liegenschaft!$C$7=""),0,MAX(0,MIN(I15,Liegenschaft!$N$24)-MAX(H15,Liegenschaft!$M$24)+1)/DAY(Liegenschaft!$N$24)*Liegenschaft!$O$24) | Z15: =IF(OR(D15="",Liegenschaft!$C$7=""),0,MAX(0,MIN(I15,Liegenschaft!$N$25)-MAX(H15,Liegenschaft!$M$25)+1)/DAY(Liegenschaft!$N$25)*Liegenschaft!$O$25)
B16: 11 | H16: =IF(D16="","",MAX(E16,Liegenschaft!$C$7)) | I16: =IF(D16="","",IF(F16="",Liegenschaft!$C$8,MIN(F16,Liegenschaft!$C$8))) | J16: =IF(D16="",0,MAX(0,I16-H16+1)) | K16: =IF(OR(D16="",Liegenschaft!$C$9=""),0,J16/Liegenschaft!$C$9) | L16: =IF(OR(D16="",Liegenschaft!$J$26=0),0,SUM(O16:Z16)/Liegenschaft!$J$26) | M16: =IF(D16="","",IF(ISNA(MATCH(C16,Liegenschaft!$B$14:$B$25,0)),"⚠ Wohnung unbekannt",IF(J16=0,"⚠ nicht in Periode",IF(SUMPRODUCT(($C$6:$C$35=C16)*($D$6:$D$35<>"")*($J$6:$J$35>0)*($H$6:$H$35<=I16)*($I$6:$I$35>=H16))>1,"⚠ Überschneidung mit anderem Mieter","✓")))) | O16: =IF(OR(D16="",Liegenschaft!$C$7=""),0,MAX(0,MIN(I16,Liegenschaft!$N$14)-MAX(H16,Liegenschaft!$M$14)+1)/DAY(Liegenschaft!$N$14)*Liegenschaft!$O$14) | P16: =IF(OR(D16="",Liegenschaft!$C$7=""),0,MAX(0,MIN(I16,Liegenschaft!$N$15)-MAX(H16,Liegenschaft!$M$15)+1)/DAY(Liegenschaft!$N$15)*Liegenschaft!$O$15) | Q16: =IF(OR(D16="",Liegenschaft!$C$7=""),0,MAX(0,MIN(I16,Liegenschaft!$N$16)-MAX(H16,Liegenschaft!$M$16)+1)/DAY(Liegenschaft!$N$16)*Liegenschaft!$O$16) | R16: =IF(OR(D16="",Liegenschaft!$C$7=""),0,MAX(0,MIN(I16,Liegenschaft!$N$17)-MAX(H16,Liegenschaft!$M$17)+1)/DAY(Liegenschaft!$N$17)*Liegenschaft!$O$17) | S16: =IF(OR(D16="",Liegenschaft!$C$7=""),0,MAX(0,MIN(I16,Liegenschaft!$N$18)-MAX(H16,Liegenschaft!$M$18)+1)/DAY(Liegenschaft!$N$18)*Liegenschaft!$O$18) | T16: =IF(OR(D16="",Liegenschaft!$C$7=""),0,MAX(0,MIN(I16,Liegenschaft!$N$19)-MAX(H16,Liegenschaft!$M$19)+1)/DAY(Liegenschaft!$N$19)*Liegenschaft!$O$19) | U16: =IF(OR(D16="",Liegenschaft!$C$7=""),0,MAX(0,MIN(I16,Liegenschaft!$N$20)-MAX(H16,Liegenschaft!$M$20)+1)/DAY(Liegenschaft!$N$20)*Liegenschaft!$O$20) | V16: =IF(OR(D16="",Liegenschaft!$C$7=""),0,MAX(0,MIN(I16,Liegenschaft!$N$21)-MAX(H16,Liegenschaft!$M$21)+1)/DAY(Liegenschaft!$N$21)*Liegenschaft!$O$21) | W16: =IF(OR(D16="",Liegenschaft!$C$7=""),0,MAX(0,MIN(I16,Liegenschaft!$N$22)-MAX(H16,Liegenschaft!$M$22)+1)/DAY(Liegenschaft!$N$22)*Liegenschaft!$O$22) | X16: =IF(OR(D16="",Liegenschaft!$C$7=""),0,MAX(0,MIN(I16,Liegenschaft!$N$23)-MAX(H16,Liegenschaft!$M$23)+1)/DAY(Liegenschaft!$N$23)*Liegenschaft!$O$23) | Y16: =IF(OR(D16="",Liegenschaft!$C$7=""),0,MAX(0,MIN(I16,Liegenschaft!$N$24)-MAX(H16,Liegenschaft!$M$24)+1)/DAY(Liegenschaft!$N$24)*Liegenschaft!$O$24) | Z16: =IF(OR(D16="",Liegenschaft!$C$7=""),0,MAX(0,MIN(I16,Liegenschaft!$N$25)-MAX(H16,Liegenschaft!$M$25)+1)/DAY(Liegenschaft!$N$25)*Liegenschaft!$O$25)
B17: 12 | H17: =IF(D17="","",MAX(E17,Liegenschaft!$C$7)) | I17: =IF(D17="","",IF(F17="",Liegenschaft!$C$8,MIN(F17,Liegenschaft!$C$8))) | J17: =IF(D17="",0,MAX(0,I17-H17+1)) | K17: =IF(OR(D17="",Liegenschaft!$C$9=""),0,J17/Liegenschaft!$C$9) | L17: =IF(OR(D17="",Liegenschaft!$J$26=0),0,SUM(O17:Z17)/Liegenschaft!$J$26) | M17: =IF(D17="","",IF(ISNA(MATCH(C17,Liegenschaft!$B$14:$B$25,0)),"⚠ Wohnung unbekannt",IF(J17=0,"⚠ nicht in Periode",IF(SUMPRODUCT(($C$6:$C$35=C17)*($D$6:$D$35<>"")*($J$6:$J$35>0)*($H$6:$H$35<=I17)*($I$6:$I$35>=H17))>1,"⚠ Überschneidung mit anderem Mieter","✓")))) | O17: =IF(OR(D17="",Liegenschaft!$C$7=""),0,MAX(0,MIN(I17,Liegenschaft!$N$14)-MAX(H17,Liegenschaft!$M$14)+1)/DAY(Liegenschaft!$N$14)*Liegenschaft!$O$14) | P17: =IF(OR(D17="",Liegenschaft!$C$7=""),0,MAX(0,MIN(I17,Liegenschaft!$N$15)-MAX(H17,Liegenschaft!$M$15)+1)/DAY(Liegenschaft!$N$15)*Liegenschaft!$O$15) | Q17: =IF(OR(D17="",Liegenschaft!$C$7=""),0,MAX(0,MIN(I17,Liegenschaft!$N$16)-MAX(H17,Liegenschaft!$M$16)+1)/DAY(Liegenschaft!$N$16)*Liegenschaft!$O$16) | R17: =IF(OR(D17="",Liegenschaft!$C$7=""),0,MAX(0,MIN(I17,Liegenschaft!$N$17)-MAX(H17,Liegenschaft!$M$17)+1)/DAY(Liegenschaft!$N$17)*Liegenschaft!$O$17) | S17: =IF(OR(D17="",Liegenschaft!$C$7=""),0,MAX(0,MIN(I17,Liegenschaft!$N$18)-MAX(H17,Liegenschaft!$M$18)+1)/DAY(Liegenschaft!$N$18)*Liegenschaft!$O$18) | T17: =IF(OR(D17="",Liegenschaft!$C$7=""),0,MAX(0,MIN(I17,Liegenschaft!$N$19)-MAX(H17,Liegenschaft!$M$19)+1)/DAY(Liegenschaft!$N$19)*Liegenschaft!$O$19) | U17: =IF(OR(D17="",Liegenschaft!$C$7=""),0,MAX(0,MIN(I17,Liegenschaft!$N$20)-MAX(H17,Liegenschaft!$M$20)+1)/DAY(Liegenschaft!$N$20)*Liegenschaft!$O$20) | V17: =IF(OR(D17="",Liegenschaft!$C$7=""),0,MAX(0,MIN(I17,Liegenschaft!$N$21)-MAX(H17,Liegenschaft!$M$21)+1)/DAY(Liegenschaft!$N$21)*Liegenschaft!$O$21) | W17: =IF(OR(D17="",Liegenschaft!$C$7=""),0,MAX(0,MIN(I17,Liegenschaft!$N$22)-MAX(H17,Liegenschaft!$M$22)+1)/DAY(Liegenschaft!$N$22)*Liegenschaft!$O$22) | X17: =IF(OR(D17="",Liegenschaft!$C$7=""),0,MAX(0,MIN(I17,Liegenschaft!$N$23)-MAX(H17,Liegenschaft!$M$23)+1)/DAY(Liegenschaft!$N$23)*Liegenschaft!$O$23) | Y17: =IF(OR(D17="",Liegenschaft!$C$7=""),0,MAX(0,MIN(I17,Liegenschaft!$N$24)-MAX(H17,Liegenschaft!$M$24)+1)/DAY(Liegenschaft!$N$24)*Liegenschaft!$O$24) | Z17: =IF(OR(D17="",Liegenschaft!$C$7=""),0,MAX(0,MIN(I17,Liegenschaft!$N$25)-MAX(H17,Liegenschaft!$M$25)+1)/DAY(Liegenschaft!$N$25)*Liegenschaft!$O$25)
... B35: 30 | H35: =IF(D35="","",MAX(E35,Liegenschaft!$C$7)) | I35: =IF(D35="","",IF(F35="",Liegenschaft!$C$8,MIN(F35,Liegenschaft!$C$8))) | J35: =IF(D35="",0,MAX(0,I35-H35+1)) | K35: =IF(OR(D35="",Liegenschaft!$C$9=""),0,J35/Liegenschaft!$C$9) | L35: =IF(OR(D35="",Liegenschaft!$J$26=0),0,SUM(O35:Z35)/Liegenschaft!$J$26) | M35: =IF(D35="","",IF(ISNA(MATCH(C35,Liegenschaft!$B$14:$B$25,0)),"⚠ Wohnung unbekannt",IF(J35=0,"⚠ nicht in Periode",IF(SUMPRODUCT(($C$6:$C$35=C35)*($D$6:$D$35<>"")*($J$6:$J$35>0)*($H$6:$H$35<=I35)*($I$6:$I$35>=H35))>1,"⚠ Überschneidung mit anderem Mieter","✓")))) | O35: =IF(OR(D35="",Liegenschaft!$C$7=""),0,MAX(0,MIN(I35,Liegenschaft!$N$14)-MAX(H35,Liegenschaft!$M$14)+1)/DAY(Liegenschaft!$N$14)*Liegenschaft!$O$14) | P35: =IF(OR(D35="",Liegenschaft!$C$7=""),0,MAX(0,MIN(I35,Liegenschaft!$N$15)-MAX(H35,Liegenschaft!$M$15)+1)/DAY(Liegenschaft!$N$15)*Liegenschaft!$O$15) | Q35: =IF(OR(D35="",Liegenschaft!$C$7=""),0,MAX(0,MIN(I35,Liegenschaft!$N$16)-MAX(H35,Liegenschaft!$M$16)+1)/DAY(Liegenschaft!$N$16)*Liegenschaft!$O$16) | R35: =IF(OR(D35="",Liegenschaft!$C$7=""),0,MAX(0,MIN(I35,Liegenschaft!$N$17)-MAX(H35,Liegenschaft!$M$17)+1)/DAY(Liegenschaft!$N$17)*Liegenschaft!$O$17) | S35: =IF(OR(D35="",Liegenschaft!$C$7=""),0,MAX(0,MIN(I35,Liegenschaft!$N$18)-MAX(H35,Liegenschaft!$M$18)+1)/DAY(Liegenschaft!$N$18)*Liegenschaft!$O$18) | T35: =IF(OR(D35="",Liegenschaft!$C$7=""),0,MAX(0,MIN(I35,Liegenschaft!$N$19)-MAX(H35,Liegenschaft!$M$19)+1)/DAY(Liegenschaft!$N$19)*Liegenschaft!$O$19) | U35: =IF(OR(D35="",Liegenschaft!$C$7=""),0,MAX(0,MIN(I35,Liegenschaft!$N$20)-MAX(H35,Liegenschaft!$M$20)+1)/DAY(Liegenschaft!$N$20)*Liegenschaft!$O$20) | V35: =IF(OR(D35="",Liegenschaft!$C$7=""),0,MAX(0,MIN(I35,Liegenschaft!$N$21)-MAX(H35,Liegenschaft!$M$21)+1)/DAY(Liegenschaft!$N$21)*Liegenschaft!$O$21) | W35: =IF(OR(D35="",Liegenschaft!$C$7=""),0,MAX(0,MIN(I35,Liegenschaft!$N$22)-MAX(H35,Liegenschaft!$M$22)+1)/DAY(Liegenschaft!$N$22)*Liegenschaft!$O$22) | X35: =IF(OR(D35="",Liegenschaft!$C$7=""),0,MAX(0,MIN(I35,Liegenschaft!$N$23)-MAX(H35,Liegenschaft!$M$23)+1)/DAY(Liegenschaft!$N$23)*Liegenschaft!$O$23) | Y35: =IF(OR(D35="",Liegenschaft!$C$7=""),0,MAX(0,MIN(I35,Liegenschaft!$N$24)-MAX(H35,Liegenschaft!$M$24)+1)/DAY(Liegenschaft!$N$24)*Liegenschaft!$O$24) | Z35: =IF(OR(D35="",Liegenschaft!$C$7=""),0,MAX(0,MIN(I35,Liegenschaft!$N$25)-MAX(H35,Liegenschaft!$M$25)+1)/DAY(Liegenschaft!$N$25)*Liegenschaft!$O$25)

Sheet Kosten
B2: Nebenkosten der Periode
B3: Rechnungsbeträge der ganzen Liegenschaft erfassen. Nur Positionen mit «Ja» / «Ja» werden den Mietern belastet.
B5: Kostenposition | C5: Betrag CHF | D5: Art | E5: Verteilschlüssel | F5: Im Mietvertrag ausgeschieden? | G5: Umlagefähig? | H5: Abrechenbar
H6: =IF(OR(B6="",C6=""),"",IF(AND(F6="Ja",G6="Ja",D6<>"",E6<>""),"Ja","Nein")) | I6: =IF(E6="",1,MATCH(E6,{"Fläche m²","Zimmer","Wertquote","Volumen m³","pro Einheit gleich"},0)) | J6: Hinweise
H7: =IF(OR(B7="",C7=""),"",IF(AND(F7="Ja",G7="Ja",D7<>"",E7<>""),"Ja","Nein")) | I7: =IF(E7="",1,MATCH(E7,{"Fläche m²","Zimmer","Wertquote","Volumen m³","pro Einheit gleich"},0)) | J7: Umlagefähig sind nur Betriebskosten (Heizung, Warmwasser, Wasser, Abwasser, Allgemeinstrom, Hauswart, Kehricht, Lift-Service …).
H8: =IF(OR(B8="",C8=""),"",IF(AND(F8="Ja",G8="Ja",D8<>"",E8<>""),"Ja","Nein")) | I8: =IF(E8="",1,MATCH(E8,{"Fläche m²","Zimmer","Wertquote","Volumen m³","pro Einheit gleich"},0)) | J8: NICHT umlagefähig: Reparaturen, Unterhalt, Erneuerungen, Hypothekarzinsen, Gebäudeversicherung (Praxis), Abschreibungen.
H9: =IF(OR(B9="",C9=""),"",IF(AND(F9="Ja",G9="Ja",D9<>"",E9<>""),"Ja","Nein")) | I9: =IF(E9="",1,MATCH(E9,{"Fläche m²","Zimmer","Wertquote","Volumen m³","pro Einheit gleich"},0)) | J9: Nebenkosten dürfen nur belastet werden, wenn sie im Mietvertrag einzeln ausgeschieden sind (Art. 257a Abs. 2 OR).
H10: =IF(OR(B10="",C10=""),"",IF(AND(F10="Ja",G10="Ja",D10<>"",E10<>""),"Ja","Nein")) | I10: =IF(E10="",1,MATCH(E10,{"Fläche m²","Zimmer","Wertquote","Volumen m³","pro Einheit gleich"},0)) | J10: Heizung/Warmwasser wird nach Heizgradtagen verteilt, alles andere zeitanteilig nach Tagen.
H11: =IF(OR(B11="",C11=""),"",IF(AND(F11="Ja",G11="Ja",D11<>"",E11<>""),"Ja","Nein")) | I11: =IF(E11="",1,MATCH(E11,{"Fläche m²","Zimmer","Wertquote","Volumen m³","pro Einheit gleich"},0))
H12: =IF(OR(B12="",C12=""),"",IF(AND(F12="Ja",G12="Ja",D12<>"",E12<>""),"Ja","Nein")) | I12: =IF(E12="",1,MATCH(E12,{"Fläche m²","Zimmer","Wertquote","Volumen m³","pro Einheit gleich"},0))
H13: =IF(OR(B13="",C13=""),"",IF(AND(F13="Ja",G13="Ja",D13<>"",E13<>""),"Ja","Nein")) | I13: =IF(E13="",1,MATCH(E13,{"Fläche m²","Zimmer","Wertquote","Volumen m³","pro Einheit gleich"},0))
H14: =IF(OR(B14="",C14=""),"",IF(AND(F14="Ja",G14="Ja",D14<>"",E14<>""),"Ja","Nein")) | I14: =IF(E14="",1,MATCH(E14,{"Fläche m²","Zimmer","Wertquote","Volumen m³","pro Einheit gleich"},0))
H15: =IF(OR(B15="",C15=""),"",IF(AND(F15="Ja",G15="Ja",D15<>"",E15<>""),"Ja","Nein")) | I15: =IF(E15="",1,MATCH(E15,{"Fläche m²","Zimmer","Wertquote","Volumen m³","pro Einheit gleich"},0))
H16: =IF(OR(B16="",C16=""),"",IF(AND(F16="Ja",G16="Ja",D16<>"",E16<>""),"Ja","Nein")) | I16: =IF(E16="",1,MATCH(E16,{"Fläche m²","Zimmer","Wertquote","Volumen m³","pro Einheit gleich"},0))
H17: =IF(OR(B17="",C17=""),"",IF(AND(F17="Ja",G17="Ja",D17<>"",E17<>""),"Ja","Nein")) | I17: =IF(E17="",1,MATCH(E17,{"Fläche m²","Zimmer","Wertquote","Volumen m³","pro Einheit gleich"},0))
H18: =IF(OR(B18="",C18=""),"",IF(AND(F18="Ja",G18="Ja",D18<>"",E18<>""),"Ja","Nein")) | I18: =IF(E18="",1,MATCH(E18,{"Fläche m²","Zimmer","Wertquote","Volumen m³","pro Einheit gleich"},0))
H19: =IF(OR(B19="",C19=""),"",IF(AND(F19="Ja",G19="Ja",D19<>"",E19<>""),"Ja","Nein")) | I19: =IF(E19="",1,MATCH(E19,{"Fläche m²","Zimmer","Wertquote","Volumen m³","pro Einheit gleich"},0))
H20: =IF(OR(B20="",C20=""),"",IF(AND(F20="Ja",G20="Ja",D20<>"",E20<>""),"Ja","Nein")) | I20: =IF(E20="",1,MATCH(E20,{"Fläche m²","Zimmer","Wertquote","Volumen m³","pro Einheit gleich"},0))
H21: =IF(OR(B21="",C21=""),"",IF(AND(F21="Ja",G21="Ja",D21<>"",E21<>""),"Ja","Nein")) | I21: =IF(E21="",1,MATCH(E21,{"Fläche m²","Zimmer","Wertquote","Volumen m³","pro Einheit gleich"},0))
H22: =IF(OR(B22="",C22=""),"",IF(AND(F22="Ja",G22="Ja",D22<>"",E22<>""),"Ja","Nein")) | I22: =IF(E22="",1,MATCH(E22,{"Fläche m²","Zimmer","Wertquote","Volumen m³","pro Einheit gleich"},0))
... H25: =IF(OR(B25="",C25=""),"",IF(AND(F25="Ja",G25="Ja",D25<>"",E25<>""),"Ja","Nein")) | I25: =IF(E25="",1,MATCH(E25,{"Fläche m²","Zimmer","Wertquote","Volumen m³","pro Einheit gleich"},0))
B26: Total erfasste Kosten | C26: =SUM(C6:C25)
B27: davon abrechenbar | C27: =SUMIF(H6:H25,"Ja",C6:C25)
B28: nicht abrechenbar (trägt Vermieter) | C28: =C26-C27

Sheet Verteilung
B2: Verteilung auf die Mietverhältnisse
B3: Wird automatisch berechnet. Zeilen = Mieter (wie Blatt «Mieter»), Spalten = Kostenpositionen.
B5: Nr | C5: Mieter/in | D5: =IF(Kosten!B6="","Pos. 1",Kosten!B6) | E5: =IF(Kosten!B7="","Pos. 2",Kosten!B7) | F5: =IF(Kosten!B8="","Pos. 3",Kosten!B8) | G5: =IF(Kosten!B9="","Pos. 4",Kosten!B9) | H5: =IF(Kosten!B10="","Pos. 5",Kosten!B10) | I5: =IF(Kosten!B11="","Pos. 6",Kosten!B11) | J5: =IF(Kosten!B12="","Pos. 7",Kosten!B12) | K5: =IF(Kosten!B13="","Pos. 8",Kosten!B13) | L5: =IF(Kosten!B14="","Pos. 9",Kosten!B14) | M5: =IF(Kosten!B15="","Pos. 10",Kosten!B15) | N5: =IF(Kosten!B16="","Pos. 11",Kosten!B16) | O5: =IF(Kosten!B17="","Pos. 12",Kosten!B17) | P5: =IF(Kosten!B18="","Pos. 13",Kosten!B18) | Q5: =IF(Kosten!B19="","Pos. 14",Kosten!B19) | R5: =IF(Kosten!B20="","Pos. 15",Kosten!B20) | S5: =IF(Kosten!B21="","Pos. 16",Kosten!B21) | T5: =IF(Kosten!B22="","Pos. 17",Kosten!B22) | U5: =IF(Kosten!B23="","Pos. 18",Kosten!B23) | V5: =IF(Kosten!B24="","Pos. 19",Kosten!B24) | W5: =IF(Kosten!B25="","Pos. 20",Kosten!B25) | X5: Nebenkosten | Y5: Verwaltungs-honorar | Z5: Total Anteil | AA5: Akonto bezahlt | AB5: Saldo (+ Nachzahlung / − Guthaben)
B6: 1 | C6: =IF(Mieter!D6="","",Mieter!D6) | D6: =IF(OR(Mieter!$D6="",Kosten!$H$6<>"Ja"),0,IFERROR(Kosten!$C$6*INDEX(Liegenschaft!$C$14:$G$25,MATCH(Mieter!$C6,Liegenschaft!$B$14:$B$25,0),Kosten!$I$6)/INDEX(Liegenschaft!$C$26:$G$26,1,Kosten!$I$6)*IF(Kosten!$D$6="Heizung/Warmwasser",Mieter!$L6,Mieter!$K6),0)) | E6: =IF(OR(Mieter!$D6="",Kosten!$H$7<>"Ja"),0,IFERROR(Kosten!$C$7*INDEX(Liegenschaft!$C$14:$G$25,MATCH(Mieter!$C6,Liegenschaft!$B$14:$B$25,0),Kosten!$I$7)/INDEX(Liegenschaft!$C$26:$G$26,1,Kosten!$I$7)*IF(Kosten!$D$7="Heizung/Warmwasser",Mieter!$L6,Mieter!$K6),0)) | F6: =IF(OR(Mieter!$D6="",Kosten!$H$8<>"Ja"),0,IFERROR(Kosten!$C$8*INDEX(Liegenschaft!$C$14:$G$25,MATCH(Mieter!$C6,Liegenschaft!$B$14:$B$25,0),Kosten!$I$8)/INDEX(Liegenschaft!$C$26:$G$26,1,Kosten!$I$8)*IF(Kosten!$D$8="Heizung/Warmwasser",Mieter!$L6,Mieter!$K6),0)) | G6: =IF(OR(Mieter!$D6="",Kosten!$H$9<>"Ja"),0,IFERROR(Kosten!$C$9*INDEX(Liegenschaft!$C$14:$G$25,MATCH(Mieter!$C6,Liegenschaft!$B$14:$B$25,0),Kosten!$I$9)/INDEX(Liegenschaft!$C$26:$G$26,1,Kosten!$I$9)*IF(Kosten!$D$9="Heizung/Warmwasser",Mieter!$L6,Mieter!$K6),0)) | H6: =IF(OR(Mieter!$D6="",Kosten!$H$10<>"Ja"),0,IFERROR(Kosten!$C$10*INDEX(Liegenschaft!$C$14:$G$25,MATCH(Mieter!$C6,Liegenschaft!$B$14:$B$25,0),Kosten!$I$10)/INDEX(Liegenschaft!$C$26:$G$26,1,Kosten!$I$10)*IF(Kosten!$D$10="Heizung/Warmwasser",Mieter!$L6,Mieter!$K6),0)) | I6: =IF(OR(Mieter!$D6="",Kosten!$H$11<>"Ja"),0,IFERROR(Kosten!$C$11*INDEX(Liegenschaft!$C$14:$G$25,MATCH(Mieter!$C6,Liegenschaft!$B$14:$B$25,0),Kosten!$I$11)/INDEX(Liegenschaft!$C$26:$G$26,1,Kosten!$I$11)*IF(Kosten!$D$11="Heizung/Warmwasser",Mieter!$L6,Mieter!$K6),0)) | J6: =IF(OR(Mieter!$D6="",Kosten!$H$12<>"Ja"),0,IFERROR(Kosten!$C$12*INDEX(Liegenschaft!$C$14:$G$25,MATCH(Mieter!$C6,Liegenschaft!$B$14:$B$25,0),Kosten!$I$12)/INDEX(Liegenschaft!$C$26:$G$26,1,Kosten!$I$12)*IF(Kosten!$D$12="Heizung/Warmwasser",Mieter!$L6,Mieter!$K6),0)) | K6: =IF(OR(Mieter!$D6="",Kosten!$H$13<>"Ja"),0,IFERROR(Kosten!$C$13*INDEX(Liegenschaft!$C$14:$G$25,MATCH(Mieter!$C6,Liegenschaft!$B$14:$B$25,0),Kosten!$I$13)/INDEX(Liegenschaft!$C$26:$G$26,1,Kosten!$I$13)*IF(Kosten!$D$13="Heizung/Warmwasser",Mieter!$L6,Mieter!$K6),0)) | L6: =IF(OR(Mieter!$D6="",Kosten!$H$14<>"Ja"),0,IFERROR(Kosten!$C$14*INDEX(Liegenschaft!$C$14:$G$25,MATCH(Mieter!$C6,Liegenschaft!$B$14:$B$25,0),Kosten!$I$14)/INDEX(Liegenschaft!$C$26:$G$26,1,Kosten!$I$14)*IF(Kosten!$D$14="Heizung/Warmwasser",Mieter!$L6,Mieter!$K6),0)) | M6: =IF(OR(Mieter!$D6="",Kosten!$H$15<>"Ja"),0,IFERROR(Kosten!$C$15*INDEX(Liegenschaft!$C$14:$G$25,MATCH(Mieter!$C6,Liegenschaft!$B$14:$B$25,0),Kosten!$I$15)/INDEX(Liegenschaft!$C$26:$G$26,1,Kosten!$I$15)*IF(Kosten!$D$15="Heizung/Warmwasser",Mieter!$L6,Mieter!$K6),0)) | N6: =IF(OR(Mieter!$D6="",Kosten!$H$16<>"Ja"),0,IFERROR(Kosten!$C$16*INDEX(Liegenschaft!$C$14:$G$25,MATCH(Mieter!$C6,Liegenschaft!$B$14:$B$25,0),Kosten!$I$16)/INDEX(Liegenschaft!$C$26:$G$26,1,Kosten!$I$16)*IF(Kosten!$D$16="Heizung/Warmwasser",Mieter!$L6,Mieter!$K6),0)) | O6: =IF(OR(Mieter!$D6="",Kosten!$H$17<>"Ja"),0,IFERROR(Kosten!$C$17*INDEX(Liegenschaft!$C$14:$G$25,MATCH(Mieter!$C6,Liegenschaft!$B$14:$B$25,0),Kosten!$I$17)/INDEX(Liegenschaft!$C$26:$G$26,1,Kosten!$I$17)*IF(Kosten!$D$17="Heizung/Warmwasser",Mieter!$L6,Mieter!$K6),0)) | P6: =IF(OR(Mieter!$D6="",Kosten!$H$18<>"Ja"),0,IFERROR(Kosten!$C$18*INDEX(Liegenschaft!$C$14:$G$25,MATCH(Mieter!$C6,Liegenschaft!$B$14:$B$25,0),Kosten!$I$18)/INDEX(Liegenschaft!$C$26:$G$26,1,Kosten!$I$18)*IF(Kosten!$D$18="Heizung/Warmwasser",Mieter!$L6,Mieter!$K6),0)) | Q6: =IF(OR(Mieter!$D6="",Kosten!$H$19<>"Ja"),0,IFERROR(Kosten!$C$19*INDEX(Liegenschaft!$C$14:$G$25,MATCH(Mieter!$C6,Liegenschaft!$B$14:$B$25,0),Kosten!$I$19)/INDEX(Liegenschaft!$C$26:$G$26,1,Kosten!$I$19)*IF(Kosten!$D$19="Heizung/Warmwasser",Mieter!$L6,Mieter!$K6),0)) | R6: =IF(OR(Mieter!$D6="",Kosten!$H$20<>"Ja"),0,IFERROR(Kosten!$C$20*INDEX(Liegenschaft!$C$14:$G$25,MATCH(Mieter!$C6,Liegenschaft!$B$14:$B$25,0),Kosten!$I$20)/INDEX(Liegenschaft!$C$26:$G$26,1,Kosten!$I$20)*IF(Kosten!$D$20="Heizung/Warmwasser",Mieter!$L6,Mieter!$K6),0)) | S6: =IF(OR(Mieter!$D6="",Kosten!$H$21<>"Ja"),0,IFERROR(Kosten!$C$21*INDEX(Liegenschaft!$C$14:$G$25,MATCH(Mieter!$C6,Liegenschaft!$B$14:$B$25,0),Kosten!$I$21)/INDEX(Liegenschaft!$C$26:$G$26,1,Kosten!$I$21)*IF(Kosten!$D$21="Heizung/Warmwasser",Mieter!$L6,Mieter!$K6),0)) | T6: =IF(OR(Mieter!$D6="",Kosten!$H$22<>"Ja"),0,IFERROR(Kosten!$C$22*INDEX(Liegenschaft!$C$14:$G$25,MATCH(Mieter!$C6,Liegenschaft!$B$14:$B$25,0),Kosten!$I$22)/INDEX(Liegenschaft!$C$26:$G$26,1,Kosten!$I$22)*IF(Kosten!$D$22="Heizung/Warmwasser",Mieter!$L6,Mieter!$K6),0)) | U6: =IF(OR(Mieter!$D6="",Kosten!$H$23<>"Ja"),0,IFERROR(Kosten!$C$23*INDEX(Liegenschaft!$C$14:$G$25,MATCH(Mieter!$C6,Liegenschaft!$B$14:$B$25,0),Kosten!$I$23)/INDEX(Liegenschaft!$C$26:$G$26,1,Kosten!$I$23)*IF(Kosten!$D$23="Heizung/Warmwasser",Mieter!$L6,Mieter!$K6),0)) | V6: =IF(OR(Mieter!$D6="",Kosten!$H$24<>"Ja"),0,IFERROR(Kosten!$C$24*INDEX(Liegenschaft!$C$14:$G$25,MATCH(Mieter!$C6,Liegenschaft!$B$14:$B$25,0),Kosten!$I$24)/INDEX(Liegenschaft!$C$26:$G$26,1,Kosten!$I$24)*IF(Kosten!$D$24="Heizung/Warmwasser",Mieter!$L6,Mieter!$K6),0)) | W6: =IF(OR(Mieter!$D6="",Kosten!$H$25<>"Ja"),0,IFERROR(Kosten!$C$25*INDEX(Liegenschaft!$C$14:$G$25,MATCH(Mieter!$C6,Liegenschaft!$B$14:$B$25,0),Kosten!$I$25)/INDEX(Liegenschaft!$C$26:$G$26,1,Kosten!$I$25)*IF(Kosten!$D$25="Heizung/Warmwasser",Mieter!$L6,Mieter!$K6),0)) | X6: =SUM(D6:W6) | Y6: =IF(Liegenschaft!$C$11="Ja",ROUND(X6*Liegenschaft!$C$10,2),0) | Z6: =ROUND(X6+Y6,2) | AA6: =N(Mieter!G6) | AB6: =IF(C6="",0,Z6-AA6)
B7: 2 | C7: =IF(Mieter!D7="","",Mieter!D7) | D7: =IF(OR(Mieter!$D7="",Kosten!$H$6<>"Ja"),0,IFERROR(Kosten!$C$6*INDEX(Liegenschaft!$C$14:$G$25,MATCH(Mieter!$C7,Liegenschaft!$B$14:$B$25,0),Kosten!$I$6)/INDEX(Liegenschaft!$C$26:$G$26,1,Kosten!$I$6)*IF(Kosten!$D$6="Heizung/Warmwasser",Mieter!$L7,Mieter!$K7),0)) | E7: =IF(OR(Mieter!$D7="",Kosten!$H$7<>"Ja"),0,IFERROR(Kosten!$C$7*INDEX(Liegenschaft!$C$14:$G$25,MATCH(Mieter!$C7,Liegenschaft!$B$14:$B$25,0),Kosten!$I$7)/INDEX(Liegenschaft!$C$26:$G$26,1,Kosten!$I$7)*IF(Kosten!$D$7="Heizung/Warmwasser",Mieter!$L7,Mieter!$K7),0)) | F7: =IF(OR(Mieter!$D7="",Kosten!$H$8<>"Ja"),0,IFERROR(Kosten!$C$8*INDEX(Liegenschaft!$C$14:$G$25,MATCH(Mieter!$C7,Liegenschaft!$B$14:$B$25,0),Kosten!$I$8)/INDEX(Liegenschaft!$C$26:$G$26,1,Kosten!$I$8)*IF(Kosten!$D$8="Heizung/Warmwasser",Mieter!$L7,Mieter!$K7),0)) | G7: =IF(OR(Mieter!$D7="",Kosten!$H$9<>"Ja"),0,IFERROR(Kosten!$C$9*INDEX(Liegenschaft!$C$14:$G$25,MATCH(Mieter!$C7,Liegenschaft!$B$14:$B$25,0),Kosten!$I$9)/INDEX(Liegenschaft!$C$26:$G$26,1,Kosten!$I$9)*IF(Kosten!$D$9="Heizung/Warmwasser",Mieter!$L7,Mieter!$K7),0)) | H7: =IF(OR(Mieter!$D7="",Kosten!$H$10<>"Ja"),0,IFERROR(Kosten!$C$10*INDEX(Liegenschaft!$C$14:$G$25,MATCH(Mieter!$C7,Liegenschaft!$B$14:$B$25,0),Kosten!$I$10)/INDEX(Liegenschaft!$C$26:$G$26,1,Kosten!$I$10)*IF(Kosten!$D$10="Heizung/Warmwasser",Mieter!$L7,Mieter!$K7),0)) | I7: =IF(OR(Mieter!$D7="",Kosten!$H$11<>"Ja"),0,IFERROR(Kosten!$C$11*INDEX(Liegenschaft!$C$14:$G$25,MATCH(Mieter!$C7,Liegenschaft!$B$14:$B$25,0),Kosten!$I$11)/INDEX(Liegenschaft!$C$26:$G$26,1,Kosten!$I$11)*IF(Kosten!$D$11="Heizung/Warmwasser",Mieter!$L7,Mieter!$K7),0)) | J7: =IF(OR(Mieter!$D7="",Kosten!$H$12<>"Ja"),0,IFERROR(Kosten!$C$12*INDEX(Liegenschaft!$C$14:$G$25,MATCH(Mieter!$C7,Liegenschaft!$B$14:$B$25,0),Kosten!$I$12)/INDEX(Liegenschaft!$C$26:$G$26,1,Kosten!$I$12)*IF(Kosten!$D$12="Heizung/Warmwasser",Mieter!$L7,Mieter!$K7),0)) | K7: =IF(OR(Mieter!$D7="",Kosten!$H$13<>"Ja"),0,IFERROR(Kosten!$C$13*INDEX(Liegenschaft!$C$14:$G$25,MATCH(Mieter!$C7,Liegenschaft!$B$14:$B$25,0),Kosten!$I$13)/INDEX(Liegenschaft!$C$26:$G$26,1,Kosten!$I$13)*IF(Kosten!$D$13="Heizung/Warmwasser",Mieter!$L7,Mieter!$K7),0)) | L7: =IF(OR(Mieter!$D7="",Kosten!$H$14<>"Ja"),0,IFERROR(Kosten!$C$14*INDEX(Liegenschaft!$C$14:$G$25,MATCH(Mieter!$C7,Liegenschaft!$B$14:$B$25,0),Kosten!$I$14)/INDEX(Liegenschaft!$C$26:$G$26,1,Kosten!$I$14)*IF(Kosten!$D$14="Heizung/Warmwasser",Mieter!$L7,Mieter!$K7),0)) | M7: =IF(OR(Mieter!$D7="",Kosten!$H$15<>"Ja"),0,IFERROR(Kosten!$C$15*INDEX(Liegenschaft!$C$14:$G$25,MATCH(Mieter!$C7,Liegenschaft!$B$14:$B$25,0),Kosten!$I$15)/INDEX(Liegenschaft!$C$26:$G$26,1,Kosten!$I$15)*IF(Kosten!$D$15="Heizung/Warmwasser",Mieter!$L7,Mieter!$K7),0)) | N7: =IF(OR(Mieter!$D7="",Kosten!$H$16<>"Ja"),0,IFERROR(Kosten!$C$16*INDEX(Liegenschaft!$C$14:$G$25,MATCH(Mieter!$C7,Liegenschaft!$B$14:$B$25,0),Kosten!$I$16)/INDEX(Liegenschaft!$C$26:$G$26,1,Kosten!$I$16)*IF(Kosten!$D$16="Heizung/Warmwasser",Mieter!$L7,Mieter!$K7),0)) | O7: =IF(OR(Mieter!$D7="",Kosten!$H$17<>"Ja"),0,IFERROR(Kosten!$C$17*INDEX(Liegenschaft!$C$14:$G$25,MATCH(Mieter!$C7,Liegenschaft!$B$14:$B$25,0),Kosten!$I$17)/INDEX(Liegenschaft!$C$26:$G$26,1,Kosten!$I$17)*IF(Kosten!$D$17="Heizung/Warmwasser",Mieter!$L7,Mieter!$K7),0)) | P7: =IF(OR(Mieter!$D7="",Kosten!$H$18<>"Ja"),0,IFERROR(Kosten!$C$18*INDEX(Liegenschaft!$C$14:$G$25,MATCH(Mieter!$C7,Liegenschaft!$B$14:$B$25,0),Kosten!$I$18)/INDEX(Liegenschaft!$C$26:$G$26,1,Kosten!$I$18)*IF(Kosten!$D$18="Heizung/Warmwasser",Mieter!$L7,Mieter!$K7),0)) | Q7: =IF(OR(Mieter!$D7="",Kosten!$H$19<>"Ja"),0,IFERROR(Kosten!$C$19*INDEX(Liegenschaft!$C$14:$G$25,MATCH(Mieter!$C7,Liegenschaft!$B$14:$B$25,0),Kosten!$I$19)/INDEX(Liegenschaft!$C$26:$G$26,1,Kosten!$I$19)*IF(Kosten!$D$19="Heizung/Warmwasser",Mieter!$L7,Mieter!$K7),0)) | R7: =IF(OR(Mieter!$D7="",Kosten!$H$20<>"Ja"),0,IFERROR(Kosten!$C$20*INDEX(Liegenschaft!$C$14:$G$25,MATCH(Mieter!$C7,Liegenschaft!$B$14:$B$25,0),Kosten!$I$20)/INDEX(Liegenschaft!$C$26:$G$26,1,Kosten!$I$20)*IF(Kosten!$D$20="Heizung/Warmwasser",Mieter!$L7,Mieter!$K7),0)) | S7: =IF(OR(Mieter!$D7="",Kosten!$H$21<>"Ja"),0,IFERROR(Kosten!$C$21*INDEX(Liegenschaft!$C$14:$G$25,MATCH(Mieter!$C7,Liegenschaft!$B$14:$B$25,0),Kosten!$I$21)/INDEX(Liegenschaft!$C$26:$G$26,1,Kosten!$I$21)*IF(Kosten!$D$21="Heizung/Warmwasser",Mieter!$L7,Mieter!$K7),0)) | T7: =IF(OR(Mieter!$D7="",Kosten!$H$22<>"Ja"),0,IFERROR(Kosten!$C$22*INDEX(Liegenschaft!$C$14:$G$25,MATCH(Mieter!$C7,Liegenschaft!$B$14:$B$25,0),Kosten!$I$22)/INDEX(Liegenschaft!$C$26:$G$26,1,Kosten!$I$22)*IF(Kosten!$D$22="Heizung/Warmwasser",Mieter!$L7,Mieter!$K7),0)) | U7: =IF(OR(Mieter!$D7="",Kosten!$H$23<>"Ja"),0,IFERROR(Kosten!$C$23*INDEX(Liegenschaft!$C$14:$G$25,MATCH(Mieter!$C7,Liegenschaft!$B$14:$B$25,0),Kosten!$I$23)/INDEX(Liegenschaft!$C$26:$G$26,1,Kosten!$I$23)*IF(Kosten!$D$23="Heizung/Warmwasser",Mieter!$L7,Mieter!$K7),0)) | V7: =IF(OR(Mieter!$D7="",Kosten!$H$24<>"Ja"),0,IFERROR(Kosten!$C$24*INDEX(Liegenschaft!$C$14:$G$25,MATCH(Mieter!$C7,Liegenschaft!$B$14:$B$25,0),Kosten!$I$24)/INDEX(Liegenschaft!$C$26:$G$26,1,Kosten!$I$24)*IF(Kosten!$D$24="Heizung/Warmwasser",Mieter!$L7,Mieter!$K7),0)) | W7: =IF(OR(Mieter!$D7="",Kosten!$H$25<>"Ja"),0,IFERROR(Kosten!$C$25*INDEX(Liegenschaft!$C$14:$G$25,MATCH(Mieter!$C7,Liegenschaft!$B$14:$B$25,0),Kosten!$I$25)/INDEX(Liegenschaft!$C$26:$G$26,1,Kosten!$I$25)*IF(Kosten!$D$25="Heizung/Warmwasser",Mieter!$L7,Mieter!$K7),0)) | X7: =SUM(D7:W7) | Y7: =IF(Liegenschaft!$C$11="Ja",ROUND(X7*Liegenschaft!$C$10,2),0) | Z7: =ROUND(X7+Y7,2) | AA7: =N(Mieter!G7) | AB7: =IF(C7="",0,Z7-AA7)
B8: 3 | C8: =IF(Mieter!D8="","",Mieter!D8) | D8: =IF(OR(Mieter!$D8="",Kosten!$H$6<>"Ja"),0,IFERROR(Kosten!$C$6*INDEX(Liegenschaft!$C$14:$G$25,MATCH(Mieter!$C8,Liegenschaft!$B$14:$B$25,0),Kosten!$I$6)/INDEX(Liegenschaft!$C$26:$G$26,1,Kosten!$I$6)*IF(Kosten!$D$6="Heizung/Warmwasser",Mieter!$L8,Mieter!$K8),0)) | E8: =IF(OR(Mieter!$D8="",Kosten!$H$7<>"Ja"),0,IFERROR(Kosten!$C$7*INDEX(Liegenschaft!$C$14:$G$25,MATCH(Mieter!$C8,Liegenschaft!$B$14:$B$25,0),Kosten!$I$7)/INDEX(Liegenschaft!$C$26:$G$26,1,Kosten!$I$7)*IF(Kosten!$D$7="Heizung/Warmwasser",Mieter!$L8,Mieter!$K8),0)) | F8: =IF(OR(Mieter!$D8="",Kosten!$H$8<>"Ja"),0,IFERROR(Kosten!$C$8*INDEX(Liegenschaft!$C$14:$G$25,MATCH(Mieter!$C8,Liegenschaft!$B$14:$B$25,0),Kosten!$I$8)/INDEX(Liegenschaft!$C$26:$G$26,1,Kosten!$I$8)*IF(Kosten!$D$8="Heizung/Warmwasser",Mieter!$L8,Mieter!$K8),0)) | G8: =IF(OR(Mieter!$D8="",Kosten!$H$9<>"Ja"),0,IFERROR(Kosten!$C$9*INDEX(Liegenschaft!$C$14:$G$25,MATCH(Mieter!$C8,Liegenschaft!$B$14:$B$25,0),Kosten!$I$9)/INDEX(Liegenschaft!$C$26:$G$26,1,Kosten!$I$9)*IF(Kosten!$D$9="Heizung/Warmwasser",Mieter!$L8,Mieter!$K8),0)) | H8: =IF(OR(Mieter!$D8="",Kosten!$H$10<>"Ja"),0,IFERROR(Kosten!$C$10*INDEX(Liegenschaft!$C$14:$G$25,MATCH(Mieter!$C8,Liegenschaft!$B$14:$B$25,0),Kosten!$I$10)/INDEX(Liegenschaft!$C$26:$G$26,1,Kosten!$I$10)*IF(Kosten!$D$10="Heizung/Warmwasser",Mieter!$L8,Mieter!$K8),0)) | I8: =IF(OR(Mieter!$D8="",Kosten!$H$11<>"Ja"),0,IFERROR(Kosten!$C$11*INDEX(Liegenschaft!$C$14:$G$25,MATCH(Mieter!$C8,Liegenschaft!$B$14:$B$25,0),Kosten!$I$11)/INDEX(Liegenschaft!$C$26:$G$26,1,Kosten!$I$11)*IF(Kosten!$D$11="Heizung/Warmwasser",Mieter!$L8,Mieter!$K8),0)) | J8: =IF(OR(Mieter!$D8="",Kosten!$H$12<>"Ja"),0,IFERROR(Kosten!$C$12*INDEX(Liegenschaft!$C$14:$G$25,MATCH(Mieter!$C8,Liegenschaft!$B$14:$B$25,0),Kosten!$I$12)/INDEX(Liegenschaft!$C$26:$G$26,1,Kosten!$I$12)*IF(Kosten!$D$12="Heizung/Warmwasser",Mieter!$L8,Mieter!$K8),0)) | K8: =IF(OR(Mieter!$D8="",Kosten!$H$13<>"Ja"),0,IFERROR(Kosten!$C$13*INDEX(Liegenschaft!$C$14:$G$25,MATCH(Mieter!$C8,Liegenschaft!$B$14:$B$25,0),Kosten!$I$13)/INDEX(Liegenschaft!$C$26:$G$26,1,Kosten!$I$13)*IF(Kosten!$D$13="Heizung/Warmwasser",Mieter!$L8,Mieter!$K8),0)) | L8: =IF(OR(Mieter!$D8="",Kosten!$H$14<>"Ja"),0,IFERROR(Kosten!$C$14*INDEX(Liegenschaft!$C$14:$G$25,MATCH(Mieter!$C8,Liegenschaft!$B$14:$B$25,0),Kosten!$I$14)/INDEX(Liegenschaft!$C$26:$G$26,1,Kosten!$I$14)*IF(Kosten!$D$14="Heizung/Warmwasser",Mieter!$L8,Mieter!$K8),0)) | M8: =IF(OR(Mieter!$D8="",Kosten!$H$15<>"Ja"),0,IFERROR(Kosten!$C$15*INDEX(Liegenschaft!$C$14:$G$25,MATCH(Mieter!$C8,Liegenschaft!$B$14:$B$25,0),Kosten!$I$15)/INDEX(Liegenschaft!$C$26:$G$26,1,Kosten!$I$15)*IF(Kosten!$D$15="Heizung/Warmwasser",Mieter!$L8,Mieter!$K8),0)) | N8: =IF(OR(Mieter!$D8="",Kosten!$H$16<>"Ja"),0,IFERROR(Kosten!$C$16*INDEX(Liegenschaft!$C$14:$G$25,MATCH(Mieter!$C8,Liegenschaft!$B$14:$B$25,0),Kosten!$I$16)/INDEX(Liegenschaft!$C$26:$G$26,1,Kosten!$I$16)*IF(Kosten!$D$16="Heizung/Warmwasser",Mieter!$L8,Mieter!$K8),0)) | O8: =IF(OR(Mieter!$D8="",Kosten!$H$17<>"Ja"),0,IFERROR(Kosten!$C$17*INDEX(Liegenschaft!$C$14:$G$25,MATCH(Mieter!$C8,Liegenschaft!$B$14:$B$25,0),Kosten!$I$17)/INDEX(Liegenschaft!$C$26:$G$26,1,Kosten!$I$17)*IF(Kosten!$D$17="Heizung/Warmwasser",Mieter!$L8,Mieter!$K8),0)) | P8: =IF(OR(Mieter!$D8="",Kosten!$H$18<>"Ja"),0,IFERROR(Kosten!$C$18*INDEX(Liegenschaft!$C$14:$G$25,MATCH(Mieter!$C8,Liegenschaft!$B$14:$B$25,0),Kosten!$I$18)/INDEX(Liegenschaft!$C$26:$G$26,1,Kosten!$I$18)*IF(Kosten!$D$18="Heizung/Warmwasser",Mieter!$L8,Mieter!$K8),0)) | Q8: =IF(OR(Mieter!$D8="",Kosten!$H$19<>"Ja"),0,IFERROR(Kosten!$C$19*INDEX(Liegenschaft!$C$14:$G$25,MATCH(Mieter!$C8,Liegenschaft!$B$14:$B$25,0),Kosten!$I$19)/INDEX(Liegenschaft!$C$26:$G$26,1,Kosten!$I$19)*IF(Kosten!$D$19="Heizung/Warmwasser",Mieter!$L8,Mieter!$K8),0)) | R8: =IF(OR(Mieter!$D8="",Kosten!$H$20<>"Ja"),0,IFERROR(Kosten!$C$20*INDEX(Liegenschaft!$C$14:$G$25,MATCH(Mieter!$C8,Liegenschaft!$B$14:$B$25,0),Kosten!$I$20)/INDEX(Liegenschaft!$C$26:$G$26,1,Kosten!$I$20)*IF(Kosten!$D$20="Heizung/Warmwasser",Mieter!$L8,Mieter!$K8),0)) | S8: =IF(OR(Mieter!$D8="",Kosten!$H$21<>"Ja"),0,IFERROR(Kosten!$C$21*INDEX(Liegenschaft!$C$14:$G$25,MATCH(Mieter!$C8,Liegenschaft!$B$14:$B$25,0),Kosten!$I$21)/INDEX(Liegenschaft!$C$26:$G$26,1,Kosten!$I$21)*IF(Kosten!$D$21="Heizung/Warmwasser",Mieter!$L8,Mieter!$K8),0)) | T8: =IF(OR(Mieter!$D8="",Kosten!$H$22<>"Ja"),0,IFERROR(Kosten!$C$22*INDEX(Liegenschaft!$C$14:$G$25,MATCH(Mieter!$C8,Liegenschaft!$B$14:$B$25,0),Kosten!$I$22)/INDEX(Liegenschaft!$C$26:$G$26,1,Kosten!$I$22)*IF(Kosten!$D$22="Heizung/Warmwasser",Mieter!$L8,Mieter!$K8),0)) | U8: =IF(OR(Mieter!$D8="",Kosten!$H$23<>"Ja"),0,IFERROR(Kosten!$C$23*INDEX(Liegenschaft!$C$14:$G$25,MATCH(Mieter!$C8,Liegenschaft!$B$14:$B$25,0),Kosten!$I$23)/INDEX(Liegenschaft!$C$26:$G$26,1,Kosten!$I$23)*IF(Kosten!$D$23="Heizung/Warmwasser",Mieter!$L8,Mieter!$K8),0)) | V8: =IF(OR(Mieter!$D8="",Kosten!$H$24<>"Ja"),0,IFERROR(Kosten!$C$24*INDEX(Liegenschaft!$C$14:$G$25,MATCH(Mieter!$C8,Liegenschaft!$B$14:$B$25,0),Kosten!$I$24)/INDEX(Liegenschaft!$C$26:$G$26,1,Kosten!$I$24)*IF(Kosten!$D$24="Heizung/Warmwasser",Mieter!$L8,Mieter!$K8),0)) | W8: =IF(OR(Mieter!$D8="",Kosten!$H$25<>"Ja"),0,IFERROR(Kosten!$C$25*INDEX(Liegenschaft!$C$14:$G$25,MATCH(Mieter!$C8,Liegenschaft!$B$14:$B$25,0),Kosten!$I$25)/INDEX(Liegenschaft!$C$26:$G$26,1,Kosten!$I$25)*IF(Kosten!$D$25="Heizung/Warmwasser",Mieter!$L8,Mieter!$K8),0)) | X8: =SUM(D8:W8) | Y8: =IF(Liegenschaft!$C$11="Ja",ROUND(X8*Liegenschaft!$C$10,2),0) | Z8: =ROUND(X8+Y8,2) | AA8: =N(Mieter!G8) | AB8: =IF(C8="",0,Z8-AA8)
B9: 4 | C9: =IF(Mieter!D9="","",Mieter!D9) | D9: =IF(OR(Mieter!$D9="",Kosten!$H$6<>"Ja"),0,IFERROR(Kosten!$C$6*INDEX(Liegenschaft!$C$14:$G$25,MATCH(Mieter!$C9,Liegenschaft!$B$14:$B$25,0),Kosten!$I$6)/INDEX(Liegenschaft!$C$26:$G$26,1,Kosten!$I$6)*IF(Kosten!$D$6="Heizung/Warmwasser",Mieter!$L9,Mieter!$K9),0)) | E9: =IF(OR(Mieter!$D9="",Kosten!$H$7<>"Ja"),0,IFERROR(Kosten!$C$7*INDEX(Liegenschaft!$C$14:$G$25,MATCH(Mieter!$C9,Liegenschaft!$B$14:$B$25,0),Kosten!$I$7)/INDEX(Liegenschaft!$C$26:$G$26,1,Kosten!$I$7)*IF(Kosten!$D$7="Heizung/Warmwasser",Mieter!$L9,Mieter!$K9),0)) | F9: =IF(OR(Mieter!$D9="",Kosten!$H$8<>"Ja"),0,IFERROR(Kosten!$C$8*INDEX(Liegenschaft!$C$14:$G$25,MATCH(Mieter!$C9,Liegenschaft!$B$14:$B$25,0),Kosten!$I$8)/INDEX(Liegenschaft!$C$26:$G$26,1,Kosten!$I$8)*IF(Kosten!$D$8="Heizung/Warmwasser",Mieter!$L9,Mieter!$K9),0)) | G9: =IF(OR(Mieter!$D9="",Kosten!$H$9<>"Ja"),0,IFERROR(Kosten!$C$9*INDEX(Liegenschaft!$C$14:$G$25,MATCH(Mieter!$C9,Liegenschaft!$B$14:$B$25,0),Kosten!$I$9)/INDEX(Liegenschaft!$C$26:$G$26,1,Kosten!$I$9)*IF(Kosten!$D$9="Heizung/Warmwasser",Mieter!$L9,Mieter!$K9),0)) | H9: =IF(OR(Mieter!$D9="",Kosten!$H$10<>"Ja"),0,IFERROR(Kosten!$C$10*INDEX(Liegenschaft!$C$14:$G$25,MATCH(Mieter!$C9,Liegenschaft!$B$14:$B$25,0),Kosten!$I$10)/INDEX(Liegenschaft!$C$26:$G$26,1,Kosten!$I$10)*IF(Kosten!$D$10="Heizung/Warmwasser",Mieter!$L9,Mieter!$K9),0)) | I9: =IF(OR(Mieter!$D9="",Kosten!$H$11<>"Ja"),0,IFERROR(Kosten!$C$11*INDEX(Liegenschaft!$C$14:$G$25,MATCH(Mieter!$C9,Liegenschaft!$B$14:$B$25,0),Kosten!$I$11)/INDEX(Liegenschaft!$C$26:$G$26,1,Kosten!$I$11)*IF(Kosten!$D$11="Heizung/Warmwasser",Mieter!$L9,Mieter!$K9),0)) | J9: =IF(OR(Mieter!$D9="",Kosten!$H$12<>"Ja"),0,IFERROR(Kosten!$C$12*INDEX(Liegenschaft!$C$14:$G$25,MATCH(Mieter!$C9,Liegenschaft!$B$14:$B$25,0),Kosten!$I$12)/INDEX(Liegenschaft!$C$26:$G$26,1,Kosten!$I$12)*IF(Kosten!$D$12="Heizung/Warmwasser",Mieter!$L9,Mieter!$K9),0)) | K9: =IF(OR(Mieter!$D9="",Kosten!$H$13<>"Ja"),0,IFERROR(Kosten!$C$13*INDEX(Liegenschaft!$C$14:$G$25,MATCH(Mieter!$C9,Liegenschaft!$B$14:$B$25,0),Kosten!$I$13)/INDEX(Liegenschaft!$C$26:$G$26,1,Kosten!$I$13)*IF(Kosten!$D$13="Heizung/Warmwasser",Mieter!$L9,Mieter!$K9),0)) | L9: =IF(OR(Mieter!$D9="",Kosten!$H$14<>"Ja"),0,IFERROR(Kosten!$C$14*INDEX(Liegenschaft!$C$14:$G$25,MATCH(Mieter!$C9,Liegenschaft!$B$14:$B$25,0),Kosten!$I$14)/INDEX(Liegenschaft!$C$26:$G$26,1,Kosten!$I$14)*IF(Kosten!$D$14="Heizung/Warmwasser",Mieter!$L9,Mieter!$K9),0)) | M9: =IF(OR(Mieter!$D9="",Kosten!$H$15<>"Ja"),0,IFERROR(Kosten!$C$15*INDEX(Liegenschaft!$C$14:$G$25,MATCH(Mieter!$C9,Liegenschaft!$B$14:$B$25,0),Kosten!$I$15)/INDEX(Liegenschaft!$C$26:$G$26,1,Kosten!$I$15)*IF(Kosten!$D$15="Heizung/Warmwasser",Mieter!$L9,Mieter!$K9),0)) | N9: =IF(OR(Mieter!$D9="",Kosten!$H$16<>"Ja"),0,IFERROR(Kosten!$C$16*INDEX(Liegenschaft!$C$14:$G$25,MATCH(Mieter!$C9,Liegenschaft!$B$14:$B$25,0),Kosten!$I$16)/INDEX(Liegenschaft!$C$26:$G$26,1,Kosten!$I$16)*IF(Kosten!$D$16="Heizung/Warmwasser",Mieter!$L9,Mieter!$K9),0)) | O9: =IF(OR(Mieter!$D9="",Kosten!$H$17<>"Ja"),0,IFERROR(Kosten!$C$17*INDEX(Liegenschaft!$C$14:$G$25,MATCH(Mieter!$C9,Liegenschaft!$B$14:$B$25,0),Kosten!$I$17)/INDEX(Liegenschaft!$C$26:$G$26,1,Kosten!$I$17)*IF(Kosten!$D$17="Heizung/Warmwasser",Mieter!$L9,Mieter!$K9),0)) | P9: =IF(OR(Mieter!$D9="",Kosten!$H$18<>"Ja"),0,IFERROR(Kosten!$C$18*INDEX(Liegenschaft!$C$14:$G$25,MATCH(Mieter!$C9,Liegenschaft!$B$14:$B$25,0),Kosten!$I$18)/INDEX(Liegenschaft!$C$26:$G$26,1,Kosten!$I$18)*IF(Kosten!$D$18="Heizung/Warmwasser",Mieter!$L9,Mieter!$K9),0)) | Q9: =IF(OR(Mieter!$D9="",Kosten!$H$19<>"Ja"),0,IFERROR(Kosten!$C$19*INDEX(Liegenschaft!$C$14:$G$25,MATCH(Mieter!$C9,Liegenschaft!$B$14:$B$25,0),Kosten!$I$19)/INDEX(Liegenschaft!$C$26:$G$26,1,Kosten!$I$19)*IF(Kosten!$D$19="Heizung/Warmwasser",Mieter!$L9,Mieter!$K9),0)) | R9: =IF(OR(Mieter!$D9="",Kosten!$H$20<>"Ja"),0,IFERROR(Kosten!$C$20*INDEX(Liegenschaft!$C$14:$G$25,MATCH(Mieter!$C9,Liegenschaft!$B$14:$B$25,0),Kosten!$I$20)/INDEX(Liegenschaft!$C$26:$G$26,1,Kosten!$I$20)*IF(Kosten!$D$20="Heizung/Warmwasser",Mieter!$L9,Mieter!$K9),0)) | S9: =IF(OR(Mieter!$D9="",Kosten!$H$21<>"Ja"),0,IFERROR(Kosten!$C$21*INDEX(Liegenschaft!$C$14:$G$25,MATCH(Mieter!$C9,Liegenschaft!$B$14:$B$25,0),Kosten!$I$21)/INDEX(Liegenschaft!$C$26:$G$26,1,Kosten!$I$21)*IF(Kosten!$D$21="Heizung/Warmwasser",Mieter!$L9,Mieter!$K9),0)) | T9: =IF(OR(Mieter!$D9="",Kosten!$H$22<>"Ja"),0,IFERROR(Kosten!$C$22*INDEX(Liegenschaft!$C$14:$G$25,MATCH(Mieter!$C9,Liegenschaft!$B$14:$B$25,0),Kosten!$I$22)/INDEX(Liegenschaft!$C$26:$G$26,1,Kosten!$I$22)*IF(Kosten!$D$22="Heizung/Warmwasser",Mieter!$L9,Mieter!$K9),0)) | U9: =IF(OR(Mieter!$D9="",Kosten!$H$23<>"Ja"),0,IFERROR(Kosten!$C$23*INDEX(Liegenschaft!$C$14:$G$25,MATCH(Mieter!$C9,Liegenschaft!$B$14:$B$25,0),Kosten!$I$23)/INDEX(Liegenschaft!$C$26:$G$26,1,Kosten!$I$23)*IF(Kosten!$D$23="Heizung/Warmwasser",Mieter!$L9,Mieter!$K9),0)) | V9: =IF(OR(Mieter!$D9="",Kosten!$H$24<>"Ja"),0,IFERROR(Kosten!$C$24*INDEX(Liegenschaft!$C$14:$G$25,MATCH(Mieter!$C9,Liegenschaft!$B$14:$B$25,0),Kosten!$I$24)/INDEX(Liegenschaft!$C$26:$G$26,1,Kosten!$I$24)*IF(Kosten!$D$24="Heizung/Warmwasser",Mieter!$L9,Mieter!$K9),0)) | W9: =IF(OR(Mieter!$D9="",Kosten!$H$25<>"Ja"),0,IFERROR(Kosten!$C$25*INDEX(Liegenschaft!$C$14:$G$25,MATCH(Mieter!$C9,Liegenschaft!$B$14:$B$25,0),Kosten!$I$25)/INDEX(Liegenschaft!$C$26:$G$26,1,Kosten!$I$25)*IF(Kosten!$D$25="Heizung/Warmwasser",Mieter!$L9,Mieter!$K9),0)) | X9: =SUM(D9:W9) | Y9: =IF(Liegenschaft!$C$11="Ja",ROUND(X9*Liegenschaft!$C$10,2),0) | Z9: =ROUND(X9+Y9,2) | AA9: =N(Mieter!G9) | AB9: =IF(C9="",0,Z9-AA9)
B10: 5 | C10: =IF(Mieter!D10="","",Mieter!D10) | D10: =IF(OR(Mieter!$D10="",Kosten!$H$6<>"Ja"),0,IFERROR(Kosten!$C$6*INDEX(Liegenschaft!$C$14:$G$25,MATCH(Mieter!$C10,Liegenschaft!$B$14:$B$25,0),Kosten!$I$6)/INDEX(Liegenschaft!$C$26:$G$26,1,Kosten!$I$6)*IF(Kosten!$D$6="Heizung/Warmwasser",Mieter!$L10,Mieter!$K10),0)) | E10: =IF(OR(Mieter!$D10="",Kosten!$H$7<>"Ja"),0,IFERROR(Kosten!$C$7*INDEX(Liegenschaft!$C$14:$G$25,MATCH(Mieter!$C10,Liegenschaft!$B$14:$B$25,0),Kosten!$I$7)/INDEX(Liegenschaft!$C$26:$G$26,1,Kosten!$I$7)*IF(Kosten!$D$7="Heizung/Warmwasser",Mieter!$L10,Mieter!$K10),0)) | F10: =IF(OR(Mieter!$D10="",Kosten!$H$8<>"Ja"),0,IFERROR(Kosten!$C$8*INDEX(Liegenschaft!$C$14:$G$25,MATCH(Mieter!$C10,Liegenschaft!$B$14:$B$25,0),Kosten!$I$8)/INDEX(Liegenschaft!$C$26:$G$26,1,Kosten!$I$8)*IF(Kosten!$D$8="Heizung/Warmwasser",Mieter!$L10,Mieter!$K10),0)) | G10: =IF(OR(Mieter!$D10="",Kosten!$H$9<>"Ja"),0,IFERROR(Kosten!$C$9*INDEX(Liegenschaft!$C$14:$G$25,MATCH(Mieter!$C10,Liegenschaft!$B$14:$B$25,0),Kosten!$I$9)/INDEX(Liegenschaft!$C$26:$G$26,1,Kosten!$I$9)*IF(Kosten!$D$9="Heizung/Warmwasser",Mieter!$L10,Mieter!$K10),0)) | H10: =IF(OR(Mieter!$D10="",Kosten!$H$10<>"Ja"),0,IFERROR(Kosten!$C$10*INDEX(Liegenschaft!$C$14:$G$25,MATCH(Mieter!$C10,Liegenschaft!$B$14:$B$25,0),Kosten!$I$10)/INDEX(Liegenschaft!$C$26:$G$26,1,Kosten!$I$10)*IF(Kosten!$D$10="Heizung/Warmwasser",Mieter!$L10,Mieter!$K10),0)) | I10: =IF(OR(Mieter!$D10="",Kosten!$H$11<>"Ja"),0,IFERROR(Kosten!$C$11*INDEX(Liegenschaft!$C$14:$G$25,MATCH(Mieter!$C10,Liegenschaft!$B$14:$B$25,0),Kosten!$I$11)/INDEX(Liegenschaft!$C$26:$G$26,1,Kosten!$I$11)*IF(Kosten!$D$11="Heizung/Warmwasser",Mieter!$L10,Mieter!$K10),0)) | J10: =IF(OR(Mieter!$D10="",Kosten!$H$12<>"Ja"),0,IFERROR(Kosten!$C$12*INDEX(Liegenschaft!$C$14:$G$25,MATCH(Mieter!$C10,Liegenschaft!$B$14:$B$25,0),Kosten!$I$12)/INDEX(Liegenschaft!$C$26:$G$26,1,Kosten!$I$12)*IF(Kosten!$D$12="Heizung/Warmwasser",Mieter!$L10,Mieter!$K10),0)) | K10: =IF(OR(Mieter!$D10="",Kosten!$H$13<>"Ja"),0,IFERROR(Kosten!$C$13*INDEX(Liegenschaft!$C$14:$G$25,MATCH(Mieter!$C10,Liegenschaft!$B$14:$B$25,0),Kosten!$I$13)/INDEX(Liegenschaft!$C$26:$G$26,1,Kosten!$I$13)*IF(Kosten!$D$13="Heizung/Warmwasser",Mieter!$L10,Mieter!$K10),0)) | L10: =IF(OR(Mieter!$D10="",Kosten!$H$14<>"Ja"),0,IFERROR(Kosten!$C$14*INDEX(Liegenschaft!$C$14:$G$25,MATCH(Mieter!$C10,Liegenschaft!$B$14:$B$25,0),Kosten!$I$14)/INDEX(Liegenschaft!$C$26:$G$26,1,Kosten!$I$14)*IF(Kosten!$D$14="Heizung/Warmwasser",Mieter!$L10,Mieter!$K10),0)) | M10: =IF(OR(Mieter!$D10="",Kosten!$H$15<>"Ja"),0,IFERROR(Kosten!$C$15*INDEX(Liegenschaft!$C$14:$G$25,MATCH(Mieter!$C10,Liegenschaft!$B$14:$B$25,0),Kosten!$I$15)/INDEX(Liegenschaft!$C$26:$G$26,1,Kosten!$I$15)*IF(Kosten!$D$15="Heizung/Warmwasser",Mieter!$L10,Mieter!$K10),0)) | N10: =IF(OR(Mieter!$D10="",Kosten!$H$16<>"Ja"),0,IFERROR(Kosten!$C$16*INDEX(Liegenschaft!$C$14:$G$25,MATCH(Mieter!$C10,Liegenschaft!$B$14:$B$25,0),Kosten!$I$16)/INDEX(Liegenschaft!$C$26:$G$26,1,Kosten!$I$16)*IF(Kosten!$D$16="Heizung/Warmwasser",Mieter!$L10,Mieter!$K10),0)) | O10: =IF(OR(Mieter!$D10="",Kosten!$H$17<>"Ja"),0,IFERROR(Kosten!$C$17*INDEX(Liegenschaft!$C$14:$G$25,MATCH(Mieter!$C10,Liegenschaft!$B$14:$B$25,0),Kosten!$I$17)/INDEX(Liegenschaft!$C$26:$G$26,1,Kosten!$I$17)*IF(Kosten!$D$17="Heizung/Warmwasser",Mieter!$L10,Mieter!$K10),0)) | P10: =IF(OR(Mieter!$D10="",Kosten!$H$18<>"Ja"),0,IFERROR(Kosten!$C$18*INDEX(Liegenschaft!$C$14:$G$25,MATCH(Mieter!$C10,Liegenschaft!$B$14:$B$25,0),Kosten!$I$18)/INDEX(Liegenschaft!$C$26:$G$26,1,Kosten!$I$18)*IF(Kosten!$D$18="Heizung/Warmwasser",Mieter!$L10,Mieter!$K10),0)) | Q10: =IF(OR(Mieter!$D10="",Kosten!$H$19<>"Ja"),0,IFERROR(Kosten!$C$19*INDEX(Liegenschaft!$C$14:$G$25,MATCH(Mieter!$C10,Liegenschaft!$B$14:$B$25,0),Kosten!$I$19)/INDEX(Liegenschaft!$C$26:$G$26,1,Kosten!$I$19)*IF(Kosten!$D$19="Heizung/Warmwasser",Mieter!$L10,Mieter!$K10),0)) | R10: =IF(OR(Mieter!$D10="",Kosten!$H$20<>"Ja"),0,IFERROR(Kosten!$C$20*INDEX(Liegenschaft!$C$14:$G$25,MATCH(Mieter!$C10,Liegenschaft!$B$14:$B$25,0),Kosten!$I$20)/INDEX(Liegenschaft!$C$26:$G$26,1,Kosten!$I$20)*IF(Kosten!$D$20="Heizung/Warmwasser",Mieter!$L10,Mieter!$K10),0)) | S10: =IF(OR(Mieter!$D10="",Kosten!$H$21<>"Ja"),0,IFERROR(Kosten!$C$21*INDEX(Liegenschaft!$C$14:$G$25,MATCH(Mieter!$C10,Liegenschaft!$B$14:$B$25,0),Kosten!$I$21)/INDEX(Liegenschaft!$C$26:$G$26,1,Kosten!$I$21)*IF(Kosten!$D$21="Heizung/Warmwasser",Mieter!$L10,Mieter!$K10),0)) | T10: =IF(OR(Mieter!$D10="",Kosten!$H$22<>"Ja"),0,IFERROR(Kosten!$C$22*INDEX(Liegenschaft!$C$14:$G$25,MATCH(Mieter!$C10,Liegenschaft!$B$14:$B$25,0),Kosten!$I$22)/INDEX(Liegenschaft!$C$26:$G$26,1,Kosten!$I$22)*IF(Kosten!$D$22="Heizung/Warmwasser",Mieter!$L10,Mieter!$K10),0)) | U10: =IF(OR(Mieter!$D10="",Kosten!$H$23<>"Ja"),0,IFERROR(Kosten!$C$23*INDEX(Liegenschaft!$C$14:$G$25,MATCH(Mieter!$C10,Liegenschaft!$B$14:$B$25,0),Kosten!$I$23)/INDEX(Liegenschaft!$C$26:$G$26,1,Kosten!$I$23)*IF(Kosten!$D$23="Heizung/Warmwasser",Mieter!$L10,Mieter!$K10),0)) | V10: =IF(OR(Mieter!$D10="",Kosten!$H$24<>"Ja"),0,IFERROR(Kosten!$C$24*INDEX(Liegenschaft!$C$14:$G$25,MATCH(Mieter!$C10,Liegenschaft!$B$14:$B$25,0),Kosten!$I$24)/INDEX(Liegenschaft!$C$26:$G$26,1,Kosten!$I$24)*IF(Kosten!$D$24="Heizung/Warmwasser",Mieter!$L10,Mieter!$K10),0)) | W10: =IF(OR(Mieter!$D10="",Kosten!$H$25<>"Ja"),0,IFERROR(Kosten!$C$25*INDEX(Liegenschaft!$C$14:$G$25,MATCH(Mieter!$C10,Liegenschaft!$B$14:$B$25,0),Kosten!$I$25)/INDEX(Liegenschaft!$C$26:$G$26,1,Kosten!$I$25)*IF(Kosten!$D$25="Heizung/Warmwasser",Mieter!$L10,Mieter!$K10),0)) | X10: =SUM(D10:W10) | Y10: =IF(Liegenschaft!$C$11="Ja",ROUND(X10*Liegenschaft!$C$10,2),0) | Z10: =ROUND(X10+Y10,2) | AA10: =N(Mieter!G10) | AB10: =IF(C10="",0,Z10-AA10)
B11: 6 | C11: =IF(Mieter!D11="","",Mieter!D11) | D11: =IF(OR(Mieter!$D11="",Kosten!$H$6<>"Ja"),0,IFERROR(Kosten!$C$6*INDEX(Liegenschaft!$C$14:$G$25,MATCH(Mieter!$C11,Liegenschaft!$B$14:$B$25,0),Kosten!$I$6)/INDEX(Liegenschaft!$C$26:$G$26,1,Kosten!$I$6)*IF(Kosten!$D$6="Heizung/Warmwasser",Mieter!$L11,Mieter!$K11),0)) | E11: =IF(OR(Mieter!$D11="",Kosten!$H$7<>"Ja"),0,IFERROR(Kosten!$C$7*INDEX(Liegenschaft!$C$14:$G$25,MATCH(Mieter!$C11,Liegenschaft!$B$14:$B$25,0),Kosten!$I$7)/INDEX(Liegenschaft!$C$26:$G$26,1,Kosten!$I$7)*IF(Kosten!$D$7="Heizung/Warmwasser",Mieter!$L11,Mieter!$K11),0)) | F11: =IF(OR(Mieter!$D11="",Kosten!$H$8<>"Ja"),0,IFERROR(Kosten!$C$8*INDEX(Liegenschaft!$C$14:$G$25,MATCH(Mieter!$C11,Liegenschaft!$B$14:$B$25,0),Kosten!$I$8)/INDEX(Liegenschaft!$C$26:$G$26,1,Kosten!$I$8)*IF(Kosten!$D$8="Heizung/Warmwasser",Mieter!$L11,Mieter!$K11),0)) | G11: =IF(OR(Mieter!$D11="",Kosten!$H$9<>"Ja"),0,IFERROR(Kosten!$C$9*INDEX(Liegenschaft!$C$14:$G$25,MATCH(Mieter!$C11,Liegenschaft!$B$14:$B$25,0),Kosten!$I$9)/INDEX(Liegenschaft!$C$26:$G$26,1,Kosten!$I$9)*IF(Kosten!$D$9="Heizung/Warmwasser",Mieter!$L11,Mieter!$K11),0)) | H11: =IF(OR(Mieter!$D11="",Kosten!$H$10<>"Ja"),0,IFERROR(Kosten!$C$10*INDEX(Liegenschaft!$C$14:$G$25,MATCH(Mieter!$C11,Liegenschaft!$B$14:$B$25,0),Kosten!$I$10)/INDEX(Liegenschaft!$C$26:$G$26,1,Kosten!$I$10)*IF(Kosten!$D$10="Heizung/Warmwasser",Mieter!$L11,Mieter!$K11),0)) | I11: =IF(OR(Mieter!$D11="",Kosten!$H$11<>"Ja"),0,IFERROR(Kosten!$C$11*INDEX(Liegenschaft!$C$14:$G$25,MATCH(Mieter!$C11,Liegenschaft!$B$14:$B$25,0),Kosten!$I$11)/INDEX(Liegenschaft!$C$26:$G$26,1,Kosten!$I$11)*IF(Kosten!$D$11="Heizung/Warmwasser",Mieter!$L11,Mieter!$K11),0)) | J11: =IF(OR(Mieter!$D11="",Kosten!$H$12<>"Ja"),0,IFERROR(Kosten!$C$12*INDEX(Liegenschaft!$C$14:$G$25,MATCH(Mieter!$C11,Liegenschaft!$B$14:$B$25,0),Kosten!$I$12)/INDEX(Liegenschaft!$C$26:$G$26,1,Kosten!$I$12)*IF(Kosten!$D$12="Heizung/Warmwasser",Mieter!$L11,Mieter!$K11),0)) | K11: =IF(OR(Mieter!$D11="",Kosten!$H$13<>"Ja"),0,IFERROR(Kosten!$C$13*INDEX(Liegenschaft!$C$14:$G$25,MATCH(Mieter!$C11,Liegenschaft!$B$14:$B$25,0),Kosten!$I$13)/INDEX(Liegenschaft!$C$26:$G$26,1,Kosten!$I$13)*IF(Kosten!$D$13="Heizung/Warmwasser",Mieter!$L11,Mieter!$K11),0)) | L11: =IF(OR(Mieter!$D11="",Kosten!$H$14<>"Ja"),0,IFERROR(Kosten!$C$14*INDEX(Liegenschaft!$C$14:$G$25,MATCH(Mieter!$C11,Liegenschaft!$B$14:$B$25,0),Kosten!$I$14)/INDEX(Liegenschaft!$C$26:$G$26,1,Kosten!$I$14)*IF(Kosten!$D$14="Heizung/Warmwasser",Mieter!$L11,Mieter!$K11),0)) | M11: =IF(OR(Mieter!$D11="",Kosten!$H$15<>"Ja"),0,IFERROR(Kosten!$C$15*INDEX(Liegenschaft!$C$14:$G$25,MATCH(Mieter!$C11,Liegenschaft!$B$14:$B$25,0),Kosten!$I$15)/INDEX(Liegenschaft!$C$26:$G$26,1,Kosten!$I$15)*IF(Kosten!$D$15="Heizung/Warmwasser",Mieter!$L11,Mieter!$K11),0)) | N11: =IF(OR(Mieter!$D11="",Kosten!$H$16<>"Ja"),0,IFERROR(Kosten!$C$16*INDEX(Liegenschaft!$C$14:$G$25,MATCH(Mieter!$C11,Liegenschaft!$B$14:$B$25,0),Kosten!$I$16)/INDEX(Liegenschaft!$C$26:$G$26,1,Kosten!$I$16)*IF(Kosten!$D$16="Heizung/Warmwasser",Mieter!$L11,Mieter!$K11),0)) | O11: =IF(OR(Mieter!$D11="",Kosten!$H$17<>"Ja"),0,IFERROR(Kosten!$C$17*INDEX(Liegenschaft!$C$14:$G$25,MATCH(Mieter!$C11,Liegenschaft!$B$14:$B$25,0),Kosten!$I$17)/INDEX(Liegenschaft!$C$26:$G$26,1,Kosten!$I$17)*IF(Kosten!$D$17="Heizung/Warmwasser",Mieter!$L11,Mieter!$K11),0)) | P11: =IF(OR(Mieter!$D11="",Kosten!$H$18<>"Ja"),0,IFERROR(Kosten!$C$18*INDEX(Liegenschaft!$C$14:$G$25,MATCH(Mieter!$C11,Liegenschaft!$B$14:$B$25,0),Kosten!$I$18)/INDEX(Liegenschaft!$C$26:$G$26,1,Kosten!$I$18)*IF(Kosten!$D$18="Heizung/Warmwasser",Mieter!$L11,Mieter!$K11),0)) | Q11: =IF(OR(Mieter!$D11="",Kosten!$H$19<>"Ja"),0,IFERROR(Kosten!$C$19*INDEX(Liegenschaft!$C$14:$G$25,MATCH(Mieter!$C11,Liegenschaft!$B$14:$B$25,0),Kosten!$I$19)/INDEX(Liegenschaft!$C$26:$G$26,1,Kosten!$I$19)*IF(Kosten!$D$19="Heizung/Warmwasser",Mieter!$L11,Mieter!$K11),0)) | R11: =IF(OR(Mieter!$D11="",Kosten!$H$20<>"Ja"),0,IFERROR(Kosten!$C$20*INDEX(Liegenschaft!$C$14:$G$25,MATCH(Mieter!$C11,Liegenschaft!$B$14:$B$25,0),Kosten!$I$20)/INDEX(Liegenschaft!$C$26:$G$26,1,Kosten!$I$20)*IF(Kosten!$D$20="Heizung/Warmwasser",Mieter!$L11,Mieter!$K11),0)) | S11: =IF(OR(Mieter!$D11="",Kosten!$H$21<>"Ja"),0,IFERROR(Kosten!$C$21*INDEX(Liegenschaft!$C$14:$G$25,MATCH(Mieter!$C11,Liegenschaft!$B$14:$B$25,0),Kosten!$I$21)/INDEX(Liegenschaft!$C$26:$G$26,1,Kosten!$I$21)*IF(Kosten!$D$21="Heizung/Warmwasser",Mieter!$L11,Mieter!$K11),0)) | T11: =IF(OR(Mieter!$D11="",Kosten!$H$22<>"Ja"),0,IFERROR(Kosten!$C$22*INDEX(Liegenschaft!$C$14:$G$25,MATCH(Mieter!$C11,Liegenschaft!$B$14:$B$25,0),Kosten!$I$22)/INDEX(Liegenschaft!$C$26:$G$26,1,Kosten!$I$22)*IF(Kosten!$D$22="Heizung/Warmwasser",Mieter!$L11,Mieter!$K11),0)) | U11: =IF(OR(Mieter!$D11="",Kosten!$H$23<>"Ja"),0,IFERROR(Kosten!$C$23*INDEX(Liegenschaft!$C$14:$G$25,MATCH(Mieter!$C11,Liegenschaft!$B$14:$B$25,0),Kosten!$I$23)/INDEX(Liegenschaft!$C$26:$G$26,1,Kosten!$I$23)*IF(Kosten!$D$23="Heizung/Warmwasser",Mieter!$L11,Mieter!$K11),0)) | V11: =IF(OR(Mieter!$D11="",Kosten!$H$24<>"Ja"),0,IFERROR(Kosten!$C$24*INDEX(Liegenschaft!$C$14:$G$25,MATCH(Mieter!$C11,Liegenschaft!$B$14:$B$25,0),Kosten!$I$24)/INDEX(Liegenschaft!$C$26:$G$26,1,Kosten!$I$24)*IF(Kosten!$D$24="Heizung/Warmwasser",Mieter!$L11,Mieter!$K11),0)) | W11: =IF(OR(Mieter!$D11="",Kosten!$H$25<>"Ja"),0,IFERROR(Kosten!$C$25*INDEX(Liegenschaft!$C$14:$G$25,MATCH(Mieter!$C11,Liegenschaft!$B$14:$B$25,0),Kosten!$I$25)/INDEX(Liegenschaft!$C$26:$G$26,1,Kosten!$I$25)*IF(Kosten!$D$25="Heizung/Warmwasser",Mieter!$L11,Mieter!$K11),0)) | X11: =SUM(D11:W11) | Y11: =IF(Liegenschaft!$C$11="Ja",ROUND(X11*Liegenschaft!$C$10,2),0) | Z11: =ROUND(X11+Y11,2) | AA11: =N(Mieter!G11) | AB11: =IF(C11="",0,Z11-AA11)
B12: 7 | C12: =IF(Mieter!D12="","",Mieter!D12) | D12: =IF(OR(Mieter!$D12="",Kosten!$H$6<>"Ja"),0,IFERROR(Kosten!$C$6*INDEX(Liegenschaft!$C$14:$G$25,MATCH(Mieter!$C12,Liegenschaft!$B$14:$B$25,0),Kosten!$I$6)/INDEX(Liegenschaft!$C$26:$G$26,1,Kosten!$I$6)*IF(Kosten!$D$6="Heizung/Warmwasser",Mieter!$L12,Mieter!$K12),0)) | E12: =IF(OR(Mieter!$D12="",Kosten!$H$7<>"Ja"),0,IFERROR(Kosten!$C$7*INDEX(Liegenschaft!$C$14:$G$25,MATCH(Mieter!$C12,Liegenschaft!$B$14:$B$25,0),Kosten!$I$7)/INDEX(Liegenschaft!$C$26:$G$26,1,Kosten!$I$7)*IF(Kosten!$D$7="Heizung/Warmwasser",Mieter!$L12,Mieter!$K12),0)) | F12: =IF(OR(Mieter!$D12="",Kosten!$H$8<>"Ja"),0,IFERROR(Kosten!$C$8*INDEX(Liegenschaft!$C$14:$G$25,MATCH(Mieter!$C12,Liegenschaft!$B$14:$B$25,0),Kosten!$I$8)/INDEX(Liegenschaft!$C$26:$G$26,1,Kosten!$I$8)*IF(Kosten!$D$8="Heizung/Warmwasser",Mieter!$L12,Mieter!$K12),0)) | G12: =IF(OR(Mieter!$D12="",Kosten!$H$9<>"Ja"),0,IFERROR(Kosten!$C$9*INDEX(Liegenschaft!$C$14:$G$25,MATCH(Mieter!$C12,Liegenschaft!$B$14:$B$25,0),Kosten!$I$9)/INDEX(Liegenschaft!$C$26:$G$26,1,Kosten!$I$9)*IF(Kosten!$D$9="Heizung/Warmwasser",Mieter!$L12,Mieter!$K12),0)) | H12: =IF(OR(Mieter!$D12="",Kosten!$H$10<>"Ja"),0,IFERROR(Kosten!$C$10*INDEX(Liegenschaft!$C$14:$G$25,MATCH(Mieter!$C12,Liegenschaft!$B$14:$B$25,0),Kosten!$I$10)/INDEX(Liegenschaft!$C$26:$G$26,1,Kosten!$I$10)*IF(Kosten!$D$10="Heizung/Warmwasser",Mieter!$L12,Mieter!$K12),0)) | I12: =IF(OR(Mieter!$D12="",Kosten!$H$11<>"Ja"),0,IFERROR(Kosten!$C$11*INDEX(Liegenschaft!$C$14:$G$25,MATCH(Mieter!$C12,Liegenschaft!$B$14:$B$25,0),Kosten!$I$11)/INDEX(Liegenschaft!$C$26:$G$26,1,Kosten!$I$11)*IF(Kosten!$D$11="Heizung/Warmwasser",Mieter!$L12,Mieter!$K12),0)) | J12: =IF(OR(Mieter!$D12="",Kosten!$H$12<>"Ja"),0,IFERROR(Kosten!$C$12*INDEX(Liegenschaft!$C$14:$G$25,MATCH(Mieter!$C12,Liegenschaft!$B$14:$B$25,0),Kosten!$I$12)/INDEX(Liegenschaft!$C$26:$G$26,1,Kosten!$I$12)*IF(Kosten!$D$12="Heizung/Warmwasser",Mieter!$L12,Mieter!$K12),0)) | K12: =IF(OR(Mieter!$D12="",Kosten!$H$13<>"Ja"),0,IFERROR(Kosten!$C$13*INDEX(Liegenschaft!$C$14:$G$25,MATCH(Mieter!$C12,Liegenschaft!$B$14:$B$25,0),Kosten!$I$13)/INDEX(Liegenschaft!$C$26:$G$26,1,Kosten!$I$13)*IF(Kosten!$D$13="Heizung/Warmwasser",Mieter!$L12,Mieter!$K12),0)) | L12: =IF(OR(Mieter!$D12="",Kosten!$H$14<>"Ja"),0,IFERROR(Kosten!$C$14*INDEX(Liegenschaft!$C$14:$G$25,MATCH(Mieter!$C12,Liegenschaft!$B$14:$B$25,0),Kosten!$I$14)/INDEX(Liegenschaft!$C$26:$G$26,1,Kosten!$I$14)*IF(Kosten!$D$14="Heizung/Warmwasser",Mieter!$L12,Mieter!$K12),0)) | M12: =IF(OR(Mieter!$D12="",Kosten!$H$15<>"Ja"),0,IFERROR(Kosten!$C$15*INDEX(Liegenschaft!$C$14:$G$25,MATCH(Mieter!$C12,Liegenschaft!$B$14:$B$25,0),Kosten!$I$15)/INDEX(Liegenschaft!$C$26:$G$26,1,Kosten!$I$15)*IF(Kosten!$D$15="Heizung/Warmwasser",Mieter!$L12,Mieter!$K12),0)) | N12: =IF(OR(Mieter!$D12="",Kosten!$H$16<>"Ja"),0,IFERROR(Kosten!$C$16*INDEX(Liegenschaft!$C$14:$G$25,MATCH(Mieter!$C12,Liegenschaft!$B$14:$B$25,0),Kosten!$I$16)/INDEX(Liegenschaft!$C$26:$G$26,1,Kosten!$I$16)*IF(Kosten!$D$16="Heizung/Warmwasser",Mieter!$L12,Mieter!$K12),0)) | O12: =IF(OR(Mieter!$D12="",Kosten!$H$17<>"Ja"),0,IFERROR(Kosten!$C$17*INDEX(Liegenschaft!$C$14:$G$25,MATCH(Mieter!$C12,Liegenschaft!$B$14:$B$25,0),Kosten!$I$17)/INDEX(Liegenschaft!$C$26:$G$26,1,Kosten!$I$17)*IF(Kosten!$D$17="Heizung/Warmwasser",Mieter!$L12,Mieter!$K12),0)) | P12: =IF(OR(Mieter!$D12="",Kosten!$H$18<>"Ja"),0,IFERROR(Kosten!$C$18*INDEX(Liegenschaft!$C$14:$G$25,MATCH(Mieter!$C12,Liegenschaft!$B$14:$B$25,0),Kosten!$I$18)/INDEX(Liegenschaft!$C$26:$G$26,1,Kosten!$I$18)*IF(Kosten!$D$18="Heizung/Warmwasser",Mieter!$L12,Mieter!$K12),0)) | Q12: =IF(OR(Mieter!$D12="",Kosten!$H$19<>"Ja"),0,IFERROR(Kosten!$C$19*INDEX(Liegenschaft!$C$14:$G$25,MATCH(Mieter!$C12,Liegenschaft!$B$14:$B$25,0),Kosten!$I$19)/INDEX(Liegenschaft!$C$26:$G$26,1,Kosten!$I$19)*IF(Kosten!$D$19="Heizung/Warmwasser",Mieter!$L12,Mieter!$K12),0)) | R12: =IF(OR(Mieter!$D12="",Kosten!$H$20<>"Ja"),0,IFERROR(Kosten!$C$20*INDEX(Liegenschaft!$C$14:$G$25,MATCH(Mieter!$C12,Liegenschaft!$B$14:$B$25,0),Kosten!$I$20)/INDEX(Liegenschaft!$C$26:$G$26,1,Kosten!$I$20)*IF(Kosten!$D$20="Heizung/Warmwasser",Mieter!$L12,Mieter!$K12),0)) | S12: =IF(OR(Mieter!$D12="",Kosten!$H$21<>"Ja"),0,IFERROR(Kosten!$C$21*INDEX(Liegenschaft!$C$14:$G$25,MATCH(Mieter!$C12,Liegenschaft!$B$14:$B$25,0),Kosten!$I$21)/INDEX(Liegenschaft!$C$26:$G$26,1,Kosten!$I$21)*IF(Kosten!$D$21="Heizung/Warmwasser",Mieter!$L12,Mieter!$K12),0)) | T12: =IF(OR(Mieter!$D12="",Kosten!$H$22<>"Ja"),0,IFERROR(Kosten!$C$22*INDEX(Liegenschaft!$C$14:$G$25,MATCH(Mieter!$C12,Liegenschaft!$B$14:$B$25,0),Kosten!$I$22)/INDEX(Liegenschaft!$C$26:$G$26,1,Kosten!$I$22)*IF(Kosten!$D$22="Heizung/Warmwasser",Mieter!$L12,Mieter!$K12),0)) | U12: =IF(OR(Mieter!$D12="",Kosten!$H$23<>"Ja"),0,IFERROR(Kosten!$C$23*INDEX(Liegenschaft!$C$14:$G$25,MATCH(Mieter!$C12,Liegenschaft!$B$14:$B$25,0),Kosten!$I$23)/INDEX(Liegenschaft!$C$26:$G$26,1,Kosten!$I$23)*IF(Kosten!$D$23="Heizung/Warmwasser",Mieter!$L12,Mieter!$K12),0)) | V12: =IF(OR(Mieter!$D12="",Kosten!$H$24<>"Ja"),0,IFERROR(Kosten!$C$24*INDEX(Liegenschaft!$C$14:$G$25,MATCH(Mieter!$C12,Liegenschaft!$B$14:$B$25,0),Kosten!$I$24)/INDEX(Liegenschaft!$C$26:$G$26,1,Kosten!$I$24)*IF(Kosten!$D$24="Heizung/Warmwasser",Mieter!$L12,Mieter!$K12),0)) | W12: =IF(OR(Mieter!$D12="",Kosten!$H$25<>"Ja"),0,IFERROR(Kosten!$C$25*INDEX(Liegenschaft!$C$14:$G$25,MATCH(Mieter!$C12,Liegenschaft!$B$14:$B$25,0),Kosten!$I$25)/INDEX(Liegenschaft!$C$26:$G$26,1,Kosten!$I$25)*IF(Kosten!$D$25="Heizung/Warmwasser",Mieter!$L12,Mieter!$K12),0)) | X12: =SUM(D12:W12) | Y12: =IF(Liegenschaft!$C$11="Ja",ROUND(X12*Liegenschaft!$C$10,2),0) | Z12: =ROUND(X12+Y12,2) | AA12: =N(Mieter!G12) | AB12: =IF(C12="",0,Z12-AA12)
B13: 8 | C13: =IF(Mieter!D13="","",Mieter!D13) | D13: =IF(OR(Mieter!$D13="",Kosten!$H$6<>"Ja"),0,IFERROR(Kosten!$C$6*INDEX(Liegenschaft!$C$14:$G$25,MATCH(Mieter!$C13,Liegenschaft!$B$14:$B$25,0),Kosten!$I$6)/INDEX(Liegenschaft!$C$26:$G$26,1,Kosten!$I$6)*IF(Kosten!$D$6="Heizung/Warmwasser",Mieter!$L13,Mieter!$K13),0)) | E13: =IF(OR(Mieter!$D13="",Kosten!$H$7<>"Ja"),0,IFERROR(Kosten!$C$7*INDEX(Liegenschaft!$C$14:$G$25,MATCH(Mieter!$C13,Liegenschaft!$B$14:$B$25,0),Kosten!$I$7)/INDEX(Liegenschaft!$C$26:$G$26,1,Kosten!$I$7)*IF(Kosten!$D$7="Heizung/Warmwasser",Mieter!$L13,Mieter!$K13),0)) | F13: =IF(OR(Mieter!$D13="",Kosten!$H$8<>"Ja"),0,IFERROR(Kosten!$C$8*INDEX(Liegenschaft!$C$14:$G$25,MATCH(Mieter!$C13,Liegenschaft!$B$14:$B$25,0),Kosten!$I$8)/INDEX(Liegenschaft!$C$26:$G$26,1,Kosten!$I$8)*IF(Kosten!$D$8="Heizung/Warmwasser",Mieter!$L13,Mieter!$K13),0)) | G13: =IF(OR(Mieter!$D13="",Kosten!$H$9<>"Ja"),0,IFERROR(Kosten!$C$9*INDEX(Liegenschaft!$C$14:$G$25,MATCH(Mieter!$C13,Liegenschaft!$B$14:$B$25,0),Kosten!$I$9)/INDEX(Liegenschaft!$C$26:$G$26,1,Kosten!$I$9)*IF(Kosten!$D$9="Heizung/Warmwasser",Mieter!$L13,Mieter!$K13),0)) | H13: =IF(OR(Mieter!$D13="",Kosten!$H$10<>"Ja"),0,IFERROR(Kosten!$C$10*INDEX(Liegenschaft!$C$14:$G$25,MATCH(Mieter!$C13,Liegenschaft!$B$14:$B$25,0),Kosten!$I$10)/INDEX(Liegenschaft!$C$26:$G$26,1,Kosten!$I$10)*IF(Kosten!$D$10="Heizung/Warmwasser",Mieter!$L13,Mieter!$K13),0)) | I13: =IF(OR(Mieter!$D13="",Kosten!$H$11<>"Ja"),0,IFERROR(Kosten!$C$11*INDEX(Liegenschaft!$C$14:$G$25,MATCH(Mieter!$C13,Liegenschaft!$B$14:$B$25,0),Kosten!$I$11)/INDEX(Liegenschaft!$C$26:$G$26,1,Kosten!$I$11)*IF(Kosten!$D$11="Heizung/Warmwasser",Mieter!$L13,Mieter!$K13),0)) | J13: =IF(OR(Mieter!$D13="",Kosten!$H$12<>"Ja"),0,IFERROR(Kosten!$C$12*INDEX(Liegenschaft!$C$14:$G$25,MATCH(Mieter!$C13,Liegenschaft!$B$14:$B$25,0),Kosten!$I$12)/INDEX(Liegenschaft!$C$26:$G$26,1,Kosten!$I$12)*IF(Kosten!$D$12="Heizung/Warmwasser",Mieter!$L13,Mieter!$K13),0)) | K13: =IF(OR(Mieter!$D13="",Kosten!$H$13<>"Ja"),0,IFERROR(Kosten!$C$13*INDEX(Liegenschaft!$C$14:$G$25,MATCH(Mieter!$C13,Liegenschaft!$B$14:$B$25,0),Kosten!$I$13)/INDEX(Liegenschaft!$C$26:$G$26,1,Kosten!$I$13)*IF(Kosten!$D$13="Heizung/Warmwasser",Mieter!$L13,Mieter!$K13),0)) | L13: =IF(OR(Mieter!$D13="",Kosten!$H$14<>"Ja"),0,IFERROR(Kosten!$C$14*INDEX(Liegenschaft!$C$14:$G$25,MATCH(Mieter!$C13,Liegenschaft!$B$14:$B$25,0),Kosten!$I$14)/INDEX(Liegenschaft!$C$26:$G$26,1,Kosten!$I$14)*IF(Kosten!$D$14="Heizung/Warmwasser",Mieter!$L13,Mieter!$K13),0)) | M13: =IF(OR(Mieter!$D13="",Kosten!$H$15<>"Ja"),0,IFERROR(Kosten!$C$15*INDEX(Liegenschaft!$C$14:$G$25,MATCH(Mieter!$C13,Liegenschaft!$B$14:$B$25,0),Kosten!$I$15)/INDEX(Liegenschaft!$C$26:$G$26,1,Kosten!$I$15)*IF(Kosten!$D$15="Heizung/Warmwasser",Mieter!$L13,Mieter!$K13),0)) | N13: =IF(OR(Mieter!$D13="",Kosten!$H$16<>"Ja"),0,IFERROR(Kosten!$C$16*INDEX(Liegenschaft!$C$14:$G$25,MATCH(Mieter!$C13,Liegenschaft!$B$14:$B$25,0),Kosten!$I$16)/INDEX(Liegenschaft!$C$26:$G$26,1,Kosten!$I$16)*IF(Kosten!$D$16="Heizung/Warmwasser",Mieter!$L13,Mieter!$K13),0)) | O13: =IF(OR(Mieter!$D13="",Kosten!$H$17<>"Ja"),0,IFERROR(Kosten!$C$17*INDEX(Liegenschaft!$C$14:$G$25,MATCH(Mieter!$C13,Liegenschaft!$B$14:$B$25,0),Kosten!$I$17)/INDEX(Liegenschaft!$C$26:$G$26,1,Kosten!$I$17)*IF(Kosten!$D$17="Heizung/Warmwasser",Mieter!$L13,Mieter!$K13),0)) | P13: =IF(OR(Mieter!$D13="",Kosten!$H$18<>"Ja"),0,IFERROR(Kosten!$C$18*INDEX(Liegenschaft!$C$14:$G$25,MATCH(Mieter!$C13,Liegenschaft!$B$14:$B$25,0),Kosten!$I$18)/INDEX(Liegenschaft!$C$26:$G$26,1,Kosten!$I$18)*IF(Kosten!$D$18="Heizung/Warmwasser",Mieter!$L13,Mieter!$K13),0)) | Q13: =IF(OR(Mieter!$D13="",Kosten!$H$19<>"Ja"),0,IFERROR(Kosten!$C$19*INDEX(Liegenschaft!$C$14:$G$25,MATCH(Mieter!$C13,Liegenschaft!$B$14:$B$25,0),Kosten!$I$19)/INDEX(Liegenschaft!$C$26:$G$26,1,Kosten!$I$19)*IF(Kosten!$D$19="Heizung/Warmwasser",Mieter!$L13,Mieter!$K13),0)) | R13: =IF(OR(Mieter!$D13="",Kosten!$H$20<>"Ja"),0,IFERROR(Kosten!$C$20*INDEX(Liegenschaft!$C$14:$G$25,MATCH(Mieter!$C13,Liegenschaft!$B$14:$B$25,0),Kosten!$I$20)/INDEX(Liegenschaft!$C$26:$G$26,1,Kosten!$I$20)*IF(Kosten!$D$20="Heizung/Warmwasser",Mieter!$L13,Mieter!$K13),0)) | S13: =IF(OR(Mieter!$D13="",Kosten!$H$21<>"Ja"),0,IFERROR(Kosten!$C$21*INDEX(Liegenschaft!$C$14:$G$25,MATCH(Mieter!$C13,Liegenschaft!$B$14:$B$25,0),Kosten!$I$21)/INDEX(Liegenschaft!$C$26:$G$26,1,Kosten!$I$21)*IF(Kosten!$D$21="Heizung/Warmwasser",Mieter!$L13,Mieter!$K13),0)) | T13: =IF(OR(Mieter!$D13="",Kosten!$H$22<>"Ja"),0,IFERROR(Kosten!$C$22*INDEX(Liegenschaft!$C$14:$G$25,MATCH(Mieter!$C13,Liegenschaft!$B$14:$B$25,0),Kosten!$I$22)/INDEX(Liegenschaft!$C$26:$G$26,1,Kosten!$I$22)*IF(Kosten!$D$22="Heizung/Warmwasser",Mieter!$L13,Mieter!$K13),0)) | U13: =IF(OR(Mieter!$D13="",Kosten!$H$23<>"Ja"),0,IFERROR(Kosten!$C$23*INDEX(Liegenschaft!$C$14:$G$25,MATCH(Mieter!$C13,Liegenschaft!$B$14:$B$25,0),Kosten!$I$23)/INDEX(Liegenschaft!$C$26:$G$26,1,Kosten!$I$23)*IF(Kosten!$D$23="Heizung/Warmwasser",Mieter!$L13,Mieter!$K13),0)) | V13: =IF(OR(Mieter!$D13="",Kosten!$H$24<>"Ja"),0,IFERROR(Kosten!$C$24*INDEX(Liegenschaft!$C$14:$G$25,MATCH(Mieter!$C13,Liegenschaft!$B$14:$B$25,0),Kosten!$I$24)/INDEX(Liegenschaft!$C$26:$G$26,1,Kosten!$I$24)*IF(Kosten!$D$24="Heizung/Warmwasser",Mieter!$L13,Mieter!$K13),0)) | W13: =IF(OR(Mieter!$D13="",Kosten!$H$25<>"Ja"),0,IFERROR(Kosten!$C$25*INDEX(Liegenschaft!$C$14:$G$25,MATCH(Mieter!$C13,Liegenschaft!$B$14:$B$25,0),Kosten!$I$25)/INDEX(Liegenschaft!$C$26:$G$26,1,Kosten!$I$25)*IF(Kosten!$D$25="Heizung/Warmwasser",Mieter!$L13,Mieter!$K13),0)) | X13: =SUM(D13:W13) | Y13: =IF(Liegenschaft!$C$11="Ja",ROUND(X13*Liegenschaft!$C$10,2),0) | Z13: =ROUND(X13+Y13,2) | AA13: =N(Mieter!G13) | AB13: =IF(C13="",0,Z13-AA13)
B14: 9 | C14: =IF(Mieter!D14="","",Mieter!D14) | D14: =IF(OR(Mieter!$D14="",Kosten!$H$6<>"Ja"),0,IFERROR(Kosten!$C$6*INDEX(Liegenschaft!$C$14:$G$25,MATCH(Mieter!$C14,Liegenschaft!$B$14:$B$25,0),Kosten!$I$6)/INDEX(Liegenschaft!$C$26:$G$26,1,Kosten!$I$6)*IF(Kosten!$D$6="Heizung/Warmwasser",Mieter!$L14,Mieter!$K14),0)) | E14: =IF(OR(Mieter!$D14="",Kosten!$H$7<>"Ja"),0,IFERROR(Kosten!$C$7*INDEX(Liegenschaft!$C$14:$G$25,MATCH(Mieter!$C14,Liegenschaft!$B$14:$B$25,0),Kosten!$I$7)/INDEX(Liegenschaft!$C$26:$G$26,1,Kosten!$I$7)*IF(Kosten!$D$7="Heizung/Warmwasser",Mieter!$L14,Mieter!$K14),0)) | F14: =IF(OR(Mieter!$D14="",Kosten!$H$8<>"Ja"),0,IFERROR(Kosten!$C$8*INDEX(Liegenschaft!$C$14:$G$25,MATCH(Mieter!$C14,Liegenschaft!$B$14:$B$25,0),Kosten!$I$8)/INDEX(Liegenschaft!$C$26:$G$26,1,Kosten!$I$8)*IF(Kosten!$D$8="Heizung/Warmwasser",Mieter!$L14,Mieter!$K14),0)) | G14: =IF(OR(Mieter!$D14="",Kosten!$H$9<>"Ja"),0,IFERROR(Kosten!$C$9*INDEX(Liegenschaft!$C$14:$G$25,MATCH(Mieter!$C14,Liegenschaft!$B$14:$B$25,0),Kosten!$I$9)/INDEX(Liegenschaft!$C$26:$G$26,1,Kosten!$I$9)*IF(Kosten!$D$9="Heizung/Warmwasser",Mieter!$L14,Mieter!$K14),0)) | H14: =IF(OR(Mieter!$D14="",Kosten!$H$10<>"Ja"),0,IFERROR(Kosten!$C$10*INDEX(Liegenschaft!$C$14:$G$25,MATCH(Mieter!$C14,Liegenschaft!$B$14:$B$25,0),Kosten!$I$10)/INDEX(Liegenschaft!$C$26:$G$26,1,Kosten!$I$10)*IF(Kosten!$D$10="Heizung/Warmwasser",Mieter!$L14,Mieter!$K14),0)) | I14: =IF(OR(Mieter!$D14="",Kosten!$H$11<>"Ja"),0,IFERROR(Kosten!$C$11*INDEX(Liegenschaft!$C$14:$G$25,MATCH(Mieter!$C14,Liegenschaft!$B$14:$B$25,0),Kosten!$I$11)/INDEX(Liegenschaft!$C$26:$G$26,1,Kosten!$I$11)*IF(Kosten!$D$11="Heizung/Warmwasser",Mieter!$L14,Mieter!$K14),0)) | J14: =IF(OR(Mieter!$D14="",Kosten!$H$12<>"Ja"),0,IFERROR(Kosten!$C$12*INDEX(Liegenschaft!$C$14:$G$25,MATCH(Mieter!$C14,Liegenschaft!$B$14:$B$25,0),Kosten!$I$12)/INDEX(Liegenschaft!$C$26:$G$26,1,Kosten!$I$12)*IF(Kosten!$D$12="Heizung/Warmwasser",Mieter!$L14,Mieter!$K14),0)) | K14: =IF(OR(Mieter!$D14="",Kosten!$H$13<>"Ja"),0,IFERROR(Kosten!$C$13*INDEX(Liegenschaft!$C$14:$G$25,MATCH(Mieter!$C14,Liegenschaft!$B$14:$B$25,0),Kosten!$I$13)/INDEX(Liegenschaft!$C$26:$G$26,1,Kosten!$I$13)*IF(Kosten!$D$13="Heizung/Warmwasser",Mieter!$L14,Mieter!$K14),0)) | L14: =IF(OR(Mieter!$D14="",Kosten!$H$14<>"Ja"),0,IFERROR(Kosten!$C$14*INDEX(Liegenschaft!$C$14:$G$25,MATCH(Mieter!$C14,Liegenschaft!$B$14:$B$25,0),Kosten!$I$14)/INDEX(Liegenschaft!$C$26:$G$26,1,Kosten!$I$14)*IF(Kosten!$D$14="Heizung/Warmwasser",Mieter!$L14,Mieter!$K14),0)) | M14: =IF(OR(Mieter!$D14="",Kosten!$H$15<>"Ja"),0,IFERROR(Kosten!$C$15*INDEX(Liegenschaft!$C$14:$G$25,MATCH(Mieter!$C14,Liegenschaft!$B$14:$B$25,0),Kosten!$I$15)/INDEX(Liegenschaft!$C$26:$G$26,1,Kosten!$I$15)*IF(Kosten!$D$15="Heizung/Warmwasser",Mieter!$L14,Mieter!$K14),0)) | N14: =IF(OR(Mieter!$D14="",Kosten!$H$16<>"Ja"),0,IFERROR(Kosten!$C$16*INDEX(Liegenschaft!$C$14:$G$25,MATCH(Mieter!$C14,Liegenschaft!$B$14:$B$25,0),Kosten!$I$16)/INDEX(Liegenschaft!$C$26:$G$26,1,Kosten!$I$16)*IF(Kosten!$D$16="Heizung/Warmwasser",Mieter!$L14,Mieter!$K14),0)) | O14: =IF(OR(Mieter!$D14="",Kosten!$H$17<>"Ja"),0,IFERROR(Kosten!$C$17*INDEX(Liegenschaft!$C$14:$G$25,MATCH(Mieter!$C14,Liegenschaft!$B$14:$B$25,0),Kosten!$I$17)/INDEX(Liegenschaft!$C$26:$G$26,1,Kosten!$I$17)*IF(Kosten!$D$17="Heizung/Warmwasser",Mieter!$L14,Mieter!$K14),0)) | P14: =IF(OR(Mieter!$D14="",Kosten!$H$18<>"Ja"),0,IFERROR(Kosten!$C$18*INDEX(Liegenschaft!$C$14:$G$25,MATCH(Mieter!$C14,Liegenschaft!$B$14:$B$25,0),Kosten!$I$18)/INDEX(Liegenschaft!$C$26:$G$26,1,Kosten!$I$18)*IF(Kosten!$D$18="Heizung/Warmwasser",Mieter!$L14,Mieter!$K14),0)) | Q14: =IF(OR(Mieter!$D14="",Kosten!$H$19<>"Ja"),0,IFERROR(Kosten!$C$19*INDEX(Liegenschaft!$C$14:$G$25,MATCH(Mieter!$C14,Liegenschaft!$B$14:$B$25,0),Kosten!$I$19)/INDEX(Liegenschaft!$C$26:$G$26,1,Kosten!$I$19)*IF(Kosten!$D$19="Heizung/Warmwasser",Mieter!$L14,Mieter!$K14),0)) | R14: =IF(OR(Mieter!$D14="",Kosten!$H$20<>"Ja"),0,IFERROR(Kosten!$C$20*INDEX(Liegenschaft!$C$14:$G$25,MATCH(Mieter!$C14,Liegenschaft!$B$14:$B$25,0),Kosten!$I$20)/INDEX(Liegenschaft!$C$26:$G$26,1,Kosten!$I$20)*IF(Kosten!$D$20="Heizung/Warmwasser",Mieter!$L14,Mieter!$K14),0)) | S14: =IF(OR(Mieter!$D14="",Kosten!$H$21<>"Ja"),0,IFERROR(Kosten!$C$21*INDEX(Liegenschaft!$C$14:$G$25,MATCH(Mieter!$C14,Liegenschaft!$B$14:$B$25,0),Kosten!$I$21)/INDEX(Liegenschaft!$C$26:$G$26,1,Kosten!$I$21)*IF(Kosten!$D$21="Heizung/Warmwasser",Mieter!$L14,Mieter!$K14),0)) | T14: =IF(OR(Mieter!$D14="",Kosten!$H$22<>"Ja"),0,IFERROR(Kosten!$C$22*INDEX(Liegenschaft!$C$14:$G$25,MATCH(Mieter!$C14,Liegenschaft!$B$14:$B$25,0),Kosten!$I$22)/INDEX(Liegenschaft!$C$26:$G$26,1,Kosten!$I$22)*IF(Kosten!$D$22="Heizung/Warmwasser",Mieter!$L14,Mieter!$K14),0)) | U14: =IF(OR(Mieter!$D14="",Kosten!$H$23<>"Ja"),0,IFERROR(Kosten!$C$23*INDEX(Liegenschaft!$C$14:$G$25,MATCH(Mieter!$C14,Liegenschaft!$B$14:$B$25,0),Kosten!$I$23)/INDEX(Liegenschaft!$C$26:$G$26,1,Kosten!$I$23)*IF(Kosten!$D$23="Heizung/Warmwasser",Mieter!$L14,Mieter!$K14),0)) | V14: =IF(OR(Mieter!$D14="",Kosten!$H$24<>"Ja"),0,IFERROR(Kosten!$C$24*INDEX(Liegenschaft!$C$14:$G$25,MATCH(Mieter!$C14,Liegenschaft!$B$14:$B$25,0),Kosten!$I$24)/INDEX(Liegenschaft!$C$26:$G$26,1,Kosten!$I$24)*IF(Kosten!$D$24="Heizung/Warmwasser",Mieter!$L14,Mieter!$K14),0)) | W14: =IF(OR(Mieter!$D14="",Kosten!$H$25<>"Ja"),0,IFERROR(Kosten!$C$25*INDEX(Liegenschaft!$C$14:$G$25,MATCH(Mieter!$C14,Liegenschaft!$B$14:$B$25,0),Kosten!$I$25)/INDEX(Liegenschaft!$C$26:$G$26,1,Kosten!$I$25)*IF(Kosten!$D$25="Heizung/Warmwasser",Mieter!$L14,Mieter!$K14),0)) | X14: =SUM(D14:W14) | Y14: =IF(Liegenschaft!$C$11="Ja",ROUND(X14*Liegenschaft!$C$10,2),0) | Z14: =ROUND(X14+Y14,2) | AA14: =N(Mieter!G14) | AB14: =IF(C14="",0,Z14-AA14)
B15: 10 | C15: =IF(Mieter!D15="","",Mieter!D15) | D15: =IF(OR(Mieter!$D15="",Kosten!$H$6<>"Ja"),0,IFERROR(Kosten!$C$6*INDEX(Liegenschaft!$C$14:$G$25,MATCH(Mieter!$C15,Liegenschaft!$B$14:$B$25,0),Kosten!$I$6)/INDEX(Liegenschaft!$C$26:$G$26,1,Kosten!$I$6)*IF(Kosten!$D$6="Heizung/Warmwasser",Mieter!$L15,Mieter!$K15),0)) | E15: =IF(OR(Mieter!$D15="",Kosten!$H$7<>"Ja"),0,IFERROR(Kosten!$C$7*INDEX(Liegenschaft!$C$14:$G$25,MATCH(Mieter!$C15,Liegenschaft!$B$14:$B$25,0),Kosten!$I$7)/INDEX(Liegenschaft!$C$26:$G$26,1,Kosten!$I$7)*IF(Kosten!$D$7="Heizung/Warmwasser",Mieter!$L15,Mieter!$K15),0)) | F15: =IF(OR(Mieter!$D15="",Kosten!$H$8<>"Ja"),0,IFERROR(Kosten!$C$8*INDEX(Liegenschaft!$C$14:$G$25,MATCH(Mieter!$C15,Liegenschaft!$B$14:$B$25,0),Kosten!$I$8)/INDEX(Liegenschaft!$C$26:$G$26,1,Kosten!$I$8)*IF(Kosten!$D$8="Heizung/Warmwasser",Mieter!$L15,Mieter!$K15),0)) | G15: =IF(OR(Mieter!$D15="",Kosten!$H$9<>"Ja"),0,IFERROR(Kosten!$C$9*INDEX(Liegenschaft!$C$14:$G$25,MATCH(Mieter!$C15,Liegenschaft!$B$14:$B$25,0),Kosten!$I$9)/INDEX(Liegenschaft!$C$26:$G$26,1,Kosten!$I$9)*IF(Kosten!$D$9="Heizung/Warmwasser",Mieter!$L15,Mieter!$K15),0)) | H15: =IF(OR(Mieter!$D15="",Kosten!$H$10<>"Ja"),0,IFERROR(Kosten!$C$10*INDEX(Liegenschaft!$C$14:$G$25,MATCH(Mieter!$C15,Liegenschaft!$B$14:$B$25,0),Kosten!$I$10)/INDEX(Liegenschaft!$C$26:$G$26,1,Kosten!$I$10)*IF(Kosten!$D$10="Heizung/Warmwasser",Mieter!$L15,Mieter!$K15),0)) | I15: =IF(OR(Mieter!$D15="",Kosten!$H$11<>"Ja"),0,IFERROR(Kosten!$C$11*INDEX(Liegenschaft!$C$14:$G$25,MATCH(Mieter!$C15,Liegenschaft!$B$14:$B$25,0),Kosten!$I$11)/INDEX(Liegenschaft!$C$26:$G$26,1,Kosten!$I$11)*IF(Kosten!$D$11="Heizung/Warmwasser",Mieter!$L15,Mieter!$K15),0)) | J15: =IF(OR(Mieter!$D15="",Kosten!$H$12<>"Ja"),0,IFERROR(Kosten!$C$12*INDEX(Liegenschaft!$C$14:$G$25,MATCH(Mieter!$C15,Liegenschaft!$B$14:$B$25,0),Kosten!$I$12)/INDEX(Liegenschaft!$C$26:$G$26,1,Kosten!$I$12)*IF(Kosten!$D$12="Heizung/Warmwasser",Mieter!$L15,Mieter!$K15),0)) | K15: =IF(OR(Mieter!$D15="",Kosten!$H$13<>"Ja"),0,IFERROR(Kosten!$C$13*INDEX(Liegenschaft!$C$14:$G$25,MATCH(Mieter!$C15,Liegenschaft!$B$14:$B$25,0),Kosten!$I$13)/INDEX(Liegenschaft!$C$26:$G$26,1,Kosten!$I$13)*IF(Kosten!$D$13="Heizung/Warmwasser",Mieter!$L15,Mieter!$K15),0)) | L15: =IF(OR(Mieter!$D15="",Kosten!$H$14<>"Ja"),0,IFERROR(Kosten!$C$14*INDEX(Liegenschaft!$C$14:$G$25,MATCH(Mieter!$C15,Liegenschaft!$B$14:$B$25,0),Kosten!$I$14)/INDEX(Liegenschaft!$C$26:$G$26,1,Kosten!$I$14)*IF(Kosten!$D$14="Heizung/Warmwasser",Mieter!$L15,Mieter!$K15),0)) | M15: =IF(OR(Mieter!$D15="",Kosten!$H$15<>"Ja"),0,IFERROR(Kosten!$C$15*INDEX(Liegenschaft!$C$14:$G$25,MATCH(Mieter!$C15,Liegenschaft!$B$14:$B$25,0),Kosten!$I$15)/INDEX(Liegenschaft!$C$26:$G$26,1,Kosten!$I$15)*IF(Kosten!$D$15="Heizung/Warmwasser",Mieter!$L15,Mieter!$K15),0)) | N15: =IF(OR(Mieter!$D15="",Kosten!$H$16<>"Ja"),0,IFERROR(Kosten!$C$16*INDEX(Liegenschaft!$C$14:$G$25,MATCH(Mieter!$C15,Liegenschaft!$B$14:$B$25,0),Kosten!$I$16)/INDEX(Liegenschaft!$C$26:$G$26,1,Kosten!$I$16)*IF(Kosten!$D$16="Heizung/Warmwasser",Mieter!$L15,Mieter!$K15),0)) | O15: =IF(OR(Mieter!$D15="",Kosten!$H$17<>"Ja"),0,IFERROR(Kosten!$C$17*INDEX(Liegenschaft!$C$14:$G$25,MATCH(Mieter!$C15,Liegenschaft!$B$14:$B$25,0),Kosten!$I$17)/INDEX(Liegenschaft!$C$26:$G$26,1,Kosten!$I$17)*IF(Kosten!$D$17="Heizung/Warmwasser",Mieter!$L15,Mieter!$K15),0)) | P15: =IF(OR(Mieter!$D15="",Kosten!$H$18<>"Ja"),0,IFERROR(Kosten!$C$18*INDEX(Liegenschaft!$C$14:$G$25,MATCH(Mieter!$C15,Liegenschaft!$B$14:$B$25,0),Kosten!$I$18)/INDEX(Liegenschaft!$C$26:$G$26,1,Kosten!$I$18)*IF(Kosten!$D$18="Heizung/Warmwasser",Mieter!$L15,Mieter!$K15),0)) | Q15: =IF(OR(Mieter!$D15="",Kosten!$H$19<>"Ja"),0,IFERROR(Kosten!$C$19*INDEX(Liegenschaft!$C$14:$G$25,MATCH(Mieter!$C15,Liegenschaft!$B$14:$B$25,0),Kosten!$I$19)/INDEX(Liegenschaft!$C$26:$G$26,1,Kosten!$I$19)*IF(Kosten!$D$19="Heizung/Warmwasser",Mieter!$L15,Mieter!$K15),0)) | R15: =IF(OR(Mieter!$D15="",Kosten!$H$20<>"Ja"),0,IFERROR(Kosten!$C$20*INDEX(Liegenschaft!$C$14:$G$25,MATCH(Mieter!$C15,Liegenschaft!$B$14:$B$25,0),Kosten!$I$20)/INDEX(Liegenschaft!$C$26:$G$26,1,Kosten!$I$20)*IF(Kosten!$D$20="Heizung/Warmwasser",Mieter!$L15,Mieter!$K15),0)) | S15: =IF(OR(Mieter!$D15="",Kosten!$H$21<>"Ja"),0,IFERROR(Kosten!$C$21*INDEX(Liegenschaft!$C$14:$G$25,MATCH(Mieter!$C15,Liegenschaft!$B$14:$B$25,0),Kosten!$I$21)/INDEX(Liegenschaft!$C$26:$G$26,1,Kosten!$I$21)*IF(Kosten!$D$21="Heizung/Warmwasser",Mieter!$L15,Mieter!$K15),0)) | T15: =IF(OR(Mieter!$D15="",Kosten!$H$22<>"Ja"),0,IFERROR(Kosten!$C$22*INDEX(Liegenschaft!$C$14:$G$25,MATCH(Mieter!$C15,Liegenschaft!$B$14:$B$25,0),Kosten!$I$22)/INDEX(Liegenschaft!$C$26:$G$26,1,Kosten!$I$22)*IF(Kosten!$D$22="Heizung/Warmwasser",Mieter!$L15,Mieter!$K15),0)) | U15: =IF(OR(Mieter!$D15="",Kosten!$H$23<>"Ja"),0,IFERROR(Kosten!$C$23*INDEX(Liegenschaft!$C$14:$G$25,MATCH(Mieter!$C15,Liegenschaft!$B$14:$B$25,0),Kosten!$I$23)/INDEX(Liegenschaft!$C$26:$G$26,1,Kosten!$I$23)*IF(Kosten!$D$23="Heizung/Warmwasser",Mieter!$L15,Mieter!$K15),0)) | V15: =IF(OR(Mieter!$D15="",Kosten!$H$24<>"Ja"),0,IFERROR(Kosten!$C$24*INDEX(Liegenschaft!$C$14:$G$25,MATCH(Mieter!$C15,Liegenschaft!$B$14:$B$25,0),Kosten!$I$24)/INDEX(Liegenschaft!$C$26:$G$26,1,Kosten!$I$24)*IF(Kosten!$D$24="Heizung/Warmwasser",Mieter!$L15,Mieter!$K15),0)) | W15: =IF(OR(Mieter!$D15="",Kosten!$H$25<>"Ja"),0,IFERROR(Kosten!$C$25*INDEX(Liegenschaft!$C$14:$G$25,MATCH(Mieter!$C15,Liegenschaft!$B$14:$B$25,0),Kosten!$I$25)/INDEX(Liegenschaft!$C$26:$G$26,1,Kosten!$I$25)*IF(Kosten!$D$25="Heizung/Warmwasser",Mieter!$L15,Mieter!$K15),0)) | X15: =SUM(D15:W15) | Y15: =IF(Liegenschaft!$C$11="Ja",ROUND(X15*Liegenschaft!$C$10,2),0) | Z15: =ROUND(X15+Y15,2) | AA15: =N(Mieter!G15) | AB15: =IF(C15="",0,Z15-AA15)
B16: 11 | C16: =IF(Mieter!D16="","",Mieter!D16) | D16: =IF(OR(Mieter!$D16="",Kosten!$H$6<>"Ja"),0,IFERROR(Kosten!$C$6*INDEX(Liegenschaft!$C$14:$G$25,MATCH(Mieter!$C16,Liegenschaft!$B$14:$B$25,0),Kosten!$I$6)/INDEX(Liegenschaft!$C$26:$G$26,1,Kosten!$I$6)*IF(Kosten!$D$6="Heizung/Warmwasser",Mieter!$L16,Mieter!$K16),0)) | E16: =IF(OR(Mieter!$D16="",Kosten!$H$7<>"Ja"),0,IFERROR(Kosten!$C$7*INDEX(Liegenschaft!$C$14:$G$25,MATCH(Mieter!$C16,Liegenschaft!$B$14:$B$25,0),Kosten!$I$7)/INDEX(Liegenschaft!$C$26:$G$26,1,Kosten!$I$7)*IF(Kosten!$D$7="Heizung/Warmwasser",Mieter!$L16,Mieter!$K16),0)) | F16: =IF(OR(Mieter!$D16="",Kosten!$H$8<>"Ja"),0,IFERROR(Kosten!$C$8*INDEX(Liegenschaft!$C$14:$G$25,MATCH(Mieter!$C16,Liegenschaft!$B$14:$B$25,0),Kosten!$I$8)/INDEX(Liegenschaft!$C$26:$G$26,1,Kosten!$I$8)*IF(Kosten!$D$8="Heizung/Warmwasser",Mieter!$L16,Mieter!$K16),0)) | G16: =IF(OR(Mieter!$D16="",Kosten!$H$9<>"Ja"),0,IFERROR(Kosten!$C$9*INDEX(Liegenschaft!$C$14:$G$25,MATCH(Mieter!$C16,Liegenschaft!$B$14:$B$25,0),Kosten!$I$9)/INDEX(Liegenschaft!$C$26:$G$26,1,Kosten!$I$9)*IF(Kosten!$D$9="Heizung/Warmwasser",Mieter!$L16,Mieter!$K16),0)) | H16: =IF(OR(Mieter!$D16="",Kosten!$H$10<>"Ja"),0,IFERROR(Kosten!$C$10*INDEX(Liegenschaft!$C$14:$G$25,MATCH(Mieter!$C16,Liegenschaft!$B$14:$B$25,0),Kosten!$I$10)/INDEX(Liegenschaft!$C$26:$G$26,1,Kosten!$I$10)*IF(Kosten!$D$10="Heizung/Warmwasser",Mieter!$L16,Mieter!$K16),0)) | I16: =IF(OR(Mieter!$D16="",Kosten!$H$11<>"Ja"),0,IFERROR(Kosten!$C$11*INDEX(Liegenschaft!$C$14:$G$25,MATCH(Mieter!$C16,Liegenschaft!$B$14:$B$25,0),Kosten!$I$11)/INDEX(Liegenschaft!$C$26:$G$26,1,Kosten!$I$11)*IF(Kosten!$D$11="Heizung/Warmwasser",Mieter!$L16,Mieter!$K16),0)) | J16: =IF(OR(Mieter!$D16="",Kosten!$H$12<>"Ja"),0,IFERROR(Kosten!$C$12*INDEX(Liegenschaft!$C$14:$G$25,MATCH(Mieter!$C16,Liegenschaft!$B$14:$B$25,0),Kosten!$I$12)/INDEX(Liegenschaft!$C$26:$G$26,1,Kosten!$I$12)*IF(Kosten!$D$12="Heizung/Warmwasser",Mieter!$L16,Mieter!$K16),0)) | K16: =IF(OR(Mieter!$D16="",Kosten!$H$13<>"Ja"),0,IFERROR(Kosten!$C$13*INDEX(Liegenschaft!$C$14:$G$25,MATCH(Mieter!$C16,Liegenschaft!$B$14:$B$25,0),Kosten!$I$13)/INDEX(Liegenschaft!$C$26:$G$26,1,Kosten!$I$13)*IF(Kosten!$D$13="Heizung/Warmwasser",Mieter!$L16,Mieter!$K16),0)) | L16: =IF(OR(Mieter!$D16="",Kosten!$H$14<>"Ja"),0,IFERROR(Kosten!$C$14*INDEX(Liegenschaft!$C$14:$G$25,MATCH(Mieter!$C16,Liegenschaft!$B$14:$B$25,0),Kosten!$I$14)/INDEX(Liegenschaft!$C$26:$G$26,1,Kosten!$I$14)*IF(Kosten!$D$14="Heizung/Warmwasser",Mieter!$L16,Mieter!$K16),0)) | M16: =IF(OR(Mieter!$D16="",Kosten!$H$15<>"Ja"),0,IFERROR(Kosten!$C$15*INDEX(Liegenschaft!$C$14:$G$25,MATCH(Mieter!$C16,Liegenschaft!$B$14:$B$25,0),Kosten!$I$15)/INDEX(Liegenschaft!$C$26:$G$26,1,Kosten!$I$15)*IF(Kosten!$D$15="Heizung/Warmwasser",Mieter!$L16,Mieter!$K16),0)) | N16: =IF(OR(Mieter!$D16="",Kosten!$H$16<>"Ja"),0,IFERROR(Kosten!$C$16*INDEX(Liegenschaft!$C$14:$G$25,MATCH(Mieter!$C16,Liegenschaft!$B$14:$B$25,0),Kosten!$I$16)/INDEX(Liegenschaft!$C$26:$G$26,1,Kosten!$I$16)*IF(Kosten!$D$16="Heizung/Warmwasser",Mieter!$L16,Mieter!$K16),0)) | O16: =IF(OR(Mieter!$D16="",Kosten!$H$17<>"Ja"),0,IFERROR(Kosten!$C$17*INDEX(Liegenschaft!$C$14:$G$25,MATCH(Mieter!$C16,Liegenschaft!$B$14:$B$25,0),Kosten!$I$17)/INDEX(Liegenschaft!$C$26:$G$26,1,Kosten!$I$17)*IF(Kosten!$D$17="Heizung/Warmwasser",Mieter!$L16,Mieter!$K16),0)) | P16: =IF(OR(Mieter!$D16="",Kosten!$H$18<>"Ja"),0,IFERROR(Kosten!$C$18*INDEX(Liegenschaft!$C$14:$G$25,MATCH(Mieter!$C16,Liegenschaft!$B$14:$B$25,0),Kosten!$I$18)/INDEX(Liegenschaft!$C$26:$G$26,1,Kosten!$I$18)*IF(Kosten!$D$18="Heizung/Warmwasser",Mieter!$L16,Mieter!$K16),0)) | Q16: =IF(OR(Mieter!$D16="",Kosten!$H$19<>"Ja"),0,IFERROR(Kosten!$C$19*INDEX(Liegenschaft!$C$14:$G$25,MATCH(Mieter!$C16,Liegenschaft!$B$14:$B$25,0),Kosten!$I$19)/INDEX(Liegenschaft!$C$26:$G$26,1,Kosten!$I$19)*IF(Kosten!$D$19="Heizung/Warmwasser",Mieter!$L16,Mieter!$K16),0)) | R16: =IF(OR(Mieter!$D16="",Kosten!$H$20<>"Ja"),0,IFERROR(Kosten!$C$20*INDEX(Liegenschaft!$C$14:$G$25,MATCH(Mieter!$C16,Liegenschaft!$B$14:$B$25,0),Kosten!$I$20)/INDEX(Liegenschaft!$C$26:$G$26,1,Kosten!$I$20)*IF(Kosten!$D$20="Heizung/Warmwasser",Mieter!$L16,Mieter!$K16),0)) | S16: =IF(OR(Mieter!$D16="",Kosten!$H$21<>"Ja"),0,IFERROR(Kosten!$C$21*INDEX(Liegenschaft!$C$14:$G$25,MATCH(Mieter!$C16,Liegenschaft!$B$14:$B$25,0),Kosten!$I$21)/INDEX(Liegenschaft!$C$26:$G$26,1,Kosten!$I$21)*IF(Kosten!$D$21="Heizung/Warmwasser",Mieter!$L16,Mieter!$K16),0)) | T16: =IF(OR(Mieter!$D16="",Kosten!$H$22<>"Ja"),0,IFERROR(Kosten!$C$22*INDEX(Liegenschaft!$C$14:$G$25,MATCH(Mieter!$C16,Liegenschaft!$B$14:$B$25,0),Kosten!$I$22)/INDEX(Liegenschaft!$C$26:$G$26,1,Kosten!$I$22)*IF(Kosten!$D$22="Heizung/Warmwasser",Mieter!$L16,Mieter!$K16),0)) | U16: =IF(OR(Mieter!$D16="",Kosten!$H$23<>"Ja"),0,IFERROR(Kosten!$C$23*INDEX(Liegenschaft!$C$14:$G$25,MATCH(Mieter!$C16,Liegenschaft!$B$14:$B$25,0),Kosten!$I$23)/INDEX(Liegenschaft!$C$26:$G$26,1,Kosten!$I$23)*IF(Kosten!$D$23="Heizung/Warmwasser",Mieter!$L16,Mieter!$K16),0)) | V16: =IF(OR(Mieter!$D16="",Kosten!$H$24<>"Ja"),0,IFERROR(Kosten!$C$24*INDEX(Liegenschaft!$C$14:$G$25,MATCH(Mieter!$C16,Liegenschaft!$B$14:$B$25,0),Kosten!$I$24)/INDEX(Liegenschaft!$C$26:$G$26,1,Kosten!$I$24)*IF(Kosten!$D$24="Heizung/Warmwasser",Mieter!$L16,Mieter!$K16),0)) | W16: =IF(OR(Mieter!$D16="",Kosten!$H$25<>"Ja"),0,IFERROR(Kosten!$C$25*INDEX(Liegenschaft!$C$14:$G$25,MATCH(Mieter!$C16,Liegenschaft!$B$14:$B$25,0),Kosten!$I$25)/INDEX(Liegenschaft!$C$26:$G$26,1,Kosten!$I$25)*IF(Kosten!$D$25="Heizung/Warmwasser",Mieter!$L16,Mieter!$K16),0)) | X16: =SUM(D16:W16) | Y16: =IF(Liegenschaft!$C$11="Ja",ROUND(X16*Liegenschaft!$C$10,2),0) | Z16: =ROUND(X16+Y16,2) | AA16: =N(Mieter!G16) | AB16: =IF(C16="",0,Z16-AA16)
B17: 12 | C17: =IF(Mieter!D17="","",Mieter!D17) | D17: =IF(OR(Mieter!$D17="",Kosten!$H$6<>"Ja"),0,IFERROR(Kosten!$C$6*INDEX(Liegenschaft!$C$14:$G$25,MATCH(Mieter!$C17,Liegenschaft!$B$14:$B$25,0),Kosten!$I$6)/INDEX(Liegenschaft!$C$26:$G$26,1,Kosten!$I$6)*IF(Kosten!$D$6="Heizung/Warmwasser",Mieter!$L17,Mieter!$K17),0)) | E17: =IF(OR(Mieter!$D17="",Kosten!$H$7<>"Ja"),0,IFERROR(Kosten!$C$7*INDEX(Liegenschaft!$C$14:$G$25,MATCH(Mieter!$C17,Liegenschaft!$B$14:$B$25,0),Kosten!$I$7)/INDEX(Liegenschaft!$C$26:$G$26,1,Kosten!$I$7)*IF(Kosten!$D$7="Heizung/Warmwasser",Mieter!$L17,Mieter!$K17),0)) | F17: =IF(OR(Mieter!$D17="",Kosten!$H$8<>"Ja"),0,IFERROR(Kosten!$C$8*INDEX(Liegenschaft!$C$14:$G$25,MATCH(Mieter!$C17,Liegenschaft!$B$14:$B$25,0),Kosten!$I$8)/INDEX(Liegenschaft!$C$26:$G$26,1,Kosten!$I$8)*IF(Kosten!$D$8="Heizung/Warmwasser",Mieter!$L17,Mieter!$K17),0)) | G17: =IF(OR(Mieter!$D17="",Kosten!$H$9<>"Ja"),0,IFERROR(Kosten!$C$9*INDEX(Liegenschaft!$C$14:$G$25,MATCH(Mieter!$C17,Liegenschaft!$B$14:$B$25,0),Kosten!$I$9)/INDEX(Liegenschaft!$C$26:$G$26,1,Kosten!$I$9)*IF(Kosten!$D$9="Heizung/Warmwasser",Mieter!$L17,Mieter!$K17),0)) | H17: =IF(OR(Mieter!$D17="",Kosten!$H$10<>"Ja"),0,IFERROR(Kosten!$C$10*INDEX(Liegenschaft!$C$14:$G$25,MATCH(Mieter!$C17,Liegenschaft!$B$14:$B$25,0),Kosten!$I$10)/INDEX(Liegenschaft!$C$26:$G$26,1,Kosten!$I$10)*IF(Kosten!$D$10="Heizung/Warmwasser",Mieter!$L17,Mieter!$K17),0)) | I17: =IF(OR(Mieter!$D17="",Kosten!$H$11<>"Ja"),0,IFERROR(Kosten!$C$11*INDEX(Liegenschaft!$C$14:$G$25,MATCH(Mieter!$C17,Liegenschaft!$B$14:$B$25,0),Kosten!$I$11)/INDEX(Liegenschaft!$C$26:$G$26,1,Kosten!$I$11)*IF(Kosten!$D$11="Heizung/Warmwasser",Mieter!$L17,Mieter!$K17),0)) | J17: =IF(OR(Mieter!$D17="",Kosten!$H$12<>"Ja"),0,IFERROR(Kosten!$C$12*INDEX(Liegenschaft!$C$14:$G$25,MATCH(Mieter!$C17,Liegenschaft!$B$14:$B$25,0),Kosten!$I$12)/INDEX(Liegenschaft!$C$26:$G$26,1,Kosten!$I$12)*IF(Kosten!$D$12="Heizung/Warmwasser",Mieter!$L17,Mieter!$K17),0)) | K17: =IF(OR(Mieter!$D17="",Kosten!$H$13<>"Ja"),0,IFERROR(Kosten!$C$13*INDEX(Liegenschaft!$C$14:$G$25,MATCH(Mieter!$C17,Liegenschaft!$B$14:$B$25,0),Kosten!$I$13)/INDEX(Liegenschaft!$C$26:$G$26,1,Kosten!$I$13)*IF(Kosten!$D$13="Heizung/Warmwasser",Mieter!$L17,Mieter!$K17),0)) | L17: =IF(OR(Mieter!$D17="",Kosten!$H$14<>"Ja"),0,IFERROR(Kosten!$C$14*INDEX(Liegenschaft!$C$14:$G$25,MATCH(Mieter!$C17,Liegenschaft!$B$14:$B$25,0),Kosten!$I$14)/INDEX(Liegenschaft!$C$26:$G$26,1,Kosten!$I$14)*IF(Kosten!$D$14="Heizung/Warmwasser",Mieter!$L17,Mieter!$K17),0)) | M17: =IF(OR(Mieter!$D17="",Kosten!$H$15<>"Ja"),0,IFERROR(Kosten!$C$15*INDEX(Liegenschaft!$C$14:$G$25,MATCH(Mieter!$C17,Liegenschaft!$B$14:$B$25,0),Kosten!$I$15)/INDEX(Liegenschaft!$C$26:$G$26,1,Kosten!$I$15)*IF(Kosten!$D$15="Heizung/Warmwasser",Mieter!$L17,Mieter!$K17),0)) | N17: =IF(OR(Mieter!$D17="",Kosten!$H$16<>"Ja"),0,IFERROR(Kosten!$C$16*INDEX(Liegenschaft!$C$14:$G$25,MATCH(Mieter!$C17,Liegenschaft!$B$14:$B$25,0),Kosten!$I$16)/INDEX(Liegenschaft!$C$26:$G$26,1,Kosten!$I$16)*IF(Kosten!$D$16="Heizung/Warmwasser",Mieter!$L17,Mieter!$K17),0)) | O17: =IF(OR(Mieter!$D17="",Kosten!$H$17<>"Ja"),0,IFERROR(Kosten!$C$17*INDEX(Liegenschaft!$C$14:$G$25,MATCH(Mieter!$C17,Liegenschaft!$B$14:$B$25,0),Kosten!$I$17)/INDEX(Liegenschaft!$C$26:$G$26,1,Kosten!$I$17)*IF(Kosten!$D$17="Heizung/Warmwasser",Mieter!$L17,Mieter!$K17),0)) | P17: =IF(OR(Mieter!$D17="",Kosten!$H$18<>"Ja"),0,IFERROR(Kosten!$C$18*INDEX(Liegenschaft!$C$14:$G$25,MATCH(Mieter!$C17,Liegenschaft!$B$14:$B$25,0),Kosten!$I$18)/INDEX(Liegenschaft!$C$26:$G$26,1,Kosten!$I$18)*IF(Kosten!$D$18="Heizung/Warmwasser",Mieter!$L17,Mieter!$K17),0)) | Q17: =IF(OR(Mieter!$D17="",Kosten!$H$19<>"Ja"),0,IFERROR(Kosten!$C$19*INDEX(Liegenschaft!$C$14:$G$25,MATCH(Mieter!$C17,Liegenschaft!$B$14:$B$25,0),Kosten!$I$19)/INDEX(Liegenschaft!$C$26:$G$26,1,Kosten!$I$19)*IF(Kosten!$D$19="Heizung/Warmwasser",Mieter!$L17,Mieter!$K17),0)) | R17: =IF(OR(Mieter!$D17="",Kosten!$H$20<>"Ja"),0,IFERROR(Kosten!$C$20*INDEX(Liegenschaft!$C$14:$G$25,MATCH(Mieter!$C17,Liegenschaft!$B$14:$B$25,0),Kosten!$I$20)/INDEX(Liegenschaft!$C$26:$G$26,1,Kosten!$I$20)*IF(Kosten!$D$20="Heizung/Warmwasser",Mieter!$L17,Mieter!$K17),0)) | S17: =IF(OR(Mieter!$D17="",Kosten!$H$21<>"Ja"),0,IFERROR(Kosten!$C$21*INDEX(Liegenschaft!$C$14:$G$25,MATCH(Mieter!$C17,Liegenschaft!$B$14:$B$25,0),Kosten!$I$21)/INDEX(Liegenschaft!$C$26:$G$26,1,Kosten!$I$21)*IF(Kosten!$D$21="Heizung/Warmwasser",Mieter!$L17,Mieter!$K17),0)) | T17: =IF(OR(Mieter!$D17="",Kosten!$H$22<>"Ja"),0,IFERROR(Kosten!$C$22*INDEX(Liegenschaft!$C$14:$G$25,MATCH(Mieter!$C17,Liegenschaft!$B$14:$B$25,0),Kosten!$I$22)/INDEX(Liegenschaft!$C$26:$G$26,1,Kosten!$I$22)*IF(Kosten!$D$22="Heizung/Warmwasser",Mieter!$L17,Mieter!$K17),0)) | U17: =IF(OR(Mieter!$D17="",Kosten!$H$23<>"Ja"),0,IFERROR(Kosten!$C$23*INDEX(Liegenschaft!$C$14:$G$25,MATCH(Mieter!$C17,Liegenschaft!$B$14:$B$25,0),Kosten!$I$23)/INDEX(Liegenschaft!$C$26:$G$26,1,Kosten!$I$23)*IF(Kosten!$D$23="Heizung/Warmwasser",Mieter!$L17,Mieter!$K17),0)) | V17: =IF(OR(Mieter!$D17="",Kosten!$H$24<>"Ja"),0,IFERROR(Kosten!$C$24*INDEX(Liegenschaft!$C$14:$G$25,MATCH(Mieter!$C17,Liegenschaft!$B$14:$B$25,0),Kosten!$I$24)/INDEX(Liegenschaft!$C$26:$G$26,1,Kosten!$I$24)*IF(Kosten!$D$24="Heizung/Warmwasser",Mieter!$L17,Mieter!$K17),0)) | W17: =IF(OR(Mieter!$D17="",Kosten!$H$25<>"Ja"),0,IFERROR(Kosten!$C$25*INDEX(Liegenschaft!$C$14:$G$25,MATCH(Mieter!$C17,Liegenschaft!$B$14:$B$25,0),Kosten!$I$25)/INDEX(Liegenschaft!$C$26:$G$26,1,Kosten!$I$25)*IF(Kosten!$D$25="Heizung/Warmwasser",Mieter!$L17,Mieter!$K17),0)) | X17: =SUM(D17:W17) | Y17: =IF(Liegenschaft!$C$11="Ja",ROUND(X17*Liegenschaft!$C$10,2),0) | Z17: =ROUND(X17+Y17,2) | AA17: =N(Mieter!G17) | AB17: =IF(C17="",0,Z17-AA17)
... B35: 30 | C35: =IF(Mieter!D35="","",Mieter!D35) | D35: =IF(OR(Mieter!$D35="",Kosten!$H$6<>"Ja"),0,IFERROR(Kosten!$C$6*INDEX(Liegenschaft!$C$14:$G$25,MATCH(Mieter!$C35,Liegenschaft!$B$14:$B$25,0),Kosten!$I$6)/INDEX(Liegenschaft!$C$26:$G$26,1,Kosten!$I$6)*IF(Kosten!$D$6="Heizung/Warmwasser",Mieter!$L35,Mieter!$K35),0)) | E35: =IF(OR(Mieter!$D35="",Kosten!$H$7<>"Ja"),0,IFERROR(Kosten!$C$7*INDEX(Liegenschaft!$C$14:$G$25,MATCH(Mieter!$C35,Liegenschaft!$B$14:$B$25,0),Kosten!$I$7)/INDEX(Liegenschaft!$C$26:$G$26,1,Kosten!$I$7)*IF(Kosten!$D$7="Heizung/Warmwasser",Mieter!$L35,Mieter!$K35),0)) | F35: =IF(OR(Mieter!$D35="",Kosten!$H$8<>"Ja"),0,IFERROR(Kosten!$C$8*INDEX(Liegenschaft!$C$14:$G$25,MATCH(Mieter!$C35,Liegenschaft!$B$14:$B$25,0),Kosten!$I$8)/INDEX(Liegenschaft!$C$26:$G$26,1,Kosten!$I$8)*IF(Kosten!$D$8="Heizung/Warmwasser",Mieter!$L35,Mieter!$K35),0)) | G35: =IF(OR(Mieter!$D35="",Kosten!$H$9<>"Ja"),0,IFERROR(Kosten!$C$9*INDEX(Liegenschaft!$C$14:$G$25,MATCH(Mieter!$C35,Liegenschaft!$B$14:$B$25,0),Kosten!$I$9)/INDEX(Liegenschaft!$C$26:$G$26,1,Kosten!$I$9)*IF(Kosten!$D$9="Heizung/Warmwasser",Mieter!$L35,Mieter!$K35),0)) | H35: =IF(OR(Mieter!$D35="",Kosten!$H$10<>"Ja"),0,IFERROR(Kosten!$C$10*INDEX(Liegenschaft!$C$14:$G$25,MATCH(Mieter!$C35,Liegenschaft!$B$14:$B$25,0),Kosten!$I$10)/INDEX(Liegenschaft!$C$26:$G$26,1,Kosten!$I$10)*IF(Kosten!$D$10="Heizung/Warmwasser",Mieter!$L35,Mieter!$K35),0)) | I35: =IF(OR(Mieter!$D35="",Kosten!$H$11<>"Ja"),0,IFERROR(Kosten!$C$11*INDEX(Liegenschaft!$C$14:$G$25,MATCH(Mieter!$C35,Liegenschaft!$B$14:$B$25,0),Kosten!$I$11)/INDEX(Liegenschaft!$C$26:$G$26,1,Kosten!$I$11)*IF(Kosten!$D$11="Heizung/Warmwasser",Mieter!$L35,Mieter!$K35),0)) | J35: =IF(OR(Mieter!$D35="",Kosten!$H$12<>"Ja"),0,IFERROR(Kosten!$C$12*INDEX(Liegenschaft!$C$14:$G$25,MATCH(Mieter!$C35,Liegenschaft!$B$14:$B$25,0),Kosten!$I$12)/INDEX(Liegenschaft!$C$26:$G$26,1,Kosten!$I$12)*IF(Kosten!$D$12="Heizung/Warmwasser",Mieter!$L35,Mieter!$K35),0)) | K35: =IF(OR(Mieter!$D35="",Kosten!$H$13<>"Ja"),0,IFERROR(Kosten!$C$13*INDEX(Liegenschaft!$C$14:$G$25,MATCH(Mieter!$C35,Liegenschaft!$B$14:$B$25,0),Kosten!$I$13)/INDEX(Liegenschaft!$C$26:$G$26,1,Kosten!$I$13)*IF(Kosten!$D$13="Heizung/Warmwasser",Mieter!$L35,Mieter!$K35),0)) | L35: =IF(OR(Mieter!$D35="",Kosten!$H$14<>"Ja"),0,IFERROR(Kosten!$C$14*INDEX(Liegenschaft!$C$14:$G$25,MATCH(Mieter!$C35,Liegenschaft!$B$14:$B$25,0),Kosten!$I$14)/INDEX(Liegenschaft!$C$26:$G$26,1,Kosten!$I$14)*IF(Kosten!$D$14="Heizung/Warmwasser",Mieter!$L35,Mieter!$K35),0)) | M35: =IF(OR(Mieter!$D35="",Kosten!$H$15<>"Ja"),0,IFERROR(Kosten!$C$15*INDEX(Liegenschaft!$C$14:$G$25,MATCH(Mieter!$C35,Liegenschaft!$B$14:$B$25,0),Kosten!$I$15)/INDEX(Liegenschaft!$C$26:$G$26,1,Kosten!$I$15)*IF(Kosten!$D$15="Heizung/Warmwasser",Mieter!$L35,Mieter!$K35),0)) | N35: =IF(OR(Mieter!$D35="",Kosten!$H$16<>"Ja"),0,IFERROR(Kosten!$C$16*INDEX(Liegenschaft!$C$14:$G$25,MATCH(Mieter!$C35,Liegenschaft!$B$14:$B$25,0),Kosten!$I$16)/INDEX(Liegenschaft!$C$26:$G$26,1,Kosten!$I$16)*IF(Kosten!$D$16="Heizung/Warmwasser",Mieter!$L35,Mieter!$K35),0)) | O35: =IF(OR(Mieter!$D35="",Kosten!$H$17<>"Ja"),0,IFERROR(Kosten!$C$17*INDEX(Liegenschaft!$C$14:$G$25,MATCH(Mieter!$C35,Liegenschaft!$B$14:$B$25,0),Kosten!$I$17)/INDEX(Liegenschaft!$C$26:$G$26,1,Kosten!$I$17)*IF(Kosten!$D$17="Heizung/Warmwasser",Mieter!$L35,Mieter!$K35),0)) | P35: =IF(OR(Mieter!$D35="",Kosten!$H$18<>"Ja"),0,IFERROR(Kosten!$C$18*INDEX(Liegenschaft!$C$14:$G$25,MATCH(Mieter!$C35,Liegenschaft!$B$14:$B$25,0),Kosten!$I$18)/INDEX(Liegenschaft!$C$26:$G$26,1,Kosten!$I$18)*IF(Kosten!$D$18="Heizung/Warmwasser",Mieter!$L35,Mieter!$K35),0)) | Q35: =IF(OR(Mieter!$D35="",Kosten!$H$19<>"Ja"),0,IFERROR(Kosten!$C$19*INDEX(Liegenschaft!$C$14:$G$25,MATCH(Mieter!$C35,Liegenschaft!$B$14:$B$25,0),Kosten!$I$19)/INDEX(Liegenschaft!$C$26:$G$26,1,Kosten!$I$19)*IF(Kosten!$D$19="Heizung/Warmwasser",Mieter!$L35,Mieter!$K35),0)) | R35: =IF(OR(Mieter!$D35="",Kosten!$H$20<>"Ja"),0,IFERROR(Kosten!$C$20*INDEX(Liegenschaft!$C$14:$G$25,MATCH(Mieter!$C35,Liegenschaft!$B$14:$B$25,0),Kosten!$I$20)/INDEX(Liegenschaft!$C$26:$G$26,1,Kosten!$I$20)*IF(Kosten!$D$20="Heizung/Warmwasser",Mieter!$L35,Mieter!$K35),0)) | S35: =IF(OR(Mieter!$D35="",Kosten!$H$21<>"Ja"),0,IFERROR(Kosten!$C$21*INDEX(Liegenschaft!$C$14:$G$25,MATCH(Mieter!$C35,Liegenschaft!$B$14:$B$25,0),Kosten!$I$21)/INDEX(Liegenschaft!$C$26:$G$26,1,Kosten!$I$21)*IF(Kosten!$D$21="Heizung/Warmwasser",Mieter!$L35,Mieter!$K35),0)) | T35: =IF(OR(Mieter!$D35="",Kosten!$H$22<>"Ja"),0,IFERROR(Kosten!$C$22*INDEX(Liegenschaft!$C$14:$G$25,MATCH(Mieter!$C35,Liegenschaft!$B$14:$B$25,0),Kosten!$I$22)/INDEX(Liegenschaft!$C$26:$G$26,1,Kosten!$I$22)*IF(Kosten!$D$22="Heizung/Warmwasser",Mieter!$L35,Mieter!$K35),0)) | U35: =IF(OR(Mieter!$D35="",Kosten!$H$23<>"Ja"),0,IFERROR(Kosten!$C$23*INDEX(Liegenschaft!$C$14:$G$25,MATCH(Mieter!$C35,Liegenschaft!$B$14:$B$25,0),Kosten!$I$23)/INDEX(Liegenschaft!$C$26:$G$26,1,Kosten!$I$23)*IF(Kosten!$D$23="Heizung/Warmwasser",Mieter!$L35,Mieter!$K35),0)) | V35: =IF(OR(Mieter!$D35="",Kosten!$H$24<>"Ja"),0,IFERROR(Kosten!$C$24*INDEX(Liegenschaft!$C$14:$G$25,MATCH(Mieter!$C35,Liegenschaft!$B$14:$B$25,0),Kosten!$I$24)/INDEX(Liegenschaft!$C$26:$G$26,1,Kosten!$I$24)*IF(Kosten!$D$24="Heizung/Warmwasser",Mieter!$L35,Mieter!$K35),0)) | W35: =IF(OR(Mieter!$D35="",Kosten!$H$25<>"Ja"),0,IFERROR(Kosten!$C$25*INDEX(Liegenschaft!$C$14:$G$25,MATCH(Mieter!$C35,Liegenschaft!$B$14:$B$25,0),Kosten!$I$25)/INDEX(Liegenschaft!$C$26:$G$26,1,Kosten!$I$25)*IF(Kosten!$D$25="Heizung/Warmwasser",Mieter!$L35,Mieter!$K35),0)) | X35: =SUM(D35:W35) | Y35: =IF(Liegenschaft!$C$11="Ja",ROUND(X35*Liegenschaft!$C$10,2),0) | Z35: =ROUND(X35+Y35,2) | AA35: =N(Mieter!G35) | AB35: =IF(C35="",0,Z35-AA35)
C36: Total Mieter | D36: =SUM(D6:D35) | E36: =SUM(E6:E35) | F36: =SUM(F6:F35) | G36: =SUM(G6:G35) | H36: =SUM(H6:H35) | I36: =SUM(I6:I35) | J36: =SUM(J6:J35) | K36: =SUM(K6:K35) | ... AB36: =SUM(AB6:AB35)
C37: Vermieteranteil (Leerstand) | D37: =D38-D36 | E37: =E38-E36 | F37: =F38-F36 | G37: =G38-G36 | H37: =H38-H36 | I37: =I38-I36 | J37: =J38-J36 | K37: =K38-K36 | ... W37: =W38-W36 | X37: =SUM(D37:W37)
C38: Abrechenbar gesamt | D38: =IF(Kosten!$H$6="Ja",Kosten!$C$6,0) | E38: =IF(Kosten!$H$7="Ja",Kosten!$C$7,0) | F38: =IF(Kosten!$H$8="Ja",Kosten!$C$8,0) | G38: =IF(Kosten!$H$9="Ja",Kosten!$C$9,0) | H38: =IF(Kosten!$H$10="Ja",Kosten!$C$10,0) | I38: =IF(Kosten!$H$11="Ja",Kosten!$C$11,0) | J38: =IF(Kosten!$H$12="Ja",Kosten!$C$12,0) | K38: =IF(Kosten!$H$13="Ja",Kosten!$C$13,0) | L38: =IF(Kosten!$H$14="Ja",Kosten!$C$14,0) | M38: =IF(Kosten!$H$15="Ja",Kosten!$C$15,0) | N38: =IF(Kosten!$H$16="Ja",Kosten!$C$16,0) | O38: =IF(Kosten!$H$17="Ja",Kosten!$C$17,0) | P38: =IF(Kosten!$H$18="Ja",Kosten!$C$18,0) | Q38: =IF(Kosten!$H$19="Ja",Kosten!$C$19,0) | R38: =IF(Kosten!$H$20="Ja",Kosten!$C$20,0) | S38: =IF(Kosten!$H$21="Ja",Kosten!$C$21,0) | T38: =IF(Kosten!$H$22="Ja",Kosten!$C$22,0) | U38: =IF(Kosten!$H$23="Ja",Kosten!$C$23,0) | V38: =IF(Kosten!$H$24="Ja",Kosten!$C$24,0) | W38: =IF(Kosten!$H$25="Ja",Kosten!$C$25,0) | X38: =SUM(D38:W38)
C40: Kontrollsumme | D40: =IF(ABS(X36+X37-Kosten!C27)<0.01,"✓ Mieter + Vermieter = abrechenbare Kosten","⚠ Differenz – Wohnungsangaben prüfen")

Sheet Abrechnung
B2: Mieter-Nr. wählen: | C2: 1 | D2: (diese Zeile wird nicht gedruckt)
B4: =Liegenschaft!C6 | E4: =INDEX(Mieter!D:D,$C$2+5)
B5: =Liegenschaft!C4&", "&Liegenschaft!C5 | E5: ="Wohnung: "&INDEX(Mieter!C:C,$C$2+5)
B8: Heiz- und Nebenkostenabrechnung
B9: ="Periode "&TEXT(Liegenschaft!C7,"DD.MM.YYYY")&" – "&TEXT(Liegenschaft!C8,"DD.MM.YYYY")
B10: ="Ihre Mietdauer in der Periode: "&TEXT(INDEX(Mieter!H:H,$C$2+5),"DD.MM.YYYY")&" – "&TEXT(INDEX(Mieter!I:I,$C$2+5),"DD.MM.YYYY")&" ("&INDEX(Mieter!J:J,$C$2+5)&" Tage)"
B12: Kostenposition | C12: Kosten Liegenschaft | D12: Verteilschlüssel | E12: Anteil Wohnung | F12: Zeit-/Heizanteil | G12: Ihr Anteil CHF
B13: =IF(Kosten!$H$6="Ja",Kosten!B6,"") | C13: =IF(Kosten!$H$6="Ja",Kosten!C6,"") | D13: =IF(Kosten!$H$6="Ja",Kosten!E6,"") | E13: =IF(Kosten!$H$6="Ja",IFERROR(INDEX(Liegenschaft!$C$14:$G$25,MATCH(INDEX(Mieter!C:C,$C$2+5),Liegenschaft!$B$14:$B$25,0),Kosten!$I$6)/INDEX(Liegenschaft!$C$26:$G$26,1,Kosten!$I$6),0),"") | F13: =IF(Kosten!$H$6="Ja",IF(Kosten!D6="Heizung/Warmwasser",INDEX(Mieter!L:L,$C$2+5),INDEX(Mieter!K:K,$C$2+5)),"") | G13: =IF(Kosten!$H$6="Ja",INDEX(Verteilung!D:D,$C$2+5),"")
B14: =IF(Kosten!$H$7="Ja",Kosten!B7,"") | C14: =IF(Kosten!$H$7="Ja",Kosten!C7,"") | D14: =IF(Kosten!$H$7="Ja",Kosten!E7,"") | E14: =IF(Kosten!$H$7="Ja",IFERROR(INDEX(Liegenschaft!$C$14:$G$25,MATCH(INDEX(Mieter!C:C,$C$2+5),Liegenschaft!$B$14:$B$25,0),Kosten!$I$7)/INDEX(Liegenschaft!$C$26:$G$26,1,Kosten!$I$7),0),"") | F14: =IF(Kosten!$H$7="Ja",IF(Kosten!D7="Heizung/Warmwasser",INDEX(Mieter!L:L,$C$2+5),INDEX(Mieter!K:K,$C$2+5)),"") | G14: =IF(Kosten!$H$7="Ja",INDEX(Verteilung!E:E,$C$2+5),"")
B15: =IF(Kosten!$H$8="Ja",Kosten!B8,"") | C15: =IF(Kosten!$H$8="Ja",Kosten!C8,"") | D15: =IF(Kosten!$H$8="Ja",Kosten!E8,"") | E15: =IF(Kosten!$H$8="Ja",IFERROR(INDEX(Liegenschaft!$C$14:$G$25,MATCH(INDEX(Mieter!C:C,$C$2+5),Liegenschaft!$B$14:$B$25,0),Kosten!$I$8)/INDEX(Liegenschaft!$C$26:$G$26,1,Kosten!$I$8),0),"") | F15: =IF(Kosten!$H$8="Ja",IF(Kosten!D8="Heizung/Warmwasser",INDEX(Mieter!L:L,$C$2+5),INDEX(Mieter!K:K,$C$2+5)),"") | G15: =IF(Kosten!$H$8="Ja",INDEX(Verteilung!F:F,$C$2+5),"")
B16: =IF(Kosten!$H$9="Ja",Kosten!B9,"") | C16: =IF(Kosten!$H$9="Ja",Kosten!C9,"") | D16: =IF(Kosten!$H$9="Ja",Kosten!E9,"") | E16: =IF(Kosten!$H$9="Ja",IFERROR(INDEX(Liegenschaft!$C$14:$G$25,MATCH(INDEX(Mieter!C:C,$C$2+5),Liegenschaft!$B$14:$B$25,0),Kosten!$I$9)/INDEX(Liegenschaft!$C$26:$G$26,1,Kosten!$I$9),0),"") | F16: =IF(Kosten!$H$9="Ja",IF(Kosten!D9="Heizung/Warmwasser",INDEX(Mieter!L:L,$C$2+5),INDEX(Mieter!K:K,$C$2+5)),"") | G16: =IF(Kosten!$H$9="Ja",INDEX(Verteilung!G:G,$C$2+5),"")
B17: =IF(Kosten!$H$10="Ja",Kosten!B10,"") | C17: =IF(Kosten!$H$10="Ja",Kosten!C10,"") | D17: =IF(Kosten!$H$10="Ja",Kosten!E10,"") | E17: =IF(Kosten!$H$10="Ja",IFERROR(INDEX(Liegenschaft!$C$14:$G$25,MATCH(INDEX(Mieter!C:C,$C$2+5),Liegenschaft!$B$14:$B$25,0),Kosten!$I$10)/INDEX(Liegenschaft!$C$26:$G$26,1,Kosten!$I$10),0),"") | F17: =IF(Kosten!$H$10="Ja",IF(Kosten!D10="Heizung/Warmwasser",INDEX(Mieter!L:L,$C$2+5),INDEX(Mieter!K:K,$C$2+5)),"") | G17: =IF(Kosten!$H$10="Ja",INDEX(Verteilung!H:H,$C$2+5),"")
B18: =IF(Kosten!$H$11="Ja",Kosten!B11,"") | C18: =IF(Kosten!$H$11="Ja",Kosten!C11,"") | D18: =IF(Kosten!$H$11="Ja",Kosten!E11,"") | E18: =IF(Kosten!$H$11="Ja",IFERROR(INDEX(Liegenschaft!$C$14:$G$25,MATCH(INDEX(Mieter!C:C,$C$2+5),Liegenschaft!$B$14:$B$25,0),Kosten!$I$11)/INDEX(Liegenschaft!$C$26:$G$26,1,Kosten!$I$11),0),"") | F18: =IF(Kosten!$H$11="Ja",IF(Kosten!D11="Heizung/Warmwasser",INDEX(Mieter!L:L,$C$2+5),INDEX(Mieter!K:K,$C$2+5)),"") | G18: =IF(Kosten!$H$11="Ja",INDEX(Verteilung!I:I,$C$2+5),"")
B19: =IF(Kosten!$H$12="Ja",Kosten!B12,"") | C19: =IF(Kosten!$H$12="Ja",Kosten!C12,"") | D19: =IF(Kosten!$H$12="Ja",Kosten!E12,"") | E19: =IF(Kosten!$H$12="Ja",IFERROR(INDEX(Liegenschaft!$C$14:$G$25,MATCH(INDEX(Mieter!C:C,$C$2+5),Liegenschaft!$B$14:$B$25,0),Kosten!$I$12)/INDEX(Liegenschaft!$C$26:$G$26,1,Kosten!$I$12),0),"") | F19: =IF(Kosten!$H$12="Ja",IF(Kosten!D12="Heizung/Warmwasser",INDEX(Mieter!L:L,$C$2+5),INDEX(Mieter!K:K,$C$2+5)),"") | G19: =IF(Kosten!$H$12="Ja",INDEX(Verteilung!J:J,$C$2+5),"")
B20: =IF(Kosten!$H$13="Ja",Kosten!B13,"") | C20: =IF(Kosten!$H$13="Ja",Kosten!C13,"") | D20: =IF(Kosten!$H$13="Ja",Kosten!E13,"") | E20: =IF(Kosten!$H$13="Ja",IFERROR(INDEX(Liegenschaft!$C$14:$G$25,MATCH(INDEX(Mieter!C:C,$C$2+5),Liegenschaft!$B$14:$B$25,0),Kosten!$I$13)/INDEX(Liegenschaft!$C$26:$G$26,1,Kosten!$I$13),0),"") | F20: =IF(Kosten!$H$13="Ja",IF(Kosten!D13="Heizung/Warmwasser",INDEX(Mieter!L:L,$C$2+5),INDEX(Mieter!K:K,$C$2+5)),"") | G20: =IF(Kosten!$H$13="Ja",INDEX(Verteilung!K:K,$C$2+5),"")
B21: =IF(Kosten!$H$14="Ja",Kosten!B14,"") | C21: =IF(Kosten!$H$14="Ja",Kosten!C14,"") | D21: =IF(Kosten!$H$14="Ja",Kosten!E14,"") | E21: =IF(Kosten!$H$14="Ja",IFERROR(INDEX(Liegenschaft!$C$14:$G$25,MATCH(INDEX(Mieter!C:C,$C$2+5),Liegenschaft!$B$14:$B$25,0),Kosten!$I$14)/INDEX(Liegenschaft!$C$26:$G$26,1,Kosten!$I$14),0),"") | F21: =IF(Kosten!$H$14="Ja",IF(Kosten!D14="Heizung/Warmwasser",INDEX(Mieter!L:L,$C$2+5),INDEX(Mieter!K:K,$C$2+5)),"") | G21: =IF(Kosten!$H$14="Ja",INDEX(Verteilung!L:L,$C$2+5),"")
B22: =IF(Kosten!$H$15="Ja",Kosten!B15,"") | C22: =IF(Kosten!$H$15="Ja",Kosten!C15,"") | D22: =IF(Kosten!$H$15="Ja",Kosten!E15,"") | E22: =IF(Kosten!$H$15="Ja",IFERROR(INDEX(Liegenschaft!$C$14:$G$25,MATCH(INDEX(Mieter!C:C,$C$2+5),Liegenschaft!$B$14:$B$25,0),Kosten!$I$15)/INDEX(Liegenschaft!$C$26:$G$26,1,Kosten!$I$15),0),"") | F22: =IF(Kosten!$H$15="Ja",IF(Kosten!D15="Heizung/Warmwasser",INDEX(Mieter!L:L,$C$2+5),INDEX(Mieter!K:K,$C$2+5)),"") | G22: =IF(Kosten!$H$15="Ja",INDEX(Verteilung!M:M,$C$2+5),"")
B23: =IF(Kosten!$H$16="Ja",Kosten!B16,"") | C23: =IF(Kosten!$H$16="Ja",Kosten!C16,"") | D23: =IF(Kosten!$H$16="Ja",Kosten!E16,"") | E23: =IF(Kosten!$H$16="Ja",IFERROR(INDEX(Liegenschaft!$C$14:$G$25,MATCH(INDEX(Mieter!C:C,$C$2+5),Liegenschaft!$B$14:$B$25,0),Kosten!$I$16)/INDEX(Liegenschaft!$C$26:$G$26,1,Kosten!$I$16),0),"") | F23: =IF(Kosten!$H$16="Ja",IF(Kosten!D16="Heizung/Warmwasser",INDEX(Mieter!L:L,$C$2+5),INDEX(Mieter!K:K,$C$2+5)),"") | G23: =IF(Kosten!$H$16="Ja",INDEX(Verteilung!N:N,$C$2+5),"")
B24: =IF(Kosten!$H$17="Ja",Kosten!B17,"") | C24: =IF(Kosten!$H$17="Ja",Kosten!C17,"") | D24: =IF(Kosten!$H$17="Ja",Kosten!E17,"") | E24: =IF(Kosten!$H$17="Ja",IFERROR(INDEX(Liegenschaft!$C$14:$G$25,MATCH(INDEX(Mieter!C:C,$C$2+5),Liegenschaft!$B$14:$B$25,0),Kosten!$I$17)/INDEX(Liegenschaft!$C$26:$G$26,1,Kosten!$I$17),0),"") | F24: =IF(Kosten!$H$17="Ja",IF(Kosten!D17="Heizung/Warmwasser",INDEX(Mieter!L:L,$C$2+5),INDEX(Mieter!K:K,$C$2+5)),"") | G24: =IF(Kosten!$H$17="Ja",INDEX(Verteilung!O:O,$C$2+5),"")
B25: =IF(Kosten!$H$18="Ja",Kosten!B18,"") | C25: =IF(Kosten!$H$18="Ja",Kosten!C18,"") | D25: =IF(Kosten!$H$18="Ja",Kosten!E18,"") | E25: =IF(Kosten!$H$18="Ja",IFERROR(INDEX(Liegenschaft!$C$14:$G$25,MATCH(INDEX(Mieter!C:C,$C$2+5),Liegenschaft!$B$14:$B$25,0),Kosten!$I$18)/INDEX(Liegenschaft!$C$26:$G$26,1,Kosten!$I$18),0),"") | F25: =IF(Kosten!$H$18="Ja",IF(Kosten!D18="Heizung/Warmwasser",INDEX(Mieter!L:L,$C$2+5),INDEX(Mieter!K:K,$C$2+5)),"") | G25: =IF(Kosten!$H$18="Ja",INDEX(Verteilung!P:P,$C$2+5),"")
B26: =IF(Kosten!$H$19="Ja",Kosten!B19,"") | C26: =IF(Kosten!$H$19="Ja",Kosten!C19,"") | D26: =IF(Kosten!$H$19="Ja",Kosten!E19,"") | E26: =IF(Kosten!$H$19="Ja",IFERROR(INDEX(Liegenschaft!$C$14:$G$25,MATCH(INDEX(Mieter!C:C,$C$2+5),Liegenschaft!$B$14:$B$25,0),Kosten!$I$19)/INDEX(Liegenschaft!$C$26:$G$26,1,Kosten!$I$19),0),"") | F26: =IF(Kosten!$H$19="Ja",IF(Kosten!D19="Heizung/Warmwasser",INDEX(Mieter!L:L,$C$2+5),INDEX(Mieter!K:K,$C$2+5)),"") | G26: =IF(Kosten!$H$19="Ja",INDEX(Verteilung!Q:Q,$C$2+5),"")
B27: =IF(Kosten!$H$20="Ja",Kosten!B20,"") | C27: =IF(Kosten!$H$20="Ja",Kosten!C20,"") | D27: =IF(Kosten!$H$20="Ja",Kosten!E20,"") | E27: =IF(Kosten!$H$20="Ja",IFERROR(INDEX(Liegenschaft!$C$14:$G$25,MATCH(INDEX(Mieter!C:C,$C$2+5),Liegenschaft!$B$14:$B$25,0),Kosten!$I$20)/INDEX(Liegenschaft!$C$26:$G$26,1,Kosten!$I$20),0),"") | F27: =IF(Kosten!$H$20="Ja",IF(Kosten!D20="Heizung/Warmwasser",INDEX(Mieter!L:L,$C$2+5),INDEX(Mieter!K:K,$C$2+5)),"") | G27: =IF(Kosten!$H$20="Ja",INDEX(Verteilung!R:R,$C$2+5),"")
B28: =IF(Kosten!$H$21="Ja",Kosten!B21,"") | C28: =IF(Kosten!$H$21="Ja",Kosten!C21,"") | D28: =IF(Kosten!$H$21="Ja",Kosten!E21,"") | E28: =IF(Kosten!$H$21="Ja",IFERROR(INDEX(Liegenschaft!$C$14:$G$25,MATCH(INDEX(Mieter!C:C,$C$2+5),Liegenschaft!$B$14:$B$25,0),Kosten!$I$21)/INDEX(Liegenschaft!$C$26:$G$26,1,Kosten!$I$21),0),"") | F28: =IF(Kosten!$H$21="Ja",IF(Kosten!D21="Heizung/Warmwasser",INDEX(Mieter!L:L,$C$2+5),INDEX(Mieter!K:K,$C$2+5)),"") | G28: =IF(Kosten!$H$21="Ja",INDEX(Verteilung!S:S,$C$2+5),"")
B29: =IF(Kosten!$H$22="Ja",Kosten!B22,"") | C29: =IF(Kosten!$H$22="Ja",Kosten!C22,"") | D29: =IF(Kosten!$H$22="Ja",Kosten!E22,"") | E29: =IF(Kosten!$H$22="Ja",IFERROR(INDEX(Liegenschaft!$C$14:$G$25,MATCH(INDEX(Mieter!C:C,$C$2+5),Liegenschaft!$B$14:$B$25,0),Kosten!$I$22)/INDEX(Liegenschaft!$C$26:$G$26,1,Kosten!$I$22),0),"") | F29: =IF(Kosten!$H$22="Ja",IF(Kosten!D22="Heizung/Warmwasser",INDEX(Mieter!L:L,$C$2+5),INDEX(Mieter!K:K,$C$2+5)),"") | G29: =IF(Kosten!$H$22="Ja",INDEX(Verteilung!T:T,$C$2+5),"")
B30: =IF(Kosten!$H$23="Ja",Kosten!B23,"") | C30: =IF(Kosten!$H$23="Ja",Kosten!C23,"") | D30: =IF(Kosten!$H$23="Ja",Kosten!E23,"") | E30: =IF(Kosten!$H$23="Ja",IFERROR(INDEX(Liegenschaft!$C$14:$G$25,MATCH(INDEX(Mieter!C:C,$C$2+5),Liegenschaft!$B$14:$B$25,0),Kosten!$I$23)/INDEX(Liegenschaft!$C$26:$G$26,1,Kosten!$I$23),0),"") | F30: =IF(Kosten!$H$23="Ja",IF(Kosten!D23="Heizung/Warmwasser",INDEX(Mieter!L:L,$C$2+5),INDEX(Mieter!K:K,$C$2+5)),"") | G30: =IF(Kosten!$H$23="Ja",INDEX(Verteilung!U:U,$C$2+5),"")
B31: =IF(Kosten!$H$24="Ja",Kosten!B24,"") | C31: =IF(Kosten!$H$24="Ja",Kosten!C24,"") | D31: =IF(Kosten!$H$24="Ja",Kosten!E24,"") | E31: =IF(Kosten!$H$24="Ja",IFERROR(INDEX(Liegenschaft!$C$14:$G$25,MATCH(INDEX(Mieter!C:C,$C$2+5),Liegenschaft!$B$14:$B$25,0),Kosten!$I$24)/INDEX(Liegenschaft!$C$26:$G$26,1,Kosten!$I$24),0),"") | F31: =IF(Kosten!$H$24="Ja",IF(Kosten!D24="Heizung/Warmwasser",INDEX(Mieter!L:L,$C$2+5),INDEX(Mieter!K:K,$C$2+5)),"") | G31: =IF(Kosten!$H$24="Ja",INDEX(Verteilung!V:V,$C$2+5),"")
B32: =IF(Kosten!$H$25="Ja",Kosten!B25,"") | C32: =IF(Kosten!$H$25="Ja",Kosten!C25,"") | D32: =IF(Kosten!$H$25="Ja",Kosten!E25,"") | E32: =IF(Kosten!$H$25="Ja",IFERROR(INDEX(Liegenschaft!$C$14:$G$25,MATCH(INDEX(Mieter!C:C,$C$2+5),Liegenschaft!$B$14:$B$25,0),Kosten!$I$25)/INDEX(Liegenschaft!$C$26:$G$26,1,Kosten!$I$25),0),"") | F32: =IF(Kosten!$H$25="Ja",IF(Kosten!D25="Heizung/Warmwasser",INDEX(Mieter!L:L,$C$2+5),INDEX(Mieter!K:K,$C$2+5)),"") | G32: =IF(Kosten!$H$25="Ja",INDEX(Verteilung!W:W,$C$2+5),"")
B34: Total Nebenkosten | G34: =INDEX(Verteilung!X:X,$C$2+5)
B35: =IF(Liegenschaft!C11="Ja","Verwaltungshonorar "&TEXT(Liegenschaft!C10,"0.0%"),"") | G35: =INDEX(Verteilung!Y:Y,$C$2+5)
B36: Total Ihr Anteil | G36: =INDEX(Verteilung!Z:Z,$C$2+5)
B37: abzüglich Akontozahlungen | G37: =-INDEX(Verteilung!AA:AA,$C$2+5)
B38: =IF(INDEX(Verteilung!AB:AB,$C$2+5)>=0,"Nachzahlung zu Ihren Lasten","Guthaben zu Ihren Gunsten") | G38: =ABS(INDEX(Verteilung!AB:AB,$C$2+5))
B41: Die Kosten der Liegenschaft werden nach den im Mietvertrag vereinbarten Schlüsseln verteilt. Heiz- und Warmwasserkosten
B42: werden bei Mieterwechseln nach Heizgradtagen, die übrigen Nebenkosten nach Tagen aufgeteilt. Kosten leerstehender
B43: Wohnungen trägt die Vermieterschaft. Die Belege können Sie auf Anfrage einsehen (Art. 257b Abs. 2 OR).
B45: ="Bitte überweisen Sie eine Nachzahlung innert 30 Tagen. Ein Guthaben überweisen wir Ihnen auf Ihr Konto."
B47: =Liegenschaft!C5&", "&TEXT(TODAY(),"DD.MM.YYYY")
B49: _______________________________
B50: =Liegenschaft!C6

Sheet Mietzins
B2: Mietzinsanpassung berechnen
B3: Referenzzinssatz (Art. 13 VMWG), Teuerung (Art. 16 VMWG) und allgemeine Kostensteigerung.
B5: Aktueller Nettomietzins pro Monat
B6: Referenzzinssatz bei der letzten Anpassung | D6: Steht im letzten Mietzinsformular bzw. im Mietvertrag.
B7: Aktueller Referenzzinssatz | C7: 0.0125 | D7: Stand Okt. 2026: 1.25 %. Quartalsweise auf bwo.admin.ch prüfen.
B8: Landesindex (LIK) bei der letzten Anpassung | D8: Gleiche Basis wie aktueller Wert verwenden (z. B. Dez. 2020 = 100).
B9: Landesindex (LIK) aktuell | D9: bfs.admin.ch › Landesindex der Konsumentenpreise.
B10: Stichtag der letzten Anpassung | D10: Ab diesem Datum wird die Kostensteigerung gerechnet.
B11: Wirksam werden der neuen Miete (erster Tag) | D11: Nächster vertraglicher Kündigungstermin + 1 Tag.
B12: Allgemeine Kostensteigerung pro Jahr | C12: 0.005 | D12: Pauschale gemäss kantonaler Praxis (häufig 0.5 %–1 %). Belegbar halten.
B13: Kündigungsfrist in Monaten | C13: 3 | D13: Wohnungen: mindestens 3 Monate (Art. 266c OR).
B15: Komponente | C15: Veränderung | D15: Erläuterung
B16: Referenzzinssatz | C16: =IF(OR(C6="",C7=""),0,IF(ROUND((C7-C6)/0.0025,0)>=0,ROUND((C7-C6)/0.0025,0)*0.03,1/(1+ROUND((C6-C7)/0.0025,0)*0.03)-1)) | D16: =IF(OR(C6="",C7=""),"",ROUND((C7-C6)/0.0025,0)&" Schritt(e) à 0.25 %: Erhöhung +3 % je Schritt, Senkung −2.91 % / −5.66 % / …"&IF(MAX(C6,C7)>0.05," ⚠ über 5 %: andere Sätze (Art. 13 VMWG)",""))
B17: Teuerung (40 % der LIK-Veränderung) | C17: =IF(OR(N(C8)=0,N(C9)=0),0,(C9/C8-1)*0.4) | D17: =IF(OR(N(C8)=0,N(C9)=0),"","LIK "&TEXT(C9/C8-1,"0.00%")&" × 40 %")
B18: Allgemeine Kostensteigerung | C18: =IF(OR(C10="",C11=""),0,C12*MAX(0,(YEAR(C11)-YEAR(C10))*12+MONTH(C11)-MONTH(C10))/12) | D18: =IF(OR(C10="",C11=""),"",MAX(0,(YEAR(C11)-YEAR(C10))*12+MONTH(C11)-MONTH(C10))&" Monate × "&TEXT(C12,"0.00%")&" / 12")
B19: Total Anpassung | C19: =C16+C17+C18
B21: Neuer Nettomietzins pro Monat | C21: =IF(N(C5)=0,0,ROUND(C5*(1+C19)*20,0)/20)
B22: Differenz pro Monat | C22: =C21-N(C5)
B23: Differenz pro Jahr | C23: =C22*12
B25: Ergebnis
B26: =IF(N(C5)=0,"Bitte Eingaben ausfüllen.",IF(C19>0,"Erhöhung möglich. Mitteilung zwingend mit amtlichem kantonalem Formular und Begründung.",IF(C19<0,"Die Mieterschaft hat Anspruch auf eine Senkung, wenn sie diese verlangt. Freiwillige Senkung möglich.","Keine Anpassung.")))
B27: Zugang beim Mieter spätestens (inkl. 1 Tag Reserve) | C27: =IF(C11="","",EDATE(C11,-C13)-11) | D27: Mitteilung muss mind. 10 Tage vor Beginn der Kündigungsfrist eintreffen (Art. 269d OR). Eingeschrieben senden.
B29: Methode: Die Komponenten werden addiert (gängige Praxis). Gerundet auf 5 Rappen. Ob eine Anpassung im Einzelfall zulässig ist (z. B. bei übersetztem Ertrag oder vorbehaltenen Reserven), prüfen Sie mit Ihrem Verband oder einer Fachperson.

Sheet Mieterwechsel
B2: Checkliste Mieterwechsel
B3: Auszugsdatum eintragen – die Termine rechnen sich selbst. Überfällige offene Schritte werden rot.
B4: Wohnung
B5: Auszug Vormieter
B6: Einzug Nachmieter
B8: Phase | C8: Schritt | D8: Tage rel. Auszug | E8: Fällig am | F8: Erledigt | G8: Bemerkung
B9: Kündigung | C9: Kündigung prüfen: Schriftform, beide Ehegatten/Partner unterschrieben, Frist und Termin (Art. 266a ff., 266n OR) | D9: -90 | E9: =IF($C$5="","",$C$5+D9)
B10: Kündigung | C10: Kündigung schriftlich bestätigen, bei ausserterminlicher Kündigung auf Ersatzmieter-Regel hinweisen (Art. 264 OR) | D10: -88 | E10: =IF($C$5="","",$C$5+D10)
B11: Kündigung | C11: Mietzins für Neuvermietung festlegen; in Kantonen mit Formularpflicht Anfangsmietzins-Formular vorbereiten (Art. 270 OR) | D11: -80 | E11: =IF($C$5="","",$C$5+D11)
B12: Vermarktung | C12: Fotos, Inserat und Besichtigungstermine mit Vormieter vereinbaren (Besichtigungsrecht Art. 257h OR) | D12: -75 | E12: =IF($C$5="","",$C$5+D12)
B13: Vermarktung | C13: Bewerbungen prüfen: Betreibungsregisterauszug, Einkommen/Miete-Verhältnis, Referenzen | D13: -55 | E13: =IF($C$5="","",$C$5+D13)
B14: Vermarktung | C14: Mietvertrag erstellen und versenden – Nebenkosten einzeln aufführen (Art. 257a OR) | D14: -45 | E14: =IF($C$5="","",$C$5+D14)
B15: Vermarktung | C15: Unterzeichneten Vertrag erhalten; Mietzinsdepot einfordern (max. 3 Monatsmieten, Sperrkonto, Art. 257e OR) | D15: -30 | E15: =IF($C$5="","",$C$5+D15)
B16: Abnahme | C16: Vorbesichtigung mit Vormieter: absehbare Mängel und Reinigung besprechen | D16: -21 | E16: =IF($C$5="","",$C$5+D16)
B17: Abnahme | C17: Termin Wohnungsabnahme festlegen und schriftlich bestätigen | D17: -14 | E17: =IF($C$5="","",$C$5+D17)
B18: Abnahme | C18: Handwerker (Maler, Bodenleger, Reinigung) provisorisch reservieren | D18: -10 | E18: =IF($C$5="","",$C$5+D18)
B19: Abnahme | C19: Wohnungsabnahme durchführen, Protokoll von beiden Seiten unterzeichnen lassen, Schlüssel zählen | D19: 0 | E19: =IF($C$5="","",$C$5+D19)
B20: Abnahme | C20: Zählerstände ablesen; Strom/Gas für Leerstand auf Vermieter melden | D20: 0 | E20: =IF($C$5="","",$C$5+D20)
... B23: Instandstellung | C23: Endreinigung / Nachreinigung organisieren, Namensschilder Briefkasten und Klingel bestellen | D23: 7 | E23: =IF($C$5="","",$C$5+D23)
B24: Übergabe | C24: Prüfen, ob Mietzinsdepot des Nachmieters eingegangen ist – erst dann Schlüssel übergeben | D24: Einzug | E24: =IF($C$6="","",$C$6)
B25: Übergabe | C25: Übergabe an Nachmieter mit Antrittsprotokoll; Frist für Mängelliste nennen (üblich 10–30 Tage) | D25: Einzug | E25: =IF($C$6="","",$C$6)
B26: Übergabe | C26: Zählerstände an Werke melden (Wechsel auf Nachmieter), Mieterliste/Hauswart informieren | D26: Einzug | E26: =IF($C$6="","",$C$6)
B27: Abrechnung | C27: Schadensabrechnung Vormieter nach Lebensdauertabelle (Altersentwertung, Blatt «Abnahme») | D27: 30 | E27: =IF($C$5="","",$C$5+D27)
B28: Abrechnung | C28: Nebenkosten-Teilabrechnung Vormieter erstellen oder in der Jahresabrechnung berücksichtigen | D28: 45 | E28: =IF($C$5="","",$C$5+D28)
B29: Abrechnung | C29: Mietzinsdepot Vormieter freigeben bzw. mit Forderungen verrechnen | D29: 60 | E29: =IF($C$5="","",$C$5+D29)
B31: Offene Schritte | C31: =COUNTIF(F9:F29,"")&" von 21 offen, davon überfällig: "&SUMPRODUCT((F9:F29="")*ISNUMBER(E9:E29)*(E9:E29<TODAY()))

Sheet Abnahme
B2: Wohnungsabnahmeprotokoll
B3: Ausdrucken oder am Tablet ausfüllen. Mängel konkret beschreiben (Ort, Grösse, Foto-Nr.).
B4: Liegenschaft / Wohnung
B5: Mieter/in (ausziehend)
B6: Mieter/in (einziehend)
B7: Datum / Uhrzeit
B8: Anwesend
B10: Raum | C10: Bauteil | D10: Zustand | E10: Mangel / Bemerkung | F10: zulasten Mieter? | G10: Foto-Nr.
B11: Eingang/Korridor | C11: Boden
C12: Wände/Decke
C13: Fenster/Storen
C14: Türen/Schlösser
C15: Elektro/Lampen
C16: Einbauten/Geräte
B17: Wohnzimmer | C17: Boden
C18: Wände/Decke
C19: Fenster/Storen
C20: Türen/Schlösser
C21: Elektro/Lampen
C22: Einbauten/Geräte
B23: Zimmer 1 | C23: Boden
C24: Wände/Decke
C25: Fenster/Storen
C26: Türen/Schlösser
C27: Elektro/Lampen
C28: Einbauten/Geräte
B29: Zimmer 2 | C29: Boden
C30: Wände/Decke
C31: Fenster/Storen
C32: Türen/Schlösser
C33: Elektro/Lampen
C34: Einbauten/Geräte
B35: Küche | C35: Boden
C36: Wände/Decke
C37: Fenster/Storen
C38: Türen/Schlösser
C39: Elektro/Lampen
C40: Einbauten/Geräte
B41: Bad/WC | C41: Boden
C42: Wände/Decke
C43: Fenster/Storen
C44: Türen/Schlösser
C45: Elektro/Lampen
C46: Einbauten/Geräte
B47: Balkon/Keller | C47: Boden
C48: Wände/Decke
C49: Fenster/Storen
C50: Türen/Schlösser
C51: Elektro/Lampen
C52: Einbauten/Geräte
B54: Schlüssel | D54: Zählerstände
B55: Wohnung | D55: Strom
B56: Briefkasten | D56: Gas
B57: Keller/Estrich | D57: Wasser
B58: Garage/Velo | D58: Wärme/HKV
B59: Badges
B62: Altersentwertung (Lebensdauer gemäss paritätischer Lebensdauertabelle eintragen)
B63: Bauteil | C63: Neuwert/Kosten CHF | D63: Lebensdauer J. | E63: Alter J. | F63: Restwert % | G63: zulasten Mieter CHF
F64: =IF(N(D64)=0,"",MAX(0,1-N(E64)/D64)) | G64: =IF(F64="","",ROUND(N(C64)*F64*20,0)/20)
F65: =IF(N(D65)=0,"",MAX(0,1-N(E65)/D65)) | G65: =IF(F65="","",ROUND(N(C65)*F65*20,0)/20)
F66: =IF(N(D66)=0,"",MAX(0,1-N(E66)/D66)) | G66: =IF(F66="","",ROUND(N(C66)*F66*20,0)/20)
F67: =IF(N(D67)=0,"",MAX(0,1-N(E67)/D67)) | G67: =IF(F67="","",ROUND(N(C67)*F67*20,0)/20)
F68: =IF(N(D68)=0,"",MAX(0,1-N(E68)/D68)) | G68: =IF(F68="","",ROUND(N(C68)*F68*20,0)/20)
F69: =IF(N(D69)=0,"",MAX(0,1-N(E69)/D69)) | G69: =IF(F69="","",ROUND(N(C69)*F69*20,0)/20)
F70: Total | G70: =SUM(G64:G69)
B72: Die Unterzeichnenden bestätigen den festgehaltenen Zustand. Mit der Unterschrift anerkennt der Mieter nur die mit «Ja» bezeichneten Mängel.
B75: ______________________ | D75: ______________________ | F75: ______________________
B76: Vermieter/in | D76: Mieter/in ausziehend | F76: Mieter/in einziehend
