Workbook

Sheet Start
A1: Vermieter-Ordner Schweiz
A2: Die wichtigsten Aufgaben einer privaten Mietliegenschaft – nach Schweizer Mietrecht, ohne Abo, ohne Makros.
A4: So arbeiten Sie
A5: 1 · Mein Haus | B5: Wohnungen und Mieter einmal erfassen
A6: 2 · Mieterwechsel | B6: Kündigung → Mietende und zehn Schritte mit Datum
A7: 3 · Rückgabe | B7: Protokoll, Schaden nach Lebensdauer, Kaution
A8: 4 · Nebenkosten | B8: Kosten verteilen, Abrechnung pro Mieter
A9: 5 · Mietzins | B9: Referenzzins, Teuerung, Kostensteigerung
A10: 6 · Kontrolle | B10: Alles plausibel? Hier steht es.
A12: Was steht an?
A13: Datum | B13: Mieter | C13: Schritt | D13: Tage
A14: =IFERROR(INT(SMALL(Mieterwechsel!$BS$9:$BS$28,1)),"") | B14: =IFERROR(INDEX(Mieterwechsel!$B$9:$B$28,MATCH(SMALL(Mieterwechsel!$BS$9:$BS$28,1),Mieterwechsel!$BS$9:$BS$28,0)),"") | C14: =IFERROR(INDEX(Mieterwechsel!$AH$9:$AH$28,MATCH(SMALL(Mieterwechsel!$BS$9:$BS$28,1),Mieterwechsel!$BS$9:$BS$28,0)),"") | D14: =IFERROR(INT(SMALL(Mieterwechsel!$BS$9:$BS$28,1))-TODAY(),"")
A15: =IFERROR(INT(SMALL(Mieterwechsel!$BS$9:$BS$28,2)),"") | B15: =IFERROR(INDEX(Mieterwechsel!$B$9:$B$28,MATCH(SMALL(Mieterwechsel!$BS$9:$BS$28,2),Mieterwechsel!$BS$9:$BS$28,0)),"") | C15: =IFERROR(INDEX(Mieterwechsel!$AH$9:$AH$28,MATCH(SMALL(Mieterwechsel!$BS$9:$BS$28,2),Mieterwechsel!$BS$9:$BS$28,0)),"") | D15: =IFERROR(INT(SMALL(Mieterwechsel!$BS$9:$BS$28,2))-TODAY(),"")
A16: =IFERROR(INT(SMALL(Mieterwechsel!$BS$9:$BS$28,3)),"") | B16: =IFERROR(INDEX(Mieterwechsel!$B$9:$B$28,MATCH(SMALL(Mieterwechsel!$BS$9:$BS$28,3),Mieterwechsel!$BS$9:$BS$28,0)),"") | C16: =IFERROR(INDEX(Mieterwechsel!$AH$9:$AH$28,MATCH(SMALL(Mieterwechsel!$BS$9:$BS$28,3),Mieterwechsel!$BS$9:$BS$28,0)),"") | D16: =IFERROR(INT(SMALL(Mieterwechsel!$BS$9:$BS$28,3))-TODAY(),"")
A17: =IFERROR(INT(SMALL(Mieterwechsel!$BS$9:$BS$28,4)),"") | B17: =IFERROR(INDEX(Mieterwechsel!$B$9:$B$28,MATCH(SMALL(Mieterwechsel!$BS$9:$BS$28,4),Mieterwechsel!$BS$9:$BS$28,0)),"") | C17: =IFERROR(INDEX(Mieterwechsel!$AH$9:$AH$28,MATCH(SMALL(Mieterwechsel!$BS$9:$BS$28,4),Mieterwechsel!$BS$9:$BS$28,0)),"") | D17: =IFERROR(INT(SMALL(Mieterwechsel!$BS$9:$BS$28,4))-TODAY(),"")
A18: =IFERROR(INT(SMALL(Mieterwechsel!$BS$9:$BS$28,5)),"") | B18: =IFERROR(INDEX(Mieterwechsel!$B$9:$B$28,MATCH(SMALL(Mieterwechsel!$BS$9:$BS$28,5),Mieterwechsel!$BS$9:$BS$28,0)),"") | C18: =IFERROR(INDEX(Mieterwechsel!$AH$9:$AH$28,MATCH(SMALL(Mieterwechsel!$BS$9:$BS$28,5),Mieterwechsel!$BS$9:$BS$28,0)),"") | D18: =IFERROR(INT(SMALL(Mieterwechsel!$BS$9:$BS$28,5))-TODAY(),"")
A21: Kennzahlen
A22: Laufende Mietverhältnisse | B22: =COUNTIF('Mein Haus'!N45:N104,"aktiv")
A23: Nettomieten pro Monat | B23: =SUMIF('Mein Haus'!N45:N104,"aktiv",'Mein Haus'!G45:G104)
A24: Kautionen laufender Mietverhältnisse | B24: =SUMIF('Mein Haus'!N45:N104,"aktiv",'Mein Haus'!I45:I104)
A25: Einheiten ohne laufendes Mietverhältnis | B25: =MAX(0,N('Mein Haus'!F41)-B22)
A26: Kontrolle | B26: =Kontrolle!B16
A29: Gelb = Eingabe · Blau = rechnet automatisch (Blattschutz ohne Passwort).
A30: Ersetzt keine Rechtsberatung. Bei Streit: Schlichtungsbehörde Ihres Kantons oder Ihr Verband.

Sheet Mein Haus
A1: Mein Haus
A2: Alles, was mehrere Teile brauchen, steht nur hier. Gelb = Eingabe, Blau = rechnet.
A4: Liegenschaft | B4: Musterstrasse 12, 8004 Zürich
A5: Vermieter | B5: Hans Beispiel, Bergstrasse 1, 8004 Zürich
A6: IBAN Vermieter
A9: Einheiten
A10: Nr. | B10: Bezeichnung | C10: Zimmer | D10: Fläche m² | E10: Anteil (Wertquote ‰ o.ä.) | F10: Zähler
A11: 1 | B11: EG links | C11: 3.5 | D11: 82 | E11: 250 | F11: =IF(A11="","",1)
A12: 2 | B12: EG rechts | C12: 2.5 | D12: 61 | E12: 190 | F12: =IF(A12="","",1)
A13: 3 | B13: 1. OG | C13: 4.5 | D13: 104 | E13: 320 | F13: =IF(A13="","",1)
A14: 4 | B14: DG | C14: 3.5 | D14: 78 | E14: 240 | F14: =IF(A14="","",1)
F15: =IF(A15="","",1)
F16: =IF(A16="","",1)
F17: =IF(A17="","",1)
F18: =IF(A18="","",1)
F19: =IF(A19="","",1)
F20: =IF(A20="","",1)
F21: =IF(A21="","",1)
F22: =IF(A22="","",1)
F23: =IF(A23="","",1)
F24: =IF(A24="","",1)
F25: =IF(A25="","",1)
F26: =IF(A26="","",1)
... F40: =IF(A40="","",1)
B41: Total | D41: =SUM(D11:D40) | E41: =SUM(E11:E40) | F41: =SUM(F11:F40)
A43: Mietverhältnisse
A44: ID | B44: Einheit Nr. | C44: Mieter | D44: Mietbeginn | E44: Mietende (manuell) | F44: Mietende wirksam | G44: Nettomiete / Mt. | H44: Akonto NK / Mt. | I44: Kaution | J44: Kautionskonto (Bank) | K44: Referenzzins Basis % | L44: LIK Basis (Punkte) | M44: Basis seit (letzte Anpassung) | N44: Status | O44: Prüfen
A45: 1 | B45: 1 | C45: Muster Anna | D45: 43556 | F45: =IF(E45<>"",E45,IFERROR(INDEX(Mieterwechsel!$H$9:$H$28,MATCH(A45,Mieterwechsel!$A$9:$A$28,0)),"")) | G45: 1650 | H45: 380 | I45: 4950 | J45: Musterbank, Konto 11-1 | K45: 1.75 | L45: 106.2 | M45: 45261 | N45: =IF(C45="","",IF(AND(F45<>"",F45<TODAY()),"beendet",IF(AND(D45<>"",D45>TODAY()),"künftig","aktiv"))) | O45: =IF(C45="","",IF(B45="","Einheit fehlt",IF(ISNA(MATCH(B45,$A$11:$A$40,0)),"Einheit unbekannt",IF(AND(D45<>"",F45<>"",F45<D45),"Ende vor Beginn",IF(R45>0,"Überschneidung mit anderem Mieter",""))))) | P45: =IF(C45="","",IF(D45="",1,D45)) | Q45: =IF(C45="","",IF(F45="",401768,F45)) | R45: =IF(C45="",0,COUNTIFS($B$45:$B$104,B45,$P$45:$P$104,"<="&Q45,$Q$45:$Q$104,">="&P45)-1)
A46: 2 | B46: 2 | C46: Beispiel Marco | D46: 43009 | F46: =IF(E46<>"",E46,IFERROR(INDEX(Mieterwechsel!$H$9:$H$28,MATCH(A46,Mieterwechsel!$A$9:$A$28,0)),"")) | G46: 1290 | H46: 400 | I46: 3870 | J46: Musterbank, Konto 11-2 | K46: 1.5 | L46: 104.9 | M46: 44652 | N46: =IF(C46="","",IF(AND(F46<>"",F46<TODAY()),"beendet",IF(AND(D46<>"",D46>TODAY()),"künftig","aktiv"))) | O46: =IF(C46="","",IF(B46="","Einheit fehlt",IF(ISNA(MATCH(B46,$A$11:$A$40,0)),"Einheit unbekannt",IF(AND(D46<>"",F46<>"",F46<D46),"Ende vor Beginn",IF(R46>0,"Überschneidung mit anderem Mieter",""))))) | P46: =IF(C46="","",IF(D46="",1,D46)) | Q46: =IF(C46="","",IF(F46="",401768,F46)) | R46: =IF(C46="",0,COUNTIFS($B$45:$B$104,B46,$P$45:$P$104,"<="&Q46,$Q$45:$Q$104,">="&P46)-1)
A47: 3 | B47: 2 | C47: Probst Lea | D47: 45748 | F47: =IF(E47<>"",E47,IFERROR(INDEX(Mieterwechsel!$H$9:$H$28,MATCH(A47,Mieterwechsel!$A$9:$A$28,0)),"")) | G47: 1350 | H47: 260 | I47: 4050 | J47: Musterbank, Konto 11-3 | K47: 1.75 | L47: 107.1 | M47: 45748 | N47: =IF(C47="","",IF(AND(F47<>"",F47<TODAY()),"beendet",IF(AND(D47<>"",D47>TODAY()),"künftig","aktiv"))) | O47: =IF(C47="","",IF(B47="","Einheit fehlt",IF(ISNA(MATCH(B47,$A$11:$A$40,0)),"Einheit unbekannt",IF(AND(D47<>"",F47<>"",F47<D47),"Ende vor Beginn",IF(R47>0,"Überschneidung mit anderem Mieter",""))))) | P47: =IF(C47="","",IF(D47="",1,D47)) | Q47: =IF(C47="","",IF(F47="",401768,F47)) | R47: =IF(C47="",0,COUNTIFS($B$45:$B$104,B47,$P$45:$P$104,"<="&Q47,$Q$45:$Q$104,">="&P47)-1)
A48: 4 | B48: 3 | C48: Keller Familie | D48: 41030 | F48: =IF(E48<>"",E48,IFERROR(INDEX(Mieterwechsel!$H$9:$H$28,MATCH(A48,Mieterwechsel!$A$9:$A$28,0)),"")) | G48: 2150 | H48: 480 | I48: 6000 | J48: Musterbank, Konto 11-4 | K48: 1.75 | L48: 106.2 | M48: 45261 | N48: =IF(C48="","",IF(AND(F48<>"",F48<TODAY()),"beendet",IF(AND(D48<>"",D48>TODAY()),"künftig","aktiv"))) | O48: =IF(C48="","",IF(B48="","Einheit fehlt",IF(ISNA(MATCH(B48,$A$11:$A$40,0)),"Einheit unbekannt",IF(AND(D48<>"",F48<>"",F48<D48),"Ende vor Beginn",IF(R48>0,"Überschneidung mit anderem Mieter",""))))) | P48: =IF(C48="","",IF(D48="",1,D48)) | Q48: =IF(C48="","",IF(F48="",401768,F48)) | R48: =IF(C48="",0,COUNTIFS($B$45:$B$104,B48,$P$45:$P$104,"<="&Q48,$Q$45:$Q$104,">="&P48)-1)
A49: 5 | B49: 4 | C49: Weber Tim | D49: 42430 | F49: =IF(E49<>"",E49,IFERROR(INDEX(Mieterwechsel!$H$9:$H$28,MATCH(A49,Mieterwechsel!$A$9:$A$28,0)),"")) | G49: 1720 | H49: 350 | I49: 4950 | J49: Musterbank, Konto 11-5 | K49: 1.75 | L49: 106.2 | M49: 45261 | N49: =IF(C49="","",IF(AND(F49<>"",F49<TODAY()),"beendet",IF(AND(D49<>"",D49>TODAY()),"künftig","aktiv"))) | O49: =IF(C49="","",IF(B49="","Einheit fehlt",IF(ISNA(MATCH(B49,$A$11:$A$40,0)),"Einheit unbekannt",IF(AND(D49<>"",F49<>"",F49<D49),"Ende vor Beginn",IF(R49>0,"Überschneidung mit anderem Mieter",""))))) | P49: =IF(C49="","",IF(D49="",1,D49)) | Q49: =IF(C49="","",IF(F49="",401768,F49)) | R49: =IF(C49="",0,COUNTIFS($B$45:$B$104,B49,$P$45:$P$104,"<="&Q49,$Q$45:$Q$104,">="&P49)-1)
A50: 6 | B50: 4 | C50: Frei Sara | D50: 45992 | F50: =IF(E50<>"",E50,IFERROR(INDEX(Mieterwechsel!$H$9:$H$28,MATCH(A50,Mieterwechsel!$A$9:$A$28,0)),"")) | G50: 1750 | H50: 200 | I50: 5250 | J50: Musterbank, Konto 11-6 | K50: 1.25 | L50: 107.3 | M50: 45992 | N50: =IF(C50="","",IF(AND(F50<>"",F50<TODAY()),"beendet",IF(AND(D50<>"",D50>TODAY()),"künftig","aktiv"))) | O50: =IF(C50="","",IF(B50="","Einheit fehlt",IF(ISNA(MATCH(B50,$A$11:$A$40,0)),"Einheit unbekannt",IF(AND(D50<>"",F50<>"",F50<D50),"Ende vor Beginn",IF(R50>0,"Überschneidung mit anderem Mieter",""))))) | P50: =IF(C50="","",IF(D50="",1,D50)) | Q50: =IF(C50="","",IF(F50="",401768,F50)) | R50: =IF(C50="",0,COUNTIFS($B$45:$B$104,B50,$P$45:$P$104,"<="&Q50,$Q$45:$Q$104,">="&P50)-1)
A51: 7 | F51: =IF(E51<>"",E51,IFERROR(INDEX(Mieterwechsel!$H$9:$H$28,MATCH(A51,Mieterwechsel!$A$9:$A$28,0)),"")) | N51: =IF(C51="","",IF(AND(F51<>"",F51<TODAY()),"beendet",IF(AND(D51<>"",D51>TODAY()),"künftig","aktiv"))) | O51: =IF(C51="","",IF(B51="","Einheit fehlt",IF(ISNA(MATCH(B51,$A$11:$A$40,0)),"Einheit unbekannt",IF(AND(D51<>"",F51<>"",F51<D51),"Ende vor Beginn",IF(R51>0,"Überschneidung mit anderem Mieter",""))))) | P51: =IF(C51="","",IF(D51="",1,D51)) | Q51: =IF(C51="","",IF(F51="",401768,F51)) | R51: =IF(C51="",0,COUNTIFS($B$45:$B$104,B51,$P$45:$P$104,"<="&Q51,$Q$45:$Q$104,">="&P51)-1)
A52: 8 | F52: =IF(E52<>"",E52,IFERROR(INDEX(Mieterwechsel!$H$9:$H$28,MATCH(A52,Mieterwechsel!$A$9:$A$28,0)),"")) | N52: =IF(C52="","",IF(AND(F52<>"",F52<TODAY()),"beendet",IF(AND(D52<>"",D52>TODAY()),"künftig","aktiv"))) | O52: =IF(C52="","",IF(B52="","Einheit fehlt",IF(ISNA(MATCH(B52,$A$11:$A$40,0)),"Einheit unbekannt",IF(AND(D52<>"",F52<>"",F52<D52),"Ende vor Beginn",IF(R52>0,"Überschneidung mit anderem Mieter",""))))) | P52: =IF(C52="","",IF(D52="",1,D52)) | Q52: =IF(C52="","",IF(F52="",401768,F52)) | R52: =IF(C52="",0,COUNTIFS($B$45:$B$104,B52,$P$45:$P$104,"<="&Q52,$Q$45:$Q$104,">="&P52)-1)
A53: 9 | F53: =IF(E53<>"",E53,IFERROR(INDEX(Mieterwechsel!$H$9:$H$28,MATCH(A53,Mieterwechsel!$A$9:$A$28,0)),"")) | N53: =IF(C53="","",IF(AND(F53<>"",F53<TODAY()),"beendet",IF(AND(D53<>"",D53>TODAY()),"künftig","aktiv"))) | O53: =IF(C53="","",IF(B53="","Einheit fehlt",IF(ISNA(MATCH(B53,$A$11:$A$40,0)),"Einheit unbekannt",IF(AND(D53<>"",F53<>"",F53<D53),"Ende vor Beginn",IF(R53>0,"Überschneidung mit anderem Mieter",""))))) | P53: =IF(C53="","",IF(D53="",1,D53)) | Q53: =IF(C53="","",IF(F53="",401768,F53)) | R53: =IF(C53="",0,COUNTIFS($B$45:$B$104,B53,$P$45:$P$104,"<="&Q53,$Q$45:$Q$104,">="&P53)-1)
A54: 10 | F54: =IF(E54<>"",E54,IFERROR(INDEX(Mieterwechsel!$H$9:$H$28,MATCH(A54,Mieterwechsel!$A$9:$A$28,0)),"")) | N54: =IF(C54="","",IF(AND(F54<>"",F54<TODAY()),"beendet",IF(AND(D54<>"",D54>TODAY()),"künftig","aktiv"))) | O54: =IF(C54="","",IF(B54="","Einheit fehlt",IF(ISNA(MATCH(B54,$A$11:$A$40,0)),"Einheit unbekannt",IF(AND(D54<>"",F54<>"",F54<D54),"Ende vor Beginn",IF(R54>0,"Überschneidung mit anderem Mieter",""))))) | P54: =IF(C54="","",IF(D54="",1,D54)) | Q54: =IF(C54="","",IF(F54="",401768,F54)) | R54: =IF(C54="",0,COUNTIFS($B$45:$B$104,B54,$P$45:$P$104,"<="&Q54,$Q$45:$Q$104,">="&P54)-1)
A55: 11 | F55: =IF(E55<>"",E55,IFERROR(INDEX(Mieterwechsel!$H$9:$H$28,MATCH(A55,Mieterwechsel!$A$9:$A$28,0)),"")) | N55: =IF(C55="","",IF(AND(F55<>"",F55<TODAY()),"beendet",IF(AND(D55<>"",D55>TODAY()),"künftig","aktiv"))) | O55: =IF(C55="","",IF(B55="","Einheit fehlt",IF(ISNA(MATCH(B55,$A$11:$A$40,0)),"Einheit unbekannt",IF(AND(D55<>"",F55<>"",F55<D55),"Ende vor Beginn",IF(R55>0,"Überschneidung mit anderem Mieter",""))))) | P55: =IF(C55="","",IF(D55="",1,D55)) | Q55: =IF(C55="","",IF(F55="",401768,F55)) | R55: =IF(C55="",0,COUNTIFS($B$45:$B$104,B55,$P$45:$P$104,"<="&Q55,$Q$45:$Q$104,">="&P55)-1)
A56: 12 | F56: =IF(E56<>"",E56,IFERROR(INDEX(Mieterwechsel!$H$9:$H$28,MATCH(A56,Mieterwechsel!$A$9:$A$28,0)),"")) | N56: =IF(C56="","",IF(AND(F56<>"",F56<TODAY()),"beendet",IF(AND(D56<>"",D56>TODAY()),"künftig","aktiv"))) | O56: =IF(C56="","",IF(B56="","Einheit fehlt",IF(ISNA(MATCH(B56,$A$11:$A$40,0)),"Einheit unbekannt",IF(AND(D56<>"",F56<>"",F56<D56),"Ende vor Beginn",IF(R56>0,"Überschneidung mit anderem Mieter",""))))) | P56: =IF(C56="","",IF(D56="",1,D56)) | Q56: =IF(C56="","",IF(F56="",401768,F56)) | R56: =IF(C56="",0,COUNTIFS($B$45:$B$104,B56,$P$45:$P$104,"<="&Q56,$Q$45:$Q$104,">="&P56)-1)
A57: 13 | F57: =IF(E57<>"",E57,IFERROR(INDEX(Mieterwechsel!$H$9:$H$28,MATCH(A57,Mieterwechsel!$A$9:$A$28,0)),"")) | N57: =IF(C57="","",IF(AND(F57<>"",F57<TODAY()),"beendet",IF(AND(D57<>"",D57>TODAY()),"künftig","aktiv"))) | O57: =IF(C57="","",IF(B57="","Einheit fehlt",IF(ISNA(MATCH(B57,$A$11:$A$40,0)),"Einheit unbekannt",IF(AND(D57<>"",F57<>"",F57<D57),"Ende vor Beginn",IF(R57>0,"Überschneidung mit anderem Mieter",""))))) | P57: =IF(C57="","",IF(D57="",1,D57)) | Q57: =IF(C57="","",IF(F57="",401768,F57)) | R57: =IF(C57="",0,COUNTIFS($B$45:$B$104,B57,$P$45:$P$104,"<="&Q57,$Q$45:$Q$104,">="&P57)-1)
A58: 14 | F58: =IF(E58<>"",E58,IFERROR(INDEX(Mieterwechsel!$H$9:$H$28,MATCH(A58,Mieterwechsel!$A$9:$A$28,0)),"")) | N58: =IF(C58="","",IF(AND(F58<>"",F58<TODAY()),"beendet",IF(AND(D58<>"",D58>TODAY()),"künftig","aktiv"))) | O58: =IF(C58="","",IF(B58="","Einheit fehlt",IF(ISNA(MATCH(B58,$A$11:$A$40,0)),"Einheit unbekannt",IF(AND(D58<>"",F58<>"",F58<D58),"Ende vor Beginn",IF(R58>0,"Überschneidung mit anderem Mieter",""))))) | P58: =IF(C58="","",IF(D58="",1,D58)) | Q58: =IF(C58="","",IF(F58="",401768,F58)) | R58: =IF(C58="",0,COUNTIFS($B$45:$B$104,B58,$P$45:$P$104,"<="&Q58,$Q$45:$Q$104,">="&P58)-1)
A59: 15 | F59: =IF(E59<>"",E59,IFERROR(INDEX(Mieterwechsel!$H$9:$H$28,MATCH(A59,Mieterwechsel!$A$9:$A$28,0)),"")) | N59: =IF(C59="","",IF(AND(F59<>"",F59<TODAY()),"beendet",IF(AND(D59<>"",D59>TODAY()),"künftig","aktiv"))) | O59: =IF(C59="","",IF(B59="","Einheit fehlt",IF(ISNA(MATCH(B59,$A$11:$A$40,0)),"Einheit unbekannt",IF(AND(D59<>"",F59<>"",F59<D59),"Ende vor Beginn",IF(R59>0,"Überschneidung mit anderem Mieter",""))))) | P59: =IF(C59="","",IF(D59="",1,D59)) | Q59: =IF(C59="","",IF(F59="",401768,F59)) | R59: =IF(C59="",0,COUNTIFS($B$45:$B$104,B59,$P$45:$P$104,"<="&Q59,$Q$45:$Q$104,">="&P59)-1)
A60: 16 | F60: =IF(E60<>"",E60,IFERROR(INDEX(Mieterwechsel!$H$9:$H$28,MATCH(A60,Mieterwechsel!$A$9:$A$28,0)),"")) | N60: =IF(C60="","",IF(AND(F60<>"",F60<TODAY()),"beendet",IF(AND(D60<>"",D60>TODAY()),"künftig","aktiv"))) | O60: =IF(C60="","",IF(B60="","Einheit fehlt",IF(ISNA(MATCH(B60,$A$11:$A$40,0)),"Einheit unbekannt",IF(AND(D60<>"",F60<>"",F60<D60),"Ende vor Beginn",IF(R60>0,"Überschneidung mit anderem Mieter",""))))) | P60: =IF(C60="","",IF(D60="",1,D60)) | Q60: =IF(C60="","",IF(F60="",401768,F60)) | R60: =IF(C60="",0,COUNTIFS($B$45:$B$104,B60,$P$45:$P$104,"<="&Q60,$Q$45:$Q$104,">="&P60)-1)
A61: 17 | F61: =IF(E61<>"",E61,IFERROR(INDEX(Mieterwechsel!$H$9:$H$28,MATCH(A61,Mieterwechsel!$A$9:$A$28,0)),"")) | N61: =IF(C61="","",IF(AND(F61<>"",F61<TODAY()),"beendet",IF(AND(D61<>"",D61>TODAY()),"künftig","aktiv"))) | O61: =IF(C61="","",IF(B61="","Einheit fehlt",IF(ISNA(MATCH(B61,$A$11:$A$40,0)),"Einheit unbekannt",IF(AND(D61<>"",F61<>"",F61<D61),"Ende vor Beginn",IF(R61>0,"Überschneidung mit anderem Mieter",""))))) | P61: =IF(C61="","",IF(D61="",1,D61)) | Q61: =IF(C61="","",IF(F61="",401768,F61)) | R61: =IF(C61="",0,COUNTIFS($B$45:$B$104,B61,$P$45:$P$104,"<="&Q61,$Q$45:$Q$104,">="&P61)-1)
A62: 18 | F62: =IF(E62<>"",E62,IFERROR(INDEX(Mieterwechsel!$H$9:$H$28,MATCH(A62,Mieterwechsel!$A$9:$A$28,0)),"")) | N62: =IF(C62="","",IF(AND(F62<>"",F62<TODAY()),"beendet",IF(AND(D62<>"",D62>TODAY()),"künftig","aktiv"))) | O62: =IF(C62="","",IF(B62="","Einheit fehlt",IF(ISNA(MATCH(B62,$A$11:$A$40,0)),"Einheit unbekannt",IF(AND(D62<>"",F62<>"",F62<D62),"Ende vor Beginn",IF(R62>0,"Überschneidung mit anderem Mieter",""))))) | P62: =IF(C62="","",IF(D62="",1,D62)) | Q62: =IF(C62="","",IF(F62="",401768,F62)) | R62: =IF(C62="",0,COUNTIFS($B$45:$B$104,B62,$P$45:$P$104,"<="&Q62,$Q$45:$Q$104,">="&P62)-1)
... A104: 60 | F104: =IF(E104<>"",E104,IFERROR(INDEX(Mieterwechsel!$H$9:$H$28,MATCH(A104,Mieterwechsel!$A$9:$A$28,0)),"")) | N104: =IF(C104="","",IF(AND(F104<>"",F104<TODAY()),"beendet",IF(AND(D104<>"",D104>TODAY()),"künftig","aktiv"))) | O104: =IF(C104="","",IF(B104="","Einheit fehlt",IF(ISNA(MATCH(B104,$A$11:$A$40,0)),"Einheit unbekannt",IF(AND(D104<>"",F104<>"",F104<D104),"Ende vor Beginn",IF(R104>0,"Überschneidung mit anderem Mieter",""))))) | P104: =IF(C104="","",IF(D104="",1,D104)) | Q104: =IF(C104="","",IF(F104="",401768,F104)) | R104: =IF(C104="",0,COUNTIFS($B$45:$B$104,B104,$P$45:$P$104,"<="&Q104,$Q$45:$Q$104,">="&P104)-1)

Sheet Mieterwechsel
A1: Mieterwechsel & Fristen
A2: START: Pro Kündigung eine Zeile: Mietverhältnis-ID, wer kündigt, Eingangsdatum.
A3: BERECHNUNG: Mietende auf den nächsten zulässigen Termin, zehn Schritte mit Datum, Leerstand in Franken.
A4: ERGEBNIS: Spalte «Nächste Frist»: rot überfällig, gelb innert 7 Tagen. Erledigtes mit x markieren.
A5: AUSGABE: Blatt «Checkliste»: ein Mieterwechsel als druckbare Liste.
BI7: Kündigung schriftlich bestätigen | BJ7: Nachmieter suchen / Inserat | BK7: Vorabnahme | BL7: Neuen Mietvertrag abschliessen | BM7: Abnahme · Protokoll · Zähler · Schlüssel | BN7: Mängelrüge schriftlich | BO7: Übergabe an Neumieter | BP7: Kaution abrechnen | BQ7: Nebenkosten-Schlussabrechnung | BR7: Kautionsfrist (1 Jahr nach Mietende)
A8: ID | B8: Mieter | C8: Einheit | D8: Kündigung durch | E8: Eingang Kündigung | F8: Frist (Mt.) | G8: Vereinbartes Ende | H8: Ende Mietverhältnis | I8: Neuer Mieter ab | J8: Leerstand Tage | K8: Leerstandskosten | L8: Kündigung schriftlich bestätigen | M8: erl. | N8: Nachmieter suchen / Inserat | O8: erl. | P8: Vorabnahme | Q8: erl. | R8: Neuen Mietvertrag abschliessen | S8: erl. | T8: Abnahme · Protokoll · Zähler · Schlüssel | U8: erl. | V8: Mängelrüge schriftlich | W8: erl. | X8: Übergabe an Neumieter | Y8: erl. | Z8: Kaution abrechnen | AA8: erl. | AB8: Nebenkosten-Schlussabrechnung | AC8: erl. | AD8: Kautionsfrist (1 Jahr nach Mietende) | AE8: erl. | AF8: Nächste Frist | AG8: Tage | AH8: Nächster Schritt | AI8: Hinweis
A9: 2 | B9: =IF(A9="","",IFERROR(INDEX('Mein Haus'!$C$45:$C$104,A9)&"","")) | C9: =IF(A9="","",IFERROR(INDEX('Mein Haus'!$B$45:$B$104,A9)&"","")) | D9: Mieter | E9: 45636 | F9: 3 | H9: =IF(G9<>"",G9,IF(E9="","",IF(COUNT(AK9:BH9)=0,"",MIN(AK9:BH9)))) | I9: 45748 | J9: =IF(OR(H9="",I9=""),"",MAX(0,I9-H9-1)) | K9: =IF(J9="","",ROUND(N(IFERROR(INDEX('Mein Haus'!$G$45:$G$104,A9),0))*12/365*J9,2)) | L9: =IF(E9="","",E9+7) | M9: x | N9: =IF(E9="","",E9) | O9: x | P9: =IF(H9="","",WORKDAY(H9,-10,Einstellungen!$D$5:$D$34)) | Q9: x | R9: =IF(H9="","",H9-30) | S9: x | T9: =IF(H9="","",WORKDAY(H9-1,1,Einstellungen!$D$5:$D$34)) | U9: x | V9: =IF(T9="","",WORKDAY(T9,2,Einstellungen!$D$5:$D$34)) | W9: x | X9: =IF(I9="","",I9) | Y9: x | Z9: =IF(T9="","",T9+30) | AA9: x | AB9: =IF(OR(H9="",Nebenkosten!$B$7=""),"",EDATE(Nebenkosten!$B$7,12*MAX(1,ROUNDUP(((YEAR(H9)-YEAR(Nebenkosten!$B$7))*12+MONTH(H9)-MONTH(Nebenkosten!$B$7)+1)/12,0)))) | AC9: x | AD9: =IF(H9="","",EDATE(H9,12)) | AE9: x | AF9: =IF(COUNT(BI9:BR9)=0,"",MIN(BI9:BR9)) | AG9: =IF(AF9="","",AF9-TODAY()) | AH9: =IF(AF9="","",INDEX($BI$7:$BR$7,MATCH(AF9,BI9:BR9,0))) | AI9: =IF(A9="","",IF(B9="","ID ohne Mieter in «Mein Haus»",IF(AND(IFERROR(INDEX('Mein Haus'!$E$45:$E$104,A9),"")<>"",H9<>"",IFERROR(INDEX('Mein Haus'!$E$45:$E$104,A9),"")<>H9),"Mietende in «Mein Haus» weicht ab",IF(D9="Vermieter","Amtliches Formular? Familienwohnung: beide Ehegatten.",IF(D9="Ausserterminlich","Nachmieter zumutbar? Vereinbartes Ende eintragen.",""))))) | AK9: =IF(E9="","",IF(OR(COUNTIF(Einstellungen!$B$5:$B$16,"x")=0,INDEX(Einstellungen!$B$5:$B$16,MONTH(EOMONTH(E9,IF(F9="",3,F9)+0)))="x"),EOMONTH(E9,IF(F9="",3,F9)+0),"")) | AL9: =IF(E9="","",IF(OR(COUNTIF(Einstellungen!$B$5:$B$16,"x")=0,INDEX(Einstellungen!$B$5:$B$16,MONTH(EOMONTH(E9,IF(F9="",3,F9)+1)))="x"),EOMONTH(E9,IF(F9="",3,F9)+1),"")) | AM9: =IF(E9="","",IF(OR(COUNTIF(Einstellungen!$B$5:$B$16,"x")=0,INDEX(Einstellungen!$B$5:$B$16,MONTH(EOMONTH(E9,IF(F9="",3,F9)+2)))="x"),EOMONTH(E9,IF(F9="",3,F9)+2),"")) | AN9: =IF(E9="","",IF(OR(COUNTIF(Einstellungen!$B$5:$B$16,"x")=0,INDEX(Einstellungen!$B$5:$B$16,MONTH(EOMONTH(E9,IF(F9="",3,F9)+3)))="x"),EOMONTH(E9,IF(F9="",3,F9)+3),"")) | AO9: =IF(E9="","",IF(OR(COUNTIF(Einstellungen!$B$5:$B$16,"x")=0,INDEX(Einstellungen!$B$5:$B$16,MONTH(EOMONTH(E9,IF(F9="",3,F9)+4)))="x"),EOMONTH(E9,IF(F9="",3,F9)+4),"")) | AP9: =IF(E9="","",IF(OR(COUNTIF(Einstellungen!$B$5:$B$16,"x")=0,INDEX(Einstellungen!$B$5:$B$16,MONTH(EOMONTH(E9,IF(F9="",3,F9)+5)))="x"),EOMONTH(E9,IF(F9="",3,F9)+5),"")) | AQ9: =IF(E9="","",IF(OR(COUNTIF(Einstellungen!$B$5:$B$16,"x")=0,INDEX(Einstellungen!$B$5:$B$16,MONTH(EOMONTH(E9,IF(F9="",3,F9)+6)))="x"),EOMONTH(E9,IF(F9="",3,F9)+6),"")) | AR9: =IF(E9="","",IF(OR(COUNTIF(Einstellungen!$B$5:$B$16,"x")=0,INDEX(Einstellungen!$B$5:$B$16,MONTH(EOMONTH(E9,IF(F9="",3,F9)+7)))="x"),EOMONTH(E9,IF(F9="",3,F9)+7),"")) | AS9: =IF(E9="","",IF(OR(COUNTIF(Einstellungen!$B$5:$B$16,"x")=0,INDEX(Einstellungen!$B$5:$B$16,MONTH(EOMONTH(E9,IF(F9="",3,F9)+8)))="x"),EOMONTH(E9,IF(F9="",3,F9)+8),"")) | AT9: =IF(E9="","",IF(OR(COUNTIF(Einstellungen!$B$5:$B$16,"x")=0,INDEX(Einstellungen!$B$5:$B$16,MONTH(EOMONTH(E9,IF(F9="",3,F9)+9)))="x"),EOMONTH(E9,IF(F9="",3,F9)+9),"")) | AU9: =IF(E9="","",IF(OR(COUNTIF(Einstellungen!$B$5:$B$16,"x")=0,INDEX(Einstellungen!$B$5:$B$16,MONTH(EOMONTH(E9,IF(F9="",3,F9)+10)))="x"),EOMONTH(E9,IF(F9="",3,F9)+10),"")) | AV9: =IF(E9="","",IF(OR(COUNTIF(Einstellungen!$B$5:$B$16,"x")=0,INDEX(Einstellungen!$B$5:$B$16,MONTH(EOMONTH(E9,IF(F9="",3,F9)+11)))="x"),EOMONTH(E9,IF(F9="",3,F9)+11),"")) | AW9: =IF(E9="","",IF(OR(COUNTIF(Einstellungen!$B$5:$B$16,"x")=0,INDEX(Einstellungen!$B$5:$B$16,MONTH(EOMONTH(E9,IF(F9="",3,F9)+12)))="x"),EOMONTH(E9,IF(F9="",3,F9)+12),"")) | AX9: =IF(E9="","",IF(OR(COUNTIF(Einstellungen!$B$5:$B$16,"x")=0,INDEX(Einstellungen!$B$5:$B$16,MONTH(EOMONTH(E9,IF(F9="",3,F9)+13)))="x"),EOMONTH(E9,IF(F9="",3,F9)+13),"")) | AY9: =IF(E9="","",IF(OR(COUNTIF(Einstellungen!$B$5:$B$16,"x")=0,INDEX(Einstellungen!$B$5:$B$16,MONTH(EOMONTH(E9,IF(F9="",3,F9)+14)))="x"),EOMONTH(E9,IF(F9="",3,F9)+14),"")) | AZ9: =IF(E9="","",IF(OR(COUNTIF(Einstellungen!$B$5:$B$16,"x")=0,INDEX(Einstellungen!$B$5:$B$16,MONTH(EOMONTH(E9,IF(F9="",3,F9)+15)))="x"),EOMONTH(E9,IF(F9="",3,F9)+15),"")) | BA9: =IF(E9="","",IF(OR(COUNTIF(Einstellungen!$B$5:$B$16,"x")=0,INDEX(Einstellungen!$B$5:$B$16,MONTH(EOMONTH(E9,IF(F9="",3,F9)+16)))="x"),EOMONTH(E9,IF(F9="",3,F9)+16),"")) | BB9: =IF(E9="","",IF(OR(COUNTIF(Einstellungen!$B$5:$B$16,"x")=0,INDEX(Einstellungen!$B$5:$B$16,MONTH(EOMONTH(E9,IF(F9="",3,F9)+17)))="x"),EOMONTH(E9,IF(F9="",3,F9)+17),"")) | BC9: =IF(E9="","",IF(OR(COUNTIF(Einstellungen!$B$5:$B$16,"x")=0,INDEX(Einstellungen!$B$5:$B$16,MONTH(EOMONTH(E9,IF(F9="",3,F9)+18)))="x"),EOMONTH(E9,IF(F9="",3,F9)+18),"")) | BD9: =IF(E9="","",IF(OR(COUNTIF(Einstellungen!$B$5:$B$16,"x")=0,INDEX(Einstellungen!$B$5:$B$16,MONTH(EOMONTH(E9,IF(F9="",3,F9)+19)))="x"),EOMONTH(E9,IF(F9="",3,F9)+19),"")) | BE9: =IF(E9="","",IF(OR(COUNTIF(Einstellungen!$B$5:$B$16,"x")=0,INDEX(Einstellungen!$B$5:$B$16,MONTH(EOMONTH(E9,IF(F9="",3,F9)+20)))="x"),EOMONTH(E9,IF(F9="",3,F9)+20),"")) | BF9: =IF(E9="","",IF(OR(COUNTIF(Einstellungen!$B$5:$B$16,"x")=0,INDEX(Einstellungen!$B$5:$B$16,MONTH(EOMONTH(E9,IF(F9="",3,F9)+21)))="x"),EOMONTH(E9,IF(F9="",3,F9)+21),"")) | BG9: =IF(E9="","",IF(OR(COUNTIF(Einstellungen!$B$5:$B$16,"x")=0,INDEX(Einstellungen!$B$5:$B$16,MONTH(EOMONTH(E9,IF(F9="",3,F9)+22)))="x"),EOMONTH(E9,IF(F9="",3,F9)+22),"")) | BH9: =IF(E9="","",IF(OR(COUNTIF(Einstellungen!$B$5:$B$16,"x")=0,INDEX(Einstellungen!$B$5:$B$16,MONTH(EOMONTH(E9,IF(F9="",3,F9)+23)))="x"),EOMONTH(E9,IF(F9="",3,F9)+23),"")) | BI9: =IF(AND(L9<>"",M9=""),L9,"") | BJ9: =IF(AND(N9<>"",O9=""),N9,"") | BK9: =IF(AND(P9<>"",Q9=""),P9,"") | BL9: =IF(AND(R9<>"",S9=""),R9,"") | BM9: =IF(AND(T9<>"",U9=""),T9,"") | BN9: =IF(AND(V9<>"",W9=""),V9,"") | BO9: =IF(AND(X9<>"",Y9=""),X9,"") | BP9: =IF(AND(Z9<>"",AA9=""),Z9,"") | BQ9: =IF(AND(AB9<>"",AC9=""),AB9,"") | BR9: =IF(AND(AD9<>"",AE9=""),AD9,"") | BS9: =IF(AF9="","",AF9+ROW()/100000)
A10: 5 | B10: =IF(A10="","",IFERROR(INDEX('Mein Haus'!$C$45:$C$104,A10)&"","")) | C10: =IF(A10="","",IFERROR(INDEX('Mein Haus'!$B$45:$B$104,A10)&"","")) | D10: Vermieter | E10: 45838 | F10: 3 | H10: =IF(G10<>"",G10,IF(E10="","",IF(COUNT(AK10:BH10)=0,"",MIN(AK10:BH10)))) | I10: 45992 | J10: =IF(OR(H10="",I10=""),"",MAX(0,I10-H10-1)) | K10: =IF(J10="","",ROUND(N(IFERROR(INDEX('Mein Haus'!$G$45:$G$104,A10),0))*12/365*J10,2)) | L10: =IF(E10="","",E10+7) | M10: x | N10: =IF(E10="","",E10) | O10: x | P10: =IF(H10="","",WORKDAY(H10,-10,Einstellungen!$D$5:$D$34)) | Q10: x | R10: =IF(H10="","",H10-30) | S10: x | T10: =IF(H10="","",WORKDAY(H10-1,1,Einstellungen!$D$5:$D$34)) | U10: x | V10: =IF(T10="","",WORKDAY(T10,2,Einstellungen!$D$5:$D$34)) | W10: x | X10: =IF(I10="","",I10) | Y10: x | Z10: =IF(T10="","",T10+30) | AA10: x | AB10: =IF(OR(H10="",Nebenkosten!$B$7=""),"",EDATE(Nebenkosten!$B$7,12*MAX(1,ROUNDUP(((YEAR(H10)-YEAR(Nebenkosten!$B$7))*12+MONTH(H10)-MONTH(Nebenkosten!$B$7)+1)/12,0)))) | AC10: x | AD10: =IF(H10="","",EDATE(H10,12)) | AE10: x | AF10: =IF(COUNT(BI10:BR10)=0,"",MIN(BI10:BR10)) | AG10: =IF(AF10="","",AF10-TODAY()) | AH10: =IF(AF10="","",INDEX($BI$7:$BR$7,MATCH(AF10,BI10:BR10,0))) | AI10: =IF(A10="","",IF(B10="","ID ohne Mieter in «Mein Haus»",IF(AND(IFERROR(INDEX('Mein Haus'!$E$45:$E$104,A10),"")<>"",H10<>"",IFERROR(INDEX('Mein Haus'!$E$45:$E$104,A10),"")<>H10),"Mietende in «Mein Haus» weicht ab",IF(D10="Vermieter","Amtliches Formular? Familienwohnung: beide Ehegatten.",IF(D10="Ausserterminlich","Nachmieter zumutbar? Vereinbartes Ende eintragen.",""))))) | AK10: =IF(E10="","",IF(OR(COUNTIF(Einstellungen!$B$5:$B$16,"x")=0,INDEX(Einstellungen!$B$5:$B$16,MONTH(EOMONTH(E10,IF(F10="",3,F10)+0)))="x"),EOMONTH(E10,IF(F10="",3,F10)+0),"")) | AL10: =IF(E10="","",IF(OR(COUNTIF(Einstellungen!$B$5:$B$16,"x")=0,INDEX(Einstellungen!$B$5:$B$16,MONTH(EOMONTH(E10,IF(F10="",3,F10)+1)))="x"),EOMONTH(E10,IF(F10="",3,F10)+1),"")) | AM10: =IF(E10="","",IF(OR(COUNTIF(Einstellungen!$B$5:$B$16,"x")=0,INDEX(Einstellungen!$B$5:$B$16,MONTH(EOMONTH(E10,IF(F10="",3,F10)+2)))="x"),EOMONTH(E10,IF(F10="",3,F10)+2),"")) | AN10: =IF(E10="","",IF(OR(COUNTIF(Einstellungen!$B$5:$B$16,"x")=0,INDEX(Einstellungen!$B$5:$B$16,MONTH(EOMONTH(E10,IF(F10="",3,F10)+3)))="x"),EOMONTH(E10,IF(F10="",3,F10)+3),"")) | AO10: =IF(E10="","",IF(OR(COUNTIF(Einstellungen!$B$5:$B$16,"x")=0,INDEX(Einstellungen!$B$5:$B$16,MONTH(EOMONTH(E10,IF(F10="",3,F10)+4)))="x"),EOMONTH(E10,IF(F10="",3,F10)+4),"")) | AP10: =IF(E10="","",IF(OR(COUNTIF(Einstellungen!$B$5:$B$16,"x")=0,INDEX(Einstellungen!$B$5:$B$16,MONTH(EOMONTH(E10,IF(F10="",3,F10)+5)))="x"),EOMONTH(E10,IF(F10="",3,F10)+5),"")) | AQ10: =IF(E10="","",IF(OR(COUNTIF(Einstellungen!$B$5:$B$16,"x")=0,INDEX(Einstellungen!$B$5:$B$16,MONTH(EOMONTH(E10,IF(F10="",3,F10)+6)))="x"),EOMONTH(E10,IF(F10="",3,F10)+6),"")) | AR10: =IF(E10="","",IF(OR(COUNTIF(Einstellungen!$B$5:$B$16,"x")=0,INDEX(Einstellungen!$B$5:$B$16,MONTH(EOMONTH(E10,IF(F10="",3,F10)+7)))="x"),EOMONTH(E10,IF(F10="",3,F10)+7),"")) | AS10: =IF(E10="","",IF(OR(COUNTIF(Einstellungen!$B$5:$B$16,"x")=0,INDEX(Einstellungen!$B$5:$B$16,MONTH(EOMONTH(E10,IF(F10="",3,F10)+8)))="x"),EOMONTH(E10,IF(F10="",3,F10)+8),"")) | AT10: =IF(E10="","",IF(OR(COUNTIF(Einstellungen!$B$5:$B$16,"x")=0,INDEX(Einstellungen!$B$5:$B$16,MONTH(EOMONTH(E10,IF(F10="",3,F10)+9)))="x"),EOMONTH(E10,IF(F10="",3,F10)+9),"")) | AU10: =IF(E10="","",IF(OR(COUNTIF(Einstellungen!$B$5:$B$16,"x")=0,INDEX(Einstellungen!$B$5:$B$16,MONTH(EOMONTH(E10,IF(F10="",3,F10)+10)))="x"),EOMONTH(E10,IF(F10="",3,F10)+10),"")) | AV10: =IF(E10="","",IF(OR(COUNTIF(Einstellungen!$B$5:$B$16,"x")=0,INDEX(Einstellungen!$B$5:$B$16,MONTH(EOMONTH(E10,IF(F10="",3,F10)+11)))="x"),EOMONTH(E10,IF(F10="",3,F10)+11),"")) | AW10: =IF(E10="","",IF(OR(COUNTIF(Einstellungen!$B$5:$B$16,"x")=0,INDEX(Einstellungen!$B$5:$B$16,MONTH(EOMONTH(E10,IF(F10="",3,F10)+12)))="x"),EOMONTH(E10,IF(F10="",3,F10)+12),"")) | AX10: =IF(E10="","",IF(OR(COUNTIF(Einstellungen!$B$5:$B$16,"x")=0,INDEX(Einstellungen!$B$5:$B$16,MONTH(EOMONTH(E10,IF(F10="",3,F10)+13)))="x"),EOMONTH(E10,IF(F10="",3,F10)+13),"")) | AY10: =IF(E10="","",IF(OR(COUNTIF(Einstellungen!$B$5:$B$16,"x")=0,INDEX(Einstellungen!$B$5:$B$16,MONTH(EOMONTH(E10,IF(F10="",3,F10)+14)))="x"),EOMONTH(E10,IF(F10="",3,F10)+14),"")) | AZ10: =IF(E10="","",IF(OR(COUNTIF(Einstellungen!$B$5:$B$16,"x")=0,INDEX(Einstellungen!$B$5:$B$16,MONTH(EOMONTH(E10,IF(F10="",3,F10)+15)))="x"),EOMONTH(E10,IF(F10="",3,F10)+15),"")) | BA10: =IF(E10="","",IF(OR(COUNTIF(Einstellungen!$B$5:$B$16,"x")=0,INDEX(Einstellungen!$B$5:$B$16,MONTH(EOMONTH(E10,IF(F10="",3,F10)+16)))="x"),EOMONTH(E10,IF(F10="",3,F10)+16),"")) | BB10: =IF(E10="","",IF(OR(COUNTIF(Einstellungen!$B$5:$B$16,"x")=0,INDEX(Einstellungen!$B$5:$B$16,MONTH(EOMONTH(E10,IF(F10="",3,F10)+17)))="x"),EOMONTH(E10,IF(F10="",3,F10)+17),"")) | BC10: =IF(E10="","",IF(OR(COUNTIF(Einstellungen!$B$5:$B$16,"x")=0,INDEX(Einstellungen!$B$5:$B$16,MONTH(EOMONTH(E10,IF(F10="",3,F10)+18)))="x"),EOMONTH(E10,IF(F10="",3,F10)+18),"")) | BD10: =IF(E10="","",IF(OR(COUNTIF(Einstellungen!$B$5:$B$16,"x")=0,INDEX(Einstellungen!$B$5:$B$16,MONTH(EOMONTH(E10,IF(F10="",3,F10)+19)))="x"),EOMONTH(E10,IF(F10="",3,F10)+19),"")) | BE10: =IF(E10="","",IF(OR(COUNTIF(Einstellungen!$B$5:$B$16,"x")=0,INDEX(Einstellungen!$B$5:$B$16,MONTH(EOMONTH(E10,IF(F10="",3,F10)+20)))="x"),EOMONTH(E10,IF(F10="",3,F10)+20),"")) | BF10: =IF(E10="","",IF(OR(COUNTIF(Einstellungen!$B$5:$B$16,"x")=0,INDEX(Einstellungen!$B$5:$B$16,MONTH(EOMONTH(E10,IF(F10="",3,F10)+21)))="x"),EOMONTH(E10,IF(F10="",3,F10)+21),"")) | BG10: =IF(E10="","",IF(OR(COUNTIF(Einstellungen!$B$5:$B$16,"x")=0,INDEX(Einstellungen!$B$5:$B$16,MONTH(EOMONTH(E10,IF(F10="",3,F10)+22)))="x"),EOMONTH(E10,IF(F10="",3,F10)+22),"")) | BH10: =IF(E10="","",IF(OR(COUNTIF(Einstellungen!$B$5:$B$16,"x")=0,INDEX(Einstellungen!$B$5:$B$16,MONTH(EOMONTH(E10,IF(F10="",3,F10)+23)))="x"),EOMONTH(E10,IF(F10="",3,F10)+23),"")) | BI10: =IF(AND(L10<>"",M10=""),L10,"") | BJ10: =IF(AND(N10<>"",O10=""),N10,"") | BK10: =IF(AND(P10<>"",Q10=""),P10,"") | BL10: =IF(AND(R10<>"",S10=""),R10,"") | BM10: =IF(AND(T10<>"",U10=""),T10,"") | BN10: =IF(AND(V10<>"",W10=""),V10,"") | BO10: =IF(AND(X10<>"",Y10=""),X10,"") | BP10: =IF(AND(Z10<>"",AA10=""),Z10,"") | BQ10: =IF(AND(AB10<>"",AC10=""),AB10,"") | BR10: =IF(AND(AD10<>"",AE10=""),AD10,"") | BS10: =IF(AF10="","",AF10+ROW()/100000)
A11: 1 | B11: =IF(A11="","",IFERROR(INDEX('Mein Haus'!$C$45:$C$104,A11)&"","")) | C11: =IF(A11="","",IFERROR(INDEX('Mein Haus'!$B$45:$B$104,A11)&"","")) | D11: Mieter | E11: 46254 | F11: 3 | H11: =IF(G11<>"",G11,IF(E11="","",IF(COUNT(AK11:BH11)=0,"",MIN(AK11:BH11)))) | J11: =IF(OR(H11="",I11=""),"",MAX(0,I11-H11-1)) | K11: =IF(J11="","",ROUND(N(IFERROR(INDEX('Mein Haus'!$G$45:$G$104,A11),0))*12/365*J11,2)) | L11: =IF(E11="","",E11+7) | N11: =IF(E11="","",E11) | P11: =IF(H11="","",WORKDAY(H11,-10,Einstellungen!$D$5:$D$34)) | R11: =IF(H11="","",H11-30) | T11: =IF(H11="","",WORKDAY(H11-1,1,Einstellungen!$D$5:$D$34)) | V11: =IF(T11="","",WORKDAY(T11,2,Einstellungen!$D$5:$D$34)) | X11: =IF(I11="","",I11) | Z11: =IF(T11="","",T11+30) | AB11: =IF(OR(H11="",Nebenkosten!$B$7=""),"",EDATE(Nebenkosten!$B$7,12*MAX(1,ROUNDUP(((YEAR(H11)-YEAR(Nebenkosten!$B$7))*12+MONTH(H11)-MONTH(Nebenkosten!$B$7)+1)/12,0)))) | AD11: =IF(H11="","",EDATE(H11,12)) | AF11: =IF(COUNT(BI11:BR11)=0,"",MIN(BI11:BR11)) | AG11: =IF(AF11="","",AF11-TODAY()) | AH11: =IF(AF11="","",INDEX($BI$7:$BR$7,MATCH(AF11,BI11:BR11,0))) | AI11: =IF(A11="","",IF(B11="","ID ohne Mieter in «Mein Haus»",IF(AND(IFERROR(INDEX('Mein Haus'!$E$45:$E$104,A11),"")<>"",H11<>"",IFERROR(INDEX('Mein Haus'!$E$45:$E$104,A11),"")<>H11),"Mietende in «Mein Haus» weicht ab",IF(D11="Vermieter","Amtliches Formular? Familienwohnung: beide Ehegatten.",IF(D11="Ausserterminlich","Nachmieter zumutbar? Vereinbartes Ende eintragen.",""))))) | AK11: =IF(E11="","",IF(OR(COUNTIF(Einstellungen!$B$5:$B$16,"x")=0,INDEX(Einstellungen!$B$5:$B$16,MONTH(EOMONTH(E11,IF(F11="",3,F11)+0)))="x"),EOMONTH(E11,IF(F11="",3,F11)+0),"")) | AL11: =IF(E11="","",IF(OR(COUNTIF(Einstellungen!$B$5:$B$16,"x")=0,INDEX(Einstellungen!$B$5:$B$16,MONTH(EOMONTH(E11,IF(F11="",3,F11)+1)))="x"),EOMONTH(E11,IF(F11="",3,F11)+1),"")) | AM11: =IF(E11="","",IF(OR(COUNTIF(Einstellungen!$B$5:$B$16,"x")=0,INDEX(Einstellungen!$B$5:$B$16,MONTH(EOMONTH(E11,IF(F11="",3,F11)+2)))="x"),EOMONTH(E11,IF(F11="",3,F11)+2),"")) | AN11: =IF(E11="","",IF(OR(COUNTIF(Einstellungen!$B$5:$B$16,"x")=0,INDEX(Einstellungen!$B$5:$B$16,MONTH(EOMONTH(E11,IF(F11="",3,F11)+3)))="x"),EOMONTH(E11,IF(F11="",3,F11)+3),"")) | AO11: =IF(E11="","",IF(OR(COUNTIF(Einstellungen!$B$5:$B$16,"x")=0,INDEX(Einstellungen!$B$5:$B$16,MONTH(EOMONTH(E11,IF(F11="",3,F11)+4)))="x"),EOMONTH(E11,IF(F11="",3,F11)+4),"")) | AP11: =IF(E11="","",IF(OR(COUNTIF(Einstellungen!$B$5:$B$16,"x")=0,INDEX(Einstellungen!$B$5:$B$16,MONTH(EOMONTH(E11,IF(F11="",3,F11)+5)))="x"),EOMONTH(E11,IF(F11="",3,F11)+5),"")) | AQ11: =IF(E11="","",IF(OR(COUNTIF(Einstellungen!$B$5:$B$16,"x")=0,INDEX(Einstellungen!$B$5:$B$16,MONTH(EOMONTH(E11,IF(F11="",3,F11)+6)))="x"),EOMONTH(E11,IF(F11="",3,F11)+6),"")) | AR11: =IF(E11="","",IF(OR(COUNTIF(Einstellungen!$B$5:$B$16,"x")=0,INDEX(Einstellungen!$B$5:$B$16,MONTH(EOMONTH(E11,IF(F11="",3,F11)+7)))="x"),EOMONTH(E11,IF(F11="",3,F11)+7),"")) | AS11: =IF(E11="","",IF(OR(COUNTIF(Einstellungen!$B$5:$B$16,"x")=0,INDEX(Einstellungen!$B$5:$B$16,MONTH(EOMONTH(E11,IF(F11="",3,F11)+8)))="x"),EOMONTH(E11,IF(F11="",3,F11)+8),"")) | AT11: =IF(E11="","",IF(OR(COUNTIF(Einstellungen!$B$5:$B$16,"x")=0,INDEX(Einstellungen!$B$5:$B$16,MONTH(EOMONTH(E11,IF(F11="",3,F11)+9)))="x"),EOMONTH(E11,IF(F11="",3,F11)+9),"")) | AU11: =IF(E11="","",IF(OR(COUNTIF(Einstellungen!$B$5:$B$16,"x")=0,INDEX(Einstellungen!$B$5:$B$16,MONTH(EOMONTH(E11,IF(F11="",3,F11)+10)))="x"),EOMONTH(E11,IF(F11="",3,F11)+10),"")) | AV11: =IF(E11="","",IF(OR(COUNTIF(Einstellungen!$B$5:$B$16,"x")=0,INDEX(Einstellungen!$B$5:$B$16,MONTH(EOMONTH(E11,IF(F11="",3,F11)+11)))="x"),EOMONTH(E11,IF(F11="",3,F11)+11),"")) | AW11: =IF(E11="","",IF(OR(COUNTIF(Einstellungen!$B$5:$B$16,"x")=0,INDEX(Einstellungen!$B$5:$B$16,MONTH(EOMONTH(E11,IF(F11="",3,F11)+12)))="x"),EOMONTH(E11,IF(F11="",3,F11)+12),"")) | AX11: =IF(E11="","",IF(OR(COUNTIF(Einstellungen!$B$5:$B$16,"x")=0,INDEX(Einstellungen!$B$5:$B$16,MONTH(EOMONTH(E11,IF(F11="",3,F11)+13)))="x"),EOMONTH(E11,IF(F11="",3,F11)+13),"")) | AY11: =IF(E11="","",IF(OR(COUNTIF(Einstellungen!$B$5:$B$16,"x")=0,INDEX(Einstellungen!$B$5:$B$16,MONTH(EOMONTH(E11,IF(F11="",3,F11)+14)))="x"),EOMONTH(E11,IF(F11="",3,F11)+14),"")) | AZ11: =IF(E11="","",IF(OR(COUNTIF(Einstellungen!$B$5:$B$16,"x")=0,INDEX(Einstellungen!$B$5:$B$16,MONTH(EOMONTH(E11,IF(F11="",3,F11)+15)))="x"),EOMONTH(E11,IF(F11="",3,F11)+15),"")) | BA11: =IF(E11="","",IF(OR(COUNTIF(Einstellungen!$B$5:$B$16,"x")=0,INDEX(Einstellungen!$B$5:$B$16,MONTH(EOMONTH(E11,IF(F11="",3,F11)+16)))="x"),EOMONTH(E11,IF(F11="",3,F11)+16),"")) | BB11: =IF(E11="","",IF(OR(COUNTIF(Einstellungen!$B$5:$B$16,"x")=0,INDEX(Einstellungen!$B$5:$B$16,MONTH(EOMONTH(E11,IF(F11="",3,F11)+17)))="x"),EOMONTH(E11,IF(F11="",3,F11)+17),"")) | BC11: =IF(E11="","",IF(OR(COUNTIF(Einstellungen!$B$5:$B$16,"x")=0,INDEX(Einstellungen!$B$5:$B$16,MONTH(EOMONTH(E11,IF(F11="",3,F11)+18)))="x"),EOMONTH(E11,IF(F11="",3,F11)+18),"")) | BD11: =IF(E11="","",IF(OR(COUNTIF(Einstellungen!$B$5:$B$16,"x")=0,INDEX(Einstellungen!$B$5:$B$16,MONTH(EOMONTH(E11,IF(F11="",3,F11)+19)))="x"),EOMONTH(E11,IF(F11="",3,F11)+19),"")) | BE11: =IF(E11="","",IF(OR(COUNTIF(Einstellungen!$B$5:$B$16,"x")=0,INDEX(Einstellungen!$B$5:$B$16,MONTH(EOMONTH(E11,IF(F11="",3,F11)+20)))="x"),EOMONTH(E11,IF(F11="",3,F11)+20),"")) | BF11: =IF(E11="","",IF(OR(COUNTIF(Einstellungen!$B$5:$B$16,"x")=0,INDEX(Einstellungen!$B$5:$B$16,MONTH(EOMONTH(E11,IF(F11="",3,F11)+21)))="x"),EOMONTH(E11,IF(F11="",3,F11)+21),"")) | BG11: =IF(E11="","",IF(OR(COUNTIF(Einstellungen!$B$5:$B$16,"x")=0,INDEX(Einstellungen!$B$5:$B$16,MONTH(EOMONTH(E11,IF(F11="",3,F11)+22)))="x"),EOMONTH(E11,IF(F11="",3,F11)+22),"")) | BH11: =IF(E11="","",IF(OR(COUNTIF(Einstellungen!$B$5:$B$16,"x")=0,INDEX(Einstellungen!$B$5:$B$16,MONTH(EOMONTH(E11,IF(F11="",3,F11)+23)))="x"),EOMONTH(E11,IF(F11="",3,F11)+23),"")) | BI11: =IF(AND(L11<>"",M11=""),L11,"") | BJ11: =IF(AND(N11<>"",O11=""),N11,"") | BK11: =IF(AND(P11<>"",Q11=""),P11,"") | BL11: =IF(AND(R11<>"",S11=""),R11,"") | BM11: =IF(AND(T11<>"",U11=""),T11,"") | BN11: =IF(AND(V11<>"",W11=""),V11,"") | BO11: =IF(AND(X11<>"",Y11=""),X11,"") | BP11: =IF(AND(Z11<>"",AA11=""),Z11,"") | BQ11: =IF(AND(AB11<>"",AC11=""),AB11,"") | BR11: =IF(AND(AD11<>"",AE11=""),AD11,"") | BS11: =IF(AF11="","",AF11+ROW()/100000)
B12: =IF(A12="","",IFERROR(INDEX('Mein Haus'!$C$45:$C$104,A12)&"","")) | C12: =IF(A12="","",IFERROR(INDEX('Mein Haus'!$B$45:$B$104,A12)&"","")) | H12: =IF(G12<>"",G12,IF(E12="","",IF(COUNT(AK12:BH12)=0,"",MIN(AK12:BH12)))) | J12: =IF(OR(H12="",I12=""),"",MAX(0,I12-H12-1)) | K12: =IF(J12="","",ROUND(N(IFERROR(INDEX('Mein Haus'!$G$45:$G$104,A12),0))*12/365*J12,2)) | L12: =IF(E12="","",E12+7) | N12: =IF(E12="","",E12) | P12: =IF(H12="","",WORKDAY(H12,-10,Einstellungen!$D$5:$D$34)) | R12: =IF(H12="","",H12-30) | T12: =IF(H12="","",WORKDAY(H12-1,1,Einstellungen!$D$5:$D$34)) | V12: =IF(T12="","",WORKDAY(T12,2,Einstellungen!$D$5:$D$34)) | X12: =IF(I12="","",I12) | Z12: =IF(T12="","",T12+30) | AB12: =IF(OR(H12="",Nebenkosten!$B$7=""),"",EDATE(Nebenkosten!$B$7,12*MAX(1,ROUNDUP(((YEAR(H12)-YEAR(Nebenkosten!$B$7))*12+MONTH(H12)-MONTH(Nebenkosten!$B$7)+1)/12,0)))) | AD12: =IF(H12="","",EDATE(H12,12)) | AF12: =IF(COUNT(BI12:BR12)=0,"",MIN(BI12:BR12)) | AG12: =IF(AF12="","",AF12-TODAY()) | AH12: =IF(AF12="","",INDEX($BI$7:$BR$7,MATCH(AF12,BI12:BR12,0))) | AI12: =IF(A12="","",IF(B12="","ID ohne Mieter in «Mein Haus»",IF(AND(IFERROR(INDEX('Mein Haus'!$E$45:$E$104,A12),"")<>"",H12<>"",IFERROR(INDEX('Mein Haus'!$E$45:$E$104,A12),"")<>H12),"Mietende in «Mein Haus» weicht ab",IF(D12="Vermieter","Amtliches Formular? Familienwohnung: beide Ehegatten.",IF(D12="Ausserterminlich","Nachmieter zumutbar? Vereinbartes Ende eintragen.",""))))) | AK12: =IF(E12="","",IF(OR(COUNTIF(Einstellungen!$B$5:$B$16,"x")=0,INDEX(Einstellungen!$B$5:$B$16,MONTH(EOMONTH(E12,IF(F12="",3,F12)+0)))="x"),EOMONTH(E12,IF(F12="",3,F12)+0),"")) | AL12: =IF(E12="","",IF(OR(COUNTIF(Einstellungen!$B$5:$B$16,"x")=0,INDEX(Einstellungen!$B$5:$B$16,MONTH(EOMONTH(E12,IF(F12="",3,F12)+1)))="x"),EOMONTH(E12,IF(F12="",3,F12)+1),"")) | AM12: =IF(E12="","",IF(OR(COUNTIF(Einstellungen!$B$5:$B$16,"x")=0,INDEX(Einstellungen!$B$5:$B$16,MONTH(EOMONTH(E12,IF(F12="",3,F12)+2)))="x"),EOMONTH(E12,IF(F12="",3,F12)+2),"")) | AN12: =IF(E12="","",IF(OR(COUNTIF(Einstellungen!$B$5:$B$16,"x")=0,INDEX(Einstellungen!$B$5:$B$16,MONTH(EOMONTH(E12,IF(F12="",3,F12)+3)))="x"),EOMONTH(E12,IF(F12="",3,F12)+3),"")) | AO12: =IF(E12="","",IF(OR(COUNTIF(Einstellungen!$B$5:$B$16,"x")=0,INDEX(Einstellungen!$B$5:$B$16,MONTH(EOMONTH(E12,IF(F12="",3,F12)+4)))="x"),EOMONTH(E12,IF(F12="",3,F12)+4),"")) | AP12: =IF(E12="","",IF(OR(COUNTIF(Einstellungen!$B$5:$B$16,"x")=0,INDEX(Einstellungen!$B$5:$B$16,MONTH(EOMONTH(E12,IF(F12="",3,F12)+5)))="x"),EOMONTH(E12,IF(F12="",3,F12)+5),"")) | AQ12: =IF(E12="","",IF(OR(COUNTIF(Einstellungen!$B$5:$B$16,"x")=0,INDEX(Einstellungen!$B$5:$B$16,MONTH(EOMONTH(E12,IF(F12="",3,F12)+6)))="x"),EOMONTH(E12,IF(F12="",3,F12)+6),"")) | AR12: =IF(E12="","",IF(OR(COUNTIF(Einstellungen!$B$5:$B$16,"x")=0,INDEX(Einstellungen!$B$5:$B$16,MONTH(EOMONTH(E12,IF(F12="",3,F12)+7)))="x"),EOMONTH(E12,IF(F12="",3,F12)+7),"")) | AS12: =IF(E12="","",IF(OR(COUNTIF(Einstellungen!$B$5:$B$16,"x")=0,INDEX(Einstellungen!$B$5:$B$16,MONTH(EOMONTH(E12,IF(F12="",3,F12)+8)))="x"),EOMONTH(E12,IF(F12="",3,F12)+8),"")) | AT12: =IF(E12="","",IF(OR(COUNTIF(Einstellungen!$B$5:$B$16,"x")=0,INDEX(Einstellungen!$B$5:$B$16,MONTH(EOMONTH(E12,IF(F12="",3,F12)+9)))="x"),EOMONTH(E12,IF(F12="",3,F12)+9),"")) | AU12: =IF(E12="","",IF(OR(COUNTIF(Einstellungen!$B$5:$B$16,"x")=0,INDEX(Einstellungen!$B$5:$B$16,MONTH(EOMONTH(E12,IF(F12="",3,F12)+10)))="x"),EOMONTH(E12,IF(F12="",3,F12)+10),"")) | AV12: =IF(E12="","",IF(OR(COUNTIF(Einstellungen!$B$5:$B$16,"x")=0,INDEX(Einstellungen!$B$5:$B$16,MONTH(EOMONTH(E12,IF(F12="",3,F12)+11)))="x"),EOMONTH(E12,IF(F12="",3,F12)+11),"")) | AW12: =IF(E12="","",IF(OR(COUNTIF(Einstellungen!$B$5:$B$16,"x")=0,INDEX(Einstellungen!$B$5:$B$16,MONTH(EOMONTH(E12,IF(F12="",3,F12)+12)))="x"),EOMONTH(E12,IF(F12="",3,F12)+12),"")) | AX12: =IF(E12="","",IF(OR(COUNTIF(Einstellungen!$B$5:$B$16,"x")=0,INDEX(Einstellungen!$B$5:$B$16,MONTH(EOMONTH(E12,IF(F12="",3,F12)+13)))="x"),EOMONTH(E12,IF(F12="",3,F12)+13),"")) | AY12: =IF(E12="","",IF(OR(COUNTIF(Einstellungen!$B$5:$B$16,"x")=0,INDEX(Einstellungen!$B$5:$B$16,MONTH(EOMONTH(E12,IF(F12="",3,F12)+14)))="x"),EOMONTH(E12,IF(F12="",3,F12)+14),"")) | AZ12: =IF(E12="","",IF(OR(COUNTIF(Einstellungen!$B$5:$B$16,"x")=0,INDEX(Einstellungen!$B$5:$B$16,MONTH(EOMONTH(E12,IF(F12="",3,F12)+15)))="x"),EOMONTH(E12,IF(F12="",3,F12)+15),"")) | BA12: =IF(E12="","",IF(OR(COUNTIF(Einstellungen!$B$5:$B$16,"x")=0,INDEX(Einstellungen!$B$5:$B$16,MONTH(EOMONTH(E12,IF(F12="",3,F12)+16)))="x"),EOMONTH(E12,IF(F12="",3,F12)+16),"")) | BB12: =IF(E12="","",IF(OR(COUNTIF(Einstellungen!$B$5:$B$16,"x")=0,INDEX(Einstellungen!$B$5:$B$16,MONTH(EOMONTH(E12,IF(F12="",3,F12)+17)))="x"),EOMONTH(E12,IF(F12="",3,F12)+17),"")) | BC12: =IF(E12="","",IF(OR(COUNTIF(Einstellungen!$B$5:$B$16,"x")=0,INDEX(Einstellungen!$B$5:$B$16,MONTH(EOMONTH(E12,IF(F12="",3,F12)+18)))="x"),EOMONTH(E12,IF(F12="",3,F12)+18),"")) | BD12: =IF(E12="","",IF(OR(COUNTIF(Einstellungen!$B$5:$B$16,"x")=0,INDEX(Einstellungen!$B$5:$B$16,MONTH(EOMONTH(E12,IF(F12="",3,F12)+19)))="x"),EOMONTH(E12,IF(F12="",3,F12)+19),"")) | BE12: =IF(E12="","",IF(OR(COUNTIF(Einstellungen!$B$5:$B$16,"x")=0,INDEX(Einstellungen!$B$5:$B$16,MONTH(EOMONTH(E12,IF(F12="",3,F12)+20)))="x"),EOMONTH(E12,IF(F12="",3,F12)+20),"")) | BF12: =IF(E12="","",IF(OR(COUNTIF(Einstellungen!$B$5:$B$16,"x")=0,INDEX(Einstellungen!$B$5:$B$16,MONTH(EOMONTH(E12,IF(F12="",3,F12)+21)))="x"),EOMONTH(E12,IF(F12="",3,F12)+21),"")) | BG12: =IF(E12="","",IF(OR(COUNTIF(Einstellungen!$B$5:$B$16,"x")=0,INDEX(Einstellungen!$B$5:$B$16,MONTH(EOMONTH(E12,IF(F12="",3,F12)+22)))="x"),EOMONTH(E12,IF(F12="",3,F12)+22),"")) | BH12: =IF(E12="","",IF(OR(COUNTIF(Einstellungen!$B$5:$B$16,"x")=0,INDEX(Einstellungen!$B$5:$B$16,MONTH(EOMONTH(E12,IF(F12="",3,F12)+23)))="x"),EOMONTH(E12,IF(F12="",3,F12)+23),"")) | BI12: =IF(AND(L12<>"",M12=""),L12,"") | BJ12: =IF(AND(N12<>"",O12=""),N12,"") | BK12: =IF(AND(P12<>"",Q12=""),P12,"") | BL12: =IF(AND(R12<>"",S12=""),R12,"") | BM12: =IF(AND(T12<>"",U12=""),T12,"") | BN12: =IF(AND(V12<>"",W12=""),V12,"") | BO12: =IF(AND(X12<>"",Y12=""),X12,"") | BP12: =IF(AND(Z12<>"",AA12=""),Z12,"") | BQ12: =IF(AND(AB12<>"",AC12=""),AB12,"") | BR12: =IF(AND(AD12<>"",AE12=""),AD12,"") | BS12: =IF(AF12="","",AF12+ROW()/100000)
B13: =IF(A13="","",IFERROR(INDEX('Mein Haus'!$C$45:$C$104,A13)&"","")) | C13: =IF(A13="","",IFERROR(INDEX('Mein Haus'!$B$45:$B$104,A13)&"","")) | H13: =IF(G13<>"",G13,IF(E13="","",IF(COUNT(AK13:BH13)=0,"",MIN(AK13:BH13)))) | J13: =IF(OR(H13="",I13=""),"",MAX(0,I13-H13-1)) | K13: =IF(J13="","",ROUND(N(IFERROR(INDEX('Mein Haus'!$G$45:$G$104,A13),0))*12/365*J13,2)) | L13: =IF(E13="","",E13+7) | N13: =IF(E13="","",E13) | P13: =IF(H13="","",WORKDAY(H13,-10,Einstellungen!$D$5:$D$34)) | R13: =IF(H13="","",H13-30) | T13: =IF(H13="","",WORKDAY(H13-1,1,Einstellungen!$D$5:$D$34)) | V13: =IF(T13="","",WORKDAY(T13,2,Einstellungen!$D$5:$D$34)) | X13: =IF(I13="","",I13) | Z13: =IF(T13="","",T13+30) | AB13: =IF(OR(H13="",Nebenkosten!$B$7=""),"",EDATE(Nebenkosten!$B$7,12*MAX(1,ROUNDUP(((YEAR(H13)-YEAR(Nebenkosten!$B$7))*12+MONTH(H13)-MONTH(Nebenkosten!$B$7)+1)/12,0)))) | AD13: =IF(H13="","",EDATE(H13,12)) | AF13: =IF(COUNT(BI13:BR13)=0,"",MIN(BI13:BR13)) | AG13: =IF(AF13="","",AF13-TODAY()) | AH13: =IF(AF13="","",INDEX($BI$7:$BR$7,MATCH(AF13,BI13:BR13,0))) | AI13: =IF(A13="","",IF(B13="","ID ohne Mieter in «Mein Haus»",IF(AND(IFERROR(INDEX('Mein Haus'!$E$45:$E$104,A13),"")<>"",H13<>"",IFERROR(INDEX('Mein Haus'!$E$45:$E$104,A13),"")<>H13),"Mietende in «Mein Haus» weicht ab",IF(D13="Vermieter","Amtliches Formular? Familienwohnung: beide Ehegatten.",IF(D13="Ausserterminlich","Nachmieter zumutbar? Vereinbartes Ende eintragen.",""))))) | AK13: =IF(E13="","",IF(OR(COUNTIF(Einstellungen!$B$5:$B$16,"x")=0,INDEX(Einstellungen!$B$5:$B$16,MONTH(EOMONTH(E13,IF(F13="",3,F13)+0)))="x"),EOMONTH(E13,IF(F13="",3,F13)+0),"")) | AL13: =IF(E13="","",IF(OR(COUNTIF(Einstellungen!$B$5:$B$16,"x")=0,INDEX(Einstellungen!$B$5:$B$16,MONTH(EOMONTH(E13,IF(F13="",3,F13)+1)))="x"),EOMONTH(E13,IF(F13="",3,F13)+1),"")) | AM13: =IF(E13="","",IF(OR(COUNTIF(Einstellungen!$B$5:$B$16,"x")=0,INDEX(Einstellungen!$B$5:$B$16,MONTH(EOMONTH(E13,IF(F13="",3,F13)+2)))="x"),EOMONTH(E13,IF(F13="",3,F13)+2),"")) | AN13: =IF(E13="","",IF(OR(COUNTIF(Einstellungen!$B$5:$B$16,"x")=0,INDEX(Einstellungen!$B$5:$B$16,MONTH(EOMONTH(E13,IF(F13="",3,F13)+3)))="x"),EOMONTH(E13,IF(F13="",3,F13)+3),"")) | AO13: =IF(E13="","",IF(OR(COUNTIF(Einstellungen!$B$5:$B$16,"x")=0,INDEX(Einstellungen!$B$5:$B$16,MONTH(EOMONTH(E13,IF(F13="",3,F13)+4)))="x"),EOMONTH(E13,IF(F13="",3,F13)+4),"")) | AP13: =IF(E13="","",IF(OR(COUNTIF(Einstellungen!$B$5:$B$16,"x")=0,INDEX(Einstellungen!$B$5:$B$16,MONTH(EOMONTH(E13,IF(F13="",3,F13)+5)))="x"),EOMONTH(E13,IF(F13="",3,F13)+5),"")) | AQ13: =IF(E13="","",IF(OR(COUNTIF(Einstellungen!$B$5:$B$16,"x")=0,INDEX(Einstellungen!$B$5:$B$16,MONTH(EOMONTH(E13,IF(F13="",3,F13)+6)))="x"),EOMONTH(E13,IF(F13="",3,F13)+6),"")) | AR13: =IF(E13="","",IF(OR(COUNTIF(Einstellungen!$B$5:$B$16,"x")=0,INDEX(Einstellungen!$B$5:$B$16,MONTH(EOMONTH(E13,IF(F13="",3,F13)+7)))="x"),EOMONTH(E13,IF(F13="",3,F13)+7),"")) | AS13: =IF(E13="","",IF(OR(COUNTIF(Einstellungen!$B$5:$B$16,"x")=0,INDEX(Einstellungen!$B$5:$B$16,MONTH(EOMONTH(E13,IF(F13="",3,F13)+8)))="x"),EOMONTH(E13,IF(F13="",3,F13)+8),"")) | AT13: =IF(E13="","",IF(OR(COUNTIF(Einstellungen!$B$5:$B$16,"x")=0,INDEX(Einstellungen!$B$5:$B$16,MONTH(EOMONTH(E13,IF(F13="",3,F13)+9)))="x"),EOMONTH(E13,IF(F13="",3,F13)+9),"")) | AU13: =IF(E13="","",IF(OR(COUNTIF(Einstellungen!$B$5:$B$16,"x")=0,INDEX(Einstellungen!$B$5:$B$16,MONTH(EOMONTH(E13,IF(F13="",3,F13)+10)))="x"),EOMONTH(E13,IF(F13="",3,F13)+10),"")) | AV13: =IF(E13="","",IF(OR(COUNTIF(Einstellungen!$B$5:$B$16,"x")=0,INDEX(Einstellungen!$B$5:$B$16,MONTH(EOMONTH(E13,IF(F13="",3,F13)+11)))="x"),EOMONTH(E13,IF(F13="",3,F13)+11),"")) | AW13: =IF(E13="","",IF(OR(COUNTIF(Einstellungen!$B$5:$B$16,"x")=0,INDEX(Einstellungen!$B$5:$B$16,MONTH(EOMONTH(E13,IF(F13="",3,F13)+12)))="x"),EOMONTH(E13,IF(F13="",3,F13)+12),"")) | AX13: =IF(E13="","",IF(OR(COUNTIF(Einstellungen!$B$5:$B$16,"x")=0,INDEX(Einstellungen!$B$5:$B$16,MONTH(EOMONTH(E13,IF(F13="",3,F13)+13)))="x"),EOMONTH(E13,IF(F13="",3,F13)+13),"")) | AY13: =IF(E13="","",IF(OR(COUNTIF(Einstellungen!$B$5:$B$16,"x")=0,INDEX(Einstellungen!$B$5:$B$16,MONTH(EOMONTH(E13,IF(F13="",3,F13)+14)))="x"),EOMONTH(E13,IF(F13="",3,F13)+14),"")) | AZ13: =IF(E13="","",IF(OR(COUNTIF(Einstellungen!$B$5:$B$16,"x")=0,INDEX(Einstellungen!$B$5:$B$16,MONTH(EOMONTH(E13,IF(F13="",3,F13)+15)))="x"),EOMONTH(E13,IF(F13="",3,F13)+15),"")) | BA13: =IF(E13="","",IF(OR(COUNTIF(Einstellungen!$B$5:$B$16,"x")=0,INDEX(Einstellungen!$B$5:$B$16,MONTH(EOMONTH(E13,IF(F13="",3,F13)+16)))="x"),EOMONTH(E13,IF(F13="",3,F13)+16),"")) | BB13: =IF(E13="","",IF(OR(COUNTIF(Einstellungen!$B$5:$B$16,"x")=0,INDEX(Einstellungen!$B$5:$B$16,MONTH(EOMONTH(E13,IF(F13="",3,F13)+17)))="x"),EOMONTH(E13,IF(F13="",3,F13)+17),"")) | BC13: =IF(E13="","",IF(OR(COUNTIF(Einstellungen!$B$5:$B$16,"x")=0,INDEX(Einstellungen!$B$5:$B$16,MONTH(EOMONTH(E13,IF(F13="",3,F13)+18)))="x"),EOMONTH(E13,IF(F13="",3,F13)+18),"")) | BD13: =IF(E13="","",IF(OR(COUNTIF(Einstellungen!$B$5:$B$16,"x")=0,INDEX(Einstellungen!$B$5:$B$16,MONTH(EOMONTH(E13,IF(F13="",3,F13)+19)))="x"),EOMONTH(E13,IF(F13="",3,F13)+19),"")) | BE13: =IF(E13="","",IF(OR(COUNTIF(Einstellungen!$B$5:$B$16,"x")=0,INDEX(Einstellungen!$B$5:$B$16,MONTH(EOMONTH(E13,IF(F13="",3,F13)+20)))="x"),EOMONTH(E13,IF(F13="",3,F13)+20),"")) | BF13: =IF(E13="","",IF(OR(COUNTIF(Einstellungen!$B$5:$B$16,"x")=0,INDEX(Einstellungen!$B$5:$B$16,MONTH(EOMONTH(E13,IF(F13="",3,F13)+21)))="x"),EOMONTH(E13,IF(F13="",3,F13)+21),"")) | BG13: =IF(E13="","",IF(OR(COUNTIF(Einstellungen!$B$5:$B$16,"x")=0,INDEX(Einstellungen!$B$5:$B$16,MONTH(EOMONTH(E13,IF(F13="",3,F13)+22)))="x"),EOMONTH(E13,IF(F13="",3,F13)+22),"")) | BH13: =IF(E13="","",IF(OR(COUNTIF(Einstellungen!$B$5:$B$16,"x")=0,INDEX(Einstellungen!$B$5:$B$16,MONTH(EOMONTH(E13,IF(F13="",3,F13)+23)))="x"),EOMONTH(E13,IF(F13="",3,F13)+23),"")) | BI13: =IF(AND(L13<>"",M13=""),L13,"") | BJ13: =IF(AND(N13<>"",O13=""),N13,"") | BK13: =IF(AND(P13<>"",Q13=""),P13,"") | BL13: =IF(AND(R13<>"",S13=""),R13,"") | BM13: =IF(AND(T13<>"",U13=""),T13,"") | BN13: =IF(AND(V13<>"",W13=""),V13,"") | BO13: =IF(AND(X13<>"",Y13=""),X13,"") | BP13: =IF(AND(Z13<>"",AA13=""),Z13,"") | BQ13: =IF(AND(AB13<>"",AC13=""),AB13,"") | BR13: =IF(AND(AD13<>"",AE13=""),AD13,"") | BS13: =IF(AF13="","",AF13+ROW()/100000)
B14: =IF(A14="","",IFERROR(INDEX('Mein Haus'!$C$45:$C$104,A14)&"","")) | C14: =IF(A14="","",IFERROR(INDEX('Mein Haus'!$B$45:$B$104,A14)&"","")) | H14: =IF(G14<>"",G14,IF(E14="","",IF(COUNT(AK14:BH14)=0,"",MIN(AK14:BH14)))) | J14: =IF(OR(H14="",I14=""),"",MAX(0,I14-H14-1)) | K14: =IF(J14="","",ROUND(N(IFERROR(INDEX('Mein Haus'!$G$45:$G$104,A14),0))*12/365*J14,2)) | L14: =IF(E14="","",E14+7) | N14: =IF(E14="","",E14) | P14: =IF(H14="","",WORKDAY(H14,-10,Einstellungen!$D$5:$D$34)) | R14: =IF(H14="","",H14-30) | T14: =IF(H14="","",WORKDAY(H14-1,1,Einstellungen!$D$5:$D$34)) | V14: =IF(T14="","",WORKDAY(T14,2,Einstellungen!$D$5:$D$34)) | X14: =IF(I14="","",I14) | Z14: =IF(T14="","",T14+30) | AB14: =IF(OR(H14="",Nebenkosten!$B$7=""),"",EDATE(Nebenkosten!$B$7,12*MAX(1,ROUNDUP(((YEAR(H14)-YEAR(Nebenkosten!$B$7))*12+MONTH(H14)-MONTH(Nebenkosten!$B$7)+1)/12,0)))) | AD14: =IF(H14="","",EDATE(H14,12)) | AF14: =IF(COUNT(BI14:BR14)=0,"",MIN(BI14:BR14)) | AG14: =IF(AF14="","",AF14-TODAY()) | AH14: =IF(AF14="","",INDEX($BI$7:$BR$7,MATCH(AF14,BI14:BR14,0))) | AI14: =IF(A14="","",IF(B14="","ID ohne Mieter in «Mein Haus»",IF(AND(IFERROR(INDEX('Mein Haus'!$E$45:$E$104,A14),"")<>"",H14<>"",IFERROR(INDEX('Mein Haus'!$E$45:$E$104,A14),"")<>H14),"Mietende in «Mein Haus» weicht ab",IF(D14="Vermieter","Amtliches Formular? Familienwohnung: beide Ehegatten.",IF(D14="Ausserterminlich","Nachmieter zumutbar? Vereinbartes Ende eintragen.",""))))) | AK14: =IF(E14="","",IF(OR(COUNTIF(Einstellungen!$B$5:$B$16,"x")=0,INDEX(Einstellungen!$B$5:$B$16,MONTH(EOMONTH(E14,IF(F14="",3,F14)+0)))="x"),EOMONTH(E14,IF(F14="",3,F14)+0),"")) | AL14: =IF(E14="","",IF(OR(COUNTIF(Einstellungen!$B$5:$B$16,"x")=0,INDEX(Einstellungen!$B$5:$B$16,MONTH(EOMONTH(E14,IF(F14="",3,F14)+1)))="x"),EOMONTH(E14,IF(F14="",3,F14)+1),"")) | AM14: =IF(E14="","",IF(OR(COUNTIF(Einstellungen!$B$5:$B$16,"x")=0,INDEX(Einstellungen!$B$5:$B$16,MONTH(EOMONTH(E14,IF(F14="",3,F14)+2)))="x"),EOMONTH(E14,IF(F14="",3,F14)+2),"")) | AN14: =IF(E14="","",IF(OR(COUNTIF(Einstellungen!$B$5:$B$16,"x")=0,INDEX(Einstellungen!$B$5:$B$16,MONTH(EOMONTH(E14,IF(F14="",3,F14)+3)))="x"),EOMONTH(E14,IF(F14="",3,F14)+3),"")) | AO14: =IF(E14="","",IF(OR(COUNTIF(Einstellungen!$B$5:$B$16,"x")=0,INDEX(Einstellungen!$B$5:$B$16,MONTH(EOMONTH(E14,IF(F14="",3,F14)+4)))="x"),EOMONTH(E14,IF(F14="",3,F14)+4),"")) | AP14: =IF(E14="","",IF(OR(COUNTIF(Einstellungen!$B$5:$B$16,"x")=0,INDEX(Einstellungen!$B$5:$B$16,MONTH(EOMONTH(E14,IF(F14="",3,F14)+5)))="x"),EOMONTH(E14,IF(F14="",3,F14)+5),"")) | AQ14: =IF(E14="","",IF(OR(COUNTIF(Einstellungen!$B$5:$B$16,"x")=0,INDEX(Einstellungen!$B$5:$B$16,MONTH(EOMONTH(E14,IF(F14="",3,F14)+6)))="x"),EOMONTH(E14,IF(F14="",3,F14)+6),"")) | AR14: =IF(E14="","",IF(OR(COUNTIF(Einstellungen!$B$5:$B$16,"x")=0,INDEX(Einstellungen!$B$5:$B$16,MONTH(EOMONTH(E14,IF(F14="",3,F14)+7)))="x"),EOMONTH(E14,IF(F14="",3,F14)+7),"")) | AS14: =IF(E14="","",IF(OR(COUNTIF(Einstellungen!$B$5:$B$16,"x")=0,INDEX(Einstellungen!$B$5:$B$16,MONTH(EOMONTH(E14,IF(F14="",3,F14)+8)))="x"),EOMONTH(E14,IF(F14="",3,F14)+8),"")) | AT14: =IF(E14="","",IF(OR(COUNTIF(Einstellungen!$B$5:$B$16,"x")=0,INDEX(Einstellungen!$B$5:$B$16,MONTH(EOMONTH(E14,IF(F14="",3,F14)+9)))="x"),EOMONTH(E14,IF(F14="",3,F14)+9),"")) | AU14: =IF(E14="","",IF(OR(COUNTIF(Einstellungen!$B$5:$B$16,"x")=0,INDEX(Einstellungen!$B$5:$B$16,MONTH(EOMONTH(E14,IF(F14="",3,F14)+10)))="x"),EOMONTH(E14,IF(F14="",3,F14)+10),"")) | AV14: =IF(E14="","",IF(OR(COUNTIF(Einstellungen!$B$5:$B$16,"x")=0,INDEX(Einstellungen!$B$5:$B$16,MONTH(EOMONTH(E14,IF(F14="",3,F14)+11)))="x"),EOMONTH(E14,IF(F14="",3,F14)+11),"")) | AW14: =IF(E14="","",IF(OR(COUNTIF(Einstellungen!$B$5:$B$16,"x")=0,INDEX(Einstellungen!$B$5:$B$16,MONTH(EOMONTH(E14,IF(F14="",3,F14)+12)))="x"),EOMONTH(E14,IF(F14="",3,F14)+12),"")) | AX14: =IF(E14="","",IF(OR(COUNTIF(Einstellungen!$B$5:$B$16,"x")=0,INDEX(Einstellungen!$B$5:$B$16,MONTH(EOMONTH(E14,IF(F14="",3,F14)+13)))="x"),EOMONTH(E14,IF(F14="",3,F14)+13),"")) | AY14: =IF(E14="","",IF(OR(COUNTIF(Einstellungen!$B$5:$B$16,"x")=0,INDEX(Einstellungen!$B$5:$B$16,MONTH(EOMONTH(E14,IF(F14="",3,F14)+14)))="x"),EOMONTH(E14,IF(F14="",3,F14)+14),"")) | AZ14: =IF(E14="","",IF(OR(COUNTIF(Einstellungen!$B$5:$B$16,"x")=0,INDEX(Einstellungen!$B$5:$B$16,MONTH(EOMONTH(E14,IF(F14="",3,F14)+15)))="x"),EOMONTH(E14,IF(F14="",3,F14)+15),"")) | BA14: =IF(E14="","",IF(OR(COUNTIF(Einstellungen!$B$5:$B$16,"x")=0,INDEX(Einstellungen!$B$5:$B$16,MONTH(EOMONTH(E14,IF(F14="",3,F14)+16)))="x"),EOMONTH(E14,IF(F14="",3,F14)+16),"")) | BB14: =IF(E14="","",IF(OR(COUNTIF(Einstellungen!$B$5:$B$16,"x")=0,INDEX(Einstellungen!$B$5:$B$16,MONTH(EOMONTH(E14,IF(F14="",3,F14)+17)))="x"),EOMONTH(E14,IF(F14="",3,F14)+17),"")) | BC14: =IF(E14="","",IF(OR(COUNTIF(Einstellungen!$B$5:$B$16,"x")=0,INDEX(Einstellungen!$B$5:$B$16,MONTH(EOMONTH(E14,IF(F14="",3,F14)+18)))="x"),EOMONTH(E14,IF(F14="",3,F14)+18),"")) | BD14: =IF(E14="","",IF(OR(COUNTIF(Einstellungen!$B$5:$B$16,"x")=0,INDEX(Einstellungen!$B$5:$B$16,MONTH(EOMONTH(E14,IF(F14="",3,F14)+19)))="x"),EOMONTH(E14,IF(F14="",3,F14)+19),"")) | BE14: =IF(E14="","",IF(OR(COUNTIF(Einstellungen!$B$5:$B$16,"x")=0,INDEX(Einstellungen!$B$5:$B$16,MONTH(EOMONTH(E14,IF(F14="",3,F14)+20)))="x"),EOMONTH(E14,IF(F14="",3,F14)+20),"")) | BF14: =IF(E14="","",IF(OR(COUNTIF(Einstellungen!$B$5:$B$16,"x")=0,INDEX(Einstellungen!$B$5:$B$16,MONTH(EOMONTH(E14,IF(F14="",3,F14)+21)))="x"),EOMONTH(E14,IF(F14="",3,F14)+21),"")) | BG14: =IF(E14="","",IF(OR(COUNTIF(Einstellungen!$B$5:$B$16,"x")=0,INDEX(Einstellungen!$B$5:$B$16,MONTH(EOMONTH(E14,IF(F14="",3,F14)+22)))="x"),EOMONTH(E14,IF(F14="",3,F14)+22),"")) | BH14: =IF(E14="","",IF(OR(COUNTIF(Einstellungen!$B$5:$B$16,"x")=0,INDEX(Einstellungen!$B$5:$B$16,MONTH(EOMONTH(E14,IF(F14="",3,F14)+23)))="x"),EOMONTH(E14,IF(F14="",3,F14)+23),"")) | BI14: =IF(AND(L14<>"",M14=""),L14,"") | BJ14: =IF(AND(N14<>"",O14=""),N14,"") | BK14: =IF(AND(P14<>"",Q14=""),P14,"") | BL14: =IF(AND(R14<>"",S14=""),R14,"") | BM14: =IF(AND(T14<>"",U14=""),T14,"") | BN14: =IF(AND(V14<>"",W14=""),V14,"") | BO14: =IF(AND(X14<>"",Y14=""),X14,"") | BP14: =IF(AND(Z14<>"",AA14=""),Z14,"") | BQ14: =IF(AND(AB14<>"",AC14=""),AB14,"") | BR14: =IF(AND(AD14<>"",AE14=""),AD14,"") | BS14: =IF(AF14="","",AF14+ROW()/100000)
B15: =IF(A15="","",IFERROR(INDEX('Mein Haus'!$C$45:$C$104,A15)&"","")) | C15: =IF(A15="","",IFERROR(INDEX('Mein Haus'!$B$45:$B$104,A15)&"","")) | H15: =IF(G15<>"",G15,IF(E15="","",IF(COUNT(AK15:BH15)=0,"",MIN(AK15:BH15)))) | J15: =IF(OR(H15="",I15=""),"",MAX(0,I15-H15-1)) | K15: =IF(J15="","",ROUND(N(IFERROR(INDEX('Mein Haus'!$G$45:$G$104,A15),0))*12/365*J15,2)) | L15: =IF(E15="","",E15+7) | N15: =IF(E15="","",E15) | P15: =IF(H15="","",WORKDAY(H15,-10,Einstellungen!$D$5:$D$34)) | R15: =IF(H15="","",H15-30) | T15: =IF(H15="","",WORKDAY(H15-1,1,Einstellungen!$D$5:$D$34)) | V15: =IF(T15="","",WORKDAY(T15,2,Einstellungen!$D$5:$D$34)) | X15: =IF(I15="","",I15) | Z15: =IF(T15="","",T15+30) | AB15: =IF(OR(H15="",Nebenkosten!$B$7=""),"",EDATE(Nebenkosten!$B$7,12*MAX(1,ROUNDUP(((YEAR(H15)-YEAR(Nebenkosten!$B$7))*12+MONTH(H15)-MONTH(Nebenkosten!$B$7)+1)/12,0)))) | AD15: =IF(H15="","",EDATE(H15,12)) | AF15: =IF(COUNT(BI15:BR15)=0,"",MIN(BI15:BR15)) | AG15: =IF(AF15="","",AF15-TODAY()) | AH15: =IF(AF15="","",INDEX($BI$7:$BR$7,MATCH(AF15,BI15:BR15,0))) | AI15: =IF(A15="","",IF(B15="","ID ohne Mieter in «Mein Haus»",IF(AND(IFERROR(INDEX('Mein Haus'!$E$45:$E$104,A15),"")<>"",H15<>"",IFERROR(INDEX('Mein Haus'!$E$45:$E$104,A15),"")<>H15),"Mietende in «Mein Haus» weicht ab",IF(D15="Vermieter","Amtliches Formular? Familienwohnung: beide Ehegatten.",IF(D15="Ausserterminlich","Nachmieter zumutbar? Vereinbartes Ende eintragen.",""))))) | AK15: =IF(E15="","",IF(OR(COUNTIF(Einstellungen!$B$5:$B$16,"x")=0,INDEX(Einstellungen!$B$5:$B$16,MONTH(EOMONTH(E15,IF(F15="",3,F15)+0)))="x"),EOMONTH(E15,IF(F15="",3,F15)+0),"")) | AL15: =IF(E15="","",IF(OR(COUNTIF(Einstellungen!$B$5:$B$16,"x")=0,INDEX(Einstellungen!$B$5:$B$16,MONTH(EOMONTH(E15,IF(F15="",3,F15)+1)))="x"),EOMONTH(E15,IF(F15="",3,F15)+1),"")) | AM15: =IF(E15="","",IF(OR(COUNTIF(Einstellungen!$B$5:$B$16,"x")=0,INDEX(Einstellungen!$B$5:$B$16,MONTH(EOMONTH(E15,IF(F15="",3,F15)+2)))="x"),EOMONTH(E15,IF(F15="",3,F15)+2),"")) | AN15: =IF(E15="","",IF(OR(COUNTIF(Einstellungen!$B$5:$B$16,"x")=0,INDEX(Einstellungen!$B$5:$B$16,MONTH(EOMONTH(E15,IF(F15="",3,F15)+3)))="x"),EOMONTH(E15,IF(F15="",3,F15)+3),"")) | AO15: =IF(E15="","",IF(OR(COUNTIF(Einstellungen!$B$5:$B$16,"x")=0,INDEX(Einstellungen!$B$5:$B$16,MONTH(EOMONTH(E15,IF(F15="",3,F15)+4)))="x"),EOMONTH(E15,IF(F15="",3,F15)+4),"")) | AP15: =IF(E15="","",IF(OR(COUNTIF(Einstellungen!$B$5:$B$16,"x")=0,INDEX(Einstellungen!$B$5:$B$16,MONTH(EOMONTH(E15,IF(F15="",3,F15)+5)))="x"),EOMONTH(E15,IF(F15="",3,F15)+5),"")) | AQ15: =IF(E15="","",IF(OR(COUNTIF(Einstellungen!$B$5:$B$16,"x")=0,INDEX(Einstellungen!$B$5:$B$16,MONTH(EOMONTH(E15,IF(F15="",3,F15)+6)))="x"),EOMONTH(E15,IF(F15="",3,F15)+6),"")) | AR15: =IF(E15="","",IF(OR(COUNTIF(Einstellungen!$B$5:$B$16,"x")=0,INDEX(Einstellungen!$B$5:$B$16,MONTH(EOMONTH(E15,IF(F15="",3,F15)+7)))="x"),EOMONTH(E15,IF(F15="",3,F15)+7),"")) | AS15: =IF(E15="","",IF(OR(COUNTIF(Einstellungen!$B$5:$B$16,"x")=0,INDEX(Einstellungen!$B$5:$B$16,MONTH(EOMONTH(E15,IF(F15="",3,F15)+8)))="x"),EOMONTH(E15,IF(F15="",3,F15)+8),"")) | AT15: =IF(E15="","",IF(OR(COUNTIF(Einstellungen!$B$5:$B$16,"x")=0,INDEX(Einstellungen!$B$5:$B$16,MONTH(EOMONTH(E15,IF(F15="",3,F15)+9)))="x"),EOMONTH(E15,IF(F15="",3,F15)+9),"")) | AU15: =IF(E15="","",IF(OR(COUNTIF(Einstellungen!$B$5:$B$16,"x")=0,INDEX(Einstellungen!$B$5:$B$16,MONTH(EOMONTH(E15,IF(F15="",3,F15)+10)))="x"),EOMONTH(E15,IF(F15="",3,F15)+10),"")) | AV15: =IF(E15="","",IF(OR(COUNTIF(Einstellungen!$B$5:$B$16,"x")=0,INDEX(Einstellungen!$B$5:$B$16,MONTH(EOMONTH(E15,IF(F15="",3,F15)+11)))="x"),EOMONTH(E15,IF(F15="",3,F15)+11),"")) | AW15: =IF(E15="","",IF(OR(COUNTIF(Einstellungen!$B$5:$B$16,"x")=0,INDEX(Einstellungen!$B$5:$B$16,MONTH(EOMONTH(E15,IF(F15="",3,F15)+12)))="x"),EOMONTH(E15,IF(F15="",3,F15)+12),"")) | AX15: =IF(E15="","",IF(OR(COUNTIF(Einstellungen!$B$5:$B$16,"x")=0,INDEX(Einstellungen!$B$5:$B$16,MONTH(EOMONTH(E15,IF(F15="",3,F15)+13)))="x"),EOMONTH(E15,IF(F15="",3,F15)+13),"")) | AY15: =IF(E15="","",IF(OR(COUNTIF(Einstellungen!$B$5:$B$16,"x")=0,INDEX(Einstellungen!$B$5:$B$16,MONTH(EOMONTH(E15,IF(F15="",3,F15)+14)))="x"),EOMONTH(E15,IF(F15="",3,F15)+14),"")) | AZ15: =IF(E15="","",IF(OR(COUNTIF(Einstellungen!$B$5:$B$16,"x")=0,INDEX(Einstellungen!$B$5:$B$16,MONTH(EOMONTH(E15,IF(F15="",3,F15)+15)))="x"),EOMONTH(E15,IF(F15="",3,F15)+15),"")) | BA15: =IF(E15="","",IF(OR(COUNTIF(Einstellungen!$B$5:$B$16,"x")=0,INDEX(Einstellungen!$B$5:$B$16,MONTH(EOMONTH(E15,IF(F15="",3,F15)+16)))="x"),EOMONTH(E15,IF(F15="",3,F15)+16),"")) | BB15: =IF(E15="","",IF(OR(COUNTIF(Einstellungen!$B$5:$B$16,"x")=0,INDEX(Einstellungen!$B$5:$B$16,MONTH(EOMONTH(E15,IF(F15="",3,F15)+17)))="x"),EOMONTH(E15,IF(F15="",3,F15)+17),"")) | BC15: =IF(E15="","",IF(OR(COUNTIF(Einstellungen!$B$5:$B$16,"x")=0,INDEX(Einstellungen!$B$5:$B$16,MONTH(EOMONTH(E15,IF(F15="",3,F15)+18)))="x"),EOMONTH(E15,IF(F15="",3,F15)+18),"")) | BD15: =IF(E15="","",IF(OR(COUNTIF(Einstellungen!$B$5:$B$16,"x")=0,INDEX(Einstellungen!$B$5:$B$16,MONTH(EOMONTH(E15,IF(F15="",3,F15)+19)))="x"),EOMONTH(E15,IF(F15="",3,F15)+19),"")) | BE15: =IF(E15="","",IF(OR(COUNTIF(Einstellungen!$B$5:$B$16,"x")=0,INDEX(Einstellungen!$B$5:$B$16,MONTH(EOMONTH(E15,IF(F15="",3,F15)+20)))="x"),EOMONTH(E15,IF(F15="",3,F15)+20),"")) | BF15: =IF(E15="","",IF(OR(COUNTIF(Einstellungen!$B$5:$B$16,"x")=0,INDEX(Einstellungen!$B$5:$B$16,MONTH(EOMONTH(E15,IF(F15="",3,F15)+21)))="x"),EOMONTH(E15,IF(F15="",3,F15)+21),"")) | BG15: =IF(E15="","",IF(OR(COUNTIF(Einstellungen!$B$5:$B$16,"x")=0,INDEX(Einstellungen!$B$5:$B$16,MONTH(EOMONTH(E15,IF(F15="",3,F15)+22)))="x"),EOMONTH(E15,IF(F15="",3,F15)+22),"")) | BH15: =IF(E15="","",IF(OR(COUNTIF(Einstellungen!$B$5:$B$16,"x")=0,INDEX(Einstellungen!$B$5:$B$16,MONTH(EOMONTH(E15,IF(F15="",3,F15)+23)))="x"),EOMONTH(E15,IF(F15="",3,F15)+23),"")) | BI15: =IF(AND(L15<>"",M15=""),L15,"") | BJ15: =IF(AND(N15<>"",O15=""),N15,"") | BK15: =IF(AND(P15<>"",Q15=""),P15,"") | BL15: =IF(AND(R15<>"",S15=""),R15,"") | BM15: =IF(AND(T15<>"",U15=""),T15,"") | BN15: =IF(AND(V15<>"",W15=""),V15,"") | BO15: =IF(AND(X15<>"",Y15=""),X15,"") | BP15: =IF(AND(Z15<>"",AA15=""),Z15,"") | BQ15: =IF(AND(AB15<>"",AC15=""),AB15,"") | BR15: =IF(AND(AD15<>"",AE15=""),AD15,"") | BS15: =IF(AF15="","",AF15+ROW()/100000)
B16: =IF(A16="","",IFERROR(INDEX('Mein Haus'!$C$45:$C$104,A16)&"","")) | C16: =IF(A16="","",IFERROR(INDEX('Mein Haus'!$B$45:$B$104,A16)&"","")) | H16: =IF(G16<>"",G16,IF(E16="","",IF(COUNT(AK16:BH16)=0,"",MIN(AK16:BH16)))) | J16: =IF(OR(H16="",I16=""),"",MAX(0,I16-H16-1)) | K16: =IF(J16="","",ROUND(N(IFERROR(INDEX('Mein Haus'!$G$45:$G$104,A16),0))*12/365*J16,2)) | L16: =IF(E16="","",E16+7) | N16: =IF(E16="","",E16) | P16: =IF(H16="","",WORKDAY(H16,-10,Einstellungen!$D$5:$D$34)) | R16: =IF(H16="","",H16-30) | T16: =IF(H16="","",WORKDAY(H16-1,1,Einstellungen!$D$5:$D$34)) | V16: =IF(T16="","",WORKDAY(T16,2,Einstellungen!$D$5:$D$34)) | X16: =IF(I16="","",I16) | Z16: =IF(T16="","",T16+30) | AB16: =IF(OR(H16="",Nebenkosten!$B$7=""),"",EDATE(Nebenkosten!$B$7,12*MAX(1,ROUNDUP(((YEAR(H16)-YEAR(Nebenkosten!$B$7))*12+MONTH(H16)-MONTH(Nebenkosten!$B$7)+1)/12,0)))) | AD16: =IF(H16="","",EDATE(H16,12)) | AF16: =IF(COUNT(BI16:BR16)=0,"",MIN(BI16:BR16)) | AG16: =IF(AF16="","",AF16-TODAY()) | AH16: =IF(AF16="","",INDEX($BI$7:$BR$7,MATCH(AF16,BI16:BR16,0))) | AI16: =IF(A16="","",IF(B16="","ID ohne Mieter in «Mein Haus»",IF(AND(IFERROR(INDEX('Mein Haus'!$E$45:$E$104,A16),"")<>"",H16<>"",IFERROR(INDEX('Mein Haus'!$E$45:$E$104,A16),"")<>H16),"Mietende in «Mein Haus» weicht ab",IF(D16="Vermieter","Amtliches Formular? Familienwohnung: beide Ehegatten.",IF(D16="Ausserterminlich","Nachmieter zumutbar? Vereinbartes Ende eintragen.",""))))) | AK16: =IF(E16="","",IF(OR(COUNTIF(Einstellungen!$B$5:$B$16,"x")=0,INDEX(Einstellungen!$B$5:$B$16,MONTH(EOMONTH(E16,IF(F16="",3,F16)+0)))="x"),EOMONTH(E16,IF(F16="",3,F16)+0),"")) | AL16: =IF(E16="","",IF(OR(COUNTIF(Einstellungen!$B$5:$B$16,"x")=0,INDEX(Einstellungen!$B$5:$B$16,MONTH(EOMONTH(E16,IF(F16="",3,F16)+1)))="x"),EOMONTH(E16,IF(F16="",3,F16)+1),"")) | AM16: =IF(E16="","",IF(OR(COUNTIF(Einstellungen!$B$5:$B$16,"x")=0,INDEX(Einstellungen!$B$5:$B$16,MONTH(EOMONTH(E16,IF(F16="",3,F16)+2)))="x"),EOMONTH(E16,IF(F16="",3,F16)+2),"")) | AN16: =IF(E16="","",IF(OR(COUNTIF(Einstellungen!$B$5:$B$16,"x")=0,INDEX(Einstellungen!$B$5:$B$16,MONTH(EOMONTH(E16,IF(F16="",3,F16)+3)))="x"),EOMONTH(E16,IF(F16="",3,F16)+3),"")) | AO16: =IF(E16="","",IF(OR(COUNTIF(Einstellungen!$B$5:$B$16,"x")=0,INDEX(Einstellungen!$B$5:$B$16,MONTH(EOMONTH(E16,IF(F16="",3,F16)+4)))="x"),EOMONTH(E16,IF(F16="",3,F16)+4),"")) | AP16: =IF(E16="","",IF(OR(COUNTIF(Einstellungen!$B$5:$B$16,"x")=0,INDEX(Einstellungen!$B$5:$B$16,MONTH(EOMONTH(E16,IF(F16="",3,F16)+5)))="x"),EOMONTH(E16,IF(F16="",3,F16)+5),"")) | AQ16: =IF(E16="","",IF(OR(COUNTIF(Einstellungen!$B$5:$B$16,"x")=0,INDEX(Einstellungen!$B$5:$B$16,MONTH(EOMONTH(E16,IF(F16="",3,F16)+6)))="x"),EOMONTH(E16,IF(F16="",3,F16)+6),"")) | AR16: =IF(E16="","",IF(OR(COUNTIF(Einstellungen!$B$5:$B$16,"x")=0,INDEX(Einstellungen!$B$5:$B$16,MONTH(EOMONTH(E16,IF(F16="",3,F16)+7)))="x"),EOMONTH(E16,IF(F16="",3,F16)+7),"")) | AS16: =IF(E16="","",IF(OR(COUNTIF(Einstellungen!$B$5:$B$16,"x")=0,INDEX(Einstellungen!$B$5:$B$16,MONTH(EOMONTH(E16,IF(F16="",3,F16)+8)))="x"),EOMONTH(E16,IF(F16="",3,F16)+8),"")) | AT16: =IF(E16="","",IF(OR(COUNTIF(Einstellungen!$B$5:$B$16,"x")=0,INDEX(Einstellungen!$B$5:$B$16,MONTH(EOMONTH(E16,IF(F16="",3,F16)+9)))="x"),EOMONTH(E16,IF(F16="",3,F16)+9),"")) | AU16: =IF(E16="","",IF(OR(COUNTIF(Einstellungen!$B$5:$B$16,"x")=0,INDEX(Einstellungen!$B$5:$B$16,MONTH(EOMONTH(E16,IF(F16="",3,F16)+10)))="x"),EOMONTH(E16,IF(F16="",3,F16)+10),"")) | AV16: =IF(E16="","",IF(OR(COUNTIF(Einstellungen!$B$5:$B$16,"x")=0,INDEX(Einstellungen!$B$5:$B$16,MONTH(EOMONTH(E16,IF(F16="",3,F16)+11)))="x"),EOMONTH(E16,IF(F16="",3,F16)+11),"")) | AW16: =IF(E16="","",IF(OR(COUNTIF(Einstellungen!$B$5:$B$16,"x")=0,INDEX(Einstellungen!$B$5:$B$16,MONTH(EOMONTH(E16,IF(F16="",3,F16)+12)))="x"),EOMONTH(E16,IF(F16="",3,F16)+12),"")) | AX16: =IF(E16="","",IF(OR(COUNTIF(Einstellungen!$B$5:$B$16,"x")=0,INDEX(Einstellungen!$B$5:$B$16,MONTH(EOMONTH(E16,IF(F16="",3,F16)+13)))="x"),EOMONTH(E16,IF(F16="",3,F16)+13),"")) | AY16: =IF(E16="","",IF(OR(COUNTIF(Einstellungen!$B$5:$B$16,"x")=0,INDEX(Einstellungen!$B$5:$B$16,MONTH(EOMONTH(E16,IF(F16="",3,F16)+14)))="x"),EOMONTH(E16,IF(F16="",3,F16)+14),"")) | AZ16: =IF(E16="","",IF(OR(COUNTIF(Einstellungen!$B$5:$B$16,"x")=0,INDEX(Einstellungen!$B$5:$B$16,MONTH(EOMONTH(E16,IF(F16="",3,F16)+15)))="x"),EOMONTH(E16,IF(F16="",3,F16)+15),"")) | BA16: =IF(E16="","",IF(OR(COUNTIF(Einstellungen!$B$5:$B$16,"x")=0,INDEX(Einstellungen!$B$5:$B$16,MONTH(EOMONTH(E16,IF(F16="",3,F16)+16)))="x"),EOMONTH(E16,IF(F16="",3,F16)+16),"")) | BB16: =IF(E16="","",IF(OR(COUNTIF(Einstellungen!$B$5:$B$16,"x")=0,INDEX(Einstellungen!$B$5:$B$16,MONTH(EOMONTH(E16,IF(F16="",3,F16)+17)))="x"),EOMONTH(E16,IF(F16="",3,F16)+17),"")) | BC16: =IF(E16="","",IF(OR(COUNTIF(Einstellungen!$B$5:$B$16,"x")=0,INDEX(Einstellungen!$B$5:$B$16,MONTH(EOMONTH(E16,IF(F16="",3,F16)+18)))="x"),EOMONTH(E16,IF(F16="",3,F16)+18),"")) | BD16: =IF(E16="","",IF(OR(COUNTIF(Einstellungen!$B$5:$B$16,"x")=0,INDEX(Einstellungen!$B$5:$B$16,MONTH(EOMONTH(E16,IF(F16="",3,F16)+19)))="x"),EOMONTH(E16,IF(F16="",3,F16)+19),"")) | BE16: =IF(E16="","",IF(OR(COUNTIF(Einstellungen!$B$5:$B$16,"x")=0,INDEX(Einstellungen!$B$5:$B$16,MONTH(EOMONTH(E16,IF(F16="",3,F16)+20)))="x"),EOMONTH(E16,IF(F16="",3,F16)+20),"")) | BF16: =IF(E16="","",IF(OR(COUNTIF(Einstellungen!$B$5:$B$16,"x")=0,INDEX(Einstellungen!$B$5:$B$16,MONTH(EOMONTH(E16,IF(F16="",3,F16)+21)))="x"),EOMONTH(E16,IF(F16="",3,F16)+21),"")) | BG16: =IF(E16="","",IF(OR(COUNTIF(Einstellungen!$B$5:$B$16,"x")=0,INDEX(Einstellungen!$B$5:$B$16,MONTH(EOMONTH(E16,IF(F16="",3,F16)+22)))="x"),EOMONTH(E16,IF(F16="",3,F16)+22),"")) | BH16: =IF(E16="","",IF(OR(COUNTIF(Einstellungen!$B$5:$B$16,"x")=0,INDEX(Einstellungen!$B$5:$B$16,MONTH(EOMONTH(E16,IF(F16="",3,F16)+23)))="x"),EOMONTH(E16,IF(F16="",3,F16)+23),"")) | BI16: =IF(AND(L16<>"",M16=""),L16,"") | BJ16: =IF(AND(N16<>"",O16=""),N16,"") | BK16: =IF(AND(P16<>"",Q16=""),P16,"") | BL16: =IF(AND(R16<>"",S16=""),R16,"") | BM16: =IF(AND(T16<>"",U16=""),T16,"") | BN16: =IF(AND(V16<>"",W16=""),V16,"") | BO16: =IF(AND(X16<>"",Y16=""),X16,"") | BP16: =IF(AND(Z16<>"",AA16=""),Z16,"") | BQ16: =IF(AND(AB16<>"",AC16=""),AB16,"") | BR16: =IF(AND(AD16<>"",AE16=""),AD16,"") | BS16: =IF(AF16="","",AF16+ROW()/100000)
B17: =IF(A17="","",IFERROR(INDEX('Mein Haus'!$C$45:$C$104,A17)&"","")) | C17: =IF(A17="","",IFERROR(INDEX('Mein Haus'!$B$45:$B$104,A17)&"","")) | H17: =IF(G17<>"",G17,IF(E17="","",IF(COUNT(AK17:BH17)=0,"",MIN(AK17:BH17)))) | J17: =IF(OR(H17="",I17=""),"",MAX(0,I17-H17-1)) | K17: =IF(J17="","",ROUND(N(IFERROR(INDEX('Mein Haus'!$G$45:$G$104,A17),0))*12/365*J17,2)) | L17: =IF(E17="","",E17+7) | N17: =IF(E17="","",E17) | P17: =IF(H17="","",WORKDAY(H17,-10,Einstellungen!$D$5:$D$34)) | R17: =IF(H17="","",H17-30) | T17: =IF(H17="","",WORKDAY(H17-1,1,Einstellungen!$D$5:$D$34)) | V17: =IF(T17="","",WORKDAY(T17,2,Einstellungen!$D$5:$D$34)) | X17: =IF(I17="","",I17) | Z17: =IF(T17="","",T17+30) | AB17: =IF(OR(H17="",Nebenkosten!$B$7=""),"",EDATE(Nebenkosten!$B$7,12*MAX(1,ROUNDUP(((YEAR(H17)-YEAR(Nebenkosten!$B$7))*12+MONTH(H17)-MONTH(Nebenkosten!$B$7)+1)/12,0)))) | AD17: =IF(H17="","",EDATE(H17,12)) | AF17: =IF(COUNT(BI17:BR17)=0,"",MIN(BI17:BR17)) | AG17: =IF(AF17="","",AF17-TODAY()) | AH17: =IF(AF17="","",INDEX($BI$7:$BR$7,MATCH(AF17,BI17:BR17,0))) | AI17: =IF(A17="","",IF(B17="","ID ohne Mieter in «Mein Haus»",IF(AND(IFERROR(INDEX('Mein Haus'!$E$45:$E$104,A17),"")<>"",H17<>"",IFERROR(INDEX('Mein Haus'!$E$45:$E$104,A17),"")<>H17),"Mietende in «Mein Haus» weicht ab",IF(D17="Vermieter","Amtliches Formular? Familienwohnung: beide Ehegatten.",IF(D17="Ausserterminlich","Nachmieter zumutbar? Vereinbartes Ende eintragen.",""))))) | AK17: =IF(E17="","",IF(OR(COUNTIF(Einstellungen!$B$5:$B$16,"x")=0,INDEX(Einstellungen!$B$5:$B$16,MONTH(EOMONTH(E17,IF(F17="",3,F17)+0)))="x"),EOMONTH(E17,IF(F17="",3,F17)+0),"")) | AL17: =IF(E17="","",IF(OR(COUNTIF(Einstellungen!$B$5:$B$16,"x")=0,INDEX(Einstellungen!$B$5:$B$16,MONTH(EOMONTH(E17,IF(F17="",3,F17)+1)))="x"),EOMONTH(E17,IF(F17="",3,F17)+1),"")) | AM17: =IF(E17="","",IF(OR(COUNTIF(Einstellungen!$B$5:$B$16,"x")=0,INDEX(Einstellungen!$B$5:$B$16,MONTH(EOMONTH(E17,IF(F17="",3,F17)+2)))="x"),EOMONTH(E17,IF(F17="",3,F17)+2),"")) | AN17: =IF(E17="","",IF(OR(COUNTIF(Einstellungen!$B$5:$B$16,"x")=0,INDEX(Einstellungen!$B$5:$B$16,MONTH(EOMONTH(E17,IF(F17="",3,F17)+3)))="x"),EOMONTH(E17,IF(F17="",3,F17)+3),"")) | AO17: =IF(E17="","",IF(OR(COUNTIF(Einstellungen!$B$5:$B$16,"x")=0,INDEX(Einstellungen!$B$5:$B$16,MONTH(EOMONTH(E17,IF(F17="",3,F17)+4)))="x"),EOMONTH(E17,IF(F17="",3,F17)+4),"")) | AP17: =IF(E17="","",IF(OR(COUNTIF(Einstellungen!$B$5:$B$16,"x")=0,INDEX(Einstellungen!$B$5:$B$16,MONTH(EOMONTH(E17,IF(F17="",3,F17)+5)))="x"),EOMONTH(E17,IF(F17="",3,F17)+5),"")) | AQ17: =IF(E17="","",IF(OR(COUNTIF(Einstellungen!$B$5:$B$16,"x")=0,INDEX(Einstellungen!$B$5:$B$16,MONTH(EOMONTH(E17,IF(F17="",3,F17)+6)))="x"),EOMONTH(E17,IF(F17="",3,F17)+6),"")) | AR17: =IF(E17="","",IF(OR(COUNTIF(Einstellungen!$B$5:$B$16,"x")=0,INDEX(Einstellungen!$B$5:$B$16,MONTH(EOMONTH(E17,IF(F17="",3,F17)+7)))="x"),EOMONTH(E17,IF(F17="",3,F17)+7),"")) | AS17: =IF(E17="","",IF(OR(COUNTIF(Einstellungen!$B$5:$B$16,"x")=0,INDEX(Einstellungen!$B$5:$B$16,MONTH(EOMONTH(E17,IF(F17="",3,F17)+8)))="x"),EOMONTH(E17,IF(F17="",3,F17)+8),"")) | AT17: =IF(E17="","",IF(OR(COUNTIF(Einstellungen!$B$5:$B$16,"x")=0,INDEX(Einstellungen!$B$5:$B$16,MONTH(EOMONTH(E17,IF(F17="",3,F17)+9)))="x"),EOMONTH(E17,IF(F17="",3,F17)+9),"")) | AU17: =IF(E17="","",IF(OR(COUNTIF(Einstellungen!$B$5:$B$16,"x")=0,INDEX(Einstellungen!$B$5:$B$16,MONTH(EOMONTH(E17,IF(F17="",3,F17)+10)))="x"),EOMONTH(E17,IF(F17="",3,F17)+10),"")) | AV17: =IF(E17="","",IF(OR(COUNTIF(Einstellungen!$B$5:$B$16,"x")=0,INDEX(Einstellungen!$B$5:$B$16,MONTH(EOMONTH(E17,IF(F17="",3,F17)+11)))="x"),EOMONTH(E17,IF(F17="",3,F17)+11),"")) | AW17: =IF(E17="","",IF(OR(COUNTIF(Einstellungen!$B$5:$B$16,"x")=0,INDEX(Einstellungen!$B$5:$B$16,MONTH(EOMONTH(E17,IF(F17="",3,F17)+12)))="x"),EOMONTH(E17,IF(F17="",3,F17)+12),"")) | AX17: =IF(E17="","",IF(OR(COUNTIF(Einstellungen!$B$5:$B$16,"x")=0,INDEX(Einstellungen!$B$5:$B$16,MONTH(EOMONTH(E17,IF(F17="",3,F17)+13)))="x"),EOMONTH(E17,IF(F17="",3,F17)+13),"")) | AY17: =IF(E17="","",IF(OR(COUNTIF(Einstellungen!$B$5:$B$16,"x")=0,INDEX(Einstellungen!$B$5:$B$16,MONTH(EOMONTH(E17,IF(F17="",3,F17)+14)))="x"),EOMONTH(E17,IF(F17="",3,F17)+14),"")) | AZ17: =IF(E17="","",IF(OR(COUNTIF(Einstellungen!$B$5:$B$16,"x")=0,INDEX(Einstellungen!$B$5:$B$16,MONTH(EOMONTH(E17,IF(F17="",3,F17)+15)))="x"),EOMONTH(E17,IF(F17="",3,F17)+15),"")) | BA17: =IF(E17="","",IF(OR(COUNTIF(Einstellungen!$B$5:$B$16,"x")=0,INDEX(Einstellungen!$B$5:$B$16,MONTH(EOMONTH(E17,IF(F17="",3,F17)+16)))="x"),EOMONTH(E17,IF(F17="",3,F17)+16),"")) | BB17: =IF(E17="","",IF(OR(COUNTIF(Einstellungen!$B$5:$B$16,"x")=0,INDEX(Einstellungen!$B$5:$B$16,MONTH(EOMONTH(E17,IF(F17="",3,F17)+17)))="x"),EOMONTH(E17,IF(F17="",3,F17)+17),"")) | BC17: =IF(E17="","",IF(OR(COUNTIF(Einstellungen!$B$5:$B$16,"x")=0,INDEX(Einstellungen!$B$5:$B$16,MONTH(EOMONTH(E17,IF(F17="",3,F17)+18)))="x"),EOMONTH(E17,IF(F17="",3,F17)+18),"")) | BD17: =IF(E17="","",IF(OR(COUNTIF(Einstellungen!$B$5:$B$16,"x")=0,INDEX(Einstellungen!$B$5:$B$16,MONTH(EOMONTH(E17,IF(F17="",3,F17)+19)))="x"),EOMONTH(E17,IF(F17="",3,F17)+19),"")) | BE17: =IF(E17="","",IF(OR(COUNTIF(Einstellungen!$B$5:$B$16,"x")=0,INDEX(Einstellungen!$B$5:$B$16,MONTH(EOMONTH(E17,IF(F17="",3,F17)+20)))="x"),EOMONTH(E17,IF(F17="",3,F17)+20),"")) | BF17: =IF(E17="","",IF(OR(COUNTIF(Einstellungen!$B$5:$B$16,"x")=0,INDEX(Einstellungen!$B$5:$B$16,MONTH(EOMONTH(E17,IF(F17="",3,F17)+21)))="x"),EOMONTH(E17,IF(F17="",3,F17)+21),"")) | BG17: =IF(E17="","",IF(OR(COUNTIF(Einstellungen!$B$5:$B$16,"x")=0,INDEX(Einstellungen!$B$5:$B$16,MONTH(EOMONTH(E17,IF(F17="",3,F17)+22)))="x"),EOMONTH(E17,IF(F17="",3,F17)+22),"")) | BH17: =IF(E17="","",IF(OR(COUNTIF(Einstellungen!$B$5:$B$16,"x")=0,INDEX(Einstellungen!$B$5:$B$16,MONTH(EOMONTH(E17,IF(F17="",3,F17)+23)))="x"),EOMONTH(E17,IF(F17="",3,F17)+23),"")) | BI17: =IF(AND(L17<>"",M17=""),L17,"") | BJ17: =IF(AND(N17<>"",O17=""),N17,"") | BK17: =IF(AND(P17<>"",Q17=""),P17,"") | BL17: =IF(AND(R17<>"",S17=""),R17,"") | BM17: =IF(AND(T17<>"",U17=""),T17,"") | BN17: =IF(AND(V17<>"",W17=""),V17,"") | BO17: =IF(AND(X17<>"",Y17=""),X17,"") | BP17: =IF(AND(Z17<>"",AA17=""),Z17,"") | BQ17: =IF(AND(AB17<>"",AC17=""),AB17,"") | BR17: =IF(AND(AD17<>"",AE17=""),AD17,"") | BS17: =IF(AF17="","",AF17+ROW()/100000)
B18: =IF(A18="","",IFERROR(INDEX('Mein Haus'!$C$45:$C$104,A18)&"","")) | C18: =IF(A18="","",IFERROR(INDEX('Mein Haus'!$B$45:$B$104,A18)&"","")) | H18: =IF(G18<>"",G18,IF(E18="","",IF(COUNT(AK18:BH18)=0,"",MIN(AK18:BH18)))) | J18: =IF(OR(H18="",I18=""),"",MAX(0,I18-H18-1)) | K18: =IF(J18="","",ROUND(N(IFERROR(INDEX('Mein Haus'!$G$45:$G$104,A18),0))*12/365*J18,2)) | L18: =IF(E18="","",E18+7) | N18: =IF(E18="","",E18) | P18: =IF(H18="","",WORKDAY(H18,-10,Einstellungen!$D$5:$D$34)) | R18: =IF(H18="","",H18-30) | T18: =IF(H18="","",WORKDAY(H18-1,1,Einstellungen!$D$5:$D$34)) | V18: =IF(T18="","",WORKDAY(T18,2,Einstellungen!$D$5:$D$34)) | X18: =IF(I18="","",I18) | Z18: =IF(T18="","",T18+30) | AB18: =IF(OR(H18="",Nebenkosten!$B$7=""),"",EDATE(Nebenkosten!$B$7,12*MAX(1,ROUNDUP(((YEAR(H18)-YEAR(Nebenkosten!$B$7))*12+MONTH(H18)-MONTH(Nebenkosten!$B$7)+1)/12,0)))) | AD18: =IF(H18="","",EDATE(H18,12)) | AF18: =IF(COUNT(BI18:BR18)=0,"",MIN(BI18:BR18)) | AG18: =IF(AF18="","",AF18-TODAY()) | AH18: =IF(AF18="","",INDEX($BI$7:$BR$7,MATCH(AF18,BI18:BR18,0))) | AI18: =IF(A18="","",IF(B18="","ID ohne Mieter in «Mein Haus»",IF(AND(IFERROR(INDEX('Mein Haus'!$E$45:$E$104,A18),"")<>"",H18<>"",IFERROR(INDEX('Mein Haus'!$E$45:$E$104,A18),"")<>H18),"Mietende in «Mein Haus» weicht ab",IF(D18="Vermieter","Amtliches Formular? Familienwohnung: beide Ehegatten.",IF(D18="Ausserterminlich","Nachmieter zumutbar? Vereinbartes Ende eintragen.",""))))) | AK18: =IF(E18="","",IF(OR(COUNTIF(Einstellungen!$B$5:$B$16,"x")=0,INDEX(Einstellungen!$B$5:$B$16,MONTH(EOMONTH(E18,IF(F18="",3,F18)+0)))="x"),EOMONTH(E18,IF(F18="",3,F18)+0),"")) | AL18: =IF(E18="","",IF(OR(COUNTIF(Einstellungen!$B$5:$B$16,"x")=0,INDEX(Einstellungen!$B$5:$B$16,MONTH(EOMONTH(E18,IF(F18="",3,F18)+1)))="x"),EOMONTH(E18,IF(F18="",3,F18)+1),"")) | AM18: =IF(E18="","",IF(OR(COUNTIF(Einstellungen!$B$5:$B$16,"x")=0,INDEX(Einstellungen!$B$5:$B$16,MONTH(EOMONTH(E18,IF(F18="",3,F18)+2)))="x"),EOMONTH(E18,IF(F18="",3,F18)+2),"")) | AN18: =IF(E18="","",IF(OR(COUNTIF(Einstellungen!$B$5:$B$16,"x")=0,INDEX(Einstellungen!$B$5:$B$16,MONTH(EOMONTH(E18,IF(F18="",3,F18)+3)))="x"),EOMONTH(E18,IF(F18="",3,F18)+3),"")) | AO18: =IF(E18="","",IF(OR(COUNTIF(Einstellungen!$B$5:$B$16,"x")=0,INDEX(Einstellungen!$B$5:$B$16,MONTH(EOMONTH(E18,IF(F18="",3,F18)+4)))="x"),EOMONTH(E18,IF(F18="",3,F18)+4),"")) | AP18: =IF(E18="","",IF(OR(COUNTIF(Einstellungen!$B$5:$B$16,"x")=0,INDEX(Einstellungen!$B$5:$B$16,MONTH(EOMONTH(E18,IF(F18="",3,F18)+5)))="x"),EOMONTH(E18,IF(F18="",3,F18)+5),"")) | AQ18: =IF(E18="","",IF(OR(COUNTIF(Einstellungen!$B$5:$B$16,"x")=0,INDEX(Einstellungen!$B$5:$B$16,MONTH(EOMONTH(E18,IF(F18="",3,F18)+6)))="x"),EOMONTH(E18,IF(F18="",3,F18)+6),"")) | AR18: =IF(E18="","",IF(OR(COUNTIF(Einstellungen!$B$5:$B$16,"x")=0,INDEX(Einstellungen!$B$5:$B$16,MONTH(EOMONTH(E18,IF(F18="",3,F18)+7)))="x"),EOMONTH(E18,IF(F18="",3,F18)+7),"")) | AS18: =IF(E18="","",IF(OR(COUNTIF(Einstellungen!$B$5:$B$16,"x")=0,INDEX(Einstellungen!$B$5:$B$16,MONTH(EOMONTH(E18,IF(F18="",3,F18)+8)))="x"),EOMONTH(E18,IF(F18="",3,F18)+8),"")) | AT18: =IF(E18="","",IF(OR(COUNTIF(Einstellungen!$B$5:$B$16,"x")=0,INDEX(Einstellungen!$B$5:$B$16,MONTH(EOMONTH(E18,IF(F18="",3,F18)+9)))="x"),EOMONTH(E18,IF(F18="",3,F18)+9),"")) | AU18: =IF(E18="","",IF(OR(COUNTIF(Einstellungen!$B$5:$B$16,"x")=0,INDEX(Einstellungen!$B$5:$B$16,MONTH(EOMONTH(E18,IF(F18="",3,F18)+10)))="x"),EOMONTH(E18,IF(F18="",3,F18)+10),"")) | AV18: =IF(E18="","",IF(OR(COUNTIF(Einstellungen!$B$5:$B$16,"x")=0,INDEX(Einstellungen!$B$5:$B$16,MONTH(EOMONTH(E18,IF(F18="",3,F18)+11)))="x"),EOMONTH(E18,IF(F18="",3,F18)+11),"")) | AW18: =IF(E18="","",IF(OR(COUNTIF(Einstellungen!$B$5:$B$16,"x")=0,INDEX(Einstellungen!$B$5:$B$16,MONTH(EOMONTH(E18,IF(F18="",3,F18)+12)))="x"),EOMONTH(E18,IF(F18="",3,F18)+12),"")) | AX18: =IF(E18="","",IF(OR(COUNTIF(Einstellungen!$B$5:$B$16,"x")=0,INDEX(Einstellungen!$B$5:$B$16,MONTH(EOMONTH(E18,IF(F18="",3,F18)+13)))="x"),EOMONTH(E18,IF(F18="",3,F18)+13),"")) | AY18: =IF(E18="","",IF(OR(COUNTIF(Einstellungen!$B$5:$B$16,"x")=0,INDEX(Einstellungen!$B$5:$B$16,MONTH(EOMONTH(E18,IF(F18="",3,F18)+14)))="x"),EOMONTH(E18,IF(F18="",3,F18)+14),"")) | AZ18: =IF(E18="","",IF(OR(COUNTIF(Einstellungen!$B$5:$B$16,"x")=0,INDEX(Einstellungen!$B$5:$B$16,MONTH(EOMONTH(E18,IF(F18="",3,F18)+15)))="x"),EOMONTH(E18,IF(F18="",3,F18)+15),"")) | BA18: =IF(E18="","",IF(OR(COUNTIF(Einstellungen!$B$5:$B$16,"x")=0,INDEX(Einstellungen!$B$5:$B$16,MONTH(EOMONTH(E18,IF(F18="",3,F18)+16)))="x"),EOMONTH(E18,IF(F18="",3,F18)+16),"")) | BB18: =IF(E18="","",IF(OR(COUNTIF(Einstellungen!$B$5:$B$16,"x")=0,INDEX(Einstellungen!$B$5:$B$16,MONTH(EOMONTH(E18,IF(F18="",3,F18)+17)))="x"),EOMONTH(E18,IF(F18="",3,F18)+17),"")) | BC18: =IF(E18="","",IF(OR(COUNTIF(Einstellungen!$B$5:$B$16,"x")=0,INDEX(Einstellungen!$B$5:$B$16,MONTH(EOMONTH(E18,IF(F18="",3,F18)+18)))="x"),EOMONTH(E18,IF(F18="",3,F18)+18),"")) | BD18: =IF(E18="","",IF(OR(COUNTIF(Einstellungen!$B$5:$B$16,"x")=0,INDEX(Einstellungen!$B$5:$B$16,MONTH(EOMONTH(E18,IF(F18="",3,F18)+19)))="x"),EOMONTH(E18,IF(F18="",3,F18)+19),"")) | BE18: =IF(E18="","",IF(OR(COUNTIF(Einstellungen!$B$5:$B$16,"x")=0,INDEX(Einstellungen!$B$5:$B$16,MONTH(EOMONTH(E18,IF(F18="",3,F18)+20)))="x"),EOMONTH(E18,IF(F18="",3,F18)+20),"")) | BF18: =IF(E18="","",IF(OR(COUNTIF(Einstellungen!$B$5:$B$16,"x")=0,INDEX(Einstellungen!$B$5:$B$16,MONTH(EOMONTH(E18,IF(F18="",3,F18)+21)))="x"),EOMONTH(E18,IF(F18="",3,F18)+21),"")) | BG18: =IF(E18="","",IF(OR(COUNTIF(Einstellungen!$B$5:$B$16,"x")=0,INDEX(Einstellungen!$B$5:$B$16,MONTH(EOMONTH(E18,IF(F18="",3,F18)+22)))="x"),EOMONTH(E18,IF(F18="",3,F18)+22),"")) | BH18: =IF(E18="","",IF(OR(COUNTIF(Einstellungen!$B$5:$B$16,"x")=0,INDEX(Einstellungen!$B$5:$B$16,MONTH(EOMONTH(E18,IF(F18="",3,F18)+23)))="x"),EOMONTH(E18,IF(F18="",3,F18)+23),"")) | BI18: =IF(AND(L18<>"",M18=""),L18,"") | BJ18: =IF(AND(N18<>"",O18=""),N18,"") | BK18: =IF(AND(P18<>"",Q18=""),P18,"") | BL18: =IF(AND(R18<>"",S18=""),R18,"") | BM18: =IF(AND(T18<>"",U18=""),T18,"") | BN18: =IF(AND(V18<>"",W18=""),V18,"") | BO18: =IF(AND(X18<>"",Y18=""),X18,"") | BP18: =IF(AND(Z18<>"",AA18=""),Z18,"") | BQ18: =IF(AND(AB18<>"",AC18=""),AB18,"") | BR18: =IF(AND(AD18<>"",AE18=""),AD18,"") | BS18: =IF(AF18="","",AF18+ROW()/100000)
B19: =IF(A19="","",IFERROR(INDEX('Mein Haus'!$C$45:$C$104,A19)&"","")) | C19: =IF(A19="","",IFERROR(INDEX('Mein Haus'!$B$45:$B$104,A19)&"","")) | H19: =IF(G19<>"",G19,IF(E19="","",IF(COUNT(AK19:BH19)=0,"",MIN(AK19:BH19)))) | J19: =IF(OR(H19="",I19=""),"",MAX(0,I19-H19-1)) | K19: =IF(J19="","",ROUND(N(IFERROR(INDEX('Mein Haus'!$G$45:$G$104,A19),0))*12/365*J19,2)) | L19: =IF(E19="","",E19+7) | N19: =IF(E19="","",E19) | P19: =IF(H19="","",WORKDAY(H19,-10,Einstellungen!$D$5:$D$34)) | R19: =IF(H19="","",H19-30) | T19: =IF(H19="","",WORKDAY(H19-1,1,Einstellungen!$D$5:$D$34)) | V19: =IF(T19="","",WORKDAY(T19,2,Einstellungen!$D$5:$D$34)) | X19: =IF(I19="","",I19) | Z19: =IF(T19="","",T19+30) | AB19: =IF(OR(H19="",Nebenkosten!$B$7=""),"",EDATE(Nebenkosten!$B$7,12*MAX(1,ROUNDUP(((YEAR(H19)-YEAR(Nebenkosten!$B$7))*12+MONTH(H19)-MONTH(Nebenkosten!$B$7)+1)/12,0)))) | AD19: =IF(H19="","",EDATE(H19,12)) | AF19: =IF(COUNT(BI19:BR19)=0,"",MIN(BI19:BR19)) | AG19: =IF(AF19="","",AF19-TODAY()) | AH19: =IF(AF19="","",INDEX($BI$7:$BR$7,MATCH(AF19,BI19:BR19,0))) | AI19: =IF(A19="","",IF(B19="","ID ohne Mieter in «Mein Haus»",IF(AND(IFERROR(INDEX('Mein Haus'!$E$45:$E$104,A19),"")<>"",H19<>"",IFERROR(INDEX('Mein Haus'!$E$45:$E$104,A19),"")<>H19),"Mietende in «Mein Haus» weicht ab",IF(D19="Vermieter","Amtliches Formular? Familienwohnung: beide Ehegatten.",IF(D19="Ausserterminlich","Nachmieter zumutbar? Vereinbartes Ende eintragen.",""))))) | AK19: =IF(E19="","",IF(OR(COUNTIF(Einstellungen!$B$5:$B$16,"x")=0,INDEX(Einstellungen!$B$5:$B$16,MONTH(EOMONTH(E19,IF(F19="",3,F19)+0)))="x"),EOMONTH(E19,IF(F19="",3,F19)+0),"")) | AL19: =IF(E19="","",IF(OR(COUNTIF(Einstellungen!$B$5:$B$16,"x")=0,INDEX(Einstellungen!$B$5:$B$16,MONTH(EOMONTH(E19,IF(F19="",3,F19)+1)))="x"),EOMONTH(E19,IF(F19="",3,F19)+1),"")) | AM19: =IF(E19="","",IF(OR(COUNTIF(Einstellungen!$B$5:$B$16,"x")=0,INDEX(Einstellungen!$B$5:$B$16,MONTH(EOMONTH(E19,IF(F19="",3,F19)+2)))="x"),EOMONTH(E19,IF(F19="",3,F19)+2),"")) | AN19: =IF(E19="","",IF(OR(COUNTIF(Einstellungen!$B$5:$B$16,"x")=0,INDEX(Einstellungen!$B$5:$B$16,MONTH(EOMONTH(E19,IF(F19="",3,F19)+3)))="x"),EOMONTH(E19,IF(F19="",3,F19)+3),"")) | AO19: =IF(E19="","",IF(OR(COUNTIF(Einstellungen!$B$5:$B$16,"x")=0,INDEX(Einstellungen!$B$5:$B$16,MONTH(EOMONTH(E19,IF(F19="",3,F19)+4)))="x"),EOMONTH(E19,IF(F19="",3,F19)+4),"")) | AP19: =IF(E19="","",IF(OR(COUNTIF(Einstellungen!$B$5:$B$16,"x")=0,INDEX(Einstellungen!$B$5:$B$16,MONTH(EOMONTH(E19,IF(F19="",3,F19)+5)))="x"),EOMONTH(E19,IF(F19="",3,F19)+5),"")) | AQ19: =IF(E19="","",IF(OR(COUNTIF(Einstellungen!$B$5:$B$16,"x")=0,INDEX(Einstellungen!$B$5:$B$16,MONTH(EOMONTH(E19,IF(F19="",3,F19)+6)))="x"),EOMONTH(E19,IF(F19="",3,F19)+6),"")) | AR19: =IF(E19="","",IF(OR(COUNTIF(Einstellungen!$B$5:$B$16,"x")=0,INDEX(Einstellungen!$B$5:$B$16,MONTH(EOMONTH(E19,IF(F19="",3,F19)+7)))="x"),EOMONTH(E19,IF(F19="",3,F19)+7),"")) | AS19: =IF(E19="","",IF(OR(COUNTIF(Einstellungen!$B$5:$B$16,"x")=0,INDEX(Einstellungen!$B$5:$B$16,MONTH(EOMONTH(E19,IF(F19="",3,F19)+8)))="x"),EOMONTH(E19,IF(F19="",3,F19)+8),"")) | AT19: =IF(E19="","",IF(OR(COUNTIF(Einstellungen!$B$5:$B$16,"x")=0,INDEX(Einstellungen!$B$5:$B$16,MONTH(EOMONTH(E19,IF(F19="",3,F19)+9)))="x"),EOMONTH(E19,IF(F19="",3,F19)+9),"")) | AU19: =IF(E19="","",IF(OR(COUNTIF(Einstellungen!$B$5:$B$16,"x")=0,INDEX(Einstellungen!$B$5:$B$16,MONTH(EOMONTH(E19,IF(F19="",3,F19)+10)))="x"),EOMONTH(E19,IF(F19="",3,F19)+10),"")) | AV19: =IF(E19="","",IF(OR(COUNTIF(Einstellungen!$B$5:$B$16,"x")=0,INDEX(Einstellungen!$B$5:$B$16,MONTH(EOMONTH(E19,IF(F19="",3,F19)+11)))="x"),EOMONTH(E19,IF(F19="",3,F19)+11),"")) | AW19: =IF(E19="","",IF(OR(COUNTIF(Einstellungen!$B$5:$B$16,"x")=0,INDEX(Einstellungen!$B$5:$B$16,MONTH(EOMONTH(E19,IF(F19="",3,F19)+12)))="x"),EOMONTH(E19,IF(F19="",3,F19)+12),"")) | AX19: =IF(E19="","",IF(OR(COUNTIF(Einstellungen!$B$5:$B$16,"x")=0,INDEX(Einstellungen!$B$5:$B$16,MONTH(EOMONTH(E19,IF(F19="",3,F19)+13)))="x"),EOMONTH(E19,IF(F19="",3,F19)+13),"")) | AY19: =IF(E19="","",IF(OR(COUNTIF(Einstellungen!$B$5:$B$16,"x")=0,INDEX(Einstellungen!$B$5:$B$16,MONTH(EOMONTH(E19,IF(F19="",3,F19)+14)))="x"),EOMONTH(E19,IF(F19="",3,F19)+14),"")) | AZ19: =IF(E19="","",IF(OR(COUNTIF(Einstellungen!$B$5:$B$16,"x")=0,INDEX(Einstellungen!$B$5:$B$16,MONTH(EOMONTH(E19,IF(F19="",3,F19)+15)))="x"),EOMONTH(E19,IF(F19="",3,F19)+15),"")) | BA19: =IF(E19="","",IF(OR(COUNTIF(Einstellungen!$B$5:$B$16,"x")=0,INDEX(Einstellungen!$B$5:$B$16,MONTH(EOMONTH(E19,IF(F19="",3,F19)+16)))="x"),EOMONTH(E19,IF(F19="",3,F19)+16),"")) | BB19: =IF(E19="","",IF(OR(COUNTIF(Einstellungen!$B$5:$B$16,"x")=0,INDEX(Einstellungen!$B$5:$B$16,MONTH(EOMONTH(E19,IF(F19="",3,F19)+17)))="x"),EOMONTH(E19,IF(F19="",3,F19)+17),"")) | BC19: =IF(E19="","",IF(OR(COUNTIF(Einstellungen!$B$5:$B$16,"x")=0,INDEX(Einstellungen!$B$5:$B$16,MONTH(EOMONTH(E19,IF(F19="",3,F19)+18)))="x"),EOMONTH(E19,IF(F19="",3,F19)+18),"")) | BD19: =IF(E19="","",IF(OR(COUNTIF(Einstellungen!$B$5:$B$16,"x")=0,INDEX(Einstellungen!$B$5:$B$16,MONTH(EOMONTH(E19,IF(F19="",3,F19)+19)))="x"),EOMONTH(E19,IF(F19="",3,F19)+19),"")) | BE19: =IF(E19="","",IF(OR(COUNTIF(Einstellungen!$B$5:$B$16,"x")=0,INDEX(Einstellungen!$B$5:$B$16,MONTH(EOMONTH(E19,IF(F19="",3,F19)+20)))="x"),EOMONTH(E19,IF(F19="",3,F19)+20),"")) | BF19: =IF(E19="","",IF(OR(COUNTIF(Einstellungen!$B$5:$B$16,"x")=0,INDEX(Einstellungen!$B$5:$B$16,MONTH(EOMONTH(E19,IF(F19="",3,F19)+21)))="x"),EOMONTH(E19,IF(F19="",3,F19)+21),"")) | BG19: =IF(E19="","",IF(OR(COUNTIF(Einstellungen!$B$5:$B$16,"x")=0,INDEX(Einstellungen!$B$5:$B$16,MONTH(EOMONTH(E19,IF(F19="",3,F19)+22)))="x"),EOMONTH(E19,IF(F19="",3,F19)+22),"")) | BH19: =IF(E19="","",IF(OR(COUNTIF(Einstellungen!$B$5:$B$16,"x")=0,INDEX(Einstellungen!$B$5:$B$16,MONTH(EOMONTH(E19,IF(F19="",3,F19)+23)))="x"),EOMONTH(E19,IF(F19="",3,F19)+23),"")) | BI19: =IF(AND(L19<>"",M19=""),L19,"") | BJ19: =IF(AND(N19<>"",O19=""),N19,"") | BK19: =IF(AND(P19<>"",Q19=""),P19,"") | BL19: =IF(AND(R19<>"",S19=""),R19,"") | BM19: =IF(AND(T19<>"",U19=""),T19,"") | BN19: =IF(AND(V19<>"",W19=""),V19,"") | BO19: =IF(AND(X19<>"",Y19=""),X19,"") | BP19: =IF(AND(Z19<>"",AA19=""),Z19,"") | BQ19: =IF(AND(AB19<>"",AC19=""),AB19,"") | BR19: =IF(AND(AD19<>"",AE19=""),AD19,"") | BS19: =IF(AF19="","",AF19+ROW()/100000)
B20: =IF(A20="","",IFERROR(INDEX('Mein Haus'!$C$45:$C$104,A20)&"","")) | C20: =IF(A20="","",IFERROR(INDEX('Mein Haus'!$B$45:$B$104,A20)&"","")) | H20: =IF(G20<>"",G20,IF(E20="","",IF(COUNT(AK20:BH20)=0,"",MIN(AK20:BH20)))) | J20: =IF(OR(H20="",I20=""),"",MAX(0,I20-H20-1)) | K20: =IF(J20="","",ROUND(N(IFERROR(INDEX('Mein Haus'!$G$45:$G$104,A20),0))*12/365*J20,2)) | L20: =IF(E20="","",E20+7) | N20: =IF(E20="","",E20) | P20: =IF(H20="","",WORKDAY(H20,-10,Einstellungen!$D$5:$D$34)) | R20: =IF(H20="","",H20-30) | T20: =IF(H20="","",WORKDAY(H20-1,1,Einstellungen!$D$5:$D$34)) | V20: =IF(T20="","",WORKDAY(T20,2,Einstellungen!$D$5:$D$34)) | X20: =IF(I20="","",I20) | Z20: =IF(T20="","",T20+30) | AB20: =IF(OR(H20="",Nebenkosten!$B$7=""),"",EDATE(Nebenkosten!$B$7,12*MAX(1,ROUNDUP(((YEAR(H20)-YEAR(Nebenkosten!$B$7))*12+MONTH(H20)-MONTH(Nebenkosten!$B$7)+1)/12,0)))) | AD20: =IF(H20="","",EDATE(H20,12)) | AF20: =IF(COUNT(BI20:BR20)=0,"",MIN(BI20:BR20)) | AG20: =IF(AF20="","",AF20-TODAY()) | AH20: =IF(AF20="","",INDEX($BI$7:$BR$7,MATCH(AF20,BI20:BR20,0))) | AI20: =IF(A20="","",IF(B20="","ID ohne Mieter in «Mein Haus»",IF(AND(IFERROR(INDEX('Mein Haus'!$E$45:$E$104,A20),"")<>"",H20<>"",IFERROR(INDEX('Mein Haus'!$E$45:$E$104,A20),"")<>H20),"Mietende in «Mein Haus» weicht ab",IF(D20="Vermieter","Amtliches Formular? Familienwohnung: beide Ehegatten.",IF(D20="Ausserterminlich","Nachmieter zumutbar? Vereinbartes Ende eintragen.",""))))) | AK20: =IF(E20="","",IF(OR(COUNTIF(Einstellungen!$B$5:$B$16,"x")=0,INDEX(Einstellungen!$B$5:$B$16,MONTH(EOMONTH(E20,IF(F20="",3,F20)+0)))="x"),EOMONTH(E20,IF(F20="",3,F20)+0),"")) | AL20: =IF(E20="","",IF(OR(COUNTIF(Einstellungen!$B$5:$B$16,"x")=0,INDEX(Einstellungen!$B$5:$B$16,MONTH(EOMONTH(E20,IF(F20="",3,F20)+1)))="x"),EOMONTH(E20,IF(F20="",3,F20)+1),"")) | AM20: =IF(E20="","",IF(OR(COUNTIF(Einstellungen!$B$5:$B$16,"x")=0,INDEX(Einstellungen!$B$5:$B$16,MONTH(EOMONTH(E20,IF(F20="",3,F20)+2)))="x"),EOMONTH(E20,IF(F20="",3,F20)+2),"")) | AN20: =IF(E20="","",IF(OR(COUNTIF(Einstellungen!$B$5:$B$16,"x")=0,INDEX(Einstellungen!$B$5:$B$16,MONTH(EOMONTH(E20,IF(F20="",3,F20)+3)))="x"),EOMONTH(E20,IF(F20="",3,F20)+3),"")) | AO20: =IF(E20="","",IF(OR(COUNTIF(Einstellungen!$B$5:$B$16,"x")=0,INDEX(Einstellungen!$B$5:$B$16,MONTH(EOMONTH(E20,IF(F20="",3,F20)+4)))="x"),EOMONTH(E20,IF(F20="",3,F20)+4),"")) | AP20: =IF(E20="","",IF(OR(COUNTIF(Einstellungen!$B$5:$B$16,"x")=0,INDEX(Einstellungen!$B$5:$B$16,MONTH(EOMONTH(E20,IF(F20="",3,F20)+5)))="x"),EOMONTH(E20,IF(F20="",3,F20)+5),"")) | AQ20: =IF(E20="","",IF(OR(COUNTIF(Einstellungen!$B$5:$B$16,"x")=0,INDEX(Einstellungen!$B$5:$B$16,MONTH(EOMONTH(E20,IF(F20="",3,F20)+6)))="x"),EOMONTH(E20,IF(F20="",3,F20)+6),"")) | AR20: =IF(E20="","",IF(OR(COUNTIF(Einstellungen!$B$5:$B$16,"x")=0,INDEX(Einstellungen!$B$5:$B$16,MONTH(EOMONTH(E20,IF(F20="",3,F20)+7)))="x"),EOMONTH(E20,IF(F20="",3,F20)+7),"")) | AS20: =IF(E20="","",IF(OR(COUNTIF(Einstellungen!$B$5:$B$16,"x")=0,INDEX(Einstellungen!$B$5:$B$16,MONTH(EOMONTH(E20,IF(F20="",3,F20)+8)))="x"),EOMONTH(E20,IF(F20="",3,F20)+8),"")) | AT20: =IF(E20="","",IF(OR(COUNTIF(Einstellungen!$B$5:$B$16,"x")=0,INDEX(Einstellungen!$B$5:$B$16,MONTH(EOMONTH(E20,IF(F20="",3,F20)+9)))="x"),EOMONTH(E20,IF(F20="",3,F20)+9),"")) | AU20: =IF(E20="","",IF(OR(COUNTIF(Einstellungen!$B$5:$B$16,"x")=0,INDEX(Einstellungen!$B$5:$B$16,MONTH(EOMONTH(E20,IF(F20="",3,F20)+10)))="x"),EOMONTH(E20,IF(F20="",3,F20)+10),"")) | AV20: =IF(E20="","",IF(OR(COUNTIF(Einstellungen!$B$5:$B$16,"x")=0,INDEX(Einstellungen!$B$5:$B$16,MONTH(EOMONTH(E20,IF(F20="",3,F20)+11)))="x"),EOMONTH(E20,IF(F20="",3,F20)+11),"")) | AW20: =IF(E20="","",IF(OR(COUNTIF(Einstellungen!$B$5:$B$16,"x")=0,INDEX(Einstellungen!$B$5:$B$16,MONTH(EOMONTH(E20,IF(F20="",3,F20)+12)))="x"),EOMONTH(E20,IF(F20="",3,F20)+12),"")) | AX20: =IF(E20="","",IF(OR(COUNTIF(Einstellungen!$B$5:$B$16,"x")=0,INDEX(Einstellungen!$B$5:$B$16,MONTH(EOMONTH(E20,IF(F20="",3,F20)+13)))="x"),EOMONTH(E20,IF(F20="",3,F20)+13),"")) | AY20: =IF(E20="","",IF(OR(COUNTIF(Einstellungen!$B$5:$B$16,"x")=0,INDEX(Einstellungen!$B$5:$B$16,MONTH(EOMONTH(E20,IF(F20="",3,F20)+14)))="x"),EOMONTH(E20,IF(F20="",3,F20)+14),"")) | AZ20: =IF(E20="","",IF(OR(COUNTIF(Einstellungen!$B$5:$B$16,"x")=0,INDEX(Einstellungen!$B$5:$B$16,MONTH(EOMONTH(E20,IF(F20="",3,F20)+15)))="x"),EOMONTH(E20,IF(F20="",3,F20)+15),"")) | BA20: =IF(E20="","",IF(OR(COUNTIF(Einstellungen!$B$5:$B$16,"x")=0,INDEX(Einstellungen!$B$5:$B$16,MONTH(EOMONTH(E20,IF(F20="",3,F20)+16)))="x"),EOMONTH(E20,IF(F20="",3,F20)+16),"")) | BB20: =IF(E20="","",IF(OR(COUNTIF(Einstellungen!$B$5:$B$16,"x")=0,INDEX(Einstellungen!$B$5:$B$16,MONTH(EOMONTH(E20,IF(F20="",3,F20)+17)))="x"),EOMONTH(E20,IF(F20="",3,F20)+17),"")) | BC20: =IF(E20="","",IF(OR(COUNTIF(Einstellungen!$B$5:$B$16,"x")=0,INDEX(Einstellungen!$B$5:$B$16,MONTH(EOMONTH(E20,IF(F20="",3,F20)+18)))="x"),EOMONTH(E20,IF(F20="",3,F20)+18),"")) | BD20: =IF(E20="","",IF(OR(COUNTIF(Einstellungen!$B$5:$B$16,"x")=0,INDEX(Einstellungen!$B$5:$B$16,MONTH(EOMONTH(E20,IF(F20="",3,F20)+19)))="x"),EOMONTH(E20,IF(F20="",3,F20)+19),"")) | BE20: =IF(E20="","",IF(OR(COUNTIF(Einstellungen!$B$5:$B$16,"x")=0,INDEX(Einstellungen!$B$5:$B$16,MONTH(EOMONTH(E20,IF(F20="",3,F20)+20)))="x"),EOMONTH(E20,IF(F20="",3,F20)+20),"")) | BF20: =IF(E20="","",IF(OR(COUNTIF(Einstellungen!$B$5:$B$16,"x")=0,INDEX(Einstellungen!$B$5:$B$16,MONTH(EOMONTH(E20,IF(F20="",3,F20)+21)))="x"),EOMONTH(E20,IF(F20="",3,F20)+21),"")) | BG20: =IF(E20="","",IF(OR(COUNTIF(Einstellungen!$B$5:$B$16,"x")=0,INDEX(Einstellungen!$B$5:$B$16,MONTH(EOMONTH(E20,IF(F20="",3,F20)+22)))="x"),EOMONTH(E20,IF(F20="",3,F20)+22),"")) | BH20: =IF(E20="","",IF(OR(COUNTIF(Einstellungen!$B$5:$B$16,"x")=0,INDEX(Einstellungen!$B$5:$B$16,MONTH(EOMONTH(E20,IF(F20="",3,F20)+23)))="x"),EOMONTH(E20,IF(F20="",3,F20)+23),"")) | BI20: =IF(AND(L20<>"",M20=""),L20,"") | BJ20: =IF(AND(N20<>"",O20=""),N20,"") | BK20: =IF(AND(P20<>"",Q20=""),P20,"") | BL20: =IF(AND(R20<>"",S20=""),R20,"") | BM20: =IF(AND(T20<>"",U20=""),T20,"") | BN20: =IF(AND(V20<>"",W20=""),V20,"") | BO20: =IF(AND(X20<>"",Y20=""),X20,"") | BP20: =IF(AND(Z20<>"",AA20=""),Z20,"") | BQ20: =IF(AND(AB20<>"",AC20=""),AB20,"") | BR20: =IF(AND(AD20<>"",AE20=""),AD20,"") | BS20: =IF(AF20="","",AF20+ROW()/100000)
B21: =IF(A21="","",IFERROR(INDEX('Mein Haus'!$C$45:$C$104,A21)&"","")) | C21: =IF(A21="","",IFERROR(INDEX('Mein Haus'!$B$45:$B$104,A21)&"","")) | H21: =IF(G21<>"",G21,IF(E21="","",IF(COUNT(AK21:BH21)=0,"",MIN(AK21:BH21)))) | J21: =IF(OR(H21="",I21=""),"",MAX(0,I21-H21-1)) | K21: =IF(J21="","",ROUND(N(IFERROR(INDEX('Mein Haus'!$G$45:$G$104,A21),0))*12/365*J21,2)) | L21: =IF(E21="","",E21+7) | N21: =IF(E21="","",E21) | P21: =IF(H21="","",WORKDAY(H21,-10,Einstellungen!$D$5:$D$34)) | R21: =IF(H21="","",H21-30) | T21: =IF(H21="","",WORKDAY(H21-1,1,Einstellungen!$D$5:$D$34)) | V21: =IF(T21="","",WORKDAY(T21,2,Einstellungen!$D$5:$D$34)) | X21: =IF(I21="","",I21) | Z21: =IF(T21="","",T21+30) | AB21: =IF(OR(H21="",Nebenkosten!$B$7=""),"",EDATE(Nebenkosten!$B$7,12*MAX(1,ROUNDUP(((YEAR(H21)-YEAR(Nebenkosten!$B$7))*12+MONTH(H21)-MONTH(Nebenkosten!$B$7)+1)/12,0)))) | AD21: =IF(H21="","",EDATE(H21,12)) | AF21: =IF(COUNT(BI21:BR21)=0,"",MIN(BI21:BR21)) | AG21: =IF(AF21="","",AF21-TODAY()) | AH21: =IF(AF21="","",INDEX($BI$7:$BR$7,MATCH(AF21,BI21:BR21,0))) | AI21: =IF(A21="","",IF(B21="","ID ohne Mieter in «Mein Haus»",IF(AND(IFERROR(INDEX('Mein Haus'!$E$45:$E$104,A21),"")<>"",H21<>"",IFERROR(INDEX('Mein Haus'!$E$45:$E$104,A21),"")<>H21),"Mietende in «Mein Haus» weicht ab",IF(D21="Vermieter","Amtliches Formular? Familienwohnung: beide Ehegatten.",IF(D21="Ausserterminlich","Nachmieter zumutbar? Vereinbartes Ende eintragen.",""))))) | AK21: =IF(E21="","",IF(OR(COUNTIF(Einstellungen!$B$5:$B$16,"x")=0,INDEX(Einstellungen!$B$5:$B$16,MONTH(EOMONTH(E21,IF(F21="",3,F21)+0)))="x"),EOMONTH(E21,IF(F21="",3,F21)+0),"")) | AL21: =IF(E21="","",IF(OR(COUNTIF(Einstellungen!$B$5:$B$16,"x")=0,INDEX(Einstellungen!$B$5:$B$16,MONTH(EOMONTH(E21,IF(F21="",3,F21)+1)))="x"),EOMONTH(E21,IF(F21="",3,F21)+1),"")) | AM21: =IF(E21="","",IF(OR(COUNTIF(Einstellungen!$B$5:$B$16,"x")=0,INDEX(Einstellungen!$B$5:$B$16,MONTH(EOMONTH(E21,IF(F21="",3,F21)+2)))="x"),EOMONTH(E21,IF(F21="",3,F21)+2),"")) | AN21: =IF(E21="","",IF(OR(COUNTIF(Einstellungen!$B$5:$B$16,"x")=0,INDEX(Einstellungen!$B$5:$B$16,MONTH(EOMONTH(E21,IF(F21="",3,F21)+3)))="x"),EOMONTH(E21,IF(F21="",3,F21)+3),"")) | AO21: =IF(E21="","",IF(OR(COUNTIF(Einstellungen!$B$5:$B$16,"x")=0,INDEX(Einstellungen!$B$5:$B$16,MONTH(EOMONTH(E21,IF(F21="",3,F21)+4)))="x"),EOMONTH(E21,IF(F21="",3,F21)+4),"")) | AP21: =IF(E21="","",IF(OR(COUNTIF(Einstellungen!$B$5:$B$16,"x")=0,INDEX(Einstellungen!$B$5:$B$16,MONTH(EOMONTH(E21,IF(F21="",3,F21)+5)))="x"),EOMONTH(E21,IF(F21="",3,F21)+5),"")) | AQ21: =IF(E21="","",IF(OR(COUNTIF(Einstellungen!$B$5:$B$16,"x")=0,INDEX(Einstellungen!$B$5:$B$16,MONTH(EOMONTH(E21,IF(F21="",3,F21)+6)))="x"),EOMONTH(E21,IF(F21="",3,F21)+6),"")) | AR21: =IF(E21="","",IF(OR(COUNTIF(Einstellungen!$B$5:$B$16,"x")=0,INDEX(Einstellungen!$B$5:$B$16,MONTH(EOMONTH(E21,IF(F21="",3,F21)+7)))="x"),EOMONTH(E21,IF(F21="",3,F21)+7),"")) | AS21: =IF(E21="","",IF(OR(COUNTIF(Einstellungen!$B$5:$B$16,"x")=0,INDEX(Einstellungen!$B$5:$B$16,MONTH(EOMONTH(E21,IF(F21="",3,F21)+8)))="x"),EOMONTH(E21,IF(F21="",3,F21)+8),"")) | AT21: =IF(E21="","",IF(OR(COUNTIF(Einstellungen!$B$5:$B$16,"x")=0,INDEX(Einstellungen!$B$5:$B$16,MONTH(EOMONTH(E21,IF(F21="",3,F21)+9)))="x"),EOMONTH(E21,IF(F21="",3,F21)+9),"")) | AU21: =IF(E21="","",IF(OR(COUNTIF(Einstellungen!$B$5:$B$16,"x")=0,INDEX(Einstellungen!$B$5:$B$16,MONTH(EOMONTH(E21,IF(F21="",3,F21)+10)))="x"),EOMONTH(E21,IF(F21="",3,F21)+10),"")) | AV21: =IF(E21="","",IF(OR(COUNTIF(Einstellungen!$B$5:$B$16,"x")=0,INDEX(Einstellungen!$B$5:$B$16,MONTH(EOMONTH(E21,IF(F21="",3,F21)+11)))="x"),EOMONTH(E21,IF(F21="",3,F21)+11),"")) | AW21: =IF(E21="","",IF(OR(COUNTIF(Einstellungen!$B$5:$B$16,"x")=0,INDEX(Einstellungen!$B$5:$B$16,MONTH(EOMONTH(E21,IF(F21="",3,F21)+12)))="x"),EOMONTH(E21,IF(F21="",3,F21)+12),"")) | AX21: =IF(E21="","",IF(OR(COUNTIF(Einstellungen!$B$5:$B$16,"x")=0,INDEX(Einstellungen!$B$5:$B$16,MONTH(EOMONTH(E21,IF(F21="",3,F21)+13)))="x"),EOMONTH(E21,IF(F21="",3,F21)+13),"")) | AY21: =IF(E21="","",IF(OR(COUNTIF(Einstellungen!$B$5:$B$16,"x")=0,INDEX(Einstellungen!$B$5:$B$16,MONTH(EOMONTH(E21,IF(F21="",3,F21)+14)))="x"),EOMONTH(E21,IF(F21="",3,F21)+14),"")) | AZ21: =IF(E21="","",IF(OR(COUNTIF(Einstellungen!$B$5:$B$16,"x")=0,INDEX(Einstellungen!$B$5:$B$16,MONTH(EOMONTH(E21,IF(F21="",3,F21)+15)))="x"),EOMONTH(E21,IF(F21="",3,F21)+15),"")) | BA21: =IF(E21="","",IF(OR(COUNTIF(Einstellungen!$B$5:$B$16,"x")=0,INDEX(Einstellungen!$B$5:$B$16,MONTH(EOMONTH(E21,IF(F21="",3,F21)+16)))="x"),EOMONTH(E21,IF(F21="",3,F21)+16),"")) | BB21: =IF(E21="","",IF(OR(COUNTIF(Einstellungen!$B$5:$B$16,"x")=0,INDEX(Einstellungen!$B$5:$B$16,MONTH(EOMONTH(E21,IF(F21="",3,F21)+17)))="x"),EOMONTH(E21,IF(F21="",3,F21)+17),"")) | BC21: =IF(E21="","",IF(OR(COUNTIF(Einstellungen!$B$5:$B$16,"x")=0,INDEX(Einstellungen!$B$5:$B$16,MONTH(EOMONTH(E21,IF(F21="",3,F21)+18)))="x"),EOMONTH(E21,IF(F21="",3,F21)+18),"")) | BD21: =IF(E21="","",IF(OR(COUNTIF(Einstellungen!$B$5:$B$16,"x")=0,INDEX(Einstellungen!$B$5:$B$16,MONTH(EOMONTH(E21,IF(F21="",3,F21)+19)))="x"),EOMONTH(E21,IF(F21="",3,F21)+19),"")) | BE21: =IF(E21="","",IF(OR(COUNTIF(Einstellungen!$B$5:$B$16,"x")=0,INDEX(Einstellungen!$B$5:$B$16,MONTH(EOMONTH(E21,IF(F21="",3,F21)+20)))="x"),EOMONTH(E21,IF(F21="",3,F21)+20),"")) | BF21: =IF(E21="","",IF(OR(COUNTIF(Einstellungen!$B$5:$B$16,"x")=0,INDEX(Einstellungen!$B$5:$B$16,MONTH(EOMONTH(E21,IF(F21="",3,F21)+21)))="x"),EOMONTH(E21,IF(F21="",3,F21)+21),"")) | BG21: =IF(E21="","",IF(OR(COUNTIF(Einstellungen!$B$5:$B$16,"x")=0,INDEX(Einstellungen!$B$5:$B$16,MONTH(EOMONTH(E21,IF(F21="",3,F21)+22)))="x"),EOMONTH(E21,IF(F21="",3,F21)+22),"")) | BH21: =IF(E21="","",IF(OR(COUNTIF(Einstellungen!$B$5:$B$16,"x")=0,INDEX(Einstellungen!$B$5:$B$16,MONTH(EOMONTH(E21,IF(F21="",3,F21)+23)))="x"),EOMONTH(E21,IF(F21="",3,F21)+23),"")) | BI21: =IF(AND(L21<>"",M21=""),L21,"") | BJ21: =IF(AND(N21<>"",O21=""),N21,"") | BK21: =IF(AND(P21<>"",Q21=""),P21,"") | BL21: =IF(AND(R21<>"",S21=""),R21,"") | BM21: =IF(AND(T21<>"",U21=""),T21,"") | BN21: =IF(AND(V21<>"",W21=""),V21,"") | BO21: =IF(AND(X21<>"",Y21=""),X21,"") | BP21: =IF(AND(Z21<>"",AA21=""),Z21,"") | BQ21: =IF(AND(AB21<>"",AC21=""),AB21,"") | BR21: =IF(AND(AD21<>"",AE21=""),AD21,"") | BS21: =IF(AF21="","",AF21+ROW()/100000)
B22: =IF(A22="","",IFERROR(INDEX('Mein Haus'!$C$45:$C$104,A22)&"","")) | C22: =IF(A22="","",IFERROR(INDEX('Mein Haus'!$B$45:$B$104,A22)&"","")) | H22: =IF(G22<>"",G22,IF(E22="","",IF(COUNT(AK22:BH22)=0,"",MIN(AK22:BH22)))) | J22: =IF(OR(H22="",I22=""),"",MAX(0,I22-H22-1)) | K22: =IF(J22="","",ROUND(N(IFERROR(INDEX('Mein Haus'!$G$45:$G$104,A22),0))*12/365*J22,2)) | L22: =IF(E22="","",E22+7) | N22: =IF(E22="","",E22) | P22: =IF(H22="","",WORKDAY(H22,-10,Einstellungen!$D$5:$D$34)) | R22: =IF(H22="","",H22-30) | T22: =IF(H22="","",WORKDAY(H22-1,1,Einstellungen!$D$5:$D$34)) | V22: =IF(T22="","",WORKDAY(T22,2,Einstellungen!$D$5:$D$34)) | X22: =IF(I22="","",I22) | Z22: =IF(T22="","",T22+30) | AB22: =IF(OR(H22="",Nebenkosten!$B$7=""),"",EDATE(Nebenkosten!$B$7,12*MAX(1,ROUNDUP(((YEAR(H22)-YEAR(Nebenkosten!$B$7))*12+MONTH(H22)-MONTH(Nebenkosten!$B$7)+1)/12,0)))) | AD22: =IF(H22="","",EDATE(H22,12)) | AF22: =IF(COUNT(BI22:BR22)=0,"",MIN(BI22:BR22)) | AG22: =IF(AF22="","",AF22-TODAY()) | AH22: =IF(AF22="","",INDEX($BI$7:$BR$7,MATCH(AF22,BI22:BR22,0))) | AI22: =IF(A22="","",IF(B22="","ID ohne Mieter in «Mein Haus»",IF(AND(IFERROR(INDEX('Mein Haus'!$E$45:$E$104,A22),"")<>"",H22<>"",IFERROR(INDEX('Mein Haus'!$E$45:$E$104,A22),"")<>H22),"Mietende in «Mein Haus» weicht ab",IF(D22="Vermieter","Amtliches Formular? Familienwohnung: beide Ehegatten.",IF(D22="Ausserterminlich","Nachmieter zumutbar? Vereinbartes Ende eintragen.",""))))) | AK22: =IF(E22="","",IF(OR(COUNTIF(Einstellungen!$B$5:$B$16,"x")=0,INDEX(Einstellungen!$B$5:$B$16,MONTH(EOMONTH(E22,IF(F22="",3,F22)+0)))="x"),EOMONTH(E22,IF(F22="",3,F22)+0),"")) | AL22: =IF(E22="","",IF(OR(COUNTIF(Einstellungen!$B$5:$B$16,"x")=0,INDEX(Einstellungen!$B$5:$B$16,MONTH(EOMONTH(E22,IF(F22="",3,F22)+1)))="x"),EOMONTH(E22,IF(F22="",3,F22)+1),"")) | AM22: =IF(E22="","",IF(OR(COUNTIF(Einstellungen!$B$5:$B$16,"x")=0,INDEX(Einstellungen!$B$5:$B$16,MONTH(EOMONTH(E22,IF(F22="",3,F22)+2)))="x"),EOMONTH(E22,IF(F22="",3,F22)+2),"")) | AN22: =IF(E22="","",IF(OR(COUNTIF(Einstellungen!$B$5:$B$16,"x")=0,INDEX(Einstellungen!$B$5:$B$16,MONTH(EOMONTH(E22,IF(F22="",3,F22)+3)))="x"),EOMONTH(E22,IF(F22="",3,F22)+3),"")) | AO22: =IF(E22="","",IF(OR(COUNTIF(Einstellungen!$B$5:$B$16,"x")=0,INDEX(Einstellungen!$B$5:$B$16,MONTH(EOMONTH(E22,IF(F22="",3,F22)+4)))="x"),EOMONTH(E22,IF(F22="",3,F22)+4),"")) | AP22: =IF(E22="","",IF(OR(COUNTIF(Einstellungen!$B$5:$B$16,"x")=0,INDEX(Einstellungen!$B$5:$B$16,MONTH(EOMONTH(E22,IF(F22="",3,F22)+5)))="x"),EOMONTH(E22,IF(F22="",3,F22)+5),"")) | AQ22: =IF(E22="","",IF(OR(COUNTIF(Einstellungen!$B$5:$B$16,"x")=0,INDEX(Einstellungen!$B$5:$B$16,MONTH(EOMONTH(E22,IF(F22="",3,F22)+6)))="x"),EOMONTH(E22,IF(F22="",3,F22)+6),"")) | AR22: =IF(E22="","",IF(OR(COUNTIF(Einstellungen!$B$5:$B$16,"x")=0,INDEX(Einstellungen!$B$5:$B$16,MONTH(EOMONTH(E22,IF(F22="",3,F22)+7)))="x"),EOMONTH(E22,IF(F22="",3,F22)+7),"")) | AS22: =IF(E22="","",IF(OR(COUNTIF(Einstellungen!$B$5:$B$16,"x")=0,INDEX(Einstellungen!$B$5:$B$16,MONTH(EOMONTH(E22,IF(F22="",3,F22)+8)))="x"),EOMONTH(E22,IF(F22="",3,F22)+8),"")) | AT22: =IF(E22="","",IF(OR(COUNTIF(Einstellungen!$B$5:$B$16,"x")=0,INDEX(Einstellungen!$B$5:$B$16,MONTH(EOMONTH(E22,IF(F22="",3,F22)+9)))="x"),EOMONTH(E22,IF(F22="",3,F22)+9),"")) | AU22: =IF(E22="","",IF(OR(COUNTIF(Einstellungen!$B$5:$B$16,"x")=0,INDEX(Einstellungen!$B$5:$B$16,MONTH(EOMONTH(E22,IF(F22="",3,F22)+10)))="x"),EOMONTH(E22,IF(F22="",3,F22)+10),"")) | AV22: =IF(E22="","",IF(OR(COUNTIF(Einstellungen!$B$5:$B$16,"x")=0,INDEX(Einstellungen!$B$5:$B$16,MONTH(EOMONTH(E22,IF(F22="",3,F22)+11)))="x"),EOMONTH(E22,IF(F22="",3,F22)+11),"")) | AW22: =IF(E22="","",IF(OR(COUNTIF(Einstellungen!$B$5:$B$16,"x")=0,INDEX(Einstellungen!$B$5:$B$16,MONTH(EOMONTH(E22,IF(F22="",3,F22)+12)))="x"),EOMONTH(E22,IF(F22="",3,F22)+12),"")) | AX22: =IF(E22="","",IF(OR(COUNTIF(Einstellungen!$B$5:$B$16,"x")=0,INDEX(Einstellungen!$B$5:$B$16,MONTH(EOMONTH(E22,IF(F22="",3,F22)+13)))="x"),EOMONTH(E22,IF(F22="",3,F22)+13),"")) | AY22: =IF(E22="","",IF(OR(COUNTIF(Einstellungen!$B$5:$B$16,"x")=0,INDEX(Einstellungen!$B$5:$B$16,MONTH(EOMONTH(E22,IF(F22="",3,F22)+14)))="x"),EOMONTH(E22,IF(F22="",3,F22)+14),"")) | AZ22: =IF(E22="","",IF(OR(COUNTIF(Einstellungen!$B$5:$B$16,"x")=0,INDEX(Einstellungen!$B$5:$B$16,MONTH(EOMONTH(E22,IF(F22="",3,F22)+15)))="x"),EOMONTH(E22,IF(F22="",3,F22)+15),"")) | BA22: =IF(E22="","",IF(OR(COUNTIF(Einstellungen!$B$5:$B$16,"x")=0,INDEX(Einstellungen!$B$5:$B$16,MONTH(EOMONTH(E22,IF(F22="",3,F22)+16)))="x"),EOMONTH(E22,IF(F22="",3,F22)+16),"")) | BB22: =IF(E22="","",IF(OR(COUNTIF(Einstellungen!$B$5:$B$16,"x")=0,INDEX(Einstellungen!$B$5:$B$16,MONTH(EOMONTH(E22,IF(F22="",3,F22)+17)))="x"),EOMONTH(E22,IF(F22="",3,F22)+17),"")) | BC22: =IF(E22="","",IF(OR(COUNTIF(Einstellungen!$B$5:$B$16,"x")=0,INDEX(Einstellungen!$B$5:$B$16,MONTH(EOMONTH(E22,IF(F22="",3,F22)+18)))="x"),EOMONTH(E22,IF(F22="",3,F22)+18),"")) | BD22: =IF(E22="","",IF(OR(COUNTIF(Einstellungen!$B$5:$B$16,"x")=0,INDEX(Einstellungen!$B$5:$B$16,MONTH(EOMONTH(E22,IF(F22="",3,F22)+19)))="x"),EOMONTH(E22,IF(F22="",3,F22)+19),"")) | BE22: =IF(E22="","",IF(OR(COUNTIF(Einstellungen!$B$5:$B$16,"x")=0,INDEX(Einstellungen!$B$5:$B$16,MONTH(EOMONTH(E22,IF(F22="",3,F22)+20)))="x"),EOMONTH(E22,IF(F22="",3,F22)+20),"")) | BF22: =IF(E22="","",IF(OR(COUNTIF(Einstellungen!$B$5:$B$16,"x")=0,INDEX(Einstellungen!$B$5:$B$16,MONTH(EOMONTH(E22,IF(F22="",3,F22)+21)))="x"),EOMONTH(E22,IF(F22="",3,F22)+21),"")) | BG22: =IF(E22="","",IF(OR(COUNTIF(Einstellungen!$B$5:$B$16,"x")=0,INDEX(Einstellungen!$B$5:$B$16,MONTH(EOMONTH(E22,IF(F22="",3,F22)+22)))="x"),EOMONTH(E22,IF(F22="",3,F22)+22),"")) | BH22: =IF(E22="","",IF(OR(COUNTIF(Einstellungen!$B$5:$B$16,"x")=0,INDEX(Einstellungen!$B$5:$B$16,MONTH(EOMONTH(E22,IF(F22="",3,F22)+23)))="x"),EOMONTH(E22,IF(F22="",3,F22)+23),"")) | BI22: =IF(AND(L22<>"",M22=""),L22,"") | BJ22: =IF(AND(N22<>"",O22=""),N22,"") | BK22: =IF(AND(P22<>"",Q22=""),P22,"") | BL22: =IF(AND(R22<>"",S22=""),R22,"") | BM22: =IF(AND(T22<>"",U22=""),T22,"") | BN22: =IF(AND(V22<>"",W22=""),V22,"") | BO22: =IF(AND(X22<>"",Y22=""),X22,"") | BP22: =IF(AND(Z22<>"",AA22=""),Z22,"") | BQ22: =IF(AND(AB22<>"",AC22=""),AB22,"") | BR22: =IF(AND(AD22<>"",AE22=""),AD22,"") | BS22: =IF(AF22="","",AF22+ROW()/100000)
B23: =IF(A23="","",IFERROR(INDEX('Mein Haus'!$C$45:$C$104,A23)&"","")) | C23: =IF(A23="","",IFERROR(INDEX('Mein Haus'!$B$45:$B$104,A23)&"","")) | H23: =IF(G23<>"",G23,IF(E23="","",IF(COUNT(AK23:BH23)=0,"",MIN(AK23:BH23)))) | J23: =IF(OR(H23="",I23=""),"",MAX(0,I23-H23-1)) | K23: =IF(J23="","",ROUND(N(IFERROR(INDEX('Mein Haus'!$G$45:$G$104,A23),0))*12/365*J23,2)) | L23: =IF(E23="","",E23+7) | N23: =IF(E23="","",E23) | P23: =IF(H23="","",WORKDAY(H23,-10,Einstellungen!$D$5:$D$34)) | R23: =IF(H23="","",H23-30) | T23: =IF(H23="","",WORKDAY(H23-1,1,Einstellungen!$D$5:$D$34)) | V23: =IF(T23="","",WORKDAY(T23,2,Einstellungen!$D$5:$D$34)) | X23: =IF(I23="","",I23) | Z23: =IF(T23="","",T23+30) | AB23: =IF(OR(H23="",Nebenkosten!$B$7=""),"",EDATE(Nebenkosten!$B$7,12*MAX(1,ROUNDUP(((YEAR(H23)-YEAR(Nebenkosten!$B$7))*12+MONTH(H23)-MONTH(Nebenkosten!$B$7)+1)/12,0)))) | AD23: =IF(H23="","",EDATE(H23,12)) | AF23: =IF(COUNT(BI23:BR23)=0,"",MIN(BI23:BR23)) | AG23: =IF(AF23="","",AF23-TODAY()) | AH23: =IF(AF23="","",INDEX($BI$7:$BR$7,MATCH(AF23,BI23:BR23,0))) | AI23: =IF(A23="","",IF(B23="","ID ohne Mieter in «Mein Haus»",IF(AND(IFERROR(INDEX('Mein Haus'!$E$45:$E$104,A23),"")<>"",H23<>"",IFERROR(INDEX('Mein Haus'!$E$45:$E$104,A23),"")<>H23),"Mietende in «Mein Haus» weicht ab",IF(D23="Vermieter","Amtliches Formular? Familienwohnung: beide Ehegatten.",IF(D23="Ausserterminlich","Nachmieter zumutbar? Vereinbartes Ende eintragen.",""))))) | AK23: =IF(E23="","",IF(OR(COUNTIF(Einstellungen!$B$5:$B$16,"x")=0,INDEX(Einstellungen!$B$5:$B$16,MONTH(EOMONTH(E23,IF(F23="",3,F23)+0)))="x"),EOMONTH(E23,IF(F23="",3,F23)+0),"")) | AL23: =IF(E23="","",IF(OR(COUNTIF(Einstellungen!$B$5:$B$16,"x")=0,INDEX(Einstellungen!$B$5:$B$16,MONTH(EOMONTH(E23,IF(F23="",3,F23)+1)))="x"),EOMONTH(E23,IF(F23="",3,F23)+1),"")) | AM23: =IF(E23="","",IF(OR(COUNTIF(Einstellungen!$B$5:$B$16,"x")=0,INDEX(Einstellungen!$B$5:$B$16,MONTH(EOMONTH(E23,IF(F23="",3,F23)+2)))="x"),EOMONTH(E23,IF(F23="",3,F23)+2),"")) | AN23: =IF(E23="","",IF(OR(COUNTIF(Einstellungen!$B$5:$B$16,"x")=0,INDEX(Einstellungen!$B$5:$B$16,MONTH(EOMONTH(E23,IF(F23="",3,F23)+3)))="x"),EOMONTH(E23,IF(F23="",3,F23)+3),"")) | AO23: =IF(E23="","",IF(OR(COUNTIF(Einstellungen!$B$5:$B$16,"x")=0,INDEX(Einstellungen!$B$5:$B$16,MONTH(EOMONTH(E23,IF(F23="",3,F23)+4)))="x"),EOMONTH(E23,IF(F23="",3,F23)+4),"")) | AP23: =IF(E23="","",IF(OR(COUNTIF(Einstellungen!$B$5:$B$16,"x")=0,INDEX(Einstellungen!$B$5:$B$16,MONTH(EOMONTH(E23,IF(F23="",3,F23)+5)))="x"),EOMONTH(E23,IF(F23="",3,F23)+5),"")) | AQ23: =IF(E23="","",IF(OR(COUNTIF(Einstellungen!$B$5:$B$16,"x")=0,INDEX(Einstellungen!$B$5:$B$16,MONTH(EOMONTH(E23,IF(F23="",3,F23)+6)))="x"),EOMONTH(E23,IF(F23="",3,F23)+6),"")) | AR23: =IF(E23="","",IF(OR(COUNTIF(Einstellungen!$B$5:$B$16,"x")=0,INDEX(Einstellungen!$B$5:$B$16,MONTH(EOMONTH(E23,IF(F23="",3,F23)+7)))="x"),EOMONTH(E23,IF(F23="",3,F23)+7),"")) | AS23: =IF(E23="","",IF(OR(COUNTIF(Einstellungen!$B$5:$B$16,"x")=0,INDEX(Einstellungen!$B$5:$B$16,MONTH(EOMONTH(E23,IF(F23="",3,F23)+8)))="x"),EOMONTH(E23,IF(F23="",3,F23)+8),"")) | AT23: =IF(E23="","",IF(OR(COUNTIF(Einstellungen!$B$5:$B$16,"x")=0,INDEX(Einstellungen!$B$5:$B$16,MONTH(EOMONTH(E23,IF(F23="",3,F23)+9)))="x"),EOMONTH(E23,IF(F23="",3,F23)+9),"")) | AU23: =IF(E23="","",IF(OR(COUNTIF(Einstellungen!$B$5:$B$16,"x")=0,INDEX(Einstellungen!$B$5:$B$16,MONTH(EOMONTH(E23,IF(F23="",3,F23)+10)))="x"),EOMONTH(E23,IF(F23="",3,F23)+10),"")) | AV23: =IF(E23="","",IF(OR(COUNTIF(Einstellungen!$B$5:$B$16,"x")=0,INDEX(Einstellungen!$B$5:$B$16,MONTH(EOMONTH(E23,IF(F23="",3,F23)+11)))="x"),EOMONTH(E23,IF(F23="",3,F23)+11),"")) | AW23: =IF(E23="","",IF(OR(COUNTIF(Einstellungen!$B$5:$B$16,"x")=0,INDEX(Einstellungen!$B$5:$B$16,MONTH(EOMONTH(E23,IF(F23="",3,F23)+12)))="x"),EOMONTH(E23,IF(F23="",3,F23)+12),"")) | AX23: =IF(E23="","",IF(OR(COUNTIF(Einstellungen!$B$5:$B$16,"x")=0,INDEX(Einstellungen!$B$5:$B$16,MONTH(EOMONTH(E23,IF(F23="",3,F23)+13)))="x"),EOMONTH(E23,IF(F23="",3,F23)+13),"")) | AY23: =IF(E23="","",IF(OR(COUNTIF(Einstellungen!$B$5:$B$16,"x")=0,INDEX(Einstellungen!$B$5:$B$16,MONTH(EOMONTH(E23,IF(F23="",3,F23)+14)))="x"),EOMONTH(E23,IF(F23="",3,F23)+14),"")) | AZ23: =IF(E23="","",IF(OR(COUNTIF(Einstellungen!$B$5:$B$16,"x")=0,INDEX(Einstellungen!$B$5:$B$16,MONTH(EOMONTH(E23,IF(F23="",3,F23)+15)))="x"),EOMONTH(E23,IF(F23="",3,F23)+15),"")) | BA23: =IF(E23="","",IF(OR(COUNTIF(Einstellungen!$B$5:$B$16,"x")=0,INDEX(Einstellungen!$B$5:$B$16,MONTH(EOMONTH(E23,IF(F23="",3,F23)+16)))="x"),EOMONTH(E23,IF(F23="",3,F23)+16),"")) | BB23: =IF(E23="","",IF(OR(COUNTIF(Einstellungen!$B$5:$B$16,"x")=0,INDEX(Einstellungen!$B$5:$B$16,MONTH(EOMONTH(E23,IF(F23="",3,F23)+17)))="x"),EOMONTH(E23,IF(F23="",3,F23)+17),"")) | BC23: =IF(E23="","",IF(OR(COUNTIF(Einstellungen!$B$5:$B$16,"x")=0,INDEX(Einstellungen!$B$5:$B$16,MONTH(EOMONTH(E23,IF(F23="",3,F23)+18)))="x"),EOMONTH(E23,IF(F23="",3,F23)+18),"")) | BD23: =IF(E23="","",IF(OR(COUNTIF(Einstellungen!$B$5:$B$16,"x")=0,INDEX(Einstellungen!$B$5:$B$16,MONTH(EOMONTH(E23,IF(F23="",3,F23)+19)))="x"),EOMONTH(E23,IF(F23="",3,F23)+19),"")) | BE23: =IF(E23="","",IF(OR(COUNTIF(Einstellungen!$B$5:$B$16,"x")=0,INDEX(Einstellungen!$B$5:$B$16,MONTH(EOMONTH(E23,IF(F23="",3,F23)+20)))="x"),EOMONTH(E23,IF(F23="",3,F23)+20),"")) | BF23: =IF(E23="","",IF(OR(COUNTIF(Einstellungen!$B$5:$B$16,"x")=0,INDEX(Einstellungen!$B$5:$B$16,MONTH(EOMONTH(E23,IF(F23="",3,F23)+21)))="x"),EOMONTH(E23,IF(F23="",3,F23)+21),"")) | BG23: =IF(E23="","",IF(OR(COUNTIF(Einstellungen!$B$5:$B$16,"x")=0,INDEX(Einstellungen!$B$5:$B$16,MONTH(EOMONTH(E23,IF(F23="",3,F23)+22)))="x"),EOMONTH(E23,IF(F23="",3,F23)+22),"")) | BH23: =IF(E23="","",IF(OR(COUNTIF(Einstellungen!$B$5:$B$16,"x")=0,INDEX(Einstellungen!$B$5:$B$16,MONTH(EOMONTH(E23,IF(F23="",3,F23)+23)))="x"),EOMONTH(E23,IF(F23="",3,F23)+23),"")) | BI23: =IF(AND(L23<>"",M23=""),L23,"") | BJ23: =IF(AND(N23<>"",O23=""),N23,"") | BK23: =IF(AND(P23<>"",Q23=""),P23,"") | BL23: =IF(AND(R23<>"",S23=""),R23,"") | BM23: =IF(AND(T23<>"",U23=""),T23,"") | BN23: =IF(AND(V23<>"",W23=""),V23,"") | BO23: =IF(AND(X23<>"",Y23=""),X23,"") | BP23: =IF(AND(Z23<>"",AA23=""),Z23,"") | BQ23: =IF(AND(AB23<>"",AC23=""),AB23,"") | BR23: =IF(AND(AD23<>"",AE23=""),AD23,"") | BS23: =IF(AF23="","",AF23+ROW()/100000)
... B28: =IF(A28="","",IFERROR(INDEX('Mein Haus'!$C$45:$C$104,A28)&"","")) | C28: =IF(A28="","",IFERROR(INDEX('Mein Haus'!$B$45:$B$104,A28)&"","")) | H28: =IF(G28<>"",G28,IF(E28="","",IF(COUNT(AK28:BH28)=0,"",MIN(AK28:BH28)))) | J28: =IF(OR(H28="",I28=""),"",MAX(0,I28-H28-1)) | K28: =IF(J28="","",ROUND(N(IFERROR(INDEX('Mein Haus'!$G$45:$G$104,A28),0))*12/365*J28,2)) | L28: =IF(E28="","",E28+7) | N28: =IF(E28="","",E28) | P28: =IF(H28="","",WORKDAY(H28,-10,Einstellungen!$D$5:$D$34)) | R28: =IF(H28="","",H28-30) | T28: =IF(H28="","",WORKDAY(H28-1,1,Einstellungen!$D$5:$D$34)) | V28: =IF(T28="","",WORKDAY(T28,2,Einstellungen!$D$5:$D$34)) | X28: =IF(I28="","",I28) | Z28: =IF(T28="","",T28+30) | AB28: =IF(OR(H28="",Nebenkosten!$B$7=""),"",EDATE(Nebenkosten!$B$7,12*MAX(1,ROUNDUP(((YEAR(H28)-YEAR(Nebenkosten!$B$7))*12+MONTH(H28)-MONTH(Nebenkosten!$B$7)+1)/12,0)))) | AD28: =IF(H28="","",EDATE(H28,12)) | AF28: =IF(COUNT(BI28:BR28)=0,"",MIN(BI28:BR28)) | AG28: =IF(AF28="","",AF28-TODAY()) | AH28: =IF(AF28="","",INDEX($BI$7:$BR$7,MATCH(AF28,BI28:BR28,0))) | AI28: =IF(A28="","",IF(B28="","ID ohne Mieter in «Mein Haus»",IF(AND(IFERROR(INDEX('Mein Haus'!$E$45:$E$104,A28),"")<>"",H28<>"",IFERROR(INDEX('Mein Haus'!$E$45:$E$104,A28),"")<>H28),"Mietende in «Mein Haus» weicht ab",IF(D28="Vermieter","Amtliches Formular? Familienwohnung: beide Ehegatten.",IF(D28="Ausserterminlich","Nachmieter zumutbar? Vereinbartes Ende eintragen.",""))))) | AK28: =IF(E28="","",IF(OR(COUNTIF(Einstellungen!$B$5:$B$16,"x")=0,INDEX(Einstellungen!$B$5:$B$16,MONTH(EOMONTH(E28,IF(F28="",3,F28)+0)))="x"),EOMONTH(E28,IF(F28="",3,F28)+0),"")) | AL28: =IF(E28="","",IF(OR(COUNTIF(Einstellungen!$B$5:$B$16,"x")=0,INDEX(Einstellungen!$B$5:$B$16,MONTH(EOMONTH(E28,IF(F28="",3,F28)+1)))="x"),EOMONTH(E28,IF(F28="",3,F28)+1),"")) | AM28: =IF(E28="","",IF(OR(COUNTIF(Einstellungen!$B$5:$B$16,"x")=0,INDEX(Einstellungen!$B$5:$B$16,MONTH(EOMONTH(E28,IF(F28="",3,F28)+2)))="x"),EOMONTH(E28,IF(F28="",3,F28)+2),"")) | AN28: =IF(E28="","",IF(OR(COUNTIF(Einstellungen!$B$5:$B$16,"x")=0,INDEX(Einstellungen!$B$5:$B$16,MONTH(EOMONTH(E28,IF(F28="",3,F28)+3)))="x"),EOMONTH(E28,IF(F28="",3,F28)+3),"")) | AO28: =IF(E28="","",IF(OR(COUNTIF(Einstellungen!$B$5:$B$16,"x")=0,INDEX(Einstellungen!$B$5:$B$16,MONTH(EOMONTH(E28,IF(F28="",3,F28)+4)))="x"),EOMONTH(E28,IF(F28="",3,F28)+4),"")) | AP28: =IF(E28="","",IF(OR(COUNTIF(Einstellungen!$B$5:$B$16,"x")=0,INDEX(Einstellungen!$B$5:$B$16,MONTH(EOMONTH(E28,IF(F28="",3,F28)+5)))="x"),EOMONTH(E28,IF(F28="",3,F28)+5),"")) | AQ28: =IF(E28="","",IF(OR(COUNTIF(Einstellungen!$B$5:$B$16,"x")=0,INDEX(Einstellungen!$B$5:$B$16,MONTH(EOMONTH(E28,IF(F28="",3,F28)+6)))="x"),EOMONTH(E28,IF(F28="",3,F28)+6),"")) | AR28: =IF(E28="","",IF(OR(COUNTIF(Einstellungen!$B$5:$B$16,"x")=0,INDEX(Einstellungen!$B$5:$B$16,MONTH(EOMONTH(E28,IF(F28="",3,F28)+7)))="x"),EOMONTH(E28,IF(F28="",3,F28)+7),"")) | AS28: =IF(E28="","",IF(OR(COUNTIF(Einstellungen!$B$5:$B$16,"x")=0,INDEX(Einstellungen!$B$5:$B$16,MONTH(EOMONTH(E28,IF(F28="",3,F28)+8)))="x"),EOMONTH(E28,IF(F28="",3,F28)+8),"")) | AT28: =IF(E28="","",IF(OR(COUNTIF(Einstellungen!$B$5:$B$16,"x")=0,INDEX(Einstellungen!$B$5:$B$16,MONTH(EOMONTH(E28,IF(F28="",3,F28)+9)))="x"),EOMONTH(E28,IF(F28="",3,F28)+9),"")) | AU28: =IF(E28="","",IF(OR(COUNTIF(Einstellungen!$B$5:$B$16,"x")=0,INDEX(Einstellungen!$B$5:$B$16,MONTH(EOMONTH(E28,IF(F28="",3,F28)+10)))="x"),EOMONTH(E28,IF(F28="",3,F28)+10),"")) | AV28: =IF(E28="","",IF(OR(COUNTIF(Einstellungen!$B$5:$B$16,"x")=0,INDEX(Einstellungen!$B$5:$B$16,MONTH(EOMONTH(E28,IF(F28="",3,F28)+11)))="x"),EOMONTH(E28,IF(F28="",3,F28)+11),"")) | AW28: =IF(E28="","",IF(OR(COUNTIF(Einstellungen!$B$5:$B$16,"x")=0,INDEX(Einstellungen!$B$5:$B$16,MONTH(EOMONTH(E28,IF(F28="",3,F28)+12)))="x"),EOMONTH(E28,IF(F28="",3,F28)+12),"")) | AX28: =IF(E28="","",IF(OR(COUNTIF(Einstellungen!$B$5:$B$16,"x")=0,INDEX(Einstellungen!$B$5:$B$16,MONTH(EOMONTH(E28,IF(F28="",3,F28)+13)))="x"),EOMONTH(E28,IF(F28="",3,F28)+13),"")) | AY28: =IF(E28="","",IF(OR(COUNTIF(Einstellungen!$B$5:$B$16,"x")=0,INDEX(Einstellungen!$B$5:$B$16,MONTH(EOMONTH(E28,IF(F28="",3,F28)+14)))="x"),EOMONTH(E28,IF(F28="",3,F28)+14),"")) | AZ28: =IF(E28="","",IF(OR(COUNTIF(Einstellungen!$B$5:$B$16,"x")=0,INDEX(Einstellungen!$B$5:$B$16,MONTH(EOMONTH(E28,IF(F28="",3,F28)+15)))="x"),EOMONTH(E28,IF(F28="",3,F28)+15),"")) | BA28: =IF(E28="","",IF(OR(COUNTIF(Einstellungen!$B$5:$B$16,"x")=0,INDEX(Einstellungen!$B$5:$B$16,MONTH(EOMONTH(E28,IF(F28="",3,F28)+16)))="x"),EOMONTH(E28,IF(F28="",3,F28)+16),"")) | BB28: =IF(E28="","",IF(OR(COUNTIF(Einstellungen!$B$5:$B$16,"x")=0,INDEX(Einstellungen!$B$5:$B$16,MONTH(EOMONTH(E28,IF(F28="",3,F28)+17)))="x"),EOMONTH(E28,IF(F28="",3,F28)+17),"")) | BC28: =IF(E28="","",IF(OR(COUNTIF(Einstellungen!$B$5:$B$16,"x")=0,INDEX(Einstellungen!$B$5:$B$16,MONTH(EOMONTH(E28,IF(F28="",3,F28)+18)))="x"),EOMONTH(E28,IF(F28="",3,F28)+18),"")) | BD28: =IF(E28="","",IF(OR(COUNTIF(Einstellungen!$B$5:$B$16,"x")=0,INDEX(Einstellungen!$B$5:$B$16,MONTH(EOMONTH(E28,IF(F28="",3,F28)+19)))="x"),EOMONTH(E28,IF(F28="",3,F28)+19),"")) | BE28: =IF(E28="","",IF(OR(COUNTIF(Einstellungen!$B$5:$B$16,"x")=0,INDEX(Einstellungen!$B$5:$B$16,MONTH(EOMONTH(E28,IF(F28="",3,F28)+20)))="x"),EOMONTH(E28,IF(F28="",3,F28)+20),"")) | BF28: =IF(E28="","",IF(OR(COUNTIF(Einstellungen!$B$5:$B$16,"x")=0,INDEX(Einstellungen!$B$5:$B$16,MONTH(EOMONTH(E28,IF(F28="",3,F28)+21)))="x"),EOMONTH(E28,IF(F28="",3,F28)+21),"")) | BG28: =IF(E28="","",IF(OR(COUNTIF(Einstellungen!$B$5:$B$16,"x")=0,INDEX(Einstellungen!$B$5:$B$16,MONTH(EOMONTH(E28,IF(F28="",3,F28)+22)))="x"),EOMONTH(E28,IF(F28="",3,F28)+22),"")) | BH28: =IF(E28="","",IF(OR(COUNTIF(Einstellungen!$B$5:$B$16,"x")=0,INDEX(Einstellungen!$B$5:$B$16,MONTH(EOMONTH(E28,IF(F28="",3,F28)+23)))="x"),EOMONTH(E28,IF(F28="",3,F28)+23),"")) | BI28: =IF(AND(L28<>"",M28=""),L28,"") | BJ28: =IF(AND(N28<>"",O28=""),N28,"") | BK28: =IF(AND(P28<>"",Q28=""),P28,"") | BL28: =IF(AND(R28<>"",S28=""),R28,"") | BM28: =IF(AND(T28<>"",U28=""),T28,"") | BN28: =IF(AND(V28<>"",W28=""),V28,"") | BO28: =IF(AND(X28<>"",Y28=""),X28,"") | BP28: =IF(AND(Z28<>"",AA28=""),Z28,"") | BQ28: =IF(AND(AB28<>"",AC28=""),AB28,"") | BR28: =IF(AND(AD28<>"",AE28=""),AD28,"") | BS28: =IF(AF28="","",AF28+ROW()/100000)

Sheet Checkliste
A1: Checkliste Mieterwechsel | F1: Zeile im Blatt «Mieterwechsel» (wird nicht gedruckt):
F2: 1
A3: Liegenschaft | B3: ='Mein Haus'!B4
A4: Mieter | B4: =INDEX(Mieterwechsel!$B$9:$B$28,$F$2)&""
A5: Einheit | B5: =INDEX(Mieterwechsel!$C$9:$C$28,$F$2)&""
A6: Ende Mietverhältnis | B6: =IF(INDEX(Mieterwechsel!$H$9:$H$28,$F$2)="","",INDEX(Mieterwechsel!$H$9:$H$28,$F$2))
A7: Neuer Mieter ab | B7: =IF(INDEX(Mieterwechsel!$I$9:$I$28,$F$2)="","",INDEX(Mieterwechsel!$I$9:$I$28,$F$2))
A9: Schritt | B9: Datum | C9: Status | D9: Was zu tun ist
A10: 1. Kündigung schriftlich bestätigen | B10: =IF(INDEX(Mieterwechsel!$L$9:$L$28,$F$2)="","",INDEX(Mieterwechsel!$L$9:$L$28,$F$2)) | C10: =IF(INDEX(Mieterwechsel!$M$9:$M$28,$F$2)="x","erledigt",IF(INDEX(Mieterwechsel!$L$9:$L$28,$F$2)="","–",IF(INDEX(Mieterwechsel!$L$9:$L$28,$F$2)<TODAY(),"überfällig","offen"))) | D10: Eingang bestätigen; bei Mieterkündigung Form und Termin prüfen.
A11: 2. Nachmieter suchen / Inserat | B11: =IF(INDEX(Mieterwechsel!$N$9:$N$28,$F$2)="","",INDEX(Mieterwechsel!$N$9:$N$28,$F$2)) | C11: =IF(INDEX(Mieterwechsel!$O$9:$O$28,$F$2)="x","erledigt",IF(INDEX(Mieterwechsel!$N$9:$N$28,$F$2)="","–",IF(INDEX(Mieterwechsel!$N$9:$N$28,$F$2)<TODAY(),"überfällig","offen"))) | D11: Inserat schalten, Besichtigungen planen. Bei ausserterminlicher Kündigung: Nachmieter prüfen (Art. 264 OR).
A12: 3. Vorabnahme | B12: =IF(INDEX(Mieterwechsel!$P$9:$P$28,$F$2)="","",INDEX(Mieterwechsel!$P$9:$P$28,$F$2)) | C12: =IF(INDEX(Mieterwechsel!$Q$9:$Q$28,$F$2)="x","erledigt",IF(INDEX(Mieterwechsel!$P$9:$P$28,$F$2)="","–",IF(INDEX(Mieterwechsel!$P$9:$P$28,$F$2)<TODAY(),"überfällig","offen"))) | D12: Wohnung mit dem Mieter begehen, notwendige Arbeiten absprechen.
A13: 4. Neuen Mietvertrag abschliessen | B13: =IF(INDEX(Mieterwechsel!$R$9:$R$28,$F$2)="","",INDEX(Mieterwechsel!$R$9:$R$28,$F$2)) | C13: =IF(INDEX(Mieterwechsel!$S$9:$S$28,$F$2)="x","erledigt",IF(INDEX(Mieterwechsel!$R$9:$R$28,$F$2)="","–",IF(INDEX(Mieterwechsel!$R$9:$R$28,$F$2)<TODAY(),"überfällig","offen"))) | D13: Sollfrist 30 Tage vor Mietende, damit kein Leerstand entsteht.
A14: 5. Abnahme · Protokoll · Zähler · Schlüssel | B14: =IF(INDEX(Mieterwechsel!$T$9:$T$28,$F$2)="","",INDEX(Mieterwechsel!$T$9:$T$28,$F$2)) | C14: =IF(INDEX(Mieterwechsel!$U$9:$U$28,$F$2)="x","erledigt",IF(INDEX(Mieterwechsel!$T$9:$T$28,$F$2)="","–",IF(INDEX(Mieterwechsel!$T$9:$T$28,$F$2)<TODAY(),"überfällig","offen"))) | D14: Blatt «Rückgabe»: Zählerstände, Schlüssel und Mängel erfassen, «Protokoll» drucken und unterschreiben.
A15: 6. Mängelrüge schriftlich | B15: =IF(INDEX(Mieterwechsel!$V$9:$V$28,$F$2)="","",INDEX(Mieterwechsel!$V$9:$V$28,$F$2)) | C15: =IF(INDEX(Mieterwechsel!$W$9:$W$28,$F$2)="x","erledigt",IF(INDEX(Mieterwechsel!$V$9:$V$28,$F$2)="","–",IF(INDEX(Mieterwechsel!$V$9:$V$28,$F$2)<TODAY(),"überfällig","offen"))) | D15: Sofort nach der Abnahme rügen (Art. 267a OR), sonst verwirkt.
A16: 7. Übergabe an Neumieter | B16: =IF(INDEX(Mieterwechsel!$X$9:$X$28,$F$2)="","",INDEX(Mieterwechsel!$X$9:$X$28,$F$2)) | C16: =IF(INDEX(Mieterwechsel!$Y$9:$Y$28,$F$2)="x","erledigt",IF(INDEX(Mieterwechsel!$X$9:$X$28,$F$2)="","–",IF(INDEX(Mieterwechsel!$X$9:$X$28,$F$2)<TODAY(),"überfällig","offen"))) | D16: Mit Protokoll übergeben; Neumieter kann das Rückgabeprotokoll des Vormieters verlangen (Art. 256a OR).
A17: 8. Kaution abrechnen | B17: =IF(INDEX(Mieterwechsel!$Z$9:$Z$28,$F$2)="","",INDEX(Mieterwechsel!$Z$9:$Z$28,$F$2)) | C17: =IF(INDEX(Mieterwechsel!$AA$9:$AA$28,$F$2)="x","erledigt",IF(INDEX(Mieterwechsel!$Z$9:$Z$28,$F$2)="","–",IF(INDEX(Mieterwechsel!$Z$9:$Z$28,$F$2)<TODAY(),"überfällig","offen"))) | D17: Blatt «Kautionsabrechnung» und «Freigabe Kaution».
A18: 9. Nebenkosten-Schlussabrechnung | B18: =IF(INDEX(Mieterwechsel!$AB$9:$AB$28,$F$2)="","",INDEX(Mieterwechsel!$AB$9:$AB$28,$F$2)) | C18: =IF(INDEX(Mieterwechsel!$AC$9:$AC$28,$F$2)="x","erledigt",IF(INDEX(Mieterwechsel!$AB$9:$AB$28,$F$2)="","–",IF(INDEX(Mieterwechsel!$AB$9:$AB$28,$F$2)<TODAY(),"überfällig","offen"))) | D18: Nach Ende der Abrechnungsperiode, Blatt «Nebenkosten».
A19: 10. Kautionsfrist (1 Jahr nach Mietende) | B19: =IF(INDEX(Mieterwechsel!$AD$9:$AD$28,$F$2)="","",INDEX(Mieterwechsel!$AD$9:$AD$28,$F$2)) | C19: =IF(INDEX(Mieterwechsel!$AE$9:$AE$28,$F$2)="x","erledigt",IF(INDEX(Mieterwechsel!$AD$9:$AD$28,$F$2)="","–",IF(INDEX(Mieterwechsel!$AD$9:$AD$28,$F$2)<TODAY(),"überfällig","offen"))) | D19: Ohne geltend gemachten Anspruch kann der Mieter die Kaution allein herausverlangen (Art. 257e OR).

Sheet Rückgabe
A1: Wohnungsrückgabe: Protokoll, Schaden & Kaution
H2: START: Pro Auszug eine Zeile «Fälle»; Mängel unten mit derselben ID. Lebensdauer aus der paritätischen Tabelle HEV/MV.
A3: Auszug für Protokoll, Abrechnung und Freigabe: Mietverhältnis-ID | E3: 5 | H3: BERECHNUNG: Mieteranteil = Kosten × (1 − Alter ÷ Lebensdauer); normale Abnutzung und Vorbestehendes = 0. Kaution wird aufgeteilt.
H4: ERGEBNIS: Spalte «An Vermieter» / «An Mieter»; «Prüfen» meldet fehlende Angaben.
H5: AUSGABE: Blätter «Protokoll», «Kautionsabrechnung», «Freigabe Kaution» für die oben gewählte ID.
A7: ID | B7: Mieter | C7: Mietende | D7: Abnahme am | E7: Anwesend | F7: Zähler Strom | G7: Zähler Wasser | H7: Zähler Wärme | I7: Schlüssel erhalten | J7: Kaution | K7: Kautionszins | L7: Ausstehende Mietzinse | M7: NK-Saldo (aus Nebenkosten) | N7: NK-Saldo manuell | O7: Weitere Forderungen | P7: Schäden zulasten Mieter | Q7: Total Forderungen | R7: Kaution inkl. Zins | S7: An Vermieter | T7: An Mieter | U7: Restforderung | V7: Zusätzlich vom Vermieter | W7: Prüfen
A8: 5 | B8: =IF(A8="","",IFERROR(INDEX('Mein Haus'!$C$45:$C$104,A8)&"","")) | C8: =IF(A8="","",IFERROR(IF(INDEX('Mein Haus'!$F$45:$F$104,A8)="","",INDEX('Mein Haus'!$F$45:$F$104,A8)),"")) | D8: 45930 | E8: T. Weber, H. Beispiel | F8: 12873 | I8: 4 von 5 | J8: =IF(A8="","",IFERROR(N(INDEX('Mein Haus'!$I$45:$I$104,A8)),0)) | K8: 9.8 | L8: 0 | M8: =IF(A8="","",IFERROR(INDEX('NK Verteilung'!$BB$5:$BB$64,A8),0)) | O8: 0 | P8: =IF(A8="","",SUMIF($A$32:$A$131,A8,$K$32:$K$131)) | Q8: =IF(A8="","",P8+N(L8)+IF(N8<>"",N8,N(M8))+N(O8)) | R8: =IF(A8="","",N(J8)+N(K8)) | S8: =IF(A8="","",MAX(0,MIN(Q8,R8))) | T8: =IF(A8="","",R8-S8) | U8: =IF(A8="","",MAX(0,Q8-R8)) | V8: =IF(A8="","",MAX(0,-Q8)) | W8: =IF(A8="","",IF(B8="","ID ohne Mieter",IF(C8="","Mietende fehlt",IF(AND(D8<>"",D8-C8>5),"Abnahme > 5 Tage nach Mietende: Rügefrist",""))))
B9: =IF(A9="","",IFERROR(INDEX('Mein Haus'!$C$45:$C$104,A9)&"","")) | C9: =IF(A9="","",IFERROR(IF(INDEX('Mein Haus'!$F$45:$F$104,A9)="","",INDEX('Mein Haus'!$F$45:$F$104,A9)),"")) | J9: =IF(A9="","",IFERROR(N(INDEX('Mein Haus'!$I$45:$I$104,A9)),0)) | M9: =IF(A9="","",IFERROR(INDEX('NK Verteilung'!$BB$5:$BB$64,A9),0)) | P9: =IF(A9="","",SUMIF($A$32:$A$131,A9,$K$32:$K$131)) | Q9: =IF(A9="","",P9+N(L9)+IF(N9<>"",N9,N(M9))+N(O9)) | R9: =IF(A9="","",N(J9)+N(K9)) | S9: =IF(A9="","",MAX(0,MIN(Q9,R9))) | T9: =IF(A9="","",R9-S9) | U9: =IF(A9="","",MAX(0,Q9-R9)) | V9: =IF(A9="","",MAX(0,-Q9)) | W9: =IF(A9="","",IF(B9="","ID ohne Mieter",IF(C9="","Mietende fehlt",IF(AND(D9<>"",D9-C9>5),"Abnahme > 5 Tage nach Mietende: Rügefrist",""))))
B10: =IF(A10="","",IFERROR(INDEX('Mein Haus'!$C$45:$C$104,A10)&"","")) | C10: =IF(A10="","",IFERROR(IF(INDEX('Mein Haus'!$F$45:$F$104,A10)="","",INDEX('Mein Haus'!$F$45:$F$104,A10)),"")) | J10: =IF(A10="","",IFERROR(N(INDEX('Mein Haus'!$I$45:$I$104,A10)),0)) | M10: =IF(A10="","",IFERROR(INDEX('NK Verteilung'!$BB$5:$BB$64,A10),0)) | P10: =IF(A10="","",SUMIF($A$32:$A$131,A10,$K$32:$K$131)) | Q10: =IF(A10="","",P10+N(L10)+IF(N10<>"",N10,N(M10))+N(O10)) | R10: =IF(A10="","",N(J10)+N(K10)) | S10: =IF(A10="","",MAX(0,MIN(Q10,R10))) | T10: =IF(A10="","",R10-S10) | U10: =IF(A10="","",MAX(0,Q10-R10)) | V10: =IF(A10="","",MAX(0,-Q10)) | W10: =IF(A10="","",IF(B10="","ID ohne Mieter",IF(C10="","Mietende fehlt",IF(AND(D10<>"",D10-C10>5),"Abnahme > 5 Tage nach Mietende: Rügefrist",""))))
B11: =IF(A11="","",IFERROR(INDEX('Mein Haus'!$C$45:$C$104,A11)&"","")) | C11: =IF(A11="","",IFERROR(IF(INDEX('Mein Haus'!$F$45:$F$104,A11)="","",INDEX('Mein Haus'!$F$45:$F$104,A11)),"")) | J11: =IF(A11="","",IFERROR(N(INDEX('Mein Haus'!$I$45:$I$104,A11)),0)) | M11: =IF(A11="","",IFERROR(INDEX('NK Verteilung'!$BB$5:$BB$64,A11),0)) | P11: =IF(A11="","",SUMIF($A$32:$A$131,A11,$K$32:$K$131)) | Q11: =IF(A11="","",P11+N(L11)+IF(N11<>"",N11,N(M11))+N(O11)) | R11: =IF(A11="","",N(J11)+N(K11)) | S11: =IF(A11="","",MAX(0,MIN(Q11,R11))) | T11: =IF(A11="","",R11-S11) | U11: =IF(A11="","",MAX(0,Q11-R11)) | V11: =IF(A11="","",MAX(0,-Q11)) | W11: =IF(A11="","",IF(B11="","ID ohne Mieter",IF(C11="","Mietende fehlt",IF(AND(D11<>"",D11-C11>5),"Abnahme > 5 Tage nach Mietende: Rügefrist",""))))
B12: =IF(A12="","",IFERROR(INDEX('Mein Haus'!$C$45:$C$104,A12)&"","")) | C12: =IF(A12="","",IFERROR(IF(INDEX('Mein Haus'!$F$45:$F$104,A12)="","",INDEX('Mein Haus'!$F$45:$F$104,A12)),"")) | J12: =IF(A12="","",IFERROR(N(INDEX('Mein Haus'!$I$45:$I$104,A12)),0)) | M12: =IF(A12="","",IFERROR(INDEX('NK Verteilung'!$BB$5:$BB$64,A12),0)) | P12: =IF(A12="","",SUMIF($A$32:$A$131,A12,$K$32:$K$131)) | Q12: =IF(A12="","",P12+N(L12)+IF(N12<>"",N12,N(M12))+N(O12)) | R12: =IF(A12="","",N(J12)+N(K12)) | S12: =IF(A12="","",MAX(0,MIN(Q12,R12))) | T12: =IF(A12="","",R12-S12) | U12: =IF(A12="","",MAX(0,Q12-R12)) | V12: =IF(A12="","",MAX(0,-Q12)) | W12: =IF(A12="","",IF(B12="","ID ohne Mieter",IF(C12="","Mietende fehlt",IF(AND(D12<>"",D12-C12>5),"Abnahme > 5 Tage nach Mietende: Rügefrist",""))))
B13: =IF(A13="","",IFERROR(INDEX('Mein Haus'!$C$45:$C$104,A13)&"","")) | C13: =IF(A13="","",IFERROR(IF(INDEX('Mein Haus'!$F$45:$F$104,A13)="","",INDEX('Mein Haus'!$F$45:$F$104,A13)),"")) | J13: =IF(A13="","",IFERROR(N(INDEX('Mein Haus'!$I$45:$I$104,A13)),0)) | M13: =IF(A13="","",IFERROR(INDEX('NK Verteilung'!$BB$5:$BB$64,A13),0)) | P13: =IF(A13="","",SUMIF($A$32:$A$131,A13,$K$32:$K$131)) | Q13: =IF(A13="","",P13+N(L13)+IF(N13<>"",N13,N(M13))+N(O13)) | R13: =IF(A13="","",N(J13)+N(K13)) | S13: =IF(A13="","",MAX(0,MIN(Q13,R13))) | T13: =IF(A13="","",R13-S13) | U13: =IF(A13="","",MAX(0,Q13-R13)) | V13: =IF(A13="","",MAX(0,-Q13)) | W13: =IF(A13="","",IF(B13="","ID ohne Mieter",IF(C13="","Mietende fehlt",IF(AND(D13<>"",D13-C13>5),"Abnahme > 5 Tage nach Mietende: Rügefrist",""))))
B14: =IF(A14="","",IFERROR(INDEX('Mein Haus'!$C$45:$C$104,A14)&"","")) | C14: =IF(A14="","",IFERROR(IF(INDEX('Mein Haus'!$F$45:$F$104,A14)="","",INDEX('Mein Haus'!$F$45:$F$104,A14)),"")) | J14: =IF(A14="","",IFERROR(N(INDEX('Mein Haus'!$I$45:$I$104,A14)),0)) | M14: =IF(A14="","",IFERROR(INDEX('NK Verteilung'!$BB$5:$BB$64,A14),0)) | P14: =IF(A14="","",SUMIF($A$32:$A$131,A14,$K$32:$K$131)) | Q14: =IF(A14="","",P14+N(L14)+IF(N14<>"",N14,N(M14))+N(O14)) | R14: =IF(A14="","",N(J14)+N(K14)) | S14: =IF(A14="","",MAX(0,MIN(Q14,R14))) | T14: =IF(A14="","",R14-S14) | U14: =IF(A14="","",MAX(0,Q14-R14)) | V14: =IF(A14="","",MAX(0,-Q14)) | W14: =IF(A14="","",IF(B14="","ID ohne Mieter",IF(C14="","Mietende fehlt",IF(AND(D14<>"",D14-C14>5),"Abnahme > 5 Tage nach Mietende: Rügefrist",""))))
B15: =IF(A15="","",IFERROR(INDEX('Mein Haus'!$C$45:$C$104,A15)&"","")) | C15: =IF(A15="","",IFERROR(IF(INDEX('Mein Haus'!$F$45:$F$104,A15)="","",INDEX('Mein Haus'!$F$45:$F$104,A15)),"")) | J15: =IF(A15="","",IFERROR(N(INDEX('Mein Haus'!$I$45:$I$104,A15)),0)) | M15: =IF(A15="","",IFERROR(INDEX('NK Verteilung'!$BB$5:$BB$64,A15),0)) | P15: =IF(A15="","",SUMIF($A$32:$A$131,A15,$K$32:$K$131)) | Q15: =IF(A15="","",P15+N(L15)+IF(N15<>"",N15,N(M15))+N(O15)) | R15: =IF(A15="","",N(J15)+N(K15)) | S15: =IF(A15="","",MAX(0,MIN(Q15,R15))) | T15: =IF(A15="","",R15-S15) | U15: =IF(A15="","",MAX(0,Q15-R15)) | V15: =IF(A15="","",MAX(0,-Q15)) | W15: =IF(A15="","",IF(B15="","ID ohne Mieter",IF(C15="","Mietende fehlt",IF(AND(D15<>"",D15-C15>5),"Abnahme > 5 Tage nach Mietende: Rügefrist",""))))
B16: =IF(A16="","",IFERROR(INDEX('Mein Haus'!$C$45:$C$104,A16)&"","")) | C16: =IF(A16="","",IFERROR(IF(INDEX('Mein Haus'!$F$45:$F$104,A16)="","",INDEX('Mein Haus'!$F$45:$F$104,A16)),"")) | J16: =IF(A16="","",IFERROR(N(INDEX('Mein Haus'!$I$45:$I$104,A16)),0)) | M16: =IF(A16="","",IFERROR(INDEX('NK Verteilung'!$BB$5:$BB$64,A16),0)) | P16: =IF(A16="","",SUMIF($A$32:$A$131,A16,$K$32:$K$131)) | Q16: =IF(A16="","",P16+N(L16)+IF(N16<>"",N16,N(M16))+N(O16)) | R16: =IF(A16="","",N(J16)+N(K16)) | S16: =IF(A16="","",MAX(0,MIN(Q16,R16))) | T16: =IF(A16="","",R16-S16) | U16: =IF(A16="","",MAX(0,Q16-R16)) | V16: =IF(A16="","",MAX(0,-Q16)) | W16: =IF(A16="","",IF(B16="","ID ohne Mieter",IF(C16="","Mietende fehlt",IF(AND(D16<>"",D16-C16>5),"Abnahme > 5 Tage nach Mietende: Rügefrist",""))))
B17: =IF(A17="","",IFERROR(INDEX('Mein Haus'!$C$45:$C$104,A17)&"","")) | C17: =IF(A17="","",IFERROR(IF(INDEX('Mein Haus'!$F$45:$F$104,A17)="","",INDEX('Mein Haus'!$F$45:$F$104,A17)),"")) | J17: =IF(A17="","",IFERROR(N(INDEX('Mein Haus'!$I$45:$I$104,A17)),0)) | M17: =IF(A17="","",IFERROR(INDEX('NK Verteilung'!$BB$5:$BB$64,A17),0)) | P17: =IF(A17="","",SUMIF($A$32:$A$131,A17,$K$32:$K$131)) | Q17: =IF(A17="","",P17+N(L17)+IF(N17<>"",N17,N(M17))+N(O17)) | R17: =IF(A17="","",N(J17)+N(K17)) | S17: =IF(A17="","",MAX(0,MIN(Q17,R17))) | T17: =IF(A17="","",R17-S17) | U17: =IF(A17="","",MAX(0,Q17-R17)) | V17: =IF(A17="","",MAX(0,-Q17)) | W17: =IF(A17="","",IF(B17="","ID ohne Mieter",IF(C17="","Mietende fehlt",IF(AND(D17<>"",D17-C17>5),"Abnahme > 5 Tage nach Mietende: Rügefrist",""))))
B18: =IF(A18="","",IFERROR(INDEX('Mein Haus'!$C$45:$C$104,A18)&"","")) | C18: =IF(A18="","",IFERROR(IF(INDEX('Mein Haus'!$F$45:$F$104,A18)="","",INDEX('Mein Haus'!$F$45:$F$104,A18)),"")) | J18: =IF(A18="","",IFERROR(N(INDEX('Mein Haus'!$I$45:$I$104,A18)),0)) | M18: =IF(A18="","",IFERROR(INDEX('NK Verteilung'!$BB$5:$BB$64,A18),0)) | P18: =IF(A18="","",SUMIF($A$32:$A$131,A18,$K$32:$K$131)) | Q18: =IF(A18="","",P18+N(L18)+IF(N18<>"",N18,N(M18))+N(O18)) | R18: =IF(A18="","",N(J18)+N(K18)) | S18: =IF(A18="","",MAX(0,MIN(Q18,R18))) | T18: =IF(A18="","",R18-S18) | U18: =IF(A18="","",MAX(0,Q18-R18)) | V18: =IF(A18="","",MAX(0,-Q18)) | W18: =IF(A18="","",IF(B18="","ID ohne Mieter",IF(C18="","Mietende fehlt",IF(AND(D18<>"",D18-C18>5),"Abnahme > 5 Tage nach Mietende: Rügefrist",""))))
B19: =IF(A19="","",IFERROR(INDEX('Mein Haus'!$C$45:$C$104,A19)&"","")) | C19: =IF(A19="","",IFERROR(IF(INDEX('Mein Haus'!$F$45:$F$104,A19)="","",INDEX('Mein Haus'!$F$45:$F$104,A19)),"")) | J19: =IF(A19="","",IFERROR(N(INDEX('Mein Haus'!$I$45:$I$104,A19)),0)) | M19: =IF(A19="","",IFERROR(INDEX('NK Verteilung'!$BB$5:$BB$64,A19),0)) | P19: =IF(A19="","",SUMIF($A$32:$A$131,A19,$K$32:$K$131)) | Q19: =IF(A19="","",P19+N(L19)+IF(N19<>"",N19,N(M19))+N(O19)) | R19: =IF(A19="","",N(J19)+N(K19)) | S19: =IF(A19="","",MAX(0,MIN(Q19,R19))) | T19: =IF(A19="","",R19-S19) | U19: =IF(A19="","",MAX(0,Q19-R19)) | V19: =IF(A19="","",MAX(0,-Q19)) | W19: =IF(A19="","",IF(B19="","ID ohne Mieter",IF(C19="","Mietende fehlt",IF(AND(D19<>"",D19-C19>5),"Abnahme > 5 Tage nach Mietende: Rügefrist",""))))
B20: =IF(A20="","",IFERROR(INDEX('Mein Haus'!$C$45:$C$104,A20)&"","")) | C20: =IF(A20="","",IFERROR(IF(INDEX('Mein Haus'!$F$45:$F$104,A20)="","",INDEX('Mein Haus'!$F$45:$F$104,A20)),"")) | J20: =IF(A20="","",IFERROR(N(INDEX('Mein Haus'!$I$45:$I$104,A20)),0)) | M20: =IF(A20="","",IFERROR(INDEX('NK Verteilung'!$BB$5:$BB$64,A20),0)) | P20: =IF(A20="","",SUMIF($A$32:$A$131,A20,$K$32:$K$131)) | Q20: =IF(A20="","",P20+N(L20)+IF(N20<>"",N20,N(M20))+N(O20)) | R20: =IF(A20="","",N(J20)+N(K20)) | S20: =IF(A20="","",MAX(0,MIN(Q20,R20))) | T20: =IF(A20="","",R20-S20) | U20: =IF(A20="","",MAX(0,Q20-R20)) | V20: =IF(A20="","",MAX(0,-Q20)) | W20: =IF(A20="","",IF(B20="","ID ohne Mieter",IF(C20="","Mietende fehlt",IF(AND(D20<>"",D20-C20>5),"Abnahme > 5 Tage nach Mietende: Rügefrist",""))))
... B27: =IF(A27="","",IFERROR(INDEX('Mein Haus'!$C$45:$C$104,A27)&"","")) | C27: =IF(A27="","",IFERROR(IF(INDEX('Mein Haus'!$F$45:$F$104,A27)="","",INDEX('Mein Haus'!$F$45:$F$104,A27)),"")) | J27: =IF(A27="","",IFERROR(N(INDEX('Mein Haus'!$I$45:$I$104,A27)),0)) | M27: =IF(A27="","",IFERROR(INDEX('NK Verteilung'!$BB$5:$BB$64,A27),0)) | P27: =IF(A27="","",SUMIF($A$32:$A$131,A27,$K$32:$K$131)) | Q27: =IF(A27="","",P27+N(L27)+IF(N27<>"",N27,N(M27))+N(O27)) | R27: =IF(A27="","",N(J27)+N(K27)) | S27: =IF(A27="","",MAX(0,MIN(Q27,R27))) | T27: =IF(A27="","",R27-S27) | U27: =IF(A27="","",MAX(0,Q27-R27)) | V27: =IF(A27="","",MAX(0,-Q27)) | W27: =IF(A27="","",IF(B27="","ID ohne Mieter",IF(C27="","Mietende fehlt",IF(AND(D27<>"",D27-C27>5),"Abnahme > 5 Tage nach Mietende: Rügefrist",""))))
A30: Mängel (Abnahmeprotokoll)
A31: ID | B31: Raum | C31: Bauteil | D31: Mangel / Zustand | E31: Ursache | F31: Kosten laut Offerte | G31: Einbau / letzte Erneuerung | H31: Lebensdauer Jahre | I31: Alter bei Mietende | J31: Restwert | K31: Zulasten Mieter | L31: Prüfen | M31: Nr. im Ausdruck | N31: Mietende
A32: 5 | B32: Wohnzimmer | C32: Wandanstrich | D32: Starke Nikotinverfärbung | E32: Mieter | F32: 1800 | G32: 43556 | H32: 8 | I32: =IF(OR(G32="",N32=""),"",(N32-G32)/365.25) | J32: =IF(F32="","",IF(E32<>"Mieter",0,IF(H32="",1,IF(OR(G32="",N32=""),"",MAX(0,1-I32/H32))))) | K32: =IF(OR(J32="",F32=""),0,ROUND(F32*J32*20,0)/20) | L32: =IF(AND(A32="",B32="",F32=""),"",IF(A32="","ID fehlt",IF(F32="","",IF(F32<0,"Kosten negativ",IF(E32="","Ursache wählen",IF(N32="","Mietende fehlt",IF(AND(G32<>"",G32>N32),"Einbau nach Mietende",IF(AND(E32="Mieter",H32<>"",G32=""),"Einbaudatum fehlt",IF(AND(E32="Mieter",H32<>"",H32<=0),"Lebensdauer ungültig",""))))))))) | M32: =IF(AND(A32<>"",A32=$E$3),COUNTIF($A$32:A32,$E$3),"") | N32: =IF(A32="","",IFERROR(IF(INDEX('Mein Haus'!$F$45:$F$104,A32)="","",INDEX('Mein Haus'!$F$45:$F$104,A32)),""))
A33: 5 | B33: Küche | C33: Backofen | D33: Türglas gesprungen | E33: Mieter | F33: 950 | G33: 41791 | H33: 15 | I33: =IF(OR(G33="",N33=""),"",(N33-G33)/365.25) | J33: =IF(F33="","",IF(E33<>"Mieter",0,IF(H33="",1,IF(OR(G33="",N33=""),"",MAX(0,1-I33/H33))))) | K33: =IF(OR(J33="",F33=""),0,ROUND(F33*J33*20,0)/20) | L33: =IF(AND(A33="",B33="",F33=""),"",IF(A33="","ID fehlt",IF(F33="","",IF(F33<0,"Kosten negativ",IF(E33="","Ursache wählen",IF(N33="","Mietende fehlt",IF(AND(G33<>"",G33>N33),"Einbau nach Mietende",IF(AND(E33="Mieter",H33<>"",G33=""),"Einbaudatum fehlt",IF(AND(E33="Mieter",H33<>"",H33<=0),"Lebensdauer ungültig",""))))))))) | M33: =IF(AND(A33<>"",A33=$E$3),COUNTIF($A$32:A33,$E$3),"") | N33: =IF(A33="","",IFERROR(IF(INDEX('Mein Haus'!$F$45:$F$104,A33)="","",INDEX('Mein Haus'!$F$45:$F$104,A33)),""))
A34: 5 | B34: Wohnzimmer | C34: Parkett | D34: Wasserflecken vor Balkontür | E34: Mieter | F34: 2400 | G34: 38353 | H34: 40 | I34: =IF(OR(G34="",N34=""),"",(N34-G34)/365.25) | J34: =IF(F34="","",IF(E34<>"Mieter",0,IF(H34="",1,IF(OR(G34="",N34=""),"",MAX(0,1-I34/H34))))) | K34: =IF(OR(J34="",F34=""),0,ROUND(F34*J34*20,0)/20) | L34: =IF(AND(A34="",B34="",F34=""),"",IF(A34="","ID fehlt",IF(F34="","",IF(F34<0,"Kosten negativ",IF(E34="","Ursache wählen",IF(N34="","Mietende fehlt",IF(AND(G34<>"",G34>N34),"Einbau nach Mietende",IF(AND(E34="Mieter",H34<>"",G34=""),"Einbaudatum fehlt",IF(AND(E34="Mieter",H34<>"",H34<=0),"Lebensdauer ungültig",""))))))))) | M34: =IF(AND(A34<>"",A34=$E$3),COUNTIF($A$32:A34,$E$3),"") | N34: =IF(A34="","",IFERROR(IF(INDEX('Mein Haus'!$F$45:$F$104,A34)="","",INDEX('Mein Haus'!$F$45:$F$104,A34)),""))
A35: 5 | B35: Schlafzimmer | C35: Teppich | D35: Laufspuren | E35: Normale Abnutzung | F35: 1200 | G35: 42430 | H35: 10 | I35: =IF(OR(G35="",N35=""),"",(N35-G35)/365.25) | J35: =IF(F35="","",IF(E35<>"Mieter",0,IF(H35="",1,IF(OR(G35="",N35=""),"",MAX(0,1-I35/H35))))) | K35: =IF(OR(J35="",F35=""),0,ROUND(F35*J35*20,0)/20) | L35: =IF(AND(A35="",B35="",F35=""),"",IF(A35="","ID fehlt",IF(F35="","",IF(F35<0,"Kosten negativ",IF(E35="","Ursache wählen",IF(N35="","Mietende fehlt",IF(AND(G35<>"",G35>N35),"Einbau nach Mietende",IF(AND(E35="Mieter",H35<>"",G35=""),"Einbaudatum fehlt",IF(AND(E35="Mieter",H35<>"",H35<=0),"Lebensdauer ungültig",""))))))))) | M35: =IF(AND(A35<>"",A35=$E$3),COUNTIF($A$32:A35,$E$3),"") | N35: =IF(A35="","",IFERROR(IF(INDEX('Mein Haus'!$F$45:$F$104,A35)="","",INDEX('Mein Haus'!$F$45:$F$104,A35)),""))
A36: 5 | B36: Bad | C36: Spiegelschrank | D36: Kratzer (im Eintrittsprotokoll vermerkt) | E36: Vorbestehend | I36: =IF(OR(G36="",N36=""),"",(N36-G36)/365.25) | J36: =IF(F36="","",IF(E36<>"Mieter",0,IF(H36="",1,IF(OR(G36="",N36=""),"",MAX(0,1-I36/H36))))) | K36: =IF(OR(J36="",F36=""),0,ROUND(F36*J36*20,0)/20) | L36: =IF(AND(A36="",B36="",F36=""),"",IF(A36="","ID fehlt",IF(F36="","",IF(F36<0,"Kosten negativ",IF(E36="","Ursache wählen",IF(N36="","Mietende fehlt",IF(AND(G36<>"",G36>N36),"Einbau nach Mietende",IF(AND(E36="Mieter",H36<>"",G36=""),"Einbaudatum fehlt",IF(AND(E36="Mieter",H36<>"",H36<=0),"Lebensdauer ungültig",""))))))))) | M36: =IF(AND(A36<>"",A36=$E$3),COUNTIF($A$32:A36,$E$3),"") | N36: =IF(A36="","",IFERROR(IF(INDEX('Mein Haus'!$F$45:$F$104,A36)="","",INDEX('Mein Haus'!$F$45:$F$104,A36)),""))
A37: 5 | B37: Eingang | C37: Schlüssel | D37: 1 Wohnungsschlüssel fehlt | E37: Mieter | F37: 180 | I37: =IF(OR(G37="",N37=""),"",(N37-G37)/365.25) | J37: =IF(F37="","",IF(E37<>"Mieter",0,IF(H37="",1,IF(OR(G37="",N37=""),"",MAX(0,1-I37/H37))))) | K37: =IF(OR(J37="",F37=""),0,ROUND(F37*J37*20,0)/20) | L37: =IF(AND(A37="",B37="",F37=""),"",IF(A37="","ID fehlt",IF(F37="","",IF(F37<0,"Kosten negativ",IF(E37="","Ursache wählen",IF(N37="","Mietende fehlt",IF(AND(G37<>"",G37>N37),"Einbau nach Mietende",IF(AND(E37="Mieter",H37<>"",G37=""),"Einbaudatum fehlt",IF(AND(E37="Mieter",H37<>"",H37<=0),"Lebensdauer ungültig",""))))))))) | M37: =IF(AND(A37<>"",A37=$E$3),COUNTIF($A$32:A37,$E$3),"") | N37: =IF(A37="","",IFERROR(IF(INDEX('Mein Haus'!$F$45:$F$104,A37)="","",INDEX('Mein Haus'!$F$45:$F$104,A37)),""))
I38: =IF(OR(G38="",N38=""),"",(N38-G38)/365.25) | J38: =IF(F38="","",IF(E38<>"Mieter",0,IF(H38="",1,IF(OR(G38="",N38=""),"",MAX(0,1-I38/H38))))) | K38: =IF(OR(J38="",F38=""),0,ROUND(F38*J38*20,0)/20) | L38: =IF(AND(A38="",B38="",F38=""),"",IF(A38="","ID fehlt",IF(F38="","",IF(F38<0,"Kosten negativ",IF(E38="","Ursache wählen",IF(N38="","Mietende fehlt",IF(AND(G38<>"",G38>N38),"Einbau nach Mietende",IF(AND(E38="Mieter",H38<>"",G38=""),"Einbaudatum fehlt",IF(AND(E38="Mieter",H38<>"",H38<=0),"Lebensdauer ungültig",""))))))))) | M38: =IF(AND(A38<>"",A38=$E$3),COUNTIF($A$32:A38,$E$3),"") | N38: =IF(A38="","",IFERROR(IF(INDEX('Mein Haus'!$F$45:$F$104,A38)="","",INDEX('Mein Haus'!$F$45:$F$104,A38)),""))
I39: =IF(OR(G39="",N39=""),"",(N39-G39)/365.25) | J39: =IF(F39="","",IF(E39<>"Mieter",0,IF(H39="",1,IF(OR(G39="",N39=""),"",MAX(0,1-I39/H39))))) | K39: =IF(OR(J39="",F39=""),0,ROUND(F39*J39*20,0)/20) | L39: =IF(AND(A39="",B39="",F39=""),"",IF(A39="","ID fehlt",IF(F39="","",IF(F39<0,"Kosten negativ",IF(E39="","Ursache wählen",IF(N39="","Mietende fehlt",IF(AND(G39<>"",G39>N39),"Einbau nach Mietende",IF(AND(E39="Mieter",H39<>"",G39=""),"Einbaudatum fehlt",IF(AND(E39="Mieter",H39<>"",H39<=0),"Lebensdauer ungültig",""))))))))) | M39: =IF(AND(A39<>"",A39=$E$3),COUNTIF($A$32:A39,$E$3),"") | N39: =IF(A39="","",IFERROR(IF(INDEX('Mein Haus'!$F$45:$F$104,A39)="","",INDEX('Mein Haus'!$F$45:$F$104,A39)),""))
I40: =IF(OR(G40="",N40=""),"",(N40-G40)/365.25) | J40: =IF(F40="","",IF(E40<>"Mieter",0,IF(H40="",1,IF(OR(G40="",N40=""),"",MAX(0,1-I40/H40))))) | K40: =IF(OR(J40="",F40=""),0,ROUND(F40*J40*20,0)/20) | L40: =IF(AND(A40="",B40="",F40=""),"",IF(A40="","ID fehlt",IF(F40="","",IF(F40<0,"Kosten negativ",IF(E40="","Ursache wählen",IF(N40="","Mietende fehlt",IF(AND(G40<>"",G40>N40),"Einbau nach Mietende",IF(AND(E40="Mieter",H40<>"",G40=""),"Einbaudatum fehlt",IF(AND(E40="Mieter",H40<>"",H40<=0),"Lebensdauer ungültig",""))))))))) | M40: =IF(AND(A40<>"",A40=$E$3),COUNTIF($A$32:A40,$E$3),"") | N40: =IF(A40="","",IFERROR(IF(INDEX('Mein Haus'!$F$45:$F$104,A40)="","",INDEX('Mein Haus'!$F$45:$F$104,A40)),""))
I41: =IF(OR(G41="",N41=""),"",(N41-G41)/365.25) | J41: =IF(F41="","",IF(E41<>"Mieter",0,IF(H41="",1,IF(OR(G41="",N41=""),"",MAX(0,1-I41/H41))))) | K41: =IF(OR(J41="",F41=""),0,ROUND(F41*J41*20,0)/20) | L41: =IF(AND(A41="",B41="",F41=""),"",IF(A41="","ID fehlt",IF(F41="","",IF(F41<0,"Kosten negativ",IF(E41="","Ursache wählen",IF(N41="","Mietende fehlt",IF(AND(G41<>"",G41>N41),"Einbau nach Mietende",IF(AND(E41="Mieter",H41<>"",G41=""),"Einbaudatum fehlt",IF(AND(E41="Mieter",H41<>"",H41<=0),"Lebensdauer ungültig",""))))))))) | M41: =IF(AND(A41<>"",A41=$E$3),COUNTIF($A$32:A41,$E$3),"") | N41: =IF(A41="","",IFERROR(IF(INDEX('Mein Haus'!$F$45:$F$104,A41)="","",INDEX('Mein Haus'!$F$45:$F$104,A41)),""))
I42: =IF(OR(G42="",N42=""),"",(N42-G42)/365.25) | J42: =IF(F42="","",IF(E42<>"Mieter",0,IF(H42="",1,IF(OR(G42="",N42=""),"",MAX(0,1-I42/H42))))) | K42: =IF(OR(J42="",F42=""),0,ROUND(F42*J42*20,0)/20) | L42: =IF(AND(A42="",B42="",F42=""),"",IF(A42="","ID fehlt",IF(F42="","",IF(F42<0,"Kosten negativ",IF(E42="","Ursache wählen",IF(N42="","Mietende fehlt",IF(AND(G42<>"",G42>N42),"Einbau nach Mietende",IF(AND(E42="Mieter",H42<>"",G42=""),"Einbaudatum fehlt",IF(AND(E42="Mieter",H42<>"",H42<=0),"Lebensdauer ungültig",""))))))))) | M42: =IF(AND(A42<>"",A42=$E$3),COUNTIF($A$32:A42,$E$3),"") | N42: =IF(A42="","",IFERROR(IF(INDEX('Mein Haus'!$F$45:$F$104,A42)="","",INDEX('Mein Haus'!$F$45:$F$104,A42)),""))
I43: =IF(OR(G43="",N43=""),"",(N43-G43)/365.25) | J43: =IF(F43="","",IF(E43<>"Mieter",0,IF(H43="",1,IF(OR(G43="",N43=""),"",MAX(0,1-I43/H43))))) | K43: =IF(OR(J43="",F43=""),0,ROUND(F43*J43*20,0)/20) | L43: =IF(AND(A43="",B43="",F43=""),"",IF(A43="","ID fehlt",IF(F43="","",IF(F43<0,"Kosten negativ",IF(E43="","Ursache wählen",IF(N43="","Mietende fehlt",IF(AND(G43<>"",G43>N43),"Einbau nach Mietende",IF(AND(E43="Mieter",H43<>"",G43=""),"Einbaudatum fehlt",IF(AND(E43="Mieter",H43<>"",H43<=0),"Lebensdauer ungültig",""))))))))) | M43: =IF(AND(A43<>"",A43=$E$3),COUNTIF($A$32:A43,$E$3),"") | N43: =IF(A43="","",IFERROR(IF(INDEX('Mein Haus'!$F$45:$F$104,A43)="","",INDEX('Mein Haus'!$F$45:$F$104,A43)),""))
I44: =IF(OR(G44="",N44=""),"",(N44-G44)/365.25) | J44: =IF(F44="","",IF(E44<>"Mieter",0,IF(H44="",1,IF(OR(G44="",N44=""),"",MAX(0,1-I44/H44))))) | K44: =IF(OR(J44="",F44=""),0,ROUND(F44*J44*20,0)/20) | L44: =IF(AND(A44="",B44="",F44=""),"",IF(A44="","ID fehlt",IF(F44="","",IF(F44<0,"Kosten negativ",IF(E44="","Ursache wählen",IF(N44="","Mietende fehlt",IF(AND(G44<>"",G44>N44),"Einbau nach Mietende",IF(AND(E44="Mieter",H44<>"",G44=""),"Einbaudatum fehlt",IF(AND(E44="Mieter",H44<>"",H44<=0),"Lebensdauer ungültig",""))))))))) | M44: =IF(AND(A44<>"",A44=$E$3),COUNTIF($A$32:A44,$E$3),"") | N44: =IF(A44="","",IFERROR(IF(INDEX('Mein Haus'!$F$45:$F$104,A44)="","",INDEX('Mein Haus'!$F$45:$F$104,A44)),""))
I45: =IF(OR(G45="",N45=""),"",(N45-G45)/365.25) | J45: =IF(F45="","",IF(E45<>"Mieter",0,IF(H45="",1,IF(OR(G45="",N45=""),"",MAX(0,1-I45/H45))))) | K45: =IF(OR(J45="",F45=""),0,ROUND(F45*J45*20,0)/20) | L45: =IF(AND(A45="",B45="",F45=""),"",IF(A45="","ID fehlt",IF(F45="","",IF(F45<0,"Kosten negativ",IF(E45="","Ursache wählen",IF(N45="","Mietende fehlt",IF(AND(G45<>"",G45>N45),"Einbau nach Mietende",IF(AND(E45="Mieter",H45<>"",G45=""),"Einbaudatum fehlt",IF(AND(E45="Mieter",H45<>"",H45<=0),"Lebensdauer ungültig",""))))))))) | M45: =IF(AND(A45<>"",A45=$E$3),COUNTIF($A$32:A45,$E$3),"") | N45: =IF(A45="","",IFERROR(IF(INDEX('Mein Haus'!$F$45:$F$104,A45)="","",INDEX('Mein Haus'!$F$45:$F$104,A45)),""))
I46: =IF(OR(G46="",N46=""),"",(N46-G46)/365.25) | J46: =IF(F46="","",IF(E46<>"Mieter",0,IF(H46="",1,IF(OR(G46="",N46=""),"",MAX(0,1-I46/H46))))) | K46: =IF(OR(J46="",F46=""),0,ROUND(F46*J46*20,0)/20) | L46: =IF(AND(A46="",B46="",F46=""),"",IF(A46="","ID fehlt",IF(F46="","",IF(F46<0,"Kosten negativ",IF(E46="","Ursache wählen",IF(N46="","Mietende fehlt",IF(AND(G46<>"",G46>N46),"Einbau nach Mietende",IF(AND(E46="Mieter",H46<>"",G46=""),"Einbaudatum fehlt",IF(AND(E46="Mieter",H46<>"",H46<=0),"Lebensdauer ungültig",""))))))))) | M46: =IF(AND(A46<>"",A46=$E$3),COUNTIF($A$32:A46,$E$3),"") | N46: =IF(A46="","",IFERROR(IF(INDEX('Mein Haus'!$F$45:$F$104,A46)="","",INDEX('Mein Haus'!$F$45:$F$104,A46)),""))
I47: =IF(OR(G47="",N47=""),"",(N47-G47)/365.25) | J47: =IF(F47="","",IF(E47<>"Mieter",0,IF(H47="",1,IF(OR(G47="",N47=""),"",MAX(0,1-I47/H47))))) | K47: =IF(OR(J47="",F47=""),0,ROUND(F47*J47*20,0)/20) | L47: =IF(AND(A47="",B47="",F47=""),"",IF(A47="","ID fehlt",IF(F47="","",IF(F47<0,"Kosten negativ",IF(E47="","Ursache wählen",IF(N47="","Mietende fehlt",IF(AND(G47<>"",G47>N47),"Einbau nach Mietende",IF(AND(E47="Mieter",H47<>"",G47=""),"Einbaudatum fehlt",IF(AND(E47="Mieter",H47<>"",H47<=0),"Lebensdauer ungültig",""))))))))) | M47: =IF(AND(A47<>"",A47=$E$3),COUNTIF($A$32:A47,$E$3),"") | N47: =IF(A47="","",IFERROR(IF(INDEX('Mein Haus'!$F$45:$F$104,A47)="","",INDEX('Mein Haus'!$F$45:$F$104,A47)),""))
I48: =IF(OR(G48="",N48=""),"",(N48-G48)/365.25) | J48: =IF(F48="","",IF(E48<>"Mieter",0,IF(H48="",1,IF(OR(G48="",N48=""),"",MAX(0,1-I48/H48))))) | K48: =IF(OR(J48="",F48=""),0,ROUND(F48*J48*20,0)/20) | L48: =IF(AND(A48="",B48="",F48=""),"",IF(A48="","ID fehlt",IF(F48="","",IF(F48<0,"Kosten negativ",IF(E48="","Ursache wählen",IF(N48="","Mietende fehlt",IF(AND(G48<>"",G48>N48),"Einbau nach Mietende",IF(AND(E48="Mieter",H48<>"",G48=""),"Einbaudatum fehlt",IF(AND(E48="Mieter",H48<>"",H48<=0),"Lebensdauer ungültig",""))))))))) | M48: =IF(AND(A48<>"",A48=$E$3),COUNTIF($A$32:A48,$E$3),"") | N48: =IF(A48="","",IFERROR(IF(INDEX('Mein Haus'!$F$45:$F$104,A48)="","",INDEX('Mein Haus'!$F$45:$F$104,A48)),""))
I49: =IF(OR(G49="",N49=""),"",(N49-G49)/365.25) | J49: =IF(F49="","",IF(E49<>"Mieter",0,IF(H49="",1,IF(OR(G49="",N49=""),"",MAX(0,1-I49/H49))))) | K49: =IF(OR(J49="",F49=""),0,ROUND(F49*J49*20,0)/20) | L49: =IF(AND(A49="",B49="",F49=""),"",IF(A49="","ID fehlt",IF(F49="","",IF(F49<0,"Kosten negativ",IF(E49="","Ursache wählen",IF(N49="","Mietende fehlt",IF(AND(G49<>"",G49>N49),"Einbau nach Mietende",IF(AND(E49="Mieter",H49<>"",G49=""),"Einbaudatum fehlt",IF(AND(E49="Mieter",H49<>"",H49<=0),"Lebensdauer ungültig",""))))))))) | M49: =IF(AND(A49<>"",A49=$E$3),COUNTIF($A$32:A49,$E$3),"") | N49: =IF(A49="","",IFERROR(IF(INDEX('Mein Haus'!$F$45:$F$104,A49)="","",INDEX('Mein Haus'!$F$45:$F$104,A49)),""))
... I131: =IF(OR(G131="",N131=""),"",(N131-G131)/365.25) | J131: =IF(F131="","",IF(E131<>"Mieter",0,IF(H131="",1,IF(OR(G131="",N131=""),"",MAX(0,1-I131/H131))))) | K131: =IF(OR(J131="",F131=""),0,ROUND(F131*J131*20,0)/20) | L131: =IF(AND(A131="",B131="",F131=""),"",IF(A131="","ID fehlt",IF(F131="","",IF(F131<0,"Kosten negativ",IF(E131="","Ursache wählen",IF(N131="","Mietende fehlt",IF(AND(G131<>"",G131>N131),"Einbau nach Mietende",IF(AND(E131="Mieter",H131<>"",G131=""),"Einbaudatum fehlt",IF(AND(E131="Mieter",H131<>"",H131<=0),"Lebensdauer ungültig",""))))))))) | M131: =IF(AND(A131<>"",A131=$E$3),COUNTIF($A$32:A131,$E$3),"") | N131: =IF(A131="","",IFERROR(IF(INDEX('Mein Haus'!$F$45:$F$104,A131)="","",INDEX('Mein Haus'!$F$45:$F$104,A131)),""))

Sheet Protokoll
A1: Wohnungsabnahmeprotokoll
A2: Auswahl über die ID oben im Blatt «Rückgabe». Leere Zeilen eignen sich für Notizen vor Ort.
A4: Liegenschaft | B4: ='Mein Haus'!B4
A5: Mieter | B5: =IFERROR(INDEX(Rückgabe!$B$8:$B$27,MATCH(Rückgabe!$E$3,Rückgabe!$A$8:$A$27,0)),"")&""
A6: Einheit | B6: =IFERROR(INDEX('Mein Haus'!$B$45:$B$104,Rückgabe!$E$3)&" "&INDEX('Mein Haus'!$B$11:$B$40,MATCH(INDEX('Mein Haus'!$B$45:$B$104,Rückgabe!$E$3),'Mein Haus'!$A$11:$A$40,0)),"")
A7: Mietende | B7: =IFERROR(INDEX(Rückgabe!$C$8:$C$27,MATCH(Rückgabe!$E$3,Rückgabe!$A$8:$A$27,0)),"")
A8: Abnahme am | B8: =IFERROR(INDEX(Rückgabe!$D$8:$D$27,MATCH(Rückgabe!$E$3,Rückgabe!$A$8:$A$27,0)),"")
A9: Anwesend | B9: =IFERROR(INDEX(Rückgabe!$E$8:$E$27,MATCH(Rückgabe!$E$3,Rückgabe!$A$8:$A$27,0)),"")&""
A10: Zähler Strom / Wasser / Wärme | B10: =IFERROR(INDEX(Rückgabe!$F$8:$F$27,MATCH(Rückgabe!$E$3,Rückgabe!$A$8:$A$27,0)),"")&" / "&IFERROR(INDEX(Rückgabe!$G$8:$G$27,MATCH(Rückgabe!$E$3,Rückgabe!$A$8:$A$27,0)),"")&" / "&IFERROR(INDEX(Rückgabe!$H$8:$H$27,MATCH(Rückgabe!$E$3,Rückgabe!$A$8:$A$27,0)),"")
A11: Schlüssel erhalten | B11: =IFERROR(INDEX(Rückgabe!$I$8:$I$27,MATCH(Rückgabe!$E$3,Rückgabe!$A$8:$A$27,0)),"")&""
A13: Raum | B13: Bauteil | C13: Mangel / Zustand | D13: Ursache
A14: =IFERROR(INDEX(Rückgabe!$B$32:$B$131,MATCH(1,Rückgabe!$M$32:$M$131,0)),"") | B14: =IFERROR(INDEX(Rückgabe!$C$32:$C$131,MATCH(1,Rückgabe!$M$32:$M$131,0)),"") | C14: =IFERROR(INDEX(Rückgabe!$D$32:$D$131,MATCH(1,Rückgabe!$M$32:$M$131,0)),"") | D14: =IFERROR(INDEX(Rückgabe!$E$32:$E$131,MATCH(1,Rückgabe!$M$32:$M$131,0)),"")
A15: =IFERROR(INDEX(Rückgabe!$B$32:$B$131,MATCH(2,Rückgabe!$M$32:$M$131,0)),"") | B15: =IFERROR(INDEX(Rückgabe!$C$32:$C$131,MATCH(2,Rückgabe!$M$32:$M$131,0)),"") | C15: =IFERROR(INDEX(Rückgabe!$D$32:$D$131,MATCH(2,Rückgabe!$M$32:$M$131,0)),"") | D15: =IFERROR(INDEX(Rückgabe!$E$32:$E$131,MATCH(2,Rückgabe!$M$32:$M$131,0)),"")
A16: =IFERROR(INDEX(Rückgabe!$B$32:$B$131,MATCH(3,Rückgabe!$M$32:$M$131,0)),"") | B16: =IFERROR(INDEX(Rückgabe!$C$32:$C$131,MATCH(3,Rückgabe!$M$32:$M$131,0)),"") | C16: =IFERROR(INDEX(Rückgabe!$D$32:$D$131,MATCH(3,Rückgabe!$M$32:$M$131,0)),"") | D16: =IFERROR(INDEX(Rückgabe!$E$32:$E$131,MATCH(3,Rückgabe!$M$32:$M$131,0)),"")
A17: =IFERROR(INDEX(Rückgabe!$B$32:$B$131,MATCH(4,Rückgabe!$M$32:$M$131,0)),"") | B17: =IFERROR(INDEX(Rückgabe!$C$32:$C$131,MATCH(4,Rückgabe!$M$32:$M$131,0)),"") | C17: =IFERROR(INDEX(Rückgabe!$D$32:$D$131,MATCH(4,Rückgabe!$M$32:$M$131,0)),"") | D17: =IFERROR(INDEX(Rückgabe!$E$32:$E$131,MATCH(4,Rückgabe!$M$32:$M$131,0)),"")
A18: =IFERROR(INDEX(Rückgabe!$B$32:$B$131,MATCH(5,Rückgabe!$M$32:$M$131,0)),"") | B18: =IFERROR(INDEX(Rückgabe!$C$32:$C$131,MATCH(5,Rückgabe!$M$32:$M$131,0)),"") | C18: =IFERROR(INDEX(Rückgabe!$D$32:$D$131,MATCH(5,Rückgabe!$M$32:$M$131,0)),"") | D18: =IFERROR(INDEX(Rückgabe!$E$32:$E$131,MATCH(5,Rückgabe!$M$32:$M$131,0)),"")
A19: =IFERROR(INDEX(Rückgabe!$B$32:$B$131,MATCH(6,Rückgabe!$M$32:$M$131,0)),"") | B19: =IFERROR(INDEX(Rückgabe!$C$32:$C$131,MATCH(6,Rückgabe!$M$32:$M$131,0)),"") | C19: =IFERROR(INDEX(Rückgabe!$D$32:$D$131,MATCH(6,Rückgabe!$M$32:$M$131,0)),"") | D19: =IFERROR(INDEX(Rückgabe!$E$32:$E$131,MATCH(6,Rückgabe!$M$32:$M$131,0)),"")
A20: =IFERROR(INDEX(Rückgabe!$B$32:$B$131,MATCH(7,Rückgabe!$M$32:$M$131,0)),"") | B20: =IFERROR(INDEX(Rückgabe!$C$32:$C$131,MATCH(7,Rückgabe!$M$32:$M$131,0)),"") | C20: =IFERROR(INDEX(Rückgabe!$D$32:$D$131,MATCH(7,Rückgabe!$M$32:$M$131,0)),"") | D20: =IFERROR(INDEX(Rückgabe!$E$32:$E$131,MATCH(7,Rückgabe!$M$32:$M$131,0)),"")
A21: =IFERROR(INDEX(Rückgabe!$B$32:$B$131,MATCH(8,Rückgabe!$M$32:$M$131,0)),"") | B21: =IFERROR(INDEX(Rückgabe!$C$32:$C$131,MATCH(8,Rückgabe!$M$32:$M$131,0)),"") | C21: =IFERROR(INDEX(Rückgabe!$D$32:$D$131,MATCH(8,Rückgabe!$M$32:$M$131,0)),"") | D21: =IFERROR(INDEX(Rückgabe!$E$32:$E$131,MATCH(8,Rückgabe!$M$32:$M$131,0)),"")
A22: =IFERROR(INDEX(Rückgabe!$B$32:$B$131,MATCH(9,Rückgabe!$M$32:$M$131,0)),"") | B22: =IFERROR(INDEX(Rückgabe!$C$32:$C$131,MATCH(9,Rückgabe!$M$32:$M$131,0)),"") | C22: =IFERROR(INDEX(Rückgabe!$D$32:$D$131,MATCH(9,Rückgabe!$M$32:$M$131,0)),"") | D22: =IFERROR(INDEX(Rückgabe!$E$32:$E$131,MATCH(9,Rückgabe!$M$32:$M$131,0)),"")
A23: =IFERROR(INDEX(Rückgabe!$B$32:$B$131,MATCH(10,Rückgabe!$M$32:$M$131,0)),"") | B23: =IFERROR(INDEX(Rückgabe!$C$32:$C$131,MATCH(10,Rückgabe!$M$32:$M$131,0)),"") | C23: =IFERROR(INDEX(Rückgabe!$D$32:$D$131,MATCH(10,Rückgabe!$M$32:$M$131,0)),"") | D23: =IFERROR(INDEX(Rückgabe!$E$32:$E$131,MATCH(10,Rückgabe!$M$32:$M$131,0)),"")
A24: =IFERROR(INDEX(Rückgabe!$B$32:$B$131,MATCH(11,Rückgabe!$M$32:$M$131,0)),"") | B24: =IFERROR(INDEX(Rückgabe!$C$32:$C$131,MATCH(11,Rückgabe!$M$32:$M$131,0)),"") | C24: =IFERROR(INDEX(Rückgabe!$D$32:$D$131,MATCH(11,Rückgabe!$M$32:$M$131,0)),"") | D24: =IFERROR(INDEX(Rückgabe!$E$32:$E$131,MATCH(11,Rückgabe!$M$32:$M$131,0)),"")
A25: =IFERROR(INDEX(Rückgabe!$B$32:$B$131,MATCH(12,Rückgabe!$M$32:$M$131,0)),"") | B25: =IFERROR(INDEX(Rückgabe!$C$32:$C$131,MATCH(12,Rückgabe!$M$32:$M$131,0)),"") | C25: =IFERROR(INDEX(Rückgabe!$D$32:$D$131,MATCH(12,Rückgabe!$M$32:$M$131,0)),"") | D25: =IFERROR(INDEX(Rückgabe!$E$32:$E$131,MATCH(12,Rückgabe!$M$32:$M$131,0)),"")
A26: =IFERROR(INDEX(Rückgabe!$B$32:$B$131,MATCH(13,Rückgabe!$M$32:$M$131,0)),"") | B26: =IFERROR(INDEX(Rückgabe!$C$32:$C$131,MATCH(13,Rückgabe!$M$32:$M$131,0)),"") | C26: =IFERROR(INDEX(Rückgabe!$D$32:$D$131,MATCH(13,Rückgabe!$M$32:$M$131,0)),"") | D26: =IFERROR(INDEX(Rückgabe!$E$32:$E$131,MATCH(13,Rückgabe!$M$32:$M$131,0)),"")
A27: =IFERROR(INDEX(Rückgabe!$B$32:$B$131,MATCH(14,Rückgabe!$M$32:$M$131,0)),"") | B27: =IFERROR(INDEX(Rückgabe!$C$32:$C$131,MATCH(14,Rückgabe!$M$32:$M$131,0)),"") | C27: =IFERROR(INDEX(Rückgabe!$D$32:$D$131,MATCH(14,Rückgabe!$M$32:$M$131,0)),"") | D27: =IFERROR(INDEX(Rückgabe!$E$32:$E$131,MATCH(14,Rückgabe!$M$32:$M$131,0)),"")
A28: =IFERROR(INDEX(Rückgabe!$B$32:$B$131,MATCH(15,Rückgabe!$M$32:$M$131,0)),"") | B28: =IFERROR(INDEX(Rückgabe!$C$32:$C$131,MATCH(15,Rückgabe!$M$32:$M$131,0)),"") | C28: =IFERROR(INDEX(Rückgabe!$D$32:$D$131,MATCH(15,Rückgabe!$M$32:$M$131,0)),"") | D28: =IFERROR(INDEX(Rückgabe!$E$32:$E$131,MATCH(15,Rückgabe!$M$32:$M$131,0)),"")
A29: =IFERROR(INDEX(Rückgabe!$B$32:$B$131,MATCH(16,Rückgabe!$M$32:$M$131,0)),"") | B29: =IFERROR(INDEX(Rückgabe!$C$32:$C$131,MATCH(16,Rückgabe!$M$32:$M$131,0)),"") | C29: =IFERROR(INDEX(Rückgabe!$D$32:$D$131,MATCH(16,Rückgabe!$M$32:$M$131,0)),"") | D29: =IFERROR(INDEX(Rückgabe!$E$32:$E$131,MATCH(16,Rückgabe!$M$32:$M$131,0)),"")
A30: =IFERROR(INDEX(Rückgabe!$B$32:$B$131,MATCH(17,Rückgabe!$M$32:$M$131,0)),"") | B30: =IFERROR(INDEX(Rückgabe!$C$32:$C$131,MATCH(17,Rückgabe!$M$32:$M$131,0)),"") | C30: =IFERROR(INDEX(Rückgabe!$D$32:$D$131,MATCH(17,Rückgabe!$M$32:$M$131,0)),"") | D30: =IFERROR(INDEX(Rückgabe!$E$32:$E$131,MATCH(17,Rückgabe!$M$32:$M$131,0)),"")
A31: =IFERROR(INDEX(Rückgabe!$B$32:$B$131,MATCH(18,Rückgabe!$M$32:$M$131,0)),"") | B31: =IFERROR(INDEX(Rückgabe!$C$32:$C$131,MATCH(18,Rückgabe!$M$32:$M$131,0)),"") | C31: =IFERROR(INDEX(Rückgabe!$D$32:$D$131,MATCH(18,Rückgabe!$M$32:$M$131,0)),"") | D31: =IFERROR(INDEX(Rückgabe!$E$32:$E$131,MATCH(18,Rückgabe!$M$32:$M$131,0)),"")
A32: =IFERROR(INDEX(Rückgabe!$B$32:$B$131,MATCH(19,Rückgabe!$M$32:$M$131,0)),"") | B32: =IFERROR(INDEX(Rückgabe!$C$32:$C$131,MATCH(19,Rückgabe!$M$32:$M$131,0)),"") | C32: =IFERROR(INDEX(Rückgabe!$D$32:$D$131,MATCH(19,Rückgabe!$M$32:$M$131,0)),"") | D32: =IFERROR(INDEX(Rückgabe!$E$32:$E$131,MATCH(19,Rückgabe!$M$32:$M$131,0)),"")
A33: =IFERROR(INDEX(Rückgabe!$B$32:$B$131,MATCH(20,Rückgabe!$M$32:$M$131,0)),"") | B33: =IFERROR(INDEX(Rückgabe!$C$32:$C$131,MATCH(20,Rückgabe!$M$32:$M$131,0)),"") | C33: =IFERROR(INDEX(Rückgabe!$D$32:$D$131,MATCH(20,Rückgabe!$M$32:$M$131,0)),"") | D33: =IFERROR(INDEX(Rückgabe!$E$32:$E$131,MATCH(20,Rückgabe!$M$32:$M$131,0)),"")
A34: =IFERROR(INDEX(Rückgabe!$B$32:$B$131,MATCH(21,Rückgabe!$M$32:$M$131,0)),"") | B34: =IFERROR(INDEX(Rückgabe!$C$32:$C$131,MATCH(21,Rückgabe!$M$32:$M$131,0)),"") | C34: =IFERROR(INDEX(Rückgabe!$D$32:$D$131,MATCH(21,Rückgabe!$M$32:$M$131,0)),"") | D34: =IFERROR(INDEX(Rückgabe!$E$32:$E$131,MATCH(21,Rückgabe!$M$32:$M$131,0)),"")
A35: =IFERROR(INDEX(Rückgabe!$B$32:$B$131,MATCH(22,Rückgabe!$M$32:$M$131,0)),"") | B35: =IFERROR(INDEX(Rückgabe!$C$32:$C$131,MATCH(22,Rückgabe!$M$32:$M$131,0)),"") | C35: =IFERROR(INDEX(Rückgabe!$D$32:$D$131,MATCH(22,Rückgabe!$M$32:$M$131,0)),"") | D35: =IFERROR(INDEX(Rückgabe!$E$32:$E$131,MATCH(22,Rückgabe!$M$32:$M$131,0)),"")
A36: =IFERROR(INDEX(Rückgabe!$B$32:$B$131,MATCH(23,Rückgabe!$M$32:$M$131,0)),"") | B36: =IFERROR(INDEX(Rückgabe!$C$32:$C$131,MATCH(23,Rückgabe!$M$32:$M$131,0)),"") | C36: =IFERROR(INDEX(Rückgabe!$D$32:$D$131,MATCH(23,Rückgabe!$M$32:$M$131,0)),"") | D36: =IFERROR(INDEX(Rückgabe!$E$32:$E$131,MATCH(23,Rückgabe!$M$32:$M$131,0)),"")
A37: =IFERROR(INDEX(Rückgabe!$B$32:$B$131,MATCH(24,Rückgabe!$M$32:$M$131,0)),"") | B37: =IFERROR(INDEX(Rückgabe!$C$32:$C$131,MATCH(24,Rückgabe!$M$32:$M$131,0)),"") | C37: =IFERROR(INDEX(Rückgabe!$D$32:$D$131,MATCH(24,Rückgabe!$M$32:$M$131,0)),"") | D37: =IFERROR(INDEX(Rückgabe!$E$32:$E$131,MATCH(24,Rückgabe!$M$32:$M$131,0)),"")
A38: =IFERROR(INDEX(Rückgabe!$B$32:$B$131,MATCH(25,Rückgabe!$M$32:$M$131,0)),"") | B38: =IFERROR(INDEX(Rückgabe!$C$32:$C$131,MATCH(25,Rückgabe!$M$32:$M$131,0)),"") | C38: =IFERROR(INDEX(Rückgabe!$D$32:$D$131,MATCH(25,Rückgabe!$M$32:$M$131,0)),"") | D38: =IFERROR(INDEX(Rückgabe!$E$32:$E$131,MATCH(25,Rückgabe!$M$32:$M$131,0)),"")
A39: =IFERROR(INDEX(Rückgabe!$B$32:$B$131,MATCH(26,Rückgabe!$M$32:$M$131,0)),"") | B39: =IFERROR(INDEX(Rückgabe!$C$32:$C$131,MATCH(26,Rückgabe!$M$32:$M$131,0)),"") | C39: =IFERROR(INDEX(Rückgabe!$D$32:$D$131,MATCH(26,Rückgabe!$M$32:$M$131,0)),"") | D39: =IFERROR(INDEX(Rückgabe!$E$32:$E$131,MATCH(26,Rückgabe!$M$32:$M$131,0)),"")
A40: =IFERROR(INDEX(Rückgabe!$B$32:$B$131,MATCH(27,Rückgabe!$M$32:$M$131,0)),"") | B40: =IFERROR(INDEX(Rückgabe!$C$32:$C$131,MATCH(27,Rückgabe!$M$32:$M$131,0)),"") | C40: =IFERROR(INDEX(Rückgabe!$D$32:$D$131,MATCH(27,Rückgabe!$M$32:$M$131,0)),"") | D40: =IFERROR(INDEX(Rückgabe!$E$32:$E$131,MATCH(27,Rückgabe!$M$32:$M$131,0)),"")
A41: =IFERROR(INDEX(Rückgabe!$B$32:$B$131,MATCH(28,Rückgabe!$M$32:$M$131,0)),"") | B41: =IFERROR(INDEX(Rückgabe!$C$32:$C$131,MATCH(28,Rückgabe!$M$32:$M$131,0)),"") | C41: =IFERROR(INDEX(Rückgabe!$D$32:$D$131,MATCH(28,Rückgabe!$M$32:$M$131,0)),"") | D41: =IFERROR(INDEX(Rückgabe!$E$32:$E$131,MATCH(28,Rückgabe!$M$32:$M$131,0)),"")
A42: =IFERROR(INDEX(Rückgabe!$B$32:$B$131,MATCH(29,Rückgabe!$M$32:$M$131,0)),"") | B42: =IFERROR(INDEX(Rückgabe!$C$32:$C$131,MATCH(29,Rückgabe!$M$32:$M$131,0)),"") | C42: =IFERROR(INDEX(Rückgabe!$D$32:$D$131,MATCH(29,Rückgabe!$M$32:$M$131,0)),"") | D42: =IFERROR(INDEX(Rückgabe!$E$32:$E$131,MATCH(29,Rückgabe!$M$32:$M$131,0)),"")
A43: =IFERROR(INDEX(Rückgabe!$B$32:$B$131,MATCH(30,Rückgabe!$M$32:$M$131,0)),"") | B43: =IFERROR(INDEX(Rückgabe!$C$32:$C$131,MATCH(30,Rückgabe!$M$32:$M$131,0)),"") | C43: =IFERROR(INDEX(Rückgabe!$D$32:$D$131,MATCH(30,Rückgabe!$M$32:$M$131,0)),"") | D43: =IFERROR(INDEX(Rückgabe!$E$32:$E$131,MATCH(30,Rückgabe!$M$32:$M$131,0)),"")
A45: Versteckte Mängel werden nach ihrer Entdeckung gerügt (Art. 267a Abs. 2 OR). Der Mieter erhält eine Kopie dieses Protokolls.
A48: Mieter: ____________________________ | C48: Vermieter: ____________________________

Sheet Kautionsabrechnung
A1: Abrechnung Wohnungsrückgabe und Mietkaution
A3: Liegenschaft | B3: ='Mein Haus'!B4
A4: Mieter | B4: =IFERROR(INDEX(Rückgabe!$B$8:$B$27,MATCH(Rückgabe!$E$3,Rückgabe!$A$8:$A$27,0)),"")&""
A5: Einheit | B5: =IFERROR(INDEX('Mein Haus'!$B$45:$B$104,Rückgabe!$E$3)&" "&INDEX('Mein Haus'!$B$11:$B$40,MATCH(INDEX('Mein Haus'!$B$45:$B$104,Rückgabe!$E$3),'Mein Haus'!$A$11:$A$40,0)),"")
A6: Mietende | B6: =IFERROR(INDEX(Rückgabe!$C$8:$C$27,MATCH(Rückgabe!$E$3,Rückgabe!$A$8:$A$27,0)),"")
A7: Abnahme am | B7: =IFERROR(INDEX(Rückgabe!$D$8:$D$27,MATCH(Rückgabe!$E$3,Rückgabe!$A$8:$A$27,0)),"")
A9: Raum · Bauteil | B9: Mangel | C9: Ursache | D9: Kosten CHF | E9: Alter J. | F9: Lebensdauer J. | G9: Restwert | H9: Zulasten Mieter CHF
A10: =IF(IFERROR(INDEX(Rückgabe!$B$32:$B$131,MATCH(1,Rückgabe!$M$32:$M$131,0)),"")="","",IFERROR(INDEX(Rückgabe!$B$32:$B$131,MATCH(1,Rückgabe!$M$32:$M$131,0)),"")&" · "&IFERROR(INDEX(Rückgabe!$C$32:$C$131,MATCH(1,Rückgabe!$M$32:$M$131,0)),"")) | B10: =IF(IFERROR(INDEX(Rückgabe!$B$32:$B$131,MATCH(1,Rückgabe!$M$32:$M$131,0)),"")="","",IFERROR(INDEX(Rückgabe!$D$32:$D$131,MATCH(1,Rückgabe!$M$32:$M$131,0)),"")) | C10: =IF(IFERROR(INDEX(Rückgabe!$B$32:$B$131,MATCH(1,Rückgabe!$M$32:$M$131,0)),"")="","",IFERROR(INDEX(Rückgabe!$E$32:$E$131,MATCH(1,Rückgabe!$M$32:$M$131,0)),"")) | D10: =IF(IFERROR(INDEX(Rückgabe!$B$32:$B$131,MATCH(1,Rückgabe!$M$32:$M$131,0)),"")="","",IFERROR(INDEX(Rückgabe!$F$32:$F$131,MATCH(1,Rückgabe!$M$32:$M$131,0)),"")) | E10: =IF(IFERROR(INDEX(Rückgabe!$B$32:$B$131,MATCH(1,Rückgabe!$M$32:$M$131,0)),"")="","",IFERROR(INDEX(Rückgabe!$I$32:$I$131,MATCH(1,Rückgabe!$M$32:$M$131,0)),"")) | F10: =IF(IFERROR(INDEX(Rückgabe!$B$32:$B$131,MATCH(1,Rückgabe!$M$32:$M$131,0)),"")="","",IFERROR(INDEX(Rückgabe!$H$32:$H$131,MATCH(1,Rückgabe!$M$32:$M$131,0)),"")) | G10: =IF(IFERROR(INDEX(Rückgabe!$B$32:$B$131,MATCH(1,Rückgabe!$M$32:$M$131,0)),"")="","",IFERROR(INDEX(Rückgabe!$J$32:$J$131,MATCH(1,Rückgabe!$M$32:$M$131,0)),"")) | H10: =IF(IFERROR(INDEX(Rückgabe!$B$32:$B$131,MATCH(1,Rückgabe!$M$32:$M$131,0)),"")="","",IFERROR(INDEX(Rückgabe!$K$32:$K$131,MATCH(1,Rückgabe!$M$32:$M$131,0)),""))
A11: =IF(IFERROR(INDEX(Rückgabe!$B$32:$B$131,MATCH(2,Rückgabe!$M$32:$M$131,0)),"")="","",IFERROR(INDEX(Rückgabe!$B$32:$B$131,MATCH(2,Rückgabe!$M$32:$M$131,0)),"")&" · "&IFERROR(INDEX(Rückgabe!$C$32:$C$131,MATCH(2,Rückgabe!$M$32:$M$131,0)),"")) | B11: =IF(IFERROR(INDEX(Rückgabe!$B$32:$B$131,MATCH(2,Rückgabe!$M$32:$M$131,0)),"")="","",IFERROR(INDEX(Rückgabe!$D$32:$D$131,MATCH(2,Rückgabe!$M$32:$M$131,0)),"")) | C11: =IF(IFERROR(INDEX(Rückgabe!$B$32:$B$131,MATCH(2,Rückgabe!$M$32:$M$131,0)),"")="","",IFERROR(INDEX(Rückgabe!$E$32:$E$131,MATCH(2,Rückgabe!$M$32:$M$131,0)),"")) | D11: =IF(IFERROR(INDEX(Rückgabe!$B$32:$B$131,MATCH(2,Rückgabe!$M$32:$M$131,0)),"")="","",IFERROR(INDEX(Rückgabe!$F$32:$F$131,MATCH(2,Rückgabe!$M$32:$M$131,0)),"")) | E11: =IF(IFERROR(INDEX(Rückgabe!$B$32:$B$131,MATCH(2,Rückgabe!$M$32:$M$131,0)),"")="","",IFERROR(INDEX(Rückgabe!$I$32:$I$131,MATCH(2,Rückgabe!$M$32:$M$131,0)),"")) | F11: =IF(IFERROR(INDEX(Rückgabe!$B$32:$B$131,MATCH(2,Rückgabe!$M$32:$M$131,0)),"")="","",IFERROR(INDEX(Rückgabe!$H$32:$H$131,MATCH(2,Rückgabe!$M$32:$M$131,0)),"")) | G11: =IF(IFERROR(INDEX(Rückgabe!$B$32:$B$131,MATCH(2,Rückgabe!$M$32:$M$131,0)),"")="","",IFERROR(INDEX(Rückgabe!$J$32:$J$131,MATCH(2,Rückgabe!$M$32:$M$131,0)),"")) | H11: =IF(IFERROR(INDEX(Rückgabe!$B$32:$B$131,MATCH(2,Rückgabe!$M$32:$M$131,0)),"")="","",IFERROR(INDEX(Rückgabe!$K$32:$K$131,MATCH(2,Rückgabe!$M$32:$M$131,0)),""))
A12: =IF(IFERROR(INDEX(Rückgabe!$B$32:$B$131,MATCH(3,Rückgabe!$M$32:$M$131,0)),"")="","",IFERROR(INDEX(Rückgabe!$B$32:$B$131,MATCH(3,Rückgabe!$M$32:$M$131,0)),"")&" · "&IFERROR(INDEX(Rückgabe!$C$32:$C$131,MATCH(3,Rückgabe!$M$32:$M$131,0)),"")) | B12: =IF(IFERROR(INDEX(Rückgabe!$B$32:$B$131,MATCH(3,Rückgabe!$M$32:$M$131,0)),"")="","",IFERROR(INDEX(Rückgabe!$D$32:$D$131,MATCH(3,Rückgabe!$M$32:$M$131,0)),"")) | C12: =IF(IFERROR(INDEX(Rückgabe!$B$32:$B$131,MATCH(3,Rückgabe!$M$32:$M$131,0)),"")="","",IFERROR(INDEX(Rückgabe!$E$32:$E$131,MATCH(3,Rückgabe!$M$32:$M$131,0)),"")) | D12: =IF(IFERROR(INDEX(Rückgabe!$B$32:$B$131,MATCH(3,Rückgabe!$M$32:$M$131,0)),"")="","",IFERROR(INDEX(Rückgabe!$F$32:$F$131,MATCH(3,Rückgabe!$M$32:$M$131,0)),"")) | E12: =IF(IFERROR(INDEX(Rückgabe!$B$32:$B$131,MATCH(3,Rückgabe!$M$32:$M$131,0)),"")="","",IFERROR(INDEX(Rückgabe!$I$32:$I$131,MATCH(3,Rückgabe!$M$32:$M$131,0)),"")) | F12: =IF(IFERROR(INDEX(Rückgabe!$B$32:$B$131,MATCH(3,Rückgabe!$M$32:$M$131,0)),"")="","",IFERROR(INDEX(Rückgabe!$H$32:$H$131,MATCH(3,Rückgabe!$M$32:$M$131,0)),"")) | G12: =IF(IFERROR(INDEX(Rückgabe!$B$32:$B$131,MATCH(3,Rückgabe!$M$32:$M$131,0)),"")="","",IFERROR(INDEX(Rückgabe!$J$32:$J$131,MATCH(3,Rückgabe!$M$32:$M$131,0)),"")) | H12: =IF(IFERROR(INDEX(Rückgabe!$B$32:$B$131,MATCH(3,Rückgabe!$M$32:$M$131,0)),"")="","",IFERROR(INDEX(Rückgabe!$K$32:$K$131,MATCH(3,Rückgabe!$M$32:$M$131,0)),""))
A13: =IF(IFERROR(INDEX(Rückgabe!$B$32:$B$131,MATCH(4,Rückgabe!$M$32:$M$131,0)),"")="","",IFERROR(INDEX(Rückgabe!$B$32:$B$131,MATCH(4,Rückgabe!$M$32:$M$131,0)),"")&" · "&IFERROR(INDEX(Rückgabe!$C$32:$C$131,MATCH(4,Rückgabe!$M$32:$M$131,0)),"")) | B13: =IF(IFERROR(INDEX(Rückgabe!$B$32:$B$131,MATCH(4,Rückgabe!$M$32:$M$131,0)),"")="","",IFERROR(INDEX(Rückgabe!$D$32:$D$131,MATCH(4,Rückgabe!$M$32:$M$131,0)),"")) | C13: =IF(IFERROR(INDEX(Rückgabe!$B$32:$B$131,MATCH(4,Rückgabe!$M$32:$M$131,0)),"")="","",IFERROR(INDEX(Rückgabe!$E$32:$E$131,MATCH(4,Rückgabe!$M$32:$M$131,0)),"")) | D13: =IF(IFERROR(INDEX(Rückgabe!$B$32:$B$131,MATCH(4,Rückgabe!$M$32:$M$131,0)),"")="","",IFERROR(INDEX(Rückgabe!$F$32:$F$131,MATCH(4,Rückgabe!$M$32:$M$131,0)),"")) | E13: =IF(IFERROR(INDEX(Rückgabe!$B$32:$B$131,MATCH(4,Rückgabe!$M$32:$M$131,0)),"")="","",IFERROR(INDEX(Rückgabe!$I$32:$I$131,MATCH(4,Rückgabe!$M$32:$M$131,0)),"")) | F13: =IF(IFERROR(INDEX(Rückgabe!$B$32:$B$131,MATCH(4,Rückgabe!$M$32:$M$131,0)),"")="","",IFERROR(INDEX(Rückgabe!$H$32:$H$131,MATCH(4,Rückgabe!$M$32:$M$131,0)),"")) | G13: =IF(IFERROR(INDEX(Rückgabe!$B$32:$B$131,MATCH(4,Rückgabe!$M$32:$M$131,0)),"")="","",IFERROR(INDEX(Rückgabe!$J$32:$J$131,MATCH(4,Rückgabe!$M$32:$M$131,0)),"")) | H13: =IF(IFERROR(INDEX(Rückgabe!$B$32:$B$131,MATCH(4,Rückgabe!$M$32:$M$131,0)),"")="","",IFERROR(INDEX(Rückgabe!$K$32:$K$131,MATCH(4,Rückgabe!$M$32:$M$131,0)),""))
A14: =IF(IFERROR(INDEX(Rückgabe!$B$32:$B$131,MATCH(5,Rückgabe!$M$32:$M$131,0)),"")="","",IFERROR(INDEX(Rückgabe!$B$32:$B$131,MATCH(5,Rückgabe!$M$32:$M$131,0)),"")&" · "&IFERROR(INDEX(Rückgabe!$C$32:$C$131,MATCH(5,Rückgabe!$M$32:$M$131,0)),"")) | B14: =IF(IFERROR(INDEX(Rückgabe!$B$32:$B$131,MATCH(5,Rückgabe!$M$32:$M$131,0)),"")="","",IFERROR(INDEX(Rückgabe!$D$32:$D$131,MATCH(5,Rückgabe!$M$32:$M$131,0)),"")) | C14: =IF(IFERROR(INDEX(Rückgabe!$B$32:$B$131,MATCH(5,Rückgabe!$M$32:$M$131,0)),"")="","",IFERROR(INDEX(Rückgabe!$E$32:$E$131,MATCH(5,Rückgabe!$M$32:$M$131,0)),"")) | D14: =IF(IFERROR(INDEX(Rückgabe!$B$32:$B$131,MATCH(5,Rückgabe!$M$32:$M$131,0)),"")="","",IFERROR(INDEX(Rückgabe!$F$32:$F$131,MATCH(5,Rückgabe!$M$32:$M$131,0)),"")) | E14: =IF(IFERROR(INDEX(Rückgabe!$B$32:$B$131,MATCH(5,Rückgabe!$M$32:$M$131,0)),"")="","",IFERROR(INDEX(Rückgabe!$I$32:$I$131,MATCH(5,Rückgabe!$M$32:$M$131,0)),"")) | F14: =IF(IFERROR(INDEX(Rückgabe!$B$32:$B$131,MATCH(5,Rückgabe!$M$32:$M$131,0)),"")="","",IFERROR(INDEX(Rückgabe!$H$32:$H$131,MATCH(5,Rückgabe!$M$32:$M$131,0)),"")) | G14: =IF(IFERROR(INDEX(Rückgabe!$B$32:$B$131,MATCH(5,Rückgabe!$M$32:$M$131,0)),"")="","",IFERROR(INDEX(Rückgabe!$J$32:$J$131,MATCH(5,Rückgabe!$M$32:$M$131,0)),"")) | H14: =IF(IFERROR(INDEX(Rückgabe!$B$32:$B$131,MATCH(5,Rückgabe!$M$32:$M$131,0)),"")="","",IFERROR(INDEX(Rückgabe!$K$32:$K$131,MATCH(5,Rückgabe!$M$32:$M$131,0)),""))
A15: =IF(IFERROR(INDEX(Rückgabe!$B$32:$B$131,MATCH(6,Rückgabe!$M$32:$M$131,0)),"")="","",IFERROR(INDEX(Rückgabe!$B$32:$B$131,MATCH(6,Rückgabe!$M$32:$M$131,0)),"")&" · "&IFERROR(INDEX(Rückgabe!$C$32:$C$131,MATCH(6,Rückgabe!$M$32:$M$131,0)),"")) | B15: =IF(IFERROR(INDEX(Rückgabe!$B$32:$B$131,MATCH(6,Rückgabe!$M$32:$M$131,0)),"")="","",IFERROR(INDEX(Rückgabe!$D$32:$D$131,MATCH(6,Rückgabe!$M$32:$M$131,0)),"")) | C15: =IF(IFERROR(INDEX(Rückgabe!$B$32:$B$131,MATCH(6,Rückgabe!$M$32:$M$131,0)),"")="","",IFERROR(INDEX(Rückgabe!$E$32:$E$131,MATCH(6,Rückgabe!$M$32:$M$131,0)),"")) | D15: =IF(IFERROR(INDEX(Rückgabe!$B$32:$B$131,MATCH(6,Rückgabe!$M$32:$M$131,0)),"")="","",IFERROR(INDEX(Rückgabe!$F$32:$F$131,MATCH(6,Rückgabe!$M$32:$M$131,0)),"")) | E15: =IF(IFERROR(INDEX(Rückgabe!$B$32:$B$131,MATCH(6,Rückgabe!$M$32:$M$131,0)),"")="","",IFERROR(INDEX(Rückgabe!$I$32:$I$131,MATCH(6,Rückgabe!$M$32:$M$131,0)),"")) | F15: =IF(IFERROR(INDEX(Rückgabe!$B$32:$B$131,MATCH(6,Rückgabe!$M$32:$M$131,0)),"")="","",IFERROR(INDEX(Rückgabe!$H$32:$H$131,MATCH(6,Rückgabe!$M$32:$M$131,0)),"")) | G15: =IF(IFERROR(INDEX(Rückgabe!$B$32:$B$131,MATCH(6,Rückgabe!$M$32:$M$131,0)),"")="","",IFERROR(INDEX(Rückgabe!$J$32:$J$131,MATCH(6,Rückgabe!$M$32:$M$131,0)),"")) | H15: =IF(IFERROR(INDEX(Rückgabe!$B$32:$B$131,MATCH(6,Rückgabe!$M$32:$M$131,0)),"")="","",IFERROR(INDEX(Rückgabe!$K$32:$K$131,MATCH(6,Rückgabe!$M$32:$M$131,0)),""))
A16: =IF(IFERROR(INDEX(Rückgabe!$B$32:$B$131,MATCH(7,Rückgabe!$M$32:$M$131,0)),"")="","",IFERROR(INDEX(Rückgabe!$B$32:$B$131,MATCH(7,Rückgabe!$M$32:$M$131,0)),"")&" · "&IFERROR(INDEX(Rückgabe!$C$32:$C$131,MATCH(7,Rückgabe!$M$32:$M$131,0)),"")) | B16: =IF(IFERROR(INDEX(Rückgabe!$B$32:$B$131,MATCH(7,Rückgabe!$M$32:$M$131,0)),"")="","",IFERROR(INDEX(Rückgabe!$D$32:$D$131,MATCH(7,Rückgabe!$M$32:$M$131,0)),"")) | C16: =IF(IFERROR(INDEX(Rückgabe!$B$32:$B$131,MATCH(7,Rückgabe!$M$32:$M$131,0)),"")="","",IFERROR(INDEX(Rückgabe!$E$32:$E$131,MATCH(7,Rückgabe!$M$32:$M$131,0)),"")) | D16: =IF(IFERROR(INDEX(Rückgabe!$B$32:$B$131,MATCH(7,Rückgabe!$M$32:$M$131,0)),"")="","",IFERROR(INDEX(Rückgabe!$F$32:$F$131,MATCH(7,Rückgabe!$M$32:$M$131,0)),"")) | E16: =IF(IFERROR(INDEX(Rückgabe!$B$32:$B$131,MATCH(7,Rückgabe!$M$32:$M$131,0)),"")="","",IFERROR(INDEX(Rückgabe!$I$32:$I$131,MATCH(7,Rückgabe!$M$32:$M$131,0)),"")) | F16: =IF(IFERROR(INDEX(Rückgabe!$B$32:$B$131,MATCH(7,Rückgabe!$M$32:$M$131,0)),"")="","",IFERROR(INDEX(Rückgabe!$H$32:$H$131,MATCH(7,Rückgabe!$M$32:$M$131,0)),"")) | G16: =IF(IFERROR(INDEX(Rückgabe!$B$32:$B$131,MATCH(7,Rückgabe!$M$32:$M$131,0)),"")="","",IFERROR(INDEX(Rückgabe!$J$32:$J$131,MATCH(7,Rückgabe!$M$32:$M$131,0)),"")) | H16: =IF(IFERROR(INDEX(Rückgabe!$B$32:$B$131,MATCH(7,Rückgabe!$M$32:$M$131,0)),"")="","",IFERROR(INDEX(Rückgabe!$K$32:$K$131,MATCH(7,Rückgabe!$M$32:$M$131,0)),""))
A17: =IF(IFERROR(INDEX(Rückgabe!$B$32:$B$131,MATCH(8,Rückgabe!$M$32:$M$131,0)),"")="","",IFERROR(INDEX(Rückgabe!$B$32:$B$131,MATCH(8,Rückgabe!$M$32:$M$131,0)),"")&" · "&IFERROR(INDEX(Rückgabe!$C$32:$C$131,MATCH(8,Rückgabe!$M$32:$M$131,0)),"")) | B17: =IF(IFERROR(INDEX(Rückgabe!$B$32:$B$131,MATCH(8,Rückgabe!$M$32:$M$131,0)),"")="","",IFERROR(INDEX(Rückgabe!$D$32:$D$131,MATCH(8,Rückgabe!$M$32:$M$131,0)),"")) | C17: =IF(IFERROR(INDEX(Rückgabe!$B$32:$B$131,MATCH(8,Rückgabe!$M$32:$M$131,0)),"")="","",IFERROR(INDEX(Rückgabe!$E$32:$E$131,MATCH(8,Rückgabe!$M$32:$M$131,0)),"")) | D17: =IF(IFERROR(INDEX(Rückgabe!$B$32:$B$131,MATCH(8,Rückgabe!$M$32:$M$131,0)),"")="","",IFERROR(INDEX(Rückgabe!$F$32:$F$131,MATCH(8,Rückgabe!$M$32:$M$131,0)),"")) | E17: =IF(IFERROR(INDEX(Rückgabe!$B$32:$B$131,MATCH(8,Rückgabe!$M$32:$M$131,0)),"")="","",IFERROR(INDEX(Rückgabe!$I$32:$I$131,MATCH(8,Rückgabe!$M$32:$M$131,0)),"")) | F17: =IF(IFERROR(INDEX(Rückgabe!$B$32:$B$131,MATCH(8,Rückgabe!$M$32:$M$131,0)),"")="","",IFERROR(INDEX(Rückgabe!$H$32:$H$131,MATCH(8,Rückgabe!$M$32:$M$131,0)),"")) | G17: =IF(IFERROR(INDEX(Rückgabe!$B$32:$B$131,MATCH(8,Rückgabe!$M$32:$M$131,0)),"")="","",IFERROR(INDEX(Rückgabe!$J$32:$J$131,MATCH(8,Rückgabe!$M$32:$M$131,0)),"")) | H17: =IF(IFERROR(INDEX(Rückgabe!$B$32:$B$131,MATCH(8,Rückgabe!$M$32:$M$131,0)),"")="","",IFERROR(INDEX(Rückgabe!$K$32:$K$131,MATCH(8,Rückgabe!$M$32:$M$131,0)),""))
A18: =IF(IFERROR(INDEX(Rückgabe!$B$32:$B$131,MATCH(9,Rückgabe!$M$32:$M$131,0)),"")="","",IFERROR(INDEX(Rückgabe!$B$32:$B$131,MATCH(9,Rückgabe!$M$32:$M$131,0)),"")&" · "&IFERROR(INDEX(Rückgabe!$C$32:$C$131,MATCH(9,Rückgabe!$M$32:$M$131,0)),"")) | B18: =IF(IFERROR(INDEX(Rückgabe!$B$32:$B$131,MATCH(9,Rückgabe!$M$32:$M$131,0)),"")="","",IFERROR(INDEX(Rückgabe!$D$32:$D$131,MATCH(9,Rückgabe!$M$32:$M$131,0)),"")) | C18: =IF(IFERROR(INDEX(Rückgabe!$B$32:$B$131,MATCH(9,Rückgabe!$M$32:$M$131,0)),"")="","",IFERROR(INDEX(Rückgabe!$E$32:$E$131,MATCH(9,Rückgabe!$M$32:$M$131,0)),"")) | D18: =IF(IFERROR(INDEX(Rückgabe!$B$32:$B$131,MATCH(9,Rückgabe!$M$32:$M$131,0)),"")="","",IFERROR(INDEX(Rückgabe!$F$32:$F$131,MATCH(9,Rückgabe!$M$32:$M$131,0)),"")) | E18: =IF(IFERROR(INDEX(Rückgabe!$B$32:$B$131,MATCH(9,Rückgabe!$M$32:$M$131,0)),"")="","",IFERROR(INDEX(Rückgabe!$I$32:$I$131,MATCH(9,Rückgabe!$M$32:$M$131,0)),"")) | F18: =IF(IFERROR(INDEX(Rückgabe!$B$32:$B$131,MATCH(9,Rückgabe!$M$32:$M$131,0)),"")="","",IFERROR(INDEX(Rückgabe!$H$32:$H$131,MATCH(9,Rückgabe!$M$32:$M$131,0)),"")) | G18: =IF(IFERROR(INDEX(Rückgabe!$B$32:$B$131,MATCH(9,Rückgabe!$M$32:$M$131,0)),"")="","",IFERROR(INDEX(Rückgabe!$J$32:$J$131,MATCH(9,Rückgabe!$M$32:$M$131,0)),"")) | H18: =IF(IFERROR(INDEX(Rückgabe!$B$32:$B$131,MATCH(9,Rückgabe!$M$32:$M$131,0)),"")="","",IFERROR(INDEX(Rückgabe!$K$32:$K$131,MATCH(9,Rückgabe!$M$32:$M$131,0)),""))
A19: =IF(IFERROR(INDEX(Rückgabe!$B$32:$B$131,MATCH(10,Rückgabe!$M$32:$M$131,0)),"")="","",IFERROR(INDEX(Rückgabe!$B$32:$B$131,MATCH(10,Rückgabe!$M$32:$M$131,0)),"")&" · "&IFERROR(INDEX(Rückgabe!$C$32:$C$131,MATCH(10,Rückgabe!$M$32:$M$131,0)),"")) | B19: =IF(IFERROR(INDEX(Rückgabe!$B$32:$B$131,MATCH(10,Rückgabe!$M$32:$M$131,0)),"")="","",IFERROR(INDEX(Rückgabe!$D$32:$D$131,MATCH(10,Rückgabe!$M$32:$M$131,0)),"")) | C19: =IF(IFERROR(INDEX(Rückgabe!$B$32:$B$131,MATCH(10,Rückgabe!$M$32:$M$131,0)),"")="","",IFERROR(INDEX(Rückgabe!$E$32:$E$131,MATCH(10,Rückgabe!$M$32:$M$131,0)),"")) | D19: =IF(IFERROR(INDEX(Rückgabe!$B$32:$B$131,MATCH(10,Rückgabe!$M$32:$M$131,0)),"")="","",IFERROR(INDEX(Rückgabe!$F$32:$F$131,MATCH(10,Rückgabe!$M$32:$M$131,0)),"")) | E19: =IF(IFERROR(INDEX(Rückgabe!$B$32:$B$131,MATCH(10,Rückgabe!$M$32:$M$131,0)),"")="","",IFERROR(INDEX(Rückgabe!$I$32:$I$131,MATCH(10,Rückgabe!$M$32:$M$131,0)),"")) | F19: =IF(IFERROR(INDEX(Rückgabe!$B$32:$B$131,MATCH(10,Rückgabe!$M$32:$M$131,0)),"")="","",IFERROR(INDEX(Rückgabe!$H$32:$H$131,MATCH(10,Rückgabe!$M$32:$M$131,0)),"")) | G19: =IF(IFERROR(INDEX(Rückgabe!$B$32:$B$131,MATCH(10,Rückgabe!$M$32:$M$131,0)),"")="","",IFERROR(INDEX(Rückgabe!$J$32:$J$131,MATCH(10,Rückgabe!$M$32:$M$131,0)),"")) | H19: =IF(IFERROR(INDEX(Rückgabe!$B$32:$B$131,MATCH(10,Rückgabe!$M$32:$M$131,0)),"")="","",IFERROR(INDEX(Rückgabe!$K$32:$K$131,MATCH(10,Rückgabe!$M$32:$M$131,0)),""))
A20: =IF(IFERROR(INDEX(Rückgabe!$B$32:$B$131,MATCH(11,Rückgabe!$M$32:$M$131,0)),"")="","",IFERROR(INDEX(Rückgabe!$B$32:$B$131,MATCH(11,Rückgabe!$M$32:$M$131,0)),"")&" · "&IFERROR(INDEX(Rückgabe!$C$32:$C$131,MATCH(11,Rückgabe!$M$32:$M$131,0)),"")) | B20: =IF(IFERROR(INDEX(Rückgabe!$B$32:$B$131,MATCH(11,Rückgabe!$M$32:$M$131,0)),"")="","",IFERROR(INDEX(Rückgabe!$D$32:$D$131,MATCH(11,Rückgabe!$M$32:$M$131,0)),"")) | C20: =IF(IFERROR(INDEX(Rückgabe!$B$32:$B$131,MATCH(11,Rückgabe!$M$32:$M$131,0)),"")="","",IFERROR(INDEX(Rückgabe!$E$32:$E$131,MATCH(11,Rückgabe!$M$32:$M$131,0)),"")) | D20: =IF(IFERROR(INDEX(Rückgabe!$B$32:$B$131,MATCH(11,Rückgabe!$M$32:$M$131,0)),"")="","",IFERROR(INDEX(Rückgabe!$F$32:$F$131,MATCH(11,Rückgabe!$M$32:$M$131,0)),"")) | E20: =IF(IFERROR(INDEX(Rückgabe!$B$32:$B$131,MATCH(11,Rückgabe!$M$32:$M$131,0)),"")="","",IFERROR(INDEX(Rückgabe!$I$32:$I$131,MATCH(11,Rückgabe!$M$32:$M$131,0)),"")) | F20: =IF(IFERROR(INDEX(Rückgabe!$B$32:$B$131,MATCH(11,Rückgabe!$M$32:$M$131,0)),"")="","",IFERROR(INDEX(Rückgabe!$H$32:$H$131,MATCH(11,Rückgabe!$M$32:$M$131,0)),"")) | G20: =IF(IFERROR(INDEX(Rückgabe!$B$32:$B$131,MATCH(11,Rückgabe!$M$32:$M$131,0)),"")="","",IFERROR(INDEX(Rückgabe!$J$32:$J$131,MATCH(11,Rückgabe!$M$32:$M$131,0)),"")) | H20: =IF(IFERROR(INDEX(Rückgabe!$B$32:$B$131,MATCH(11,Rückgabe!$M$32:$M$131,0)),"")="","",IFERROR(INDEX(Rückgabe!$K$32:$K$131,MATCH(11,Rückgabe!$M$32:$M$131,0)),""))
A21: =IF(IFERROR(INDEX(Rückgabe!$B$32:$B$131,MATCH(12,Rückgabe!$M$32:$M$131,0)),"")="","",IFERROR(INDEX(Rückgabe!$B$32:$B$131,MATCH(12,Rückgabe!$M$32:$M$131,0)),"")&" · "&IFERROR(INDEX(Rückgabe!$C$32:$C$131,MATCH(12,Rückgabe!$M$32:$M$131,0)),"")) | B21: =IF(IFERROR(INDEX(Rückgabe!$B$32:$B$131,MATCH(12,Rückgabe!$M$32:$M$131,0)),"")="","",IFERROR(INDEX(Rückgabe!$D$32:$D$131,MATCH(12,Rückgabe!$M$32:$M$131,0)),"")) | C21: =IF(IFERROR(INDEX(Rückgabe!$B$32:$B$131,MATCH(12,Rückgabe!$M$32:$M$131,0)),"")="","",IFERROR(INDEX(Rückgabe!$E$32:$E$131,MATCH(12,Rückgabe!$M$32:$M$131,0)),"")) | D21: =IF(IFERROR(INDEX(Rückgabe!$B$32:$B$131,MATCH(12,Rückgabe!$M$32:$M$131,0)),"")="","",IFERROR(INDEX(Rückgabe!$F$32:$F$131,MATCH(12,Rückgabe!$M$32:$M$131,0)),"")) | E21: =IF(IFERROR(INDEX(Rückgabe!$B$32:$B$131,MATCH(12,Rückgabe!$M$32:$M$131,0)),"")="","",IFERROR(INDEX(Rückgabe!$I$32:$I$131,MATCH(12,Rückgabe!$M$32:$M$131,0)),"")) | F21: =IF(IFERROR(INDEX(Rückgabe!$B$32:$B$131,MATCH(12,Rückgabe!$M$32:$M$131,0)),"")="","",IFERROR(INDEX(Rückgabe!$H$32:$H$131,MATCH(12,Rückgabe!$M$32:$M$131,0)),"")) | G21: =IF(IFERROR(INDEX(Rückgabe!$B$32:$B$131,MATCH(12,Rückgabe!$M$32:$M$131,0)),"")="","",IFERROR(INDEX(Rückgabe!$J$32:$J$131,MATCH(12,Rückgabe!$M$32:$M$131,0)),"")) | H21: =IF(IFERROR(INDEX(Rückgabe!$B$32:$B$131,MATCH(12,Rückgabe!$M$32:$M$131,0)),"")="","",IFERROR(INDEX(Rückgabe!$K$32:$K$131,MATCH(12,Rückgabe!$M$32:$M$131,0)),""))
A22: =IF(IFERROR(INDEX(Rückgabe!$B$32:$B$131,MATCH(13,Rückgabe!$M$32:$M$131,0)),"")="","",IFERROR(INDEX(Rückgabe!$B$32:$B$131,MATCH(13,Rückgabe!$M$32:$M$131,0)),"")&" · "&IFERROR(INDEX(Rückgabe!$C$32:$C$131,MATCH(13,Rückgabe!$M$32:$M$131,0)),"")) | B22: =IF(IFERROR(INDEX(Rückgabe!$B$32:$B$131,MATCH(13,Rückgabe!$M$32:$M$131,0)),"")="","",IFERROR(INDEX(Rückgabe!$D$32:$D$131,MATCH(13,Rückgabe!$M$32:$M$131,0)),"")) | C22: =IF(IFERROR(INDEX(Rückgabe!$B$32:$B$131,MATCH(13,Rückgabe!$M$32:$M$131,0)),"")="","",IFERROR(INDEX(Rückgabe!$E$32:$E$131,MATCH(13,Rückgabe!$M$32:$M$131,0)),"")) | D22: =IF(IFERROR(INDEX(Rückgabe!$B$32:$B$131,MATCH(13,Rückgabe!$M$32:$M$131,0)),"")="","",IFERROR(INDEX(Rückgabe!$F$32:$F$131,MATCH(13,Rückgabe!$M$32:$M$131,0)),"")) | E22: =IF(IFERROR(INDEX(Rückgabe!$B$32:$B$131,MATCH(13,Rückgabe!$M$32:$M$131,0)),"")="","",IFERROR(INDEX(Rückgabe!$I$32:$I$131,MATCH(13,Rückgabe!$M$32:$M$131,0)),"")) | F22: =IF(IFERROR(INDEX(Rückgabe!$B$32:$B$131,MATCH(13,Rückgabe!$M$32:$M$131,0)),"")="","",IFERROR(INDEX(Rückgabe!$H$32:$H$131,MATCH(13,Rückgabe!$M$32:$M$131,0)),"")) | G22: =IF(IFERROR(INDEX(Rückgabe!$B$32:$B$131,MATCH(13,Rückgabe!$M$32:$M$131,0)),"")="","",IFERROR(INDEX(Rückgabe!$J$32:$J$131,MATCH(13,Rückgabe!$M$32:$M$131,0)),"")) | H22: =IF(IFERROR(INDEX(Rückgabe!$B$32:$B$131,MATCH(13,Rückgabe!$M$32:$M$131,0)),"")="","",IFERROR(INDEX(Rückgabe!$K$32:$K$131,MATCH(13,Rückgabe!$M$32:$M$131,0)),""))
A23: =IF(IFERROR(INDEX(Rückgabe!$B$32:$B$131,MATCH(14,Rückgabe!$M$32:$M$131,0)),"")="","",IFERROR(INDEX(Rückgabe!$B$32:$B$131,MATCH(14,Rückgabe!$M$32:$M$131,0)),"")&" · "&IFERROR(INDEX(Rückgabe!$C$32:$C$131,MATCH(14,Rückgabe!$M$32:$M$131,0)),"")) | B23: =IF(IFERROR(INDEX(Rückgabe!$B$32:$B$131,MATCH(14,Rückgabe!$M$32:$M$131,0)),"")="","",IFERROR(INDEX(Rückgabe!$D$32:$D$131,MATCH(14,Rückgabe!$M$32:$M$131,0)),"")) | C23: =IF(IFERROR(INDEX(Rückgabe!$B$32:$B$131,MATCH(14,Rückgabe!$M$32:$M$131,0)),"")="","",IFERROR(INDEX(Rückgabe!$E$32:$E$131,MATCH(14,Rückgabe!$M$32:$M$131,0)),"")) | D23: =IF(IFERROR(INDEX(Rückgabe!$B$32:$B$131,MATCH(14,Rückgabe!$M$32:$M$131,0)),"")="","",IFERROR(INDEX(Rückgabe!$F$32:$F$131,MATCH(14,Rückgabe!$M$32:$M$131,0)),"")) | E23: =IF(IFERROR(INDEX(Rückgabe!$B$32:$B$131,MATCH(14,Rückgabe!$M$32:$M$131,0)),"")="","",IFERROR(INDEX(Rückgabe!$I$32:$I$131,MATCH(14,Rückgabe!$M$32:$M$131,0)),"")) | F23: =IF(IFERROR(INDEX(Rückgabe!$B$32:$B$131,MATCH(14,Rückgabe!$M$32:$M$131,0)),"")="","",IFERROR(INDEX(Rückgabe!$H$32:$H$131,MATCH(14,Rückgabe!$M$32:$M$131,0)),"")) | G23: =IF(IFERROR(INDEX(Rückgabe!$B$32:$B$131,MATCH(14,Rückgabe!$M$32:$M$131,0)),"")="","",IFERROR(INDEX(Rückgabe!$J$32:$J$131,MATCH(14,Rückgabe!$M$32:$M$131,0)),"")) | H23: =IF(IFERROR(INDEX(Rückgabe!$B$32:$B$131,MATCH(14,Rückgabe!$M$32:$M$131,0)),"")="","",IFERROR(INDEX(Rückgabe!$K$32:$K$131,MATCH(14,Rückgabe!$M$32:$M$131,0)),""))
A24: =IF(IFERROR(INDEX(Rückgabe!$B$32:$B$131,MATCH(15,Rückgabe!$M$32:$M$131,0)),"")="","",IFERROR(INDEX(Rückgabe!$B$32:$B$131,MATCH(15,Rückgabe!$M$32:$M$131,0)),"")&" · "&IFERROR(INDEX(Rückgabe!$C$32:$C$131,MATCH(15,Rückgabe!$M$32:$M$131,0)),"")) | B24: =IF(IFERROR(INDEX(Rückgabe!$B$32:$B$131,MATCH(15,Rückgabe!$M$32:$M$131,0)),"")="","",IFERROR(INDEX(Rückgabe!$D$32:$D$131,MATCH(15,Rückgabe!$M$32:$M$131,0)),"")) | C24: =IF(IFERROR(INDEX(Rückgabe!$B$32:$B$131,MATCH(15,Rückgabe!$M$32:$M$131,0)),"")="","",IFERROR(INDEX(Rückgabe!$E$32:$E$131,MATCH(15,Rückgabe!$M$32:$M$131,0)),"")) | D24: =IF(IFERROR(INDEX(Rückgabe!$B$32:$B$131,MATCH(15,Rückgabe!$M$32:$M$131,0)),"")="","",IFERROR(INDEX(Rückgabe!$F$32:$F$131,MATCH(15,Rückgabe!$M$32:$M$131,0)),"")) | E24: =IF(IFERROR(INDEX(Rückgabe!$B$32:$B$131,MATCH(15,Rückgabe!$M$32:$M$131,0)),"")="","",IFERROR(INDEX(Rückgabe!$I$32:$I$131,MATCH(15,Rückgabe!$M$32:$M$131,0)),"")) | F24: =IF(IFERROR(INDEX(Rückgabe!$B$32:$B$131,MATCH(15,Rückgabe!$M$32:$M$131,0)),"")="","",IFERROR(INDEX(Rückgabe!$H$32:$H$131,MATCH(15,Rückgabe!$M$32:$M$131,0)),"")) | G24: =IF(IFERROR(INDEX(Rückgabe!$B$32:$B$131,MATCH(15,Rückgabe!$M$32:$M$131,0)),"")="","",IFERROR(INDEX(Rückgabe!$J$32:$J$131,MATCH(15,Rückgabe!$M$32:$M$131,0)),"")) | H24: =IF(IFERROR(INDEX(Rückgabe!$B$32:$B$131,MATCH(15,Rückgabe!$M$32:$M$131,0)),"")="","",IFERROR(INDEX(Rückgabe!$K$32:$K$131,MATCH(15,Rückgabe!$M$32:$M$131,0)),""))
A25: =IF(IFERROR(INDEX(Rückgabe!$B$32:$B$131,MATCH(16,Rückgabe!$M$32:$M$131,0)),"")="","",IFERROR(INDEX(Rückgabe!$B$32:$B$131,MATCH(16,Rückgabe!$M$32:$M$131,0)),"")&" · "&IFERROR(INDEX(Rückgabe!$C$32:$C$131,MATCH(16,Rückgabe!$M$32:$M$131,0)),"")) | B25: =IF(IFERROR(INDEX(Rückgabe!$B$32:$B$131,MATCH(16,Rückgabe!$M$32:$M$131,0)),"")="","",IFERROR(INDEX(Rückgabe!$D$32:$D$131,MATCH(16,Rückgabe!$M$32:$M$131,0)),"")) | C25: =IF(IFERROR(INDEX(Rückgabe!$B$32:$B$131,MATCH(16,Rückgabe!$M$32:$M$131,0)),"")="","",IFERROR(INDEX(Rückgabe!$E$32:$E$131,MATCH(16,Rückgabe!$M$32:$M$131,0)),"")) | D25: =IF(IFERROR(INDEX(Rückgabe!$B$32:$B$131,MATCH(16,Rückgabe!$M$32:$M$131,0)),"")="","",IFERROR(INDEX(Rückgabe!$F$32:$F$131,MATCH(16,Rückgabe!$M$32:$M$131,0)),"")) | E25: =IF(IFERROR(INDEX(Rückgabe!$B$32:$B$131,MATCH(16,Rückgabe!$M$32:$M$131,0)),"")="","",IFERROR(INDEX(Rückgabe!$I$32:$I$131,MATCH(16,Rückgabe!$M$32:$M$131,0)),"")) | F25: =IF(IFERROR(INDEX(Rückgabe!$B$32:$B$131,MATCH(16,Rückgabe!$M$32:$M$131,0)),"")="","",IFERROR(INDEX(Rückgabe!$H$32:$H$131,MATCH(16,Rückgabe!$M$32:$M$131,0)),"")) | G25: =IF(IFERROR(INDEX(Rückgabe!$B$32:$B$131,MATCH(16,Rückgabe!$M$32:$M$131,0)),"")="","",IFERROR(INDEX(Rückgabe!$J$32:$J$131,MATCH(16,Rückgabe!$M$32:$M$131,0)),"")) | H25: =IF(IFERROR(INDEX(Rückgabe!$B$32:$B$131,MATCH(16,Rückgabe!$M$32:$M$131,0)),"")="","",IFERROR(INDEX(Rückgabe!$K$32:$K$131,MATCH(16,Rückgabe!$M$32:$M$131,0)),""))
A26: =IF(IFERROR(INDEX(Rückgabe!$B$32:$B$131,MATCH(17,Rückgabe!$M$32:$M$131,0)),"")="","",IFERROR(INDEX(Rückgabe!$B$32:$B$131,MATCH(17,Rückgabe!$M$32:$M$131,0)),"")&" · "&IFERROR(INDEX(Rückgabe!$C$32:$C$131,MATCH(17,Rückgabe!$M$32:$M$131,0)),"")) | B26: =IF(IFERROR(INDEX(Rückgabe!$B$32:$B$131,MATCH(17,Rückgabe!$M$32:$M$131,0)),"")="","",IFERROR(INDEX(Rückgabe!$D$32:$D$131,MATCH(17,Rückgabe!$M$32:$M$131,0)),"")) | C26: =IF(IFERROR(INDEX(Rückgabe!$B$32:$B$131,MATCH(17,Rückgabe!$M$32:$M$131,0)),"")="","",IFERROR(INDEX(Rückgabe!$E$32:$E$131,MATCH(17,Rückgabe!$M$32:$M$131,0)),"")) | D26: =IF(IFERROR(INDEX(Rückgabe!$B$32:$B$131,MATCH(17,Rückgabe!$M$32:$M$131,0)),"")="","",IFERROR(INDEX(Rückgabe!$F$32:$F$131,MATCH(17,Rückgabe!$M$32:$M$131,0)),"")) | E26: =IF(IFERROR(INDEX(Rückgabe!$B$32:$B$131,MATCH(17,Rückgabe!$M$32:$M$131,0)),"")="","",IFERROR(INDEX(Rückgabe!$I$32:$I$131,MATCH(17,Rückgabe!$M$32:$M$131,0)),"")) | F26: =IF(IFERROR(INDEX(Rückgabe!$B$32:$B$131,MATCH(17,Rückgabe!$M$32:$M$131,0)),"")="","",IFERROR(INDEX(Rückgabe!$H$32:$H$131,MATCH(17,Rückgabe!$M$32:$M$131,0)),"")) | G26: =IF(IFERROR(INDEX(Rückgabe!$B$32:$B$131,MATCH(17,Rückgabe!$M$32:$M$131,0)),"")="","",IFERROR(INDEX(Rückgabe!$J$32:$J$131,MATCH(17,Rückgabe!$M$32:$M$131,0)),"")) | H26: =IF(IFERROR(INDEX(Rückgabe!$B$32:$B$131,MATCH(17,Rückgabe!$M$32:$M$131,0)),"")="","",IFERROR(INDEX(Rückgabe!$K$32:$K$131,MATCH(17,Rückgabe!$M$32:$M$131,0)),""))
A27: =IF(IFERROR(INDEX(Rückgabe!$B$32:$B$131,MATCH(18,Rückgabe!$M$32:$M$131,0)),"")="","",IFERROR(INDEX(Rückgabe!$B$32:$B$131,MATCH(18,Rückgabe!$M$32:$M$131,0)),"")&" · "&IFERROR(INDEX(Rückgabe!$C$32:$C$131,MATCH(18,Rückgabe!$M$32:$M$131,0)),"")) | B27: =IF(IFERROR(INDEX(Rückgabe!$B$32:$B$131,MATCH(18,Rückgabe!$M$32:$M$131,0)),"")="","",IFERROR(INDEX(Rückgabe!$D$32:$D$131,MATCH(18,Rückgabe!$M$32:$M$131,0)),"")) | C27: =IF(IFERROR(INDEX(Rückgabe!$B$32:$B$131,MATCH(18,Rückgabe!$M$32:$M$131,0)),"")="","",IFERROR(INDEX(Rückgabe!$E$32:$E$131,MATCH(18,Rückgabe!$M$32:$M$131,0)),"")) | D27: =IF(IFERROR(INDEX(Rückgabe!$B$32:$B$131,MATCH(18,Rückgabe!$M$32:$M$131,0)),"")="","",IFERROR(INDEX(Rückgabe!$F$32:$F$131,MATCH(18,Rückgabe!$M$32:$M$131,0)),"")) | E27: =IF(IFERROR(INDEX(Rückgabe!$B$32:$B$131,MATCH(18,Rückgabe!$M$32:$M$131,0)),"")="","",IFERROR(INDEX(Rückgabe!$I$32:$I$131,MATCH(18,Rückgabe!$M$32:$M$131,0)),"")) | F27: =IF(IFERROR(INDEX(Rückgabe!$B$32:$B$131,MATCH(18,Rückgabe!$M$32:$M$131,0)),"")="","",IFERROR(INDEX(Rückgabe!$H$32:$H$131,MATCH(18,Rückgabe!$M$32:$M$131,0)),"")) | G27: =IF(IFERROR(INDEX(Rückgabe!$B$32:$B$131,MATCH(18,Rückgabe!$M$32:$M$131,0)),"")="","",IFERROR(INDEX(Rückgabe!$J$32:$J$131,MATCH(18,Rückgabe!$M$32:$M$131,0)),"")) | H27: =IF(IFERROR(INDEX(Rückgabe!$B$32:$B$131,MATCH(18,Rückgabe!$M$32:$M$131,0)),"")="","",IFERROR(INDEX(Rückgabe!$K$32:$K$131,MATCH(18,Rückgabe!$M$32:$M$131,0)),""))
A28: =IF(IFERROR(INDEX(Rückgabe!$B$32:$B$131,MATCH(19,Rückgabe!$M$32:$M$131,0)),"")="","",IFERROR(INDEX(Rückgabe!$B$32:$B$131,MATCH(19,Rückgabe!$M$32:$M$131,0)),"")&" · "&IFERROR(INDEX(Rückgabe!$C$32:$C$131,MATCH(19,Rückgabe!$M$32:$M$131,0)),"")) | B28: =IF(IFERROR(INDEX(Rückgabe!$B$32:$B$131,MATCH(19,Rückgabe!$M$32:$M$131,0)),"")="","",IFERROR(INDEX(Rückgabe!$D$32:$D$131,MATCH(19,Rückgabe!$M$32:$M$131,0)),"")) | C28: =IF(IFERROR(INDEX(Rückgabe!$B$32:$B$131,MATCH(19,Rückgabe!$M$32:$M$131,0)),"")="","",IFERROR(INDEX(Rückgabe!$E$32:$E$131,MATCH(19,Rückgabe!$M$32:$M$131,0)),"")) | D28: =IF(IFERROR(INDEX(Rückgabe!$B$32:$B$131,MATCH(19,Rückgabe!$M$32:$M$131,0)),"")="","",IFERROR(INDEX(Rückgabe!$F$32:$F$131,MATCH(19,Rückgabe!$M$32:$M$131,0)),"")) | E28: =IF(IFERROR(INDEX(Rückgabe!$B$32:$B$131,MATCH(19,Rückgabe!$M$32:$M$131,0)),"")="","",IFERROR(INDEX(Rückgabe!$I$32:$I$131,MATCH(19,Rückgabe!$M$32:$M$131,0)),"")) | F28: =IF(IFERROR(INDEX(Rückgabe!$B$32:$B$131,MATCH(19,Rückgabe!$M$32:$M$131,0)),"")="","",IFERROR(INDEX(Rückgabe!$H$32:$H$131,MATCH(19,Rückgabe!$M$32:$M$131,0)),"")) | G28: =IF(IFERROR(INDEX(Rückgabe!$B$32:$B$131,MATCH(19,Rückgabe!$M$32:$M$131,0)),"")="","",IFERROR(INDEX(Rückgabe!$J$32:$J$131,MATCH(19,Rückgabe!$M$32:$M$131,0)),"")) | H28: =IF(IFERROR(INDEX(Rückgabe!$B$32:$B$131,MATCH(19,Rückgabe!$M$32:$M$131,0)),"")="","",IFERROR(INDEX(Rückgabe!$K$32:$K$131,MATCH(19,Rückgabe!$M$32:$M$131,0)),""))
A29: =IF(IFERROR(INDEX(Rückgabe!$B$32:$B$131,MATCH(20,Rückgabe!$M$32:$M$131,0)),"")="","",IFERROR(INDEX(Rückgabe!$B$32:$B$131,MATCH(20,Rückgabe!$M$32:$M$131,0)),"")&" · "&IFERROR(INDEX(Rückgabe!$C$32:$C$131,MATCH(20,Rückgabe!$M$32:$M$131,0)),"")) | B29: =IF(IFERROR(INDEX(Rückgabe!$B$32:$B$131,MATCH(20,Rückgabe!$M$32:$M$131,0)),"")="","",IFERROR(INDEX(Rückgabe!$D$32:$D$131,MATCH(20,Rückgabe!$M$32:$M$131,0)),"")) | C29: =IF(IFERROR(INDEX(Rückgabe!$B$32:$B$131,MATCH(20,Rückgabe!$M$32:$M$131,0)),"")="","",IFERROR(INDEX(Rückgabe!$E$32:$E$131,MATCH(20,Rückgabe!$M$32:$M$131,0)),"")) | D29: =IF(IFERROR(INDEX(Rückgabe!$B$32:$B$131,MATCH(20,Rückgabe!$M$32:$M$131,0)),"")="","",IFERROR(INDEX(Rückgabe!$F$32:$F$131,MATCH(20,Rückgabe!$M$32:$M$131,0)),"")) | E29: =IF(IFERROR(INDEX(Rückgabe!$B$32:$B$131,MATCH(20,Rückgabe!$M$32:$M$131,0)),"")="","",IFERROR(INDEX(Rückgabe!$I$32:$I$131,MATCH(20,Rückgabe!$M$32:$M$131,0)),"")) | F29: =IF(IFERROR(INDEX(Rückgabe!$B$32:$B$131,MATCH(20,Rückgabe!$M$32:$M$131,0)),"")="","",IFERROR(INDEX(Rückgabe!$H$32:$H$131,MATCH(20,Rückgabe!$M$32:$M$131,0)),"")) | G29: =IF(IFERROR(INDEX(Rückgabe!$B$32:$B$131,MATCH(20,Rückgabe!$M$32:$M$131,0)),"")="","",IFERROR(INDEX(Rückgabe!$J$32:$J$131,MATCH(20,Rückgabe!$M$32:$M$131,0)),"")) | H29: =IF(IFERROR(INDEX(Rückgabe!$B$32:$B$131,MATCH(20,Rückgabe!$M$32:$M$131,0)),"")="","",IFERROR(INDEX(Rückgabe!$K$32:$K$131,MATCH(20,Rückgabe!$M$32:$M$131,0)),""))
A30: =IF(IFERROR(INDEX(Rückgabe!$B$32:$B$131,MATCH(21,Rückgabe!$M$32:$M$131,0)),"")="","",IFERROR(INDEX(Rückgabe!$B$32:$B$131,MATCH(21,Rückgabe!$M$32:$M$131,0)),"")&" · "&IFERROR(INDEX(Rückgabe!$C$32:$C$131,MATCH(21,Rückgabe!$M$32:$M$131,0)),"")) | B30: =IF(IFERROR(INDEX(Rückgabe!$B$32:$B$131,MATCH(21,Rückgabe!$M$32:$M$131,0)),"")="","",IFERROR(INDEX(Rückgabe!$D$32:$D$131,MATCH(21,Rückgabe!$M$32:$M$131,0)),"")) | C30: =IF(IFERROR(INDEX(Rückgabe!$B$32:$B$131,MATCH(21,Rückgabe!$M$32:$M$131,0)),"")="","",IFERROR(INDEX(Rückgabe!$E$32:$E$131,MATCH(21,Rückgabe!$M$32:$M$131,0)),"")) | D30: =IF(IFERROR(INDEX(Rückgabe!$B$32:$B$131,MATCH(21,Rückgabe!$M$32:$M$131,0)),"")="","",IFERROR(INDEX(Rückgabe!$F$32:$F$131,MATCH(21,Rückgabe!$M$32:$M$131,0)),"")) | E30: =IF(IFERROR(INDEX(Rückgabe!$B$32:$B$131,MATCH(21,Rückgabe!$M$32:$M$131,0)),"")="","",IFERROR(INDEX(Rückgabe!$I$32:$I$131,MATCH(21,Rückgabe!$M$32:$M$131,0)),"")) | F30: =IF(IFERROR(INDEX(Rückgabe!$B$32:$B$131,MATCH(21,Rückgabe!$M$32:$M$131,0)),"")="","",IFERROR(INDEX(Rückgabe!$H$32:$H$131,MATCH(21,Rückgabe!$M$32:$M$131,0)),"")) | G30: =IF(IFERROR(INDEX(Rückgabe!$B$32:$B$131,MATCH(21,Rückgabe!$M$32:$M$131,0)),"")="","",IFERROR(INDEX(Rückgabe!$J$32:$J$131,MATCH(21,Rückgabe!$M$32:$M$131,0)),"")) | H30: =IF(IFERROR(INDEX(Rückgabe!$B$32:$B$131,MATCH(21,Rückgabe!$M$32:$M$131,0)),"")="","",IFERROR(INDEX(Rückgabe!$K$32:$K$131,MATCH(21,Rückgabe!$M$32:$M$131,0)),""))
A31: =IF(IFERROR(INDEX(Rückgabe!$B$32:$B$131,MATCH(22,Rückgabe!$M$32:$M$131,0)),"")="","",IFERROR(INDEX(Rückgabe!$B$32:$B$131,MATCH(22,Rückgabe!$M$32:$M$131,0)),"")&" · "&IFERROR(INDEX(Rückgabe!$C$32:$C$131,MATCH(22,Rückgabe!$M$32:$M$131,0)),"")) | B31: =IF(IFERROR(INDEX(Rückgabe!$B$32:$B$131,MATCH(22,Rückgabe!$M$32:$M$131,0)),"")="","",IFERROR(INDEX(Rückgabe!$D$32:$D$131,MATCH(22,Rückgabe!$M$32:$M$131,0)),"")) | C31: =IF(IFERROR(INDEX(Rückgabe!$B$32:$B$131,MATCH(22,Rückgabe!$M$32:$M$131,0)),"")="","",IFERROR(INDEX(Rückgabe!$E$32:$E$131,MATCH(22,Rückgabe!$M$32:$M$131,0)),"")) | D31: =IF(IFERROR(INDEX(Rückgabe!$B$32:$B$131,MATCH(22,Rückgabe!$M$32:$M$131,0)),"")="","",IFERROR(INDEX(Rückgabe!$F$32:$F$131,MATCH(22,Rückgabe!$M$32:$M$131,0)),"")) | E31: =IF(IFERROR(INDEX(Rückgabe!$B$32:$B$131,MATCH(22,Rückgabe!$M$32:$M$131,0)),"")="","",IFERROR(INDEX(Rückgabe!$I$32:$I$131,MATCH(22,Rückgabe!$M$32:$M$131,0)),"")) | F31: =IF(IFERROR(INDEX(Rückgabe!$B$32:$B$131,MATCH(22,Rückgabe!$M$32:$M$131,0)),"")="","",IFERROR(INDEX(Rückgabe!$H$32:$H$131,MATCH(22,Rückgabe!$M$32:$M$131,0)),"")) | G31: =IF(IFERROR(INDEX(Rückgabe!$B$32:$B$131,MATCH(22,Rückgabe!$M$32:$M$131,0)),"")="","",IFERROR(INDEX(Rückgabe!$J$32:$J$131,MATCH(22,Rückgabe!$M$32:$M$131,0)),"")) | H31: =IF(IFERROR(INDEX(Rückgabe!$B$32:$B$131,MATCH(22,Rückgabe!$M$32:$M$131,0)),"")="","",IFERROR(INDEX(Rückgabe!$K$32:$K$131,MATCH(22,Rückgabe!$M$32:$M$131,0)),""))
A32: =IF(IFERROR(INDEX(Rückgabe!$B$32:$B$131,MATCH(23,Rückgabe!$M$32:$M$131,0)),"")="","",IFERROR(INDEX(Rückgabe!$B$32:$B$131,MATCH(23,Rückgabe!$M$32:$M$131,0)),"")&" · "&IFERROR(INDEX(Rückgabe!$C$32:$C$131,MATCH(23,Rückgabe!$M$32:$M$131,0)),"")) | B32: =IF(IFERROR(INDEX(Rückgabe!$B$32:$B$131,MATCH(23,Rückgabe!$M$32:$M$131,0)),"")="","",IFERROR(INDEX(Rückgabe!$D$32:$D$131,MATCH(23,Rückgabe!$M$32:$M$131,0)),"")) | C32: =IF(IFERROR(INDEX(Rückgabe!$B$32:$B$131,MATCH(23,Rückgabe!$M$32:$M$131,0)),"")="","",IFERROR(INDEX(Rückgabe!$E$32:$E$131,MATCH(23,Rückgabe!$M$32:$M$131,0)),"")) | D32: =IF(IFERROR(INDEX(Rückgabe!$B$32:$B$131,MATCH(23,Rückgabe!$M$32:$M$131,0)),"")="","",IFERROR(INDEX(Rückgabe!$F$32:$F$131,MATCH(23,Rückgabe!$M$32:$M$131,0)),"")) | E32: =IF(IFERROR(INDEX(Rückgabe!$B$32:$B$131,MATCH(23,Rückgabe!$M$32:$M$131,0)),"")="","",IFERROR(INDEX(Rückgabe!$I$32:$I$131,MATCH(23,Rückgabe!$M$32:$M$131,0)),"")) | F32: =IF(IFERROR(INDEX(Rückgabe!$B$32:$B$131,MATCH(23,Rückgabe!$M$32:$M$131,0)),"")="","",IFERROR(INDEX(Rückgabe!$H$32:$H$131,MATCH(23,Rückgabe!$M$32:$M$131,0)),"")) | G32: =IF(IFERROR(INDEX(Rückgabe!$B$32:$B$131,MATCH(23,Rückgabe!$M$32:$M$131,0)),"")="","",IFERROR(INDEX(Rückgabe!$J$32:$J$131,MATCH(23,Rückgabe!$M$32:$M$131,0)),"")) | H32: =IF(IFERROR(INDEX(Rückgabe!$B$32:$B$131,MATCH(23,Rückgabe!$M$32:$M$131,0)),"")="","",IFERROR(INDEX(Rückgabe!$K$32:$K$131,MATCH(23,Rückgabe!$M$32:$M$131,0)),""))
A33: =IF(IFERROR(INDEX(Rückgabe!$B$32:$B$131,MATCH(24,Rückgabe!$M$32:$M$131,0)),"")="","",IFERROR(INDEX(Rückgabe!$B$32:$B$131,MATCH(24,Rückgabe!$M$32:$M$131,0)),"")&" · "&IFERROR(INDEX(Rückgabe!$C$32:$C$131,MATCH(24,Rückgabe!$M$32:$M$131,0)),"")) | B33: =IF(IFERROR(INDEX(Rückgabe!$B$32:$B$131,MATCH(24,Rückgabe!$M$32:$M$131,0)),"")="","",IFERROR(INDEX(Rückgabe!$D$32:$D$131,MATCH(24,Rückgabe!$M$32:$M$131,0)),"")) | C33: =IF(IFERROR(INDEX(Rückgabe!$B$32:$B$131,MATCH(24,Rückgabe!$M$32:$M$131,0)),"")="","",IFERROR(INDEX(Rückgabe!$E$32:$E$131,MATCH(24,Rückgabe!$M$32:$M$131,0)),"")) | D33: =IF(IFERROR(INDEX(Rückgabe!$B$32:$B$131,MATCH(24,Rückgabe!$M$32:$M$131,0)),"")="","",IFERROR(INDEX(Rückgabe!$F$32:$F$131,MATCH(24,Rückgabe!$M$32:$M$131,0)),"")) | E33: =IF(IFERROR(INDEX(Rückgabe!$B$32:$B$131,MATCH(24,Rückgabe!$M$32:$M$131,0)),"")="","",IFERROR(INDEX(Rückgabe!$I$32:$I$131,MATCH(24,Rückgabe!$M$32:$M$131,0)),"")) | F33: =IF(IFERROR(INDEX(Rückgabe!$B$32:$B$131,MATCH(24,Rückgabe!$M$32:$M$131,0)),"")="","",IFERROR(INDEX(Rückgabe!$H$32:$H$131,MATCH(24,Rückgabe!$M$32:$M$131,0)),"")) | G33: =IF(IFERROR(INDEX(Rückgabe!$B$32:$B$131,MATCH(24,Rückgabe!$M$32:$M$131,0)),"")="","",IFERROR(INDEX(Rückgabe!$J$32:$J$131,MATCH(24,Rückgabe!$M$32:$M$131,0)),"")) | H33: =IF(IFERROR(INDEX(Rückgabe!$B$32:$B$131,MATCH(24,Rückgabe!$M$32:$M$131,0)),"")="","",IFERROR(INDEX(Rückgabe!$K$32:$K$131,MATCH(24,Rückgabe!$M$32:$M$131,0)),""))
A34: =IF(IFERROR(INDEX(Rückgabe!$B$32:$B$131,MATCH(25,Rückgabe!$M$32:$M$131,0)),"")="","",IFERROR(INDEX(Rückgabe!$B$32:$B$131,MATCH(25,Rückgabe!$M$32:$M$131,0)),"")&" · "&IFERROR(INDEX(Rückgabe!$C$32:$C$131,MATCH(25,Rückgabe!$M$32:$M$131,0)),"")) | B34: =IF(IFERROR(INDEX(Rückgabe!$B$32:$B$131,MATCH(25,Rückgabe!$M$32:$M$131,0)),"")="","",IFERROR(INDEX(Rückgabe!$D$32:$D$131,MATCH(25,Rückgabe!$M$32:$M$131,0)),"")) | C34: =IF(IFERROR(INDEX(Rückgabe!$B$32:$B$131,MATCH(25,Rückgabe!$M$32:$M$131,0)),"")="","",IFERROR(INDEX(Rückgabe!$E$32:$E$131,MATCH(25,Rückgabe!$M$32:$M$131,0)),"")) | D34: =IF(IFERROR(INDEX(Rückgabe!$B$32:$B$131,MATCH(25,Rückgabe!$M$32:$M$131,0)),"")="","",IFERROR(INDEX(Rückgabe!$F$32:$F$131,MATCH(25,Rückgabe!$M$32:$M$131,0)),"")) | E34: =IF(IFERROR(INDEX(Rückgabe!$B$32:$B$131,MATCH(25,Rückgabe!$M$32:$M$131,0)),"")="","",IFERROR(INDEX(Rückgabe!$I$32:$I$131,MATCH(25,Rückgabe!$M$32:$M$131,0)),"")) | F34: =IF(IFERROR(INDEX(Rückgabe!$B$32:$B$131,MATCH(25,Rückgabe!$M$32:$M$131,0)),"")="","",IFERROR(INDEX(Rückgabe!$H$32:$H$131,MATCH(25,Rückgabe!$M$32:$M$131,0)),"")) | G34: =IF(IFERROR(INDEX(Rückgabe!$B$32:$B$131,MATCH(25,Rückgabe!$M$32:$M$131,0)),"")="","",IFERROR(INDEX(Rückgabe!$J$32:$J$131,MATCH(25,Rückgabe!$M$32:$M$131,0)),"")) | H34: =IF(IFERROR(INDEX(Rückgabe!$B$32:$B$131,MATCH(25,Rückgabe!$M$32:$M$131,0)),"")="","",IFERROR(INDEX(Rückgabe!$K$32:$K$131,MATCH(25,Rückgabe!$M$32:$M$131,0)),""))
A35: =IF(IFERROR(INDEX(Rückgabe!$B$32:$B$131,MATCH(26,Rückgabe!$M$32:$M$131,0)),"")="","",IFERROR(INDEX(Rückgabe!$B$32:$B$131,MATCH(26,Rückgabe!$M$32:$M$131,0)),"")&" · "&IFERROR(INDEX(Rückgabe!$C$32:$C$131,MATCH(26,Rückgabe!$M$32:$M$131,0)),"")) | B35: =IF(IFERROR(INDEX(Rückgabe!$B$32:$B$131,MATCH(26,Rückgabe!$M$32:$M$131,0)),"")="","",IFERROR(INDEX(Rückgabe!$D$32:$D$131,MATCH(26,Rückgabe!$M$32:$M$131,0)),"")) | C35: =IF(IFERROR(INDEX(Rückgabe!$B$32:$B$131,MATCH(26,Rückgabe!$M$32:$M$131,0)),"")="","",IFERROR(INDEX(Rückgabe!$E$32:$E$131,MATCH(26,Rückgabe!$M$32:$M$131,0)),"")) | D35: =IF(IFERROR(INDEX(Rückgabe!$B$32:$B$131,MATCH(26,Rückgabe!$M$32:$M$131,0)),"")="","",IFERROR(INDEX(Rückgabe!$F$32:$F$131,MATCH(26,Rückgabe!$M$32:$M$131,0)),"")) | E35: =IF(IFERROR(INDEX(Rückgabe!$B$32:$B$131,MATCH(26,Rückgabe!$M$32:$M$131,0)),"")="","",IFERROR(INDEX(Rückgabe!$I$32:$I$131,MATCH(26,Rückgabe!$M$32:$M$131,0)),"")) | F35: =IF(IFERROR(INDEX(Rückgabe!$B$32:$B$131,MATCH(26,Rückgabe!$M$32:$M$131,0)),"")="","",IFERROR(INDEX(Rückgabe!$H$32:$H$131,MATCH(26,Rückgabe!$M$32:$M$131,0)),"")) | G35: =IF(IFERROR(INDEX(Rückgabe!$B$32:$B$131,MATCH(26,Rückgabe!$M$32:$M$131,0)),"")="","",IFERROR(INDEX(Rückgabe!$J$32:$J$131,MATCH(26,Rückgabe!$M$32:$M$131,0)),"")) | H35: =IF(IFERROR(INDEX(Rückgabe!$B$32:$B$131,MATCH(26,Rückgabe!$M$32:$M$131,0)),"")="","",IFERROR(INDEX(Rückgabe!$K$32:$K$131,MATCH(26,Rückgabe!$M$32:$M$131,0)),""))
A36: =IF(IFERROR(INDEX(Rückgabe!$B$32:$B$131,MATCH(27,Rückgabe!$M$32:$M$131,0)),"")="","",IFERROR(INDEX(Rückgabe!$B$32:$B$131,MATCH(27,Rückgabe!$M$32:$M$131,0)),"")&" · "&IFERROR(INDEX(Rückgabe!$C$32:$C$131,MATCH(27,Rückgabe!$M$32:$M$131,0)),"")) | B36: =IF(IFERROR(INDEX(Rückgabe!$B$32:$B$131,MATCH(27,Rückgabe!$M$32:$M$131,0)),"")="","",IFERROR(INDEX(Rückgabe!$D$32:$D$131,MATCH(27,Rückgabe!$M$32:$M$131,0)),"")) | C36: =IF(IFERROR(INDEX(Rückgabe!$B$32:$B$131,MATCH(27,Rückgabe!$M$32:$M$131,0)),"")="","",IFERROR(INDEX(Rückgabe!$E$32:$E$131,MATCH(27,Rückgabe!$M$32:$M$131,0)),"")) | D36: =IF(IFERROR(INDEX(Rückgabe!$B$32:$B$131,MATCH(27,Rückgabe!$M$32:$M$131,0)),"")="","",IFERROR(INDEX(Rückgabe!$F$32:$F$131,MATCH(27,Rückgabe!$M$32:$M$131,0)),"")) | E36: =IF(IFERROR(INDEX(Rückgabe!$B$32:$B$131,MATCH(27,Rückgabe!$M$32:$M$131,0)),"")="","",IFERROR(INDEX(Rückgabe!$I$32:$I$131,MATCH(27,Rückgabe!$M$32:$M$131,0)),"")) | F36: =IF(IFERROR(INDEX(Rückgabe!$B$32:$B$131,MATCH(27,Rückgabe!$M$32:$M$131,0)),"")="","",IFERROR(INDEX(Rückgabe!$H$32:$H$131,MATCH(27,Rückgabe!$M$32:$M$131,0)),"")) | G36: =IF(IFERROR(INDEX(Rückgabe!$B$32:$B$131,MATCH(27,Rückgabe!$M$32:$M$131,0)),"")="","",IFERROR(INDEX(Rückgabe!$J$32:$J$131,MATCH(27,Rückgabe!$M$32:$M$131,0)),"")) | H36: =IF(IFERROR(INDEX(Rückgabe!$B$32:$B$131,MATCH(27,Rückgabe!$M$32:$M$131,0)),"")="","",IFERROR(INDEX(Rückgabe!$K$32:$K$131,MATCH(27,Rückgabe!$M$32:$M$131,0)),""))
