Workbook

Sheet Start
A1: Wohnungsrückgabe: Schaden & Kaution
A3: START – was Sie eingeben
A4: Blatt «Rückgabe»: Mietende, Kaution und offene Beträge. Dann jeden Mangel aus dem Abnahmeprotokoll: Kosten laut Offerte, Einbaudatum und Lebensdauer.
A5: BERECHNUNG – was die Vorlage macht
A6: Der Mieter zahlt nur den Restwert: Kosten × (1 − Alter ÷ Lebensdauer). Ist ein Bauteil älter als seine Lebensdauer, zahlt er nichts. Normale Abnutzung und vorbestehende Mängel gehen nie zu seinen Lasten.
A7: ERGEBNIS – was Sie jetzt tun
A8: «Abrechnung» zeigt, wie viel von der Kaution Ihnen zusteht und wie viel der Mieter zurückerhält. «Kontrolle» meldet fehlende oder unplausible Angaben.
A9: AUSGABE – was Sie versenden
A10: «Abrechnung» an den Mieter senden. «Freigabe Kaution» von beiden Parteien unterschreiben lassen und der Bank schicken.
A12: Wo finde ich die Lebensdauer?
A13: In der paritätischen Lebensdauertabelle von Hauseigentümerverband (HEV) und Mieterverband (MV). Ein Auszug ist online gratis, die vollständige Tabelle verkaufen beide Verbände.
A14: Leere Lebensdauer = keine Altersentwertung (z.B. fehlender Schlüssel, Reinigung). Die Beispielwerte im Beispiel sind vor Gebrauch in der Tabelle zu prüfen.
... A21: • Berechnen Sie Kosten nur mit Offerten oder Rechnungen. Pauschalen ohne Beleg werden häufig nicht anerkannt.

Sheet Rückgabe
A1: Wohnungsrückgabe
A2: Gelb = Eingabe · Blau = rechnet automatisch
A4: Liegenschaft | B4: Musterstrasse 12, 8004 Zürich
A5: Wohnung | B5: 1. OG links, 3.5 Zimmer
A6: Mieter | B6: Muster Anna
A7: Neue Adresse Mieter | B7: Seeweg 3, 8800 Thalwil
A8: Vermieter | B8: Hans Beispiel, Bergstrasse 1, 8004 Zürich
A9: Mietende | B9: 46295
A10: Abnahme am | B10: 46295
A11: Mietkaution (Betrag) | B11: 4950
A12: Aufgelaufener Kautionszins | B12: 12.4
A13: Bank / Kautionskonto | B13: Musterbank, Konto 123.456.789
A15: Weitere Forderungen an den Mieter
A16: Ausstehende Mietzinse | B16: 0
A17: Nebenkosten-Saldo (+ Nachzahlung / − Guthaben) | B17: 168.35 | C17: ← aus der Nebenkostenabrechnung übernehmen
A18: Weitere Forderungen (z.B. Reinigung, Entsorgung) | B18: 0
A21: Mängel aus dem Abnahmeprotokoll
A22: Ursache «Mieter» nur bei Schäden über die normale Abnutzung hinaus.
A23: Raum | B23: Bauteil | C23: Mangel | D23: Ursache | E23: Kosten laut Offerte CHF | F23: Einbau / letzte Erneuerung | G23: Lebensdauer Jahre | H23: Alter bei Mietende | I23: Restwert | J23: Zulasten Mieter CHF | K23: Prüfen
A24: Wohnzimmer | B24: Wandanstrich | C24: Starke Nikotinverfärbung | D24: Mieter | E24: 1800 | F24: 43556 | G24: 8 | H24: =IF(OR(F24="",$B$9=""),"",($B$9-F24)/365.25) | I24: =IF(E24="","",IF(D24<>"Mieter",0,IF(G24="",1,IF(OR(F24="",$B$9=""),"",MAX(0,1-H24/G24))))) | J24: =IF(OR(I24="",E24=""),0,ROUND(E24*I24*20,0)/20) | K24: =IF(E24="","",IF(E24<0,"Kosten negativ",IF(D24="","Ursache wählen",IF(AND(F24<>"",$B$9<>"",F24>$B$9),"Einbau nach Mietende",IF(AND(D24="Mieter",G24<>"",F24=""),"Einbaudatum fehlt",IF(AND(D24="Mieter",G24<>"",G24<=0),"Lebensdauer ungültig",""))))))
A25: Küche | B25: Backofen | C25: Türglas gesprungen | D25: Mieter | E25: 950 | F25: 41791 | G25: 15 | H25: =IF(OR(F25="",$B$9=""),"",($B$9-F25)/365.25) | I25: =IF(E25="","",IF(D25<>"Mieter",0,IF(G25="",1,IF(OR(F25="",$B$9=""),"",MAX(0,1-H25/G25))))) | J25: =IF(OR(I25="",E25=""),0,ROUND(E25*I25*20,0)/20) | K25: =IF(E25="","",IF(E25<0,"Kosten negativ",IF(D25="","Ursache wählen",IF(AND(F25<>"",$B$9<>"",F25>$B$9),"Einbau nach Mietende",IF(AND(D25="Mieter",G25<>"",F25=""),"Einbaudatum fehlt",IF(AND(D25="Mieter",G25<>"",G25<=0),"Lebensdauer ungültig",""))))))
A26: Wohnzimmer | B26: Parkett | C26: Wasserflecken vor Balkontür | D26: Mieter | E26: 2400 | F26: 38353 | G26: 40 | H26: =IF(OR(F26="",$B$9=""),"",($B$9-F26)/365.25) | I26: =IF(E26="","",IF(D26<>"Mieter",0,IF(G26="",1,IF(OR(F26="",$B$9=""),"",MAX(0,1-H26/G26))))) | J26: =IF(OR(I26="",E26=""),0,ROUND(E26*I26*20,0)/20) | K26: =IF(E26="","",IF(E26<0,"Kosten negativ",IF(D26="","Ursache wählen",IF(AND(F26<>"",$B$9<>"",F26>$B$9),"Einbau nach Mietende",IF(AND(D26="Mieter",G26<>"",F26=""),"Einbaudatum fehlt",IF(AND(D26="Mieter",G26<>"",G26<=0),"Lebensdauer ungültig",""))))))
A27: Schlafzimmer | B27: Teppich | C27: Laufspuren | D27: Normale Abnutzung | E27: 1200 | F27: 42430 | G27: 10 | H27: =IF(OR(F27="",$B$9=""),"",($B$9-F27)/365.25) | I27: =IF(E27="","",IF(D27<>"Mieter",0,IF(G27="",1,IF(OR(F27="",$B$9=""),"",MAX(0,1-H27/G27))))) | J27: =IF(OR(I27="",E27=""),0,ROUND(E27*I27*20,0)/20) | K27: =IF(E27="","",IF(E27<0,"Kosten negativ",IF(D27="","Ursache wählen",IF(AND(F27<>"",$B$9<>"",F27>$B$9),"Einbau nach Mietende",IF(AND(D27="Mieter",G27<>"",F27=""),"Einbaudatum fehlt",IF(AND(D27="Mieter",G27<>"",G27<=0),"Lebensdauer ungültig",""))))))
A28: Bad | B28: Spiegelschrank | C28: Kratzer (im Eintrittsprotokoll vermerkt) | D28: Vorbestehend | E28: 300 | H28: =IF(OR(F28="",$B$9=""),"",($B$9-F28)/365.25) | I28: =IF(E28="","",IF(D28<>"Mieter",0,IF(G28="",1,IF(OR(F28="",$B$9=""),"",MAX(0,1-H28/G28))))) | J28: =IF(OR(I28="",E28=""),0,ROUND(E28*I28*20,0)/20) | K28: =IF(E28="","",IF(E28<0,"Kosten negativ",IF(D28="","Ursache wählen",IF(AND(F28<>"",$B$9<>"",F28>$B$9),"Einbau nach Mietende",IF(AND(D28="Mieter",G28<>"",F28=""),"Einbaudatum fehlt",IF(AND(D28="Mieter",G28<>"",G28<=0),"Lebensdauer ungültig",""))))))
A29: Eingang | B29: Schlüssel | C29: 1 Wohnungsschlüssel fehlt | D29: Mieter | E29: 180 | H29: =IF(OR(F29="",$B$9=""),"",($B$9-F29)/365.25) | I29: =IF(E29="","",IF(D29<>"Mieter",0,IF(G29="",1,IF(OR(F29="",$B$9=""),"",MAX(0,1-H29/G29))))) | J29: =IF(OR(I29="",E29=""),0,ROUND(E29*I29*20,0)/20) | K29: =IF(E29="","",IF(E29<0,"Kosten negativ",IF(D29="","Ursache wählen",IF(AND(F29<>"",$B$9<>"",F29>$B$9),"Einbau nach Mietende",IF(AND(D29="Mieter",G29<>"",F29=""),"Einbaudatum fehlt",IF(AND(D29="Mieter",G29<>"",G29<=0),"Lebensdauer ungültig",""))))))
H30: =IF(OR(F30="",$B$9=""),"",($B$9-F30)/365.25) | I30: =IF(E30="","",IF(D30<>"Mieter",0,IF(G30="",1,IF(OR(F30="",$B$9=""),"",MAX(0,1-H30/G30))))) | J30: =IF(OR(I30="",E30=""),0,ROUND(E30*I30*20,0)/20) | K30: =IF(E30="","",IF(E30<0,"Kosten negativ",IF(D30="","Ursache wählen",IF(AND(F30<>"",$B$9<>"",F30>$B$9),"Einbau nach Mietende",IF(AND(D30="Mieter",G30<>"",F30=""),"Einbaudatum fehlt",IF(AND(D30="Mieter",G30<>"",G30<=0),"Lebensdauer ungültig",""))))))
H31: =IF(OR(F31="",$B$9=""),"",($B$9-F31)/365.25) | I31: =IF(E31="","",IF(D31<>"Mieter",0,IF(G31="",1,IF(OR(F31="",$B$9=""),"",MAX(0,1-H31/G31))))) | J31: =IF(OR(I31="",E31=""),0,ROUND(E31*I31*20,0)/20) | K31: =IF(E31="","",IF(E31<0,"Kosten negativ",IF(D31="","Ursache wählen",IF(AND(F31<>"",$B$9<>"",F31>$B$9),"Einbau nach Mietende",IF(AND(D31="Mieter",G31<>"",F31=""),"Einbaudatum fehlt",IF(AND(D31="Mieter",G31<>"",G31<=0),"Lebensdauer ungültig",""))))))
H32: =IF(OR(F32="",$B$9=""),"",($B$9-F32)/365.25) | I32: =IF(E32="","",IF(D32<>"Mieter",0,IF(G32="",1,IF(OR(F32="",$B$9=""),"",MAX(0,1-H32/G32))))) | J32: =IF(OR(I32="",E32=""),0,ROUND(E32*I32*20,0)/20) | K32: =IF(E32="","",IF(E32<0,"Kosten negativ",IF(D32="","Ursache wählen",IF(AND(F32<>"",$B$9<>"",F32>$B$9),"Einbau nach Mietende",IF(AND(D32="Mieter",G32<>"",F32=""),"Einbaudatum fehlt",IF(AND(D32="Mieter",G32<>"",G32<=0),"Lebensdauer ungültig",""))))))
H33: =IF(OR(F33="",$B$9=""),"",($B$9-F33)/365.25) | I33: =IF(E33="","",IF(D33<>"Mieter",0,IF(G33="",1,IF(OR(F33="",$B$9=""),"",MAX(0,1-H33/G33))))) | J33: =IF(OR(I33="",E33=""),0,ROUND(E33*I33*20,0)/20) | K33: =IF(E33="","",IF(E33<0,"Kosten negativ",IF(D33="","Ursache wählen",IF(AND(F33<>"",$B$9<>"",F33>$B$9),"Einbau nach Mietende",IF(AND(D33="Mieter",G33<>"",F33=""),"Einbaudatum fehlt",IF(AND(D33="Mieter",G33<>"",G33<=0),"Lebensdauer ungültig",""))))))
H34: =IF(OR(F34="",$B$9=""),"",($B$9-F34)/365.25) | I34: =IF(E34="","",IF(D34<>"Mieter",0,IF(G34="",1,IF(OR(F34="",$B$9=""),"",MAX(0,1-H34/G34))))) | J34: =IF(OR(I34="",E34=""),0,ROUND(E34*I34*20,0)/20) | K34: =IF(E34="","",IF(E34<0,"Kosten negativ",IF(D34="","Ursache wählen",IF(AND(F34<>"",$B$9<>"",F34>$B$9),"Einbau nach Mietende",IF(AND(D34="Mieter",G34<>"",F34=""),"Einbaudatum fehlt",IF(AND(D34="Mieter",G34<>"",G34<=0),"Lebensdauer ungültig",""))))))
H35: =IF(OR(F35="",$B$9=""),"",($B$9-F35)/365.25) | I35: =IF(E35="","",IF(D35<>"Mieter",0,IF(G35="",1,IF(OR(F35="",$B$9=""),"",MAX(0,1-H35/G35))))) | J35: =IF(OR(I35="",E35=""),0,ROUND(E35*I35*20,0)/20) | K35: =IF(E35="","",IF(E35<0,"Kosten negativ",IF(D35="","Ursache wählen",IF(AND(F35<>"",$B$9<>"",F35>$B$9),"Einbau nach Mietende",IF(AND(D35="Mieter",G35<>"",F35=""),"Einbaudatum fehlt",IF(AND(D35="Mieter",G35<>"",G35<=0),"Lebensdauer ungültig",""))))))
H36: =IF(OR(F36="",$B$9=""),"",($B$9-F36)/365.25) | I36: =IF(E36="","",IF(D36<>"Mieter",0,IF(G36="",1,IF(OR(F36="",$B$9=""),"",MAX(0,1-H36/G36))))) | J36: =IF(OR(I36="",E36=""),0,ROUND(E36*I36*20,0)/20) | K36: =IF(E36="","",IF(E36<0,"Kosten negativ",IF(D36="","Ursache wählen",IF(AND(F36<>"",$B$9<>"",F36>$B$9),"Einbau nach Mietende",IF(AND(D36="Mieter",G36<>"",F36=""),"Einbaudatum fehlt",IF(AND(D36="Mieter",G36<>"",G36<=0),"Lebensdauer ungültig",""))))))
H37: =IF(OR(F37="",$B$9=""),"",($B$9-F37)/365.25) | I37: =IF(E37="","",IF(D37<>"Mieter",0,IF(G37="",1,IF(OR(F37="",$B$9=""),"",MAX(0,1-H37/G37))))) | J37: =IF(OR(I37="",E37=""),0,ROUND(E37*I37*20,0)/20) | K37: =IF(E37="","",IF(E37<0,"Kosten negativ",IF(D37="","Ursache wählen",IF(AND(F37<>"",$B$9<>"",F37>$B$9),"Einbau nach Mietende",IF(AND(D37="Mieter",G37<>"",F37=""),"Einbaudatum fehlt",IF(AND(D37="Mieter",G37<>"",G37<=0),"Lebensdauer ungültig",""))))))
H38: =IF(OR(F38="",$B$9=""),"",($B$9-F38)/365.25) | I38: =IF(E38="","",IF(D38<>"Mieter",0,IF(G38="",1,IF(OR(F38="",$B$9=""),"",MAX(0,1-H38/G38))))) | J38: =IF(OR(I38="",E38=""),0,ROUND(E38*I38*20,0)/20) | K38: =IF(E38="","",IF(E38<0,"Kosten negativ",IF(D38="","Ursache wählen",IF(AND(F38<>"",$B$9<>"",F38>$B$9),"Einbau nach Mietende",IF(AND(D38="Mieter",G38<>"",F38=""),"Einbaudatum fehlt",IF(AND(D38="Mieter",G38<>"",G38<=0),"Lebensdauer ungültig",""))))))
H39: =IF(OR(F39="",$B$9=""),"",($B$9-F39)/365.25) | I39: =IF(E39="","",IF(D39<>"Mieter",0,IF(G39="",1,IF(OR(F39="",$B$9=""),"",MAX(0,1-H39/G39))))) | J39: =IF(OR(I39="",E39=""),0,ROUND(E39*I39*20,0)/20) | K39: =IF(E39="","",IF(E39<0,"Kosten negativ",IF(D39="","Ursache wählen",IF(AND(F39<>"",$B$9<>"",F39>$B$9),"Einbau nach Mietende",IF(AND(D39="Mieter",G39<>"",F39=""),"Einbaudatum fehlt",IF(AND(D39="Mieter",G39<>"",G39<=0),"Lebensdauer ungültig",""))))))
H40: =IF(OR(F40="",$B$9=""),"",($B$9-F40)/365.25) | I40: =IF(E40="","",IF(D40<>"Mieter",0,IF(G40="",1,IF(OR(F40="",$B$9=""),"",MAX(0,1-H40/G40))))) | J40: =IF(OR(I40="",E40=""),0,ROUND(E40*I40*20,0)/20) | K40: =IF(E40="","",IF(E40<0,"Kosten negativ",IF(D40="","Ursache wählen",IF(AND(F40<>"",$B$9<>"",F40>$B$9),"Einbau nach Mietende",IF(AND(D40="Mieter",G40<>"",F40=""),"Einbaudatum fehlt",IF(AND(D40="Mieter",G40<>"",G40<=0),"Lebensdauer ungültig",""))))))
H41: =IF(OR(F41="",$B$9=""),"",($B$9-F41)/365.25) | I41: =IF(E41="","",IF(D41<>"Mieter",0,IF(G41="",1,IF(OR(F41="",$B$9=""),"",MAX(0,1-H41/G41))))) | J41: =IF(OR(I41="",E41=""),0,ROUND(E41*I41*20,0)/20) | K41: =IF(E41="","",IF(E41<0,"Kosten negativ",IF(D41="","Ursache wählen",IF(AND(F41<>"",$B$9<>"",F41>$B$9),"Einbau nach Mietende",IF(AND(D41="Mieter",G41<>"",F41=""),"Einbaudatum fehlt",IF(AND(D41="Mieter",G41<>"",G41<=0),"Lebensdauer ungültig",""))))))
... H48: =IF(OR(F48="",$B$9=""),"",($B$9-F48)/365.25) | I48: =IF(E48="","",IF(D48<>"Mieter",0,IF(G48="",1,IF(OR(F48="",$B$9=""),"",MAX(0,1-H48/G48))))) | J48: =IF(OR(I48="",E48=""),0,ROUND(E48*I48*20,0)/20) | K48: =IF(E48="","",IF(E48<0,"Kosten negativ",IF(D48="","Ursache wählen",IF(AND(F48<>"",$B$9<>"",F48>$B$9),"Einbau nach Mietende",IF(AND(D48="Mieter",G48<>"",F48=""),"Einbaudatum fehlt",IF(AND(D48="Mieter",G48<>"",G48<=0),"Lebensdauer ungültig",""))))))
I49: Total | J49: =SUM(J24:J48)

Sheet Abrechnung
A1: Abrechnung Wohnungsrückgabe und Mietkaution
A3: Liegenschaft / Wohnung | B3: =Rückgabe!B4&", "&Rückgabe!B5
A4: Mieter | B4: =Rückgabe!B6&", "&Rückgabe!B7
A5: Mietende | B5: =Rückgabe!B9
A6: Abnahme am | B6: =Rückgabe!B10
A8: Raum / Bauteil | B8: Mangel | C8: Ursache | D8: Kosten CHF | E8: Alter / Lebensdauer | F8: Restwert | G8: Zulasten Mieter CHF
A9: =IF(Rückgabe!E24="","",Rückgabe!A24&" · "&Rückgabe!B24) | B9: =IF(Rückgabe!E24="","",Rückgabe!C24) | C9: =IF(Rückgabe!E24="","",Rückgabe!D24) | D9: =IF(Rückgabe!E24="","",Rückgabe!E24) | E9: =IF(OR(Rückgabe!E24="",Rückgabe!H24="",Rückgabe!G24=""),"",ROUND(Rückgabe!H24,1)&" J. / "&Rückgabe!G24&" J.") | F9: =IF(Rückgabe!E24="","",Rückgabe!I24) | G9: =IF(Rückgabe!E24="","",Rückgabe!J24)
A10: =IF(Rückgabe!E25="","",Rückgabe!A25&" · "&Rückgabe!B25) | B10: =IF(Rückgabe!E25="","",Rückgabe!C25) | C10: =IF(Rückgabe!E25="","",Rückgabe!D25) | D10: =IF(Rückgabe!E25="","",Rückgabe!E25) | E10: =IF(OR(Rückgabe!E25="",Rückgabe!H25="",Rückgabe!G25=""),"",ROUND(Rückgabe!H25,1)&" J. / "&Rückgabe!G25&" J.") | F10: =IF(Rückgabe!E25="","",Rückgabe!I25) | G10: =IF(Rückgabe!E25="","",Rückgabe!J25)
A11: =IF(Rückgabe!E26="","",Rückgabe!A26&" · "&Rückgabe!B26) | B11: =IF(Rückgabe!E26="","",Rückgabe!C26) | C11: =IF(Rückgabe!E26="","",Rückgabe!D26) | D11: =IF(Rückgabe!E26="","",Rückgabe!E26) | E11: =IF(OR(Rückgabe!E26="",Rückgabe!H26="",Rückgabe!G26=""),"",ROUND(Rückgabe!H26,1)&" J. / "&Rückgabe!G26&" J.") | F11: =IF(Rückgabe!E26="","",Rückgabe!I26) | G11: =IF(Rückgabe!E26="","",Rückgabe!J26)
A12: =IF(Rückgabe!E27="","",Rückgabe!A27&" · "&Rückgabe!B27) | B12: =IF(Rückgabe!E27="","",Rückgabe!C27) | C12: =IF(Rückgabe!E27="","",Rückgabe!D27) | D12: =IF(Rückgabe!E27="","",Rückgabe!E27) | E12: =IF(OR(Rückgabe!E27="",Rückgabe!H27="",Rückgabe!G27=""),"",ROUND(Rückgabe!H27,1)&" J. / "&Rückgabe!G27&" J.") | F12: =IF(Rückgabe!E27="","",Rückgabe!I27) | G12: =IF(Rückgabe!E27="","",Rückgabe!J27)
A13: =IF(Rückgabe!E28="","",Rückgabe!A28&" · "&Rückgabe!B28) | B13: =IF(Rückgabe!E28="","",Rückgabe!C28) | C13: =IF(Rückgabe!E28="","",Rückgabe!D28) | D13: =IF(Rückgabe!E28="","",Rückgabe!E28) | E13: =IF(OR(Rückgabe!E28="",Rückgabe!H28="",Rückgabe!G28=""),"",ROUND(Rückgabe!H28,1)&" J. / "&Rückgabe!G28&" J.") | F13: =IF(Rückgabe!E28="","",Rückgabe!I28) | G13: =IF(Rückgabe!E28="","",Rückgabe!J28)
A14: =IF(Rückgabe!E29="","",Rückgabe!A29&" · "&Rückgabe!B29) | B14: =IF(Rückgabe!E29="","",Rückgabe!C29) | C14: =IF(Rückgabe!E29="","",Rückgabe!D29) | D14: =IF(Rückgabe!E29="","",Rückgabe!E29) | E14: =IF(OR(Rückgabe!E29="",Rückgabe!H29="",Rückgabe!G29=""),"",ROUND(Rückgabe!H29,1)&" J. / "&Rückgabe!G29&" J.") | F14: =IF(Rückgabe!E29="","",Rückgabe!I29) | G14: =IF(Rückgabe!E29="","",Rückgabe!J29)
A15: =IF(Rückgabe!E30="","",Rückgabe!A30&" · "&Rückgabe!B30) | B15: =IF(Rückgabe!E30="","",Rückgabe!C30) | C15: =IF(Rückgabe!E30="","",Rückgabe!D30) | D15: =IF(Rückgabe!E30="","",Rückgabe!E30) | E15: =IF(OR(Rückgabe!E30="",Rückgabe!H30="",Rückgabe!G30=""),"",ROUND(Rückgabe!H30,1)&" J. / "&Rückgabe!G30&" J.") | F15: =IF(Rückgabe!E30="","",Rückgabe!I30) | G15: =IF(Rückgabe!E30="","",Rückgabe!J30)
A16: =IF(Rückgabe!E31="","",Rückgabe!A31&" · "&Rückgabe!B31) | B16: =IF(Rückgabe!E31="","",Rückgabe!C31) | C16: =IF(Rückgabe!E31="","",Rückgabe!D31) | D16: =IF(Rückgabe!E31="","",Rückgabe!E31) | E16: =IF(OR(Rückgabe!E31="",Rückgabe!H31="",Rückgabe!G31=""),"",ROUND(Rückgabe!H31,1)&" J. / "&Rückgabe!G31&" J.") | F16: =IF(Rückgabe!E31="","",Rückgabe!I31) | G16: =IF(Rückgabe!E31="","",Rückgabe!J31)
A17: =IF(Rückgabe!E32="","",Rückgabe!A32&" · "&Rückgabe!B32) | B17: =IF(Rückgabe!E32="","",Rückgabe!C32) | C17: =IF(Rückgabe!E32="","",Rückgabe!D32) | D17: =IF(Rückgabe!E32="","",Rückgabe!E32) | E17: =IF(OR(Rückgabe!E32="",Rückgabe!H32="",Rückgabe!G32=""),"",ROUND(Rückgabe!H32,1)&" J. / "&Rückgabe!G32&" J.") | F17: =IF(Rückgabe!E32="","",Rückgabe!I32) | G17: =IF(Rückgabe!E32="","",Rückgabe!J32)
A18: =IF(Rückgabe!E33="","",Rückgabe!A33&" · "&Rückgabe!B33) | B18: =IF(Rückgabe!E33="","",Rückgabe!C33) | C18: =IF(Rückgabe!E33="","",Rückgabe!D33) | D18: =IF(Rückgabe!E33="","",Rückgabe!E33) | E18: =IF(OR(Rückgabe!E33="",Rückgabe!H33="",Rückgabe!G33=""),"",ROUND(Rückgabe!H33,1)&" J. / "&Rückgabe!G33&" J.") | F18: =IF(Rückgabe!E33="","",Rückgabe!I33) | G18: =IF(Rückgabe!E33="","",Rückgabe!J33)
A19: =IF(Rückgabe!E34="","",Rückgabe!A34&" · "&Rückgabe!B34) | B19: =IF(Rückgabe!E34="","",Rückgabe!C34) | C19: =IF(Rückgabe!E34="","",Rückgabe!D34) | D19: =IF(Rückgabe!E34="","",Rückgabe!E34) | E19: =IF(OR(Rückgabe!E34="",Rückgabe!H34="",Rückgabe!G34=""),"",ROUND(Rückgabe!H34,1)&" J. / "&Rückgabe!G34&" J.") | F19: =IF(Rückgabe!E34="","",Rückgabe!I34) | G19: =IF(Rückgabe!E34="","",Rückgabe!J34)
A20: =IF(Rückgabe!E35="","",Rückgabe!A35&" · "&Rückgabe!B35) | B20: =IF(Rückgabe!E35="","",Rückgabe!C35) | C20: =IF(Rückgabe!E35="","",Rückgabe!D35) | D20: =IF(Rückgabe!E35="","",Rückgabe!E35) | E20: =IF(OR(Rückgabe!E35="",Rückgabe!H35="",Rückgabe!G35=""),"",ROUND(Rückgabe!H35,1)&" J. / "&Rückgabe!G35&" J.") | F20: =IF(Rückgabe!E35="","",Rückgabe!I35) | G20: =IF(Rückgabe!E35="","",Rückgabe!J35)
... A33: =IF(Rückgabe!E48="","",Rückgabe!A48&" · "&Rückgabe!B48) | B33: =IF(Rückgabe!E48="","",Rückgabe!C48) | C33: =IF(Rückgabe!E48="","",Rückgabe!D48) | D33: =IF(Rückgabe!E48="","",Rückgabe!E48) | E33: =IF(OR(Rückgabe!E48="",Rückgabe!H48="",Rückgabe!G48=""),"",ROUND(Rückgabe!H48,1)&" J. / "&Rückgabe!G48&" J.") | F33: =IF(Rückgabe!E48="","",Rückgabe!I48) | G33: =IF(Rückgabe!E48="","",Rückgabe!J48)
D35: Schäden zulasten Mieter | G35: =Rückgabe!J49
D36: Ausstehende Mietzinse | G36: =N(Rückgabe!B16)
D37: Nebenkosten-Saldo | G37: =N(Rückgabe!B17)
D38: Weitere Forderungen | G38: =N(Rückgabe!B18)
D39: Total Forderungen des Vermieters | G39: =SUM(G35:G38)
D40: Mietkaution inkl. Zins | G40: =N(Rückgabe!B11)+N(Rückgabe!B12)
D41: Aus der Kaution an den Vermieter | G41: =MAX(0,MIN(G39,G40))
D42: Aus der Kaution an den Mieter | G42: =G40-G41
D43: Restforderung über die Kaution hinaus | G43: =MAX(0,G39-G40)
D44: Zusätzlich vom Vermieter zu bezahlen | G44: =MAX(0,-G39)
A46: Berechnung: Kosten × (1 − Alter ÷ Lebensdauer) gemäss paritätischer Lebensdauertabelle HEV/MV. Normale Abnutzung geht nicht zulasten des Mieters (Art. 267 OR).
A47: Belege und Offerten können eingesehen werden. Einwände bitte innert 30 Tagen schriftlich.

Sheet Freigabe Kaution
A1: Freigabe der Mietkaution
A3: An: | B3: =Rückgabe!B13
A5: Mietobjekt: | B5: =Rückgabe!B4&", "&Rückgabe!B5
A6: Mietende: | B6: =Rückgabe!B9
A8: Die Unterzeichnenden ersuchen Sie, das Mietkautionskonto zu saldieren und wie folgt auszuzahlen:
A10: An den Mieter: | B10: =Rückgabe!B6 | C10: =Abrechnung!G42
A11: IBAN Mieter:
A12: An den Vermieter: | B12: =Rückgabe!B8 | C12: =Abrechnung!G41
A13: IBAN Vermieter:
A14: Allfälliger Zins bis zur Saldierung geht an den Mieter.
A17: Ort, Datum: ______________________
A20: Mieter: | B20: ______________________________
A23: Vermieter: | B23: ______________________________

Sheet Kontrolle
A1: Kontrolle
C2: Soll
A3: Mietende erfasst (1 = ja) | B3: =IF(Rückgabe!B9="",0,1) | C3: 1
A4: Kaution nicht negativ (1 = ja) | B4: =IF(N(Rückgabe!B11)+N(Rückgabe!B12)>=0,1,0) | C4: 1
A5: Mängelzeilen mit Hinweis «Prüfen» | B5: =COUNTIF(Rückgabe!K24:K48,"?*") | C5: 0
A6: Aufteilung der Kaution geht auf (Differenz) | B6: =ROUND(Abrechnung!G41+Abrechnung!G42-Abrechnung!G40,2) | C6: 0
A7: Abnahme mehr als 5 Tage nach Mietende (1 = ja, Rügefrist prüfen) | B7: =IF(OR(Rückgabe!B9="",Rückgabe!B10=""),0,IF(Rückgabe!B10-Rückgabe!B9>5,1,0)) | C7: 0
A9: Status | B9: =IF(AND(B3=C3,B4=C4,B5=C5,B6=C6,B7=C7),"OK","Bitte prüfen")
